Workbook

Sheet 900条整合编码
A1: 评论编号 | B1: 语言组 | C1: Steam推荐状态 | D1: 有价值人数 | E1: 欢乐人数 | F1: 游戏时长(小时) | G1: 发表时间 | H1: 原文 | I1: 中文译文/分析文本 | J1: A_视听表现 | K1: B_战斗操作 | L1: C_探索设计 | M1: D_技术稳定 | N1: E_整体评价 | O1: F_文化接近性 | P1: G_文化折扣/理解障碍 | Q1: H_国产3A/身份期待 | R1: A1_画面美术场景 | S1: A2_音乐音效配音 | T1: A3_演出角色怪物设计 | U1: B1_动作打击手感 | V1: B2_Boss战斗节奏 | W1: B3_难度挑战 | X1: B4_锁定视角 | Y1: B5_判定反馈 | Z1: C1_地图路线 | AA1: C2_空气墙可达性 | AB1: C3_探索隐藏支线 | AC1: C4_引导迷路单线 | AD1: D1_优化帧率 | AE1: D2_崩溃闪退 | AF1: D3_Bug兼容硬件 | AG1: E1_整体完成度 | AH1: E2_推荐价值判断 | AI1: F1_西游悟空符号 | AJ1: F2_童年记忆情怀 | AK1: F3_本国媒介路径 | AL1: F4_中国文化宗教语言审美 | AM1: G1_剧情叙事理解 | AN1: G2_原典知识人物关系专名 | AO1: G3_本地化翻译 | AP1: G4_外部资料依赖 | AQ1: G5_角色期待意义偏移 | AR1: H1_国产3A身份期待 | AS1: 一级编码数 | AT1: 二级编码数 | AU1: 二级编码标签 | AV1: 有编码 | AW1: 未命中 | AX1: 多主题 | AY1: 词典情感分值 | AZ1: 情感类别（自动） | BA1: 情感字母 | BB1: 计分文本来源
A2: CN-P-001 | B2: 中文 | C2: 推荐 | D2: 746 | E2: 18 | F2: 7.4 | G2: 2024-08-20 | H2: 《黑神话:悟空》对我们这代长年接触单机游戏，但往往只有欧美和日厂游戏可玩的玩家而言，真可谓是一剂强心剂。尽管近些年来优秀的国产独立游戏层出不穷，其中不乏同样能体现中华文化的佳作，但国人心中始终心怀一个梦想，“要有国产3A游戏就好了”。可能单从游戏性上规格体量高的游戏也并不能说明什么，但这却的的确确是游戏工业化的一大标签，对于突破国界向世界展现文化影响力而言，高规格游戏也有其不可替代性，从没有一个国家的玩家会整日将如“3A游戏”的词汇挂在嘴边，足可见他们的渴望。就在这如同荒漠渴望雨水时，2020年8月20日，大圣踩着筋斗云出现了 四年之约终有期 我第一次看见游戏PV时还是在大学时期，大圣变为一只金蝉进入黑风山，在就像是人参成精的土地公公指引下，进入观音禅院挑战被玩家戏称为“毛多弱火”的灵虚子。这一段预告相当激励人心，和国外一线大作肉眼几乎看不出明显差距的超强画面表现力，让无数国人玩家深藏在心中的梦想悄然间长出萌芽。毕竟相较于国外的蝙蝠侠、蜘蛛侠、美国队长等诸多有着超能力的硬汉，齐天大圣才一直是我们孩童时期的幻想，属于我们自己的超级英雄！而在高规格的游戏画面里耳边响起经典的“云宫迅音”，眼前是大圣的金箍棒，我至今难以忘记当初随着音乐鼓点颤动的心跳 但PV毕竟只是PV，我虽然在之后的每次观看黑神话预告时都还是会“焚香沐浴”一番，戴上耳机端坐在电脑前，而不会只是在手机小屏幕上观看，但在黑神话这四年时间的前后，数个尽管影响力没有这般大但同样相对高规格的国产游戏，或上线后褒贬不一、有限销量然后道歉下架绝版喜加一，要么干脆的胎死腹中，网上留存的也仅有一些片段。从以前的国产EA阶段游戏不可信、到现在的高规格游戏个个难产，让其声誉降至谷底，导致我其实对《黑神话:悟空》也难提起更多信心，说到底，这毕竟只是游戏科学团队应对如此体量作品的处女作，一个从未统筹过如此大项目的团队，甚至第一个PV的初衷还更多是因为团队缺人的缘故，面对如此这般泼天的流量和关注，是否能静下心来、保持初心的好好做游戏，对此我始终心存疑虑，更惶恐这如果真是一场“诈骗”对目前纤柔的萌芽阶段会是怎样一个毁灭性打击 2024年8月20日，没有跳票的，《黑神话:悟空》如期上线了。其实就在几天前的性能测试工具开放时，我这颗忐忑的心就放下了大半，一个如此有信心，在游戏开售前弄个测试工具事先应对玩家对游戏优化的疑虑，实际测试结果对中低端硬件的明显包容，很难让人不相信，游戏科学团队的确也已做好万全准备。而面对游戏发售前的泄露事件，制作人冯骥老师更是直接坦言道 最后，我依然很有信心，无论你（无意或是被迫）提前看过了多少已经泄露的内容，这个游戏仍然会带给你从未有过的感受与足够独特的乐趣。所以，不必担心，不必懊恼，《黑神话：悟空》没那么脆弱 是的，我相信《黑神话:悟空》没有这么脆弱，我相信这会是款足够好玩的游戏，不用媒体评分，不用看泄露视频，越临近答案揭晓的时刻，我越有信心，我从未如此笃定过 沉醉不知归路 不管是在过去观看预告PV的“云游戏”，还是此次自己的上手体验。《黑神话:悟空》那别具一格的、带有强烈东方元素的高级审美，都令我印象深刻。在如无头苍蝇般瞎转悠的同时，我总是被美好景致所感染的不由自主的停下前进探索的脚步，感受身边的风声蝉鸣、小桥流水和小妖怪的窃窃私语，观察着天边的第一缕阳光穿过大树的翠绿落到蒲团上，身边残破锈迹斑斑的佛陀像的双眼似乎尽显世态炎凉，自然风貌和人文建筑历经沧桑带来同样厚重感的和谐，这都是此前难以在其他国家的游戏作品中感受到的东方风韵，不需任何言语的堆砌，这种文化魅力只需要你站在那里，就会被深深的感染到 不过，在于光影的协调上不知道是不是因为我个人设置的关系，感觉存在一些小瑕疵。忽明忽暗的场景色调变化的较为频繁，不时的出现一些场景要么昏暗到影响探索，只能依赖于什么时候撞到空气墙然后亦步亦趋的继续，要么离开昏暗场景时瞬时的光暗反差表现过于明显到甚至有点晃眼。不少玩家认为这很有些“现实感”，我姑且认为这是调侃，毕竟这在美术表现如此高格调时所出现的一点点不良体验都足够明显 也正因为如此，《黑神话:悟空》也是我认为的相当适合如《刺客信条:起源》和《刺客信条:奥德赛》做个如“探索之旅”般，玩家只需要当个步行模拟器游玩的模式的游戏。并且，在游戏破圈后势必会有大量此前从未接触过ARPG游戏的轻度玩家，虽然并非说《黑神话:悟空》只有什么硬核高玩才能玩的下去，只是说，对于那部分可能对自己没什么信心，只是单纯想购买游戏权做支持的玩家而言，引入这样的探索模式对于他们来说，是个门槛几近于无的同时，能通过电子游戏感受这一份东方美学和文化浸染的好机会。而对于我们国家当前这个市场，尽可能多的加深游戏“文化赋分”的内容，强化更多正向的帽子，也不失为是件可以摆在台面上大肆宣传的好事 看我棍棒之下无一合之敌！ 此部分想从ARPG游戏的ACT和RPG两部分稍微展开来说一下 不得不承认，在同类游戏如此多的情况下，作为后来者《黑神话:悟空》的战斗系统还是做的很有特色。玩家主要需要通过轻重攻击来打伤害，轻攻击积累棍势，重攻击蓄力和切手技消耗棍势。除了初始的更适合追击敌人的劈棍式，还有可以将棍子撑长伫在原地然后狠狠下劈的立棍式和站在原地用长棍狠戳对面的戳棍式，三种不同的棍法也有着各自不同的延伸可供加点成长的技能点，从而产生不同的应对策略和派生流派 此外，还有诸如定身术的法术深化了悟空特色的战斗方式，随流程推进逐步解锁的诸般新法术新能力鼓励玩家尝试不同的方式战胜强敌。类同大圣七十二般变化的变身系统更让战斗的花样性有着很强的提升，虽然我个人操作有限更多时候都只能将变身期间当做肉盾扛血的休息间隙，但哪怕是最初的刀郎教头广智许多玩家也能利用好变身期间一下子打空boss们大半管血 至于和变化相似的“精魄”，玩家可以在打败精英小BOSS后，用葫芦吸收其精魄，然后在战斗中可以使出它们经典招式的一击。但老实说，我觉得“精魄”在自成体系的战斗系统中显得有些冗余，在对战中由于CD过长且作用着实有限，“精魄”的存在感属实不高，倒是在某些场合的功能性更为突出，比如可以用幽魂的捶地一击打破墙壁。不得不怀疑起初游科想的是将这些统统归到七十二变的变化中，或是工作量过大的缘故，其中的大部分变化被简化成“精魄”，让此多少显得有些格格不入 至于ARPG中的养成部分，其实《黑神话：悟空》这方面的内容较为常规，数值变化除了等级提升外的加点，更多的是通过装备属性上的加成，但装备属性的选择实则并不太自由，随阶段逐步解锁升级的装备让不同玩家之间的选择差异性也较为有限，而在某些阶段过快的装备套装更迭速度，让有些时候玩家容易产生“之前花了资源升级的某套装备好浪费，数值没提升多少不如留着升这套”的不良情绪 在BOSS Rush的路上处处碰“壁” 《黑神话：悟空》在关卡式分章节体的多张地图里塞满了各种的BOSS，按照其他玩家所说数量高达81只对应西行路上的九九八十一难，极度的堆量程度浪费到在只要不迷路的情况下往往走上几步路就要面对一只全新机制、此前从未接触过的新BOSS，更别提每一只BOSS所对应的各式场景和华丽演出，虽然有些时候因为尚未摸清套路显得有些受苦，但操控着“天命人”全情投入克服此前自以为难以逾越的困难，也自会产生成就感并更有勇气面对接下来遇到的其他“难” 战斗，爽！ 在BOSS战时视角的智能锁定成为一个问题，我因为时间有限攻略的内容不太多，关于视角问题印象很深的是在第一章关底，挑战黑熊精时，因为其庞大的体型，我在多数锁定视角下仅仅能看得到黑熊精的脚和满屏幕的黑毛，这也就导致在躲避伤害时我只能凭借此前黑熊精的攻击间隔猜测——它的下一招该出招了，或许我该躲了 而这也不仅仅是面对体型巨大的敌人会存在的视角问题，种类数量如此庞大的BOSS们，有龙跃于天的，有快速移动的，如果视角不是足够的智能，那对玩家的战斗体验多多少少会存在一些影响 在塞满BOSS的西行路上，很大一部分的BOSS并不是在主线道路上，玩家往往需要完成各种隐藏内容才能解锁，许多玩家一周目初见不看攻略通关后会赫然发现，许多的BOSS甚至都没有见到过 在大量隐藏内容之下，游戏关卡内分布较为密集的空气墙对玩家的探索造成了较负面的影响。《黑神话：悟空》并非是款开放世界的游戏，有空气墙倒逼玩家往设计好的道路上探索这无可厚非，但在一些看起来明显能走的道路上，却布好空气墙阻碍玩家前进，当这样的经历多次出现，很难说玩家能提起足够的心气在地图上尽情探索，寻找潜藏着隐藏内容。过分的限制玩家探索和塞满隐藏内容之间，这本就存在矛盾 在逼迫玩家“不撞南墙不回头”时，游戏的许多场景也缺失了必要的指引，有且仅有在附近有土地庙时我观察到在指引上有着些许设计。我丝毫不怀疑许多方向感比较强的“天命人”对此感觉毫无障碍，但对我这般麋鹿选手，在没有地图和适时指引且周边场景无明显地标之下，玩了一小时走回到了初遇的土地庙也并不新奇 重走西行路，再临九九八十一难 作为一部《西游记》后传作品，《黑神话：悟空》保持着严肃的改编风格，对自己理解的《西游记》做出了自己合乎逻辑自洽的注解，这让游戏并非只是成为一款简单的“Boss Rush”游戏，每一句台词，甚至于每一种小妖的图鉴都值得玩家细细揣摩，通过对原著的极致理解，通过大量自己的刻画，通过寥寥数笔描绘出了数个经典人物，并适时的引入包括“天命人”在内的全新设定却不显违和，就好像故事天然的就应该这么走下去 其实，设身处地的想，如果我是一名外国人，玩到《黑神话：悟空》这样的游戏，虽然依旧觉得好玩，但由于缺乏了那股子土生土长的文化浸染力，在游戏内容设计之外处处透着难以理解的排斥感，恐怕这也只是会成为我生命中一过客的游戏，和其他的动作游戏并没有太大的不同 但站在现下的这个时代背景下，国内单机游戏市场称之为荒漠虽然有些夸张但还是挺有现实性的，此时出现了一款游戏，将中国人耳熟能详的故事搬进每个玩家的荧幕前，熟悉的角色操着地道的口音，一进游戏默认的中文字幕中文配音，而老外却要苦恼有时候莫名出现BUG英文配音丢失 从想玩游戏没地方玩到处找资源，到找到资源了苦等汉化组出汉化。从终于有许多游戏玩了但都是海外游戏，到今天的国产游戏也证明了它不是丝毫没有可取之处。这条路我们走的好累，但终于见到了荒漠中的翠绿萌芽。《黑神话：悟空》于国人玩家而言远不是一款游戏这么简单，在移动端收益已进入下降趋势，手游的研发、发行、运营也变成一个“卷”且“烧钱”的过程，这样一款在商业上成功的游戏，也势必会有资本涌进高规格精品游戏的制作中，许多在过去胎死腹中的游戏甚至会有机会重新启航 就如同直到今天还不断涌现的各种类完蛋的恋爱FMV游戏，希望国产游戏的春天也能伴随着这股春风早日到来 | I2: 《黑神话:悟空》对我们这代长年接触单机游戏，但往往只有欧美和日厂游戏可玩的玩家而言，真可谓是一剂强心剂。尽管近些年来优秀的国产独立游戏层出不穷，其中不乏同样能体现中华文化的佳作，但国人心中始终心怀一个梦想，“要有国产3A游戏就好了”。可能单从游戏性上规格体量高的游戏也并不能说明什么，但这却的的确确是游戏工业化的一大标签，对于突破国界向世界展现文化影响力而言，高规格游戏也有其不可替代性，从没有一个国家的玩家会整日将如“3A游戏”的词汇挂在嘴边，足可见他们的渴望。就在这如同荒漠渴望雨水时，2020年8月20日，大圣踩着筋斗云出现了 四年之约终有期 我第一次看见游戏PV时还是在大学时期，大圣变为一只金蝉进入黑风山，在就像是人参成精的土地公公指引下，进入观音禅院挑战被玩家戏称为“毛多弱火”的灵虚子。这一段预告相当激励人心，和国外一线大作肉眼几乎看不出明显差距的超强画面表现力，让无数国人玩家深藏在心中的梦想悄然间长出萌芽。毕竟相较于国外的蝙蝠侠、蜘蛛侠、美国队长等诸多有着超能力的硬汉，齐天大圣才一直是我们孩童时期的幻想，属于我们自己的超级英雄！而在高规格的游戏画面里耳边响起经典的“云宫迅音”，眼前是大圣的金箍棒，我至今难以忘记当初随着音乐鼓点颤动的心跳 但PV毕竟只是PV，我虽然在之后的每次观看黑神话预告时都还是会“焚香沐浴”一番，戴上耳机端坐在电脑前，而不会只是在手机小屏幕上观看，但在黑神话这四年时间的前后，数个尽管影响力没有这般大但同样相对高规格的国产游戏，或上线后褒贬不一、有限销量然后道歉下架绝版喜加一，要么干脆的胎死腹中，网上留存的也仅有一些片段。从以前的国产EA阶段游戏不可信、到现在的高规格游戏个个难产，让其声誉降至谷底，导致我其实对《黑神话:悟空》也难提起更多信心，说到底，这毕竟只是游戏科学团队应对如此体量作品的处女作，一个从未统筹过如此大项目的团队，甚至第一个PV的初衷还更多是因为团队缺人的缘故，面对如此这般泼天的流量和关注，是否能静下心来、保持初心的好好做游戏，对此我始终心存疑虑，更惶恐这如果真是一场“诈骗”对目前纤柔的萌芽阶段会是怎样一个毁灭性打击 2024年8月20日，没有跳票的，《黑神话:悟空》如期上线了。其实就在几天前的性能测试工具开放时，我这颗忐忑的心就放下了大半，一个如此有信心，在游戏开售前弄个测试工具事先应对玩家对游戏优化的疑虑，实际测试结果对中低端硬件的明显包容，很难让人不相信，游戏科学团队的确也已做好万全准备。而面对游戏发售前的泄露事件，制作人冯骥老师更是直接坦言道 最后，我依然很有信心，无论你（无意或是被迫）提前看过了多少已经泄露的内容，这个游戏仍然会带给你从未有过的感受与足够独特的乐趣。所以，不必担心，不必懊恼，《黑神话：悟空》没那么脆弱 是的，我相信《黑神话:悟空》没有这么脆弱，我相信这会是款足够好玩的游戏，不用媒体评分，不用看泄露视频，越临近答案揭晓的时刻，我越有信心，我从未如此笃定过 沉醉不知归路 不管是在过去观看预告PV的“云游戏”，还是此次自己的上手体验。《黑神话:悟空》那别具一格的、带有强烈东方元素的高级审美，都令我印象深刻。在如无头苍蝇般瞎转悠的同时，我总是被美好景致所感染的不由自主的停下前进探索的脚步，感受身边的风声蝉鸣、小桥流水和小妖怪的窃窃私语，观察着天边的第一缕阳光穿过大树的翠绿落到蒲团上，身边残破锈迹斑斑的佛陀像的双眼似乎尽显世态炎凉，自然风貌和人文建筑历经沧桑带来同样厚重感的和谐，这都是此前难以在其他国家的游戏作品中感受到的东方风韵，不需任何言语的堆砌，这种文化魅力只需要你站在那里，就会被深深的感染到 不过，在于光影的协调上不知道是不是因为我个人设置的关系，感觉存在一些小瑕疵。忽明忽暗的场景色调变化的较为频繁，不时的出现一些场景要么昏暗到影响探索，只能依赖于什么时候撞到空气墙然后亦步亦趋的继续，要么离开昏暗场景时瞬时的光暗反差表现过于明显到甚至有点晃眼。不少玩家认为这很有些“现实感”，我姑且认为这是调侃，毕竟这在美术表现如此高格调时所出现的一点点不良体验都足够明显 也正因为如此，《黑神话:悟空》也是我认为的相当适合如《刺客信条:起源》和《刺客信条:奥德赛》做个如“探索之旅”般，玩家只需要当个步行模拟器游玩的模式的游戏。并且，在游戏破圈后势必会有大量此前从未接触过ARPG游戏的轻度玩家，虽然并非说《黑神话:悟空》只有什么硬核高玩才能玩的下去，只是说，对于那部分可能对自己没什么信心，只是单纯想购买游戏权做支持的玩家而言，引入这样的探索模式对于他们来说，是个门槛几近于无的同时，能通过电子游戏感受这一份东方美学和文化浸染的好机会。而对于我们国家当前这个市场，尽可能多的加深游戏“文化赋分”的内容，强化更多正向的帽子，也不失为是件可以摆在台面上大肆宣传的好事 看我棍棒之下无一合之敌！ 此部分想从ARPG游戏的ACT和RPG两部分稍微展开来说一下 不得不承认，在同类游戏如此多的情况下，作为后来者《黑神话:悟空》的战斗系统还是做的很有特色。玩家主要需要通过轻重攻击来打伤害，轻攻击积累棍势，重攻击蓄力和切手技消耗棍势。除了初始的更适合追击敌人的劈棍式，还有可以将棍子撑长伫在原地然后狠狠下劈的立棍式和站在原地用长棍狠戳对面的戳棍式，三种不同的棍法也有着各自不同的延伸可供加点成长的技能点，从而产生不同的应对策略和派生流派 此外，还有诸如定身术的法术深化了悟空特色的战斗方式，随流程推进逐步解锁的诸般新法术新能力鼓励玩家尝试不同的方式战胜强敌。类同大圣七十二般变化的变身系统更让战斗的花样性有着很强的提升，虽然我个人操作有限更多时候都只能将变身期间当做肉盾扛血的休息间隙，但哪怕是最初的刀郎教头广智许多玩家也能利用好变身期间一下子打空boss们大半管血 至于和变化相似的“精魄”，玩家可以在打败精英小BOSS后，用葫芦吸收其精魄，然后在战斗中可以使出它们经典招式的一击。但老实说，我觉得“精魄”在自成体系的战斗系统中显得有些冗余，在对战中由于CD过长且作用着实有限，“精魄”的存在感属实不高，倒是在某些场合的功能性更为突出，比如可以用幽魂的捶地一击打破墙壁。不得不怀疑起初游科想的是将这些统统归到七十二变的变化中，或是工作量过大的缘故，其中的大部分变化被简化成“精魄”，让此多少显得有些格格不入 至于ARPG中的养成部分，其实《黑神话：悟空》这方面的内容较为常规，数值变化除了等级提升外的加点，更多的是通过装备属性上的加成，但装备属性的选择实则并不太自由，随阶段逐步解锁升级的装备让不同玩家之间的选择差异性也较为有限，而在某些阶段过快的装备套装更迭速度，让有些时候玩家容易产生“之前花了资源升级的某套装备好浪费，数值没提升多少不如留着升这套”的不良情绪 在BOSS Rush的路上处处碰“壁” 《黑神话：悟空》在关卡式分章节体的多张地图里塞满了各种的BOSS，按照其他玩家所说数量高达81只对应西行路上的九九八十一难，极度的堆量程度浪费到在只要不迷路的情况下往往走上几步路就要面对一只全新机制、此前从未接触过的新BOSS，更别提每一只BOSS所对应的各式场景和华丽演出，虽然有些时候因为尚未摸清套路显得有些受苦，但操控着“天命人”全情投入克服此前自以为难以逾越的困难，也自会产生成就感并更有勇气面对接下来遇到的其他“难” 战斗，爽！ 在BOSS战时视角的智能锁定成为一个问题，我因为时间有限攻略的内容不太多，关于视角问题印象很深的是在第一章关底，挑战黑熊精时，因为其庞大的体型，我在多数锁定视角下仅仅能看得到黑熊精的脚和满屏幕的黑毛，这也就导致在躲避伤害时我只能凭借此前黑熊精的攻击间隔猜测——它的下一招该出招了，或许我该躲了 而这也不仅仅是面对体型巨大的敌人会存在的视角问题，种类数量如此庞大的BOSS们，有龙跃于天的，有快速移动的，如果视角不是足够的智能，那对玩家的战斗体验多多少少会存在一些影响 在塞满BOSS的西行路上，很大一部分的BOSS并不是在主线道路上，玩家往往需要完成各种隐藏内容才能解锁，许多玩家一周目初见不看攻略通关后会赫然发现，许多的BOSS甚至都没有见到过 在大量隐藏内容之下，游戏关卡内分布较为密集的空气墙对玩家的探索造成了较负面的影响。《黑神话：悟空》并非是款开放世界的游戏，有空气墙倒逼玩家往设计好的道路上探索这无可厚非，但在一些看起来明显能走的道路上，却布好空气墙阻碍玩家前进，当这样的经历多次出现，很难说玩家能提起足够的心气在地图上尽情探索，寻找潜藏着隐藏内容。过分的限制玩家探索和塞满隐藏内容之间，这本就存在矛盾 在逼迫玩家“不撞南墙不回头”时，游戏的许多场景也缺失了必要的指引，有且仅有在附近有土地庙时我观察到在指引上有着些许设计。我丝毫不怀疑许多方向感比较强的“天命人”对此感觉毫无障碍，但对我这般麋鹿选手，在没有地图和适时指引且周边场景无明显地标之下，玩了一小时走回到了初遇的土地庙也并不新奇 重走西行路，再临九九八十一难 作为一部《西游记》后传作品，《黑神话：悟空》保持着严肃的改编风格，对自己理解的《西游记》做出了自己合乎逻辑自洽的注解，这让游戏并非只是成为一款简单的“Boss Rush”游戏，每一句台词，甚至于每一种小妖的图鉴都值得玩家细细揣摩，通过对原著的极致理解，通过大量自己的刻画，通过寥寥数笔描绘出了数个经典人物，并适时的引入包括“天命人”在内的全新设定却不显违和，就好像故事天然的就应该这么走下去 其实，设身处地的想，如果我是一名外国人，玩到《黑神话：悟空》这样的游戏，虽然依旧觉得好玩，但由于缺乏了那股子土生土长的文化浸染力，在游戏内容设计之外处处透着难以理解的排斥感，恐怕这也只是会成为我生命中一过客的游戏，和其他的动作游戏并没有太大的不同 但站在现下的这个时代背景下，国内单机游戏市场称之为荒漠虽然有些夸张但还是挺有现实性的，此时出现了一款游戏，将中国人耳熟能详的故事搬进每个玩家的荧幕前，熟悉的角色操着地道的口音，一进游戏默认的中文字幕中文配音，而老外却要苦恼有时候莫名出现BUG英文配音丢失 从想玩游戏没地方玩到处找资源，到找到资源了苦等汉化组出汉化。从终于有许多游戏玩了但都是海外游戏，到今天的国产游戏也证明了它不是丝毫没有可取之处。这条路我们走的好累，但终于见到了荒漠中的翠绿萌芽。《黑神话：悟空》于国人玩家而言远不是一款游戏这么简单，在移动端收益已进入下降趋势，手游的研发、发行、运营也变成一个“卷”且“烧钱”的过程，这样一款在商业上成功的游戏，也势必会有资本涌进高规格精品游戏的制作中，许多在过去胎死腹中的游戏甚至会有机会重新启航 就如同直到今天还不断涌现的各种类完蛋的恋爱FMV游戏，希望国产游戏的春天也能伴随着这股春风早日到来 | J2: =IF(SUM(R2:T2)>0,1,0) -> 1 | K2: =IF(SUM(U2:Y2)>0,1,0) -> 1 | L2: =IF(SUM(Z2:AC2)>0,1,0) -> 1 | M2: =IF(SUM(AD2:AF2)>0,1,0) -> 1 | N2: =IF(SUM(AG2:AH2)>0,1,0) -> 1 | O2: =IF(SUM(AI2:AL2)>0,1,0) -> 1 | P2: =IF(SUM(AM2:AQ2)>0,1,0) -> 1 | Q2: =IF(AR2>0,1,0) -> 1 | R2: 1 | S2: 1 | T2: 1 | U2: 1 | V2: 1 | W2: 1 | X2: 1 | Y2: 1 | Z2: 1 | AA2: 1 | AB2: 1 | AC2: 1 | AD2: 1 | AE2: 0 | AF2: 1 | AG2: 1 | AH2: 1 | AI2: 1 | AJ2: 0 | AK2: 0 | AL2: 1 | AM2: 0 | AN2: 0 | AO2: 0 | AP2: 1 | AQ2: 1 | AR2: 1 | AS2: =SUM(J2:Q2) -> 8 | AT2: =SUM(R2:AR2) -> 21 | AU2: 画面美术场景；音乐音效配音；演出角色怪物设计；动作打击手感；Boss战斗节奏；难度挑战；锁定视角；判定反馈；地图路线；空气墙可达性；探索隐藏支线；引导迷路单线；优化帧率；Bug兼容硬件；整体完成度；推荐价值判断；西游悟空符号；中国文化宗教语言审美；外部资料依赖；角色期待意义偏移；国产3A身份期待 | AV2: =IF(AT2>0,1,0) -> 1 | AW2: =IF(AT2=0,1,0) -> 0 | AX2: =IF(AT2>=8,1,0) -> 1 | AY2: 189.5 | AZ2: 正面 | BA2: P | BB2: 原文
A3: CN-P-002 | B3: 中文 | C3: 推荐 | D3: 353 | E3: 11 | F3: 88.3 | G3: 2024-08-20 | H3: 历时两月，终得八十一难圆满，欢喜之余写下本测评。 还记得2020年8月20号，黑神话第一个PV横空出世的日子；对那时的我而言不过是平静且普通的一天。我在公司座位上摸鱼，数着时间等下班吃饭。突然游戏群里转了一个视频，转发人无比激动大呼牛逼。 我粗略一看标题：“...悟空...实机演示...”。嗨呀，估计又是个以西游记为噱头骗投资的玩意儿。看到大圣归来骗了那么多经费，也想学一学？ 虽说有些嗤之以鼻，但我还是点开了视频。 嗯？这个配音？嗯？这种品质的画面？？纯实机演示？真的假的？这个制作水平，真的是国内游戏公司能做出来的？ 我惊讶欣喜，紧接着，《如意金箍棒》五个大字一出，我心中一震。随后，雷音寺、紧箍咒、四大天王、筋斗云、大闹天宫等耳熟能详的元素一一展现，我仿佛又回到了小时候和弟弟挤在电视机前看86版西游记的日子；再接着，唢呐吹奏的云宫迅音如雷贯耳般将我惊醒，我这才发现我的眼眶已经湿润一片。画面结束，我却激动到不能自己，浑身止不住地颤抖，整个人恍若梦中。 那一天我把整个PV重复看了无数遍。人生中少有时刻能激动至此，以至于过了4年，当时的感受仍然历历在目。 后来，我一直在想，黑神话的PV热度如此之高，无疑已经到达破圈的程度。如果黑神话真的按PV的规格做出来了，无疑会给死气沉沉的国产单机带来改变；若发售后销量口碑不差，甚至还会给与市场对于单机蓝海的信心；也许会有更多公司将目光从手游网游转向单机，也许我作为玩家能玩到更多国产游戏？ 同时我也心慌：如果这个游戏到头来只是一场骗局，实际内容真的只有PV展示的内容，甚至大幅缩水，那对国内单机玩家而言肯定是无比沉重的一击，就像血狮、幻那样，劣质游戏一步步将玩家对国内厂商的信任消耗殆尽，最终对国产单机再无期望。 很幸运，游戏科学做到了。他们证明了，国内并不是做不出好游戏，只是没人去做。 同时，我也很高兴，玩家们也证明了，国内并不缺少为单机付费的人，而是缺少值得去付费的游戏。所谓国内单机市场小、玩家都是玩盗版，做单机死路一条的言论，或许在十几年前是对的，但到了如今，全都不攻自破。 祝愿国产单机能越来越好。 | I3: 历时两月，终得八十一难圆满，欢喜之余写下本测评。 还记得2020年8月20号，黑神话第一个PV横空出世的日子；对那时的我而言不过是平静且普通的一天。我在公司座位上摸鱼，数着时间等下班吃饭。突然游戏群里转了一个视频，转发人无比激动大呼牛逼。 我粗略一看标题：“...悟空...实机演示...”。嗨呀，估计又是个以西游记为噱头骗投资的玩意儿。看到大圣归来骗了那么多经费，也想学一学？ 虽说有些嗤之以鼻，但我还是点开了视频。 嗯？这个配音？嗯？这种品质的画面？？纯实机演示？真的假的？这个制作水平，真的是国内游戏公司能做出来的？ 我惊讶欣喜，紧接着，《如意金箍棒》五个大字一出，我心中一震。随后，雷音寺、紧箍咒、四大天王、筋斗云、大闹天宫等耳熟能详的元素一一展现，我仿佛又回到了小时候和弟弟挤在电视机前看86版西游记的日子；再接着，唢呐吹奏的云宫迅音如雷贯耳般将我惊醒，我这才发现我的眼眶已经湿润一片。画面结束，我却激动到不能自己，浑身止不住地颤抖，整个人恍若梦中。 那一天我把整个PV重复看了无数遍。人生中少有时刻能激动至此，以至于过了4年，当时的感受仍然历历在目。 后来，我一直在想，黑神话的PV热度如此之高，无疑已经到达破圈的程度。如果黑神话真的按PV的规格做出来了，无疑会给死气沉沉的国产单机带来改变；若发售后销量口碑不差，甚至还会给与市场对于单机蓝海的信心；也许会有更多公司将目光从手游网游转向单机，也许我作为玩家能玩到更多国产游戏？ 同时我也心慌：如果这个游戏到头来只是一场骗局，实际内容真的只有PV展示的内容，甚至大幅缩水，那对国内单机玩家而言肯定是无比沉重的一击，就像血狮、幻那样，劣质游戏一步步将玩家对国内厂商的信任消耗殆尽，最终对国产单机再无期望。 很幸运，游戏科学做到了。他们证明了，国内并不是做不出好游戏，只是没人去做。 同时，我也很高兴，玩家们也证明了，国内并不缺少为单机付费的人，而是缺少值得去付费的游戏。所谓国内单机市场小、玩家都是玩盗版，做单机死路一条的言论，或许在十几年前是对的，但到了如今，全都不攻自破。 祝愿国产单机能越来越好。 | J3: =IF(SUM(R3:T3)>0,1,0) -> 1 | K3: =IF(SUM(U3:Y3)>0,1,0) -> 1 | L3: =IF(SUM(Z3:AC3)>0,1,0) -> 1 | M3: =IF(SUM(AD3:AF3)>0,1,0) -> 0 | N3: =IF(SUM(AG3:AH3)>0,1,0) -> 1 | O3: =IF(SUM(AI3:AL3)>0,1,0) -> 1 | P3: =IF(SUM(AM3:AQ3)>0,1,0) -> 0 | Q3: =IF(AR3>0,1,0) -> 1 | R3: 1 | S3: 1 | T3: 0 | U3: 1 | V3: 0 | W3: 0 | X3: 0 | Y3: 0 | Z3: 0 | AA3: 0 | AB3: 0 | AC3: 1 | AD3: 0 | AE3: 0 | AF3: 0 | AG3: 1 | AH3: 1 | AI3: 1 | AJ3: 1 | AK3: 0 | AL3: 0 | AM3: 0 | AN3: 0 | AO3: 0 | AP3: 0 | AQ3: 0 | AR3: 1 | AS3: =SUM(J3:Q3) -> 6 | AT3: =SUM(R3:AR3) -> 9 | AU3: 画面美术场景；音乐音效配音；动作打击手感；引导迷路单线；整体完成度；推荐价值判断；西游悟空符号；童年记忆情怀；国产3A身份期待 | AV3: =IF(AT3>0,1,0) -> 1 | AW3: =IF(AT3=0,1,0) -> 0 | AX3: =IF(AT3>=8,1,0) -> 1 | AY3: 10 | AZ3: 正面 | BA3: P | BB3: 原文
A4: CN-P-003 | B4: 中文 | C4: 推荐 | D4: 328 | E4: 13 | F4: 106.6 | G4: 2024-08-20 | H4: 献给中国玩家的一封情书 ： 你曾无数次地在游戏世界里扮演着不同的角色：你曾纵马驰骋在狂野的美国西部，书写一代枭雄落幕前的史诗，最终见证了一位想成为好人or坏人的传奇牛仔—— “亚瑟·摩根 ”以悲剧的形式谢幕；你曾在希腊神话里屠戮众神，完成自己的复仇，挣脱命运的束缚，最终成为新的 “战神”——奎爷，于北欧国度中与儿子续写传奇；你曾扮演一位被称为 “白狼” 的猎魔人，在追寻身负上古之血的养女时沉迷于昆特牌亦或是打桩等活动，与此同时书写着属于“利维亚的杰洛特” 最后的故事；你曾徘徊于历史与现代，在文艺复兴的欧洲见证了一代刺客大师的蜕变，并造就了一代代刺客的薪火相传，只为捍卫属于他们的 “信条” ；你曾甘为 “褪色者” ，在交界地中向众神发起挑战，受尽苦痛，磨练技术，终究如愿成为“艾尔登之王”，开辟了一个新的时代；你曾扮演一位名为 “狼” 的忍者，穿梭于日本战国时代的各个角落，历经战乱与冲突，不断提升自身实力挑战各路奇能异士，只为履行职责——保护主人；你曾以 “勇者林克” 的身份在未知的神殿醒来，跨越整个海拉鲁大陆，凭借自己的创造性与想象力自由地探索，上演了一出拯救公主的经典戏码，诠释了忠诚与勇气的可贵；你也曾为实现那理想中的“美国梦”，自由地在洛圣都中做想做的事，扮演那三个男人闯出了一片天地，最终也毫不犹豫地选择以 “死亡之愿” 谢幕…… （其余请自行补充）在你曾扮演过的这些游戏角色中，你可能拯救了无数个支离破碎的世界，亦或是在许多不同的世界中自由地探索冒险，书写了无数动人心弦的故事，了解了异国他乡的风土人情，感受到了不同国家文化展现的魅力。然而在看着身边的一个个同龄人被国内的一些同质化网游和手游蚕食甚至沉迷于为皮肤氪金时，难免也会不甘地想到：我们什么时候才能做出这样的好游戏啊... 直到2020.8.20这一天，一个名不经传的公司默默地发布了一则预告片，这个带着国风标签的3A大作就此出现在了大众的视野里，重燃起了国单的希望。而四年后的这一天，你终于能够来到这个熟悉而又陌生的世界，扮演一只似曾相识的猴子，亦或是儿时耳熟能详的齐天大圣，书写独属于家乡的故事，在这充满着归属感的4k蓝光超高清修复版的“西游记”里作为一位天命人重新踏上一段熟悉的征程，直面你的天命……现在很多游戏都适配了简中甚至拥有中配了，但我还是想说： 以前是：Language——简体中文 这次是：语言——English！！！ 最后，虽然目前某些所谓的评分争议很大，可能低于很多人的期望（个人而言挺不甘心的）但是在承载了众多国内外玩家以及制作者多年的期盼，甚至已经破圈的前提下，他们已经用行动证明了国单市场是存在的，因此我认为黑神话：悟空不仅已经做到了一款国单玩家心中的3A游戏该有的水平，也让人们有了重温经典的动力，毕竟“踏上取经路，比抵达灵山更重要！”于某些更早一批的玩家而言，这一天不止等了四年，更不是七年，而是四十余年......再于中国文化而言，始于明朝吴承恩的《西游记》原著，于1961年最早的动画电影《大圣归来》开始，到经典的86版的《西游记》，95年星爷的《大话西游》，99的动画片《西游记》，15年国产动画电影回归之作《西游记之大圣归来》，再到如今横空出世的《黑神话：悟空》，大圣从始至终都在引领我们做出改变....所以无论如何，它都是独属于我们国人的浪漫。我希望游科的这群理想主义者在这部白骨之后以七年磨一剑的作品能够大卖，将我们这款中国人自己做的第一款真正意义上的3A大作带向世界。毕竟就目前国内急功近利的游戏环境而言，眼下正是黑神话，也只有黑神话，才能够打破国内外的偏见，重振国单市场，带领中国游戏真正地立足于世界，给国内那些所谓的大厂树立一个真正的榜样，做我们曾不敢做的梦。 事实证明游戏早已不仅仅是娱乐，更不只是圈钱的“电子鸦片”，而是一种能将经典再现的艺术，更是一种文化输出的全新途径。毋庸置疑的是我认为这款游戏已足矣成为中国游戏史上的一块里程碑，它也有资格代表着第九艺术传达我们的文化，为咱们的文化正名。而我也坚信这仅仅是一个开始。 ———愿云宫迅音奏响于世界之巅 接着耍🐒去了 | I4: 献给中国玩家的一封情书 ： 你曾无数次地在游戏世界里扮演着不同的角色：你曾纵马驰骋在狂野的美国西部，书写一代枭雄落幕前的史诗，最终见证了一位想成为好人or坏人的传奇牛仔—— “亚瑟·摩根 ”以悲剧的形式谢幕；你曾在希腊神话里屠戮众神，完成自己的复仇，挣脱命运的束缚，最终成为新的 “战神”——奎爷，于北欧国度中与儿子续写传奇；你曾扮演一位被称为 “白狼” 的猎魔人，在追寻身负上古之血的养女时沉迷于昆特牌亦或是打桩等活动，与此同时书写着属于“利维亚的杰洛特” 最后的故事；你曾徘徊于历史与现代，在文艺复兴的欧洲见证了一代刺客大师的蜕变，并造就了一代代刺客的薪火相传，只为捍卫属于他们的 “信条” ；你曾甘为 “褪色者” ，在交界地中向众神发起挑战，受尽苦痛，磨练技术，终究如愿成为“艾尔登之王”，开辟了一个新的时代；你曾扮演一位名为 “狼” 的忍者，穿梭于日本战国时代的各个角落，历经战乱与冲突，不断提升自身实力挑战各路奇能异士，只为履行职责——保护主人；你曾以 “勇者林克” 的身份在未知的神殿醒来，跨越整个海拉鲁大陆，凭借自己的创造性与想象力自由地探索，上演了一出拯救公主的经典戏码，诠释了忠诚与勇气的可贵；你也曾为实现那理想中的“美国梦”，自由地在洛圣都中做想做的事，扮演那三个男人闯出了一片天地，最终也毫不犹豫地选择以 “死亡之愿” 谢幕…… （其余请自行补充）在你曾扮演过的这些游戏角色中，你可能拯救了无数个支离破碎的世界，亦或是在许多不同的世界中自由地探索冒险，书写了无数动人心弦的故事，了解了异国他乡的风土人情，感受到了不同国家文化展现的魅力。然而在看着身边的一个个同龄人被国内的一些同质化网游和手游蚕食甚至沉迷于为皮肤氪金时，难免也会不甘地想到：我们什么时候才能做出这样的好游戏啊... 直到2020.8.20这一天，一个名不经传的公司默默地发布了一则预告片，这个带着国风标签的3A大作就此出现在了大众的视野里，重燃起了国单的希望。而四年后的这一天，你终于能够来到这个熟悉而又陌生的世界，扮演一只似曾相识的猴子，亦或是儿时耳熟能详的齐天大圣，书写独属于家乡的故事，在这充满着归属感的4k蓝光超高清修复版的“西游记”里作为一位天命人重新踏上一段熟悉的征程，直面你的天命……现在很多游戏都适配了简中甚至拥有中配了，但我还是想说： 以前是：Language——简体中文 这次是：语言——English！！！ 最后，虽然目前某些所谓的评分争议很大，可能低于很多人的期望（个人而言挺不甘心的）但是在承载了众多国内外玩家以及制作者多年的期盼，甚至已经破圈的前提下，他们已经用行动证明了国单市场是存在的，因此我认为黑神话：悟空不仅已经做到了一款国单玩家心中的3A游戏该有的水平，也让人们有了重温经典的动力，毕竟“踏上取经路，比抵达灵山更重要！”于某些更早一批的玩家而言，这一天不止等了四年，更不是七年，而是四十余年......再于中国文化而言，始于明朝吴承恩的《西游记》原著，于1961年最早的动画电影《大圣归来》开始，到经典的86版的《西游记》，95年星爷的《大话西游》，99的动画片《西游记》，15年国产动画电影回归之作《西游记之大圣归来》，再到如今横空出世的《黑神话：悟空》，大圣从始至终都在引领我们做出改变....所以无论如何，它都是独属于我们国人的浪漫。我希望游科的这群理想主义者在这部白骨之后以七年磨一剑的作品能够大卖，将我们这款中国人自己做的第一款真正意义上的3A大作带向世界。毕竟就目前国内急功近利的游戏环境而言，眼下正是黑神话，也只有黑神话，才能够打破国内外的偏见，重振国单市场，带领中国游戏真正地立足于世界，给国内那些所谓的大厂树立一个真正的榜样，做我们曾不敢做的梦。 事实证明游戏早已不仅仅是娱乐，更不只是圈钱的“电子鸦片”，而是一种能将经典再现的艺术，更是一种文化输出的全新途径。毋庸置疑的是我认为这款游戏已足矣成为中国游戏史上的一块里程碑，它也有资格代表着第九艺术传达我们的文化，为咱们的文化正名。而我也坚信这仅仅是一个开始。 ———愿云宫迅音奏响于世界之巅 接着耍🐒去了 | J4: =IF(SUM(R4:T4)>0,1,0) -> 1 | K4: =IF(SUM(U4:Y4)>0,1,0) -> 1 | L4: =IF(SUM(Z4:AC4)>0,1,0) -> 1 | M4: =IF(SUM(AD4:AF4)>0,1,0) -> 0 | N4: =IF(SUM(AG4:AH4)>0,1,0) -> 1 | O4: =IF(SUM(AI4:AL4)>0,1,0) -> 1 | P4: =IF(SUM(AM4:AQ4)>0,1,0) -> 1 | Q4: =IF(AR4>0,1,0) -> 1 | R4: 1 | S4: 1 | T4: 1 | U4: 0 | V4: 0 | W4: 1 | X4: 1 | Y4: 0 | Z4: 0 | AA4: 0 | AB4: 1 | AC4: 0 | AD4: 0 | AE4: 0 | AF4: 0 | AG4: 1 | AH4: 1 | AI4: 1 | AJ4: 1 | AK4: 1 | AL4: 1 | AM4: 0 | AN4: 0 | AO4: 0 | AP4: 0 | AQ4: 1 | AR4: 1 | AS4: =SUM(J4:Q4) -> 7 | AT4: =SUM(R4:AR4) -> 14 | AU4: 画面美术场景；音乐音效配音；演出角色怪物设计；难度挑战；锁定视角；探索隐藏支线；整体完成度；推荐价值判断；西游悟空符号；童年记忆情怀；本国媒介路径；中国文化宗教语言审美；角色期待意义偏移；国产3A身份期待 | AV4: =IF(AT4>0,1,0) -> 1 | AW4: =IF(AT4=0,1,0) -> 0 | AX4: =IF(AT4>=8,1,0) -> 1 | AY4: 68.5 | AZ4: 正面 | BA4: P | BB4: 原文
A5: CN-P-004 | B5: 中文 | C5: 推荐 | D5: 259 | E5: 8 | F5: 71.3 | G5: 2024-08-20 | H5: 四年等待不负期望 依稀记得，2020年8月20日，对于大多数人来说，本是平常的一天，但一款名为《黑神话悟空》的游戏发布了第一支PV实机演示视频。 欢迎关注 网易UU鉴赏家培养计划 关注UU加速器VX公众号，回复“steam”，获得专属玩家群邀请。 经典的说书人旁白，贴近原著高度还原的神通变化，如意金箍棒，定身术和分身术，激战刀郎教头与灵虚子的战斗场景，压迫感十足的四大天王与孙悟空对峙等内容都让国内的玩家沸腾了——首款国产3A游戏，还是以大家耳熟能详的西游记作为背景故事！ 视角回到现在，这段视频已不再是想象的片段，苦等4年，《黑神话悟空》终于发售了！它也没有辜负玩家们的期待，目前我已爆肝打到第六章，游戏质量早已远远超出我的预期，我必须发自真心的说一句《黑神话悟空》牛逼！ 玩法心得 先分享下攻略吧，说实话，目前很多人吹的棍花流其实到了游戏中后期强度真的一般，我来给大家推荐一套比较强力的狂战暴力玩法！ 套装：红孩儿四件套（25增伤，30易伤） 武器：天龙棍（140攻击，9暴率，蓄力引雷上身，攻击附带雷伤害） 饰品：必带两个金纽（满血加攻击一个，仙胞石片（攻击无视抗性） 葫芦：妙仙葫芦＋龙膏（倒马毒钩，双冠血，蜂山石髓，净瓶柳叶） 法宝：绣花针 精魄：疯虎 输出手法：进门吃龙光倍力丸，聚珍伏虎丸（其余药丸可以考虑吃霸体或者棍势积累），之后开禁字法，蓄满等身上落雷。基本大部分BOSS都可以2到4棍子直接敲死。 千秋万代永相颂，七十二变显神通（战斗系统） 作为一款ARPG游戏，本作的战斗体验相当爽快，玩家扮演的“天命人”可以使用类似《仁王》架势的三种棍法，每种棍法都有独特的重攻击以及普攻接重攻的切手技。 劈棍重击可移动自由态蓄力，切手技可GP（看破，弹反）敌人攻击并进行反击，是勇猛激进的棍法。 立棍重击可免疫大部分伤害竖立而上进行蓄力，切手技为大范围扫荡攻击，是适合应对群攻的棍法。 戳棍重击能超远距离攻击并击退敌人，切手技则能够自由拉开与敌人之间的距离，再合适的时机撤步还能触发一些特殊效果，是最灵活多变的棍法。 根据战况不同使用不同的棍法，会有一种兵来将挡,见招拆招的爽快感！ 除了棍法，游戏还有法术，变化，法宝等多种辅助战斗的手段！法术皆还原了原作大圣的神通，例如定住敌人的定身术，拔下一根毫毛召唤出万千分身的分身术！变化则是打败支线BOSS后消耗神力可以化身为这些BOSS，也有独特的精魄技可在短时间内幻化为妖怪形态进行攻击（妖怪技），至于法宝也是原著中各种耳熟能详的法宝，对特定敌人使用特定法宝会有一些意向不到的强力效果。 这些元素结合在一起，形成了一套没有太大上手门槛又充满可玩性的战斗系统 ，唯一的瑕疵是三个棍法普攻模组没有变化，有点小失望。 油锅刀山无所惧，入海遁地破苍穹（关卡及支线设计） 本作采用的是关卡制，每一大关都是一个规模庞大的箱庭小世界。BOSS的数量也突出一个量大管饱，有多达80多个BOSS。此外其中有三分之一是隐藏BOSS，需要玩家通过支线或者探索才能发现他们。许多BOSS还有二阶段同时有着不低的挑战性，各种招式动作也完美还原了原作，可以说本作的BOSS战也是一大亮点。但部分大型BOSS的视角锁定做的有点不尽人意，例如第三章的亢金龙，视角乱飘，攻击很容易落空。部分地图的设计跟指引也存在些许瑕疵，第二关跟第三关好多岔路感觉都不明所以，还有一些看似能走的路结果是空气墙也有点影响玩家的游玩体验。 不过瑕不掩瑜，量大管饱又富有挑战性的BOSS战完全弥补了这些缺点。 长生不死何须恋？不畏神权铁骨铮 （养成系统） 本作在养成方面也不算复杂，没有魂类游戏属性加点，只有个简单易懂的技能树。 大多数技能都能直接提升角色性能跟增加新的动作，当然也有单纯的提升数值的强化，技能随时可在土地庙无代价洗点，最后也能全部点满。（我目前还没通关，不确定高周目能不能全部点满，但我个人感觉应该是能全部点满） 除了技能树，当然少不了装备系统，游戏的装备可以通过各种素材进行打造，每套防具跟武器还有各种特殊的套装效果。打败一些头目时还能获得叫做“玲珑内丹”的道具，交予NPC炼丹后可以永久提升属性上限。 回血道具“葫芦”也能强化自由组合各种效果，使回复机制更加有趣。 关于云存档 本作在Steam平台与WeGame平台均有发售，，两个平台也均有自己的云存档，但是偶尔会遇到云存档上传下载不成功的时候。（特别是福建地区的小伙伴，云存档经常抽风），所以为云存档设置保险还是很有必要的，UU加速器的云存档功能，无论是换电脑玩时存档误覆盖，还是各种问题导致存档损坏。相信这样惨痛的经历依然时常发生，但这次决不能。即便不是会员，也可以免费使用UU云存档功能，全程无需手动，完全自动备份。 并且保留多个档位，面对一些一周目容易错过的支线或者隐藏BOSS，也可以多一个备份，免去二周目烦恼，直接在备份的档位再次选择即可。 另外UU也提供了UU存档市集， C酱、黑桐谷歌等知名主播存档，玩家可以下载下来跟着主播进度玩，多种攻略配合存档，手把手教，包爽！此外还有各种全成就档、全收集档、boss rush档等。总之，你需要的存档，这里都有。 除此之外现在还有抽奖活动，试试自己的手气，说不定就能白嫖游戏直接回本。 结语 顶尖的美术，还原原作各种宏大场景的画面表现，简单易上手又有趣的战斗跟养成系统，量大管饱富有挑战性的BOSS战，《黑神话悟空》是毫无疑问的国产神作！ 甚至对于国内玩家而言，这部作品的意义早已超越了一款普通游戏的范畴，游科现在走的正是一条国内近十几年来“前无古人”的道路——制作一款真正意义上的3A大作！ 希望国内还会有更多有志之士挑起游戏行业的大旗，接过游科的接力棒，将我们国家五千年的深厚文化底蕴展现出去。 | I5: 四年等待不负期望 依稀记得，2020年8月20日，对于大多数人来说，本是平常的一天，但一款名为《黑神话悟空》的游戏发布了第一支PV实机演示视频。 欢迎关注 网易UU鉴赏家培养计划 关注UU加速器VX公众号，回复“steam”，获得专属玩家群邀请。 经典的说书人旁白，贴近原著高度还原的神通变化，如意金箍棒，定身术和分身术，激战刀郎教头与灵虚子的战斗场景，压迫感十足的四大天王与孙悟空对峙等内容都让国内的玩家沸腾了——首款国产3A游戏，还是以大家耳熟能详的西游记作为背景故事！ 视角回到现在，这段视频已不再是想象的片段，苦等4年，《黑神话悟空》终于发售了！它也没有辜负玩家们的期待，目前我已爆肝打到第六章，游戏质量早已远远超出我的预期，我必须发自真心的说一句《黑神话悟空》牛逼！ 玩法心得 先分享下攻略吧，说实话，目前很多人吹的棍花流其实到了游戏中后期强度真的一般，我来给大家推荐一套比较强力的狂战暴力玩法！ 套装：红孩儿四件套（25增伤，30易伤） 武器：天龙棍（140攻击，9暴率，蓄力引雷上身，攻击附带雷伤害） 饰品：必带两个金纽（满血加攻击一个，仙胞石片（攻击无视抗性） 葫芦：妙仙葫芦＋龙膏（倒马毒钩，双冠血，蜂山石髓，净瓶柳叶） 法宝：绣花针 精魄：疯虎 输出手法：进门吃龙光倍力丸，聚珍伏虎丸（其余药丸可以考虑吃霸体或者棍势积累），之后开禁字法，蓄满等身上落雷。基本大部分BOSS都可以2到4棍子直接敲死。 千秋万代永相颂，七十二变显神通（战斗系统） 作为一款ARPG游戏，本作的战斗体验相当爽快，玩家扮演的“天命人”可以使用类似《仁王》架势的三种棍法，每种棍法都有独特的重攻击以及普攻接重攻的切手技。 劈棍重击可移动自由态蓄力，切手技可GP（看破，弹反）敌人攻击并进行反击，是勇猛激进的棍法。 立棍重击可免疫大部分伤害竖立而上进行蓄力，切手技为大范围扫荡攻击，是适合应对群攻的棍法。 戳棍重击能超远距离攻击并击退敌人，切手技则能够自由拉开与敌人之间的距离，再合适的时机撤步还能触发一些特殊效果，是最灵活多变的棍法。 根据战况不同使用不同的棍法，会有一种兵来将挡,见招拆招的爽快感！ 除了棍法，游戏还有法术，变化，法宝等多种辅助战斗的手段！法术皆还原了原作大圣的神通，例如定住敌人的定身术，拔下一根毫毛召唤出万千分身的分身术！变化则是打败支线BOSS后消耗神力可以化身为这些BOSS，也有独特的精魄技可在短时间内幻化为妖怪形态进行攻击（妖怪技），至于法宝也是原著中各种耳熟能详的法宝，对特定敌人使用特定法宝会有一些意向不到的强力效果。 这些元素结合在一起，形成了一套没有太大上手门槛又充满可玩性的战斗系统 ，唯一的瑕疵是三个棍法普攻模组没有变化，有点小失望。 油锅刀山无所惧，入海遁地破苍穹（关卡及支线设计） 本作采用的是关卡制，每一大关都是一个规模庞大的箱庭小世界。BOSS的数量也突出一个量大管饱，有多达80多个BOSS。此外其中有三分之一是隐藏BOSS，需要玩家通过支线或者探索才能发现他们。许多BOSS还有二阶段同时有着不低的挑战性，各种招式动作也完美还原了原作，可以说本作的BOSS战也是一大亮点。但部分大型BOSS的视角锁定做的有点不尽人意，例如第三章的亢金龙，视角乱飘，攻击很容易落空。部分地图的设计跟指引也存在些许瑕疵，第二关跟第三关好多岔路感觉都不明所以，还有一些看似能走的路结果是空气墙也有点影响玩家的游玩体验。 不过瑕不掩瑜，量大管饱又富有挑战性的BOSS战完全弥补了这些缺点。 长生不死何须恋？不畏神权铁骨铮 （养成系统） 本作在养成方面也不算复杂，没有魂类游戏属性加点，只有个简单易懂的技能树。 大多数技能都能直接提升角色性能跟增加新的动作，当然也有单纯的提升数值的强化，技能随时可在土地庙无代价洗点，最后也能全部点满。（我目前还没通关，不确定高周目能不能全部点满，但我个人感觉应该是能全部点满） 除了技能树，当然少不了装备系统，游戏的装备可以通过各种素材进行打造，每套防具跟武器还有各种特殊的套装效果。打败一些头目时还能获得叫做“玲珑内丹”的道具，交予NPC炼丹后可以永久提升属性上限。 回血道具“葫芦”也能强化自由组合各种效果，使回复机制更加有趣。 关于云存档 本作在Steam平台与WeGame平台均有发售，，两个平台也均有自己的云存档，但是偶尔会遇到云存档上传下载不成功的时候。（特别是福建地区的小伙伴，云存档经常抽风），所以为云存档设置保险还是很有必要的，UU加速器的云存档功能，无论是换电脑玩时存档误覆盖，还是各种问题导致存档损坏。相信这样惨痛的经历依然时常发生，但这次决不能。即便不是会员，也可以免费使用UU云存档功能，全程无需手动，完全自动备份。 并且保留多个档位，面对一些一周目容易错过的支线或者隐藏BOSS，也可以多一个备份，免去二周目烦恼，直接在备份的档位再次选择即可。 另外UU也提供了UU存档市集， C酱、黑桐谷歌等知名主播存档，玩家可以下载下来跟着主播进度玩，多种攻略配合存档，手把手教，包爽！此外还有各种全成就档、全收集档、boss rush档等。总之，你需要的存档，这里都有。 除此之外现在还有抽奖活动，试试自己的手气，说不定就能白嫖游戏直接回本。 结语 顶尖的美术，还原原作各种宏大场景的画面表现，简单易上手又有趣的战斗跟养成系统，量大管饱富有挑战性的BOSS战，《黑神话悟空》是毫无疑问的国产神作！ 甚至对于国内玩家而言，这部作品的意义早已超越了一款普通游戏的范畴，游科现在走的正是一条国内近十几年来“前无古人”的道路——制作一款真正意义上的3A大作！ 希望国内还会有更多有志之士挑起游戏行业的大旗，接过游科的接力棒，将我们国家五千年的深厚文化底蕴展现出去。 | J5: =IF(SUM(R5:T5)>0,1,0) -> 1 | K5: =IF(SUM(U5:Y5)>0,1,0) -> 1 | L5: =IF(SUM(Z5:AC5)>0,1,0) -> 1 | M5: =IF(SUM(AD5:AF5)>0,1,0) -> 1 | N5: =IF(SUM(AG5:AH5)>0,1,0) -> 1 | O5: =IF(SUM(AI5:AL5)>0,1,0) -> 1 | P5: =IF(SUM(AM5:AQ5)>0,1,0) -> 1 | Q5: =IF(AR5>0,1,0) -> 1 | R5: 1 | S5: 0 | T5: 0 | U5: 1 | V5: 1 | W5: 1 | X5: 1 | Y5: 0 | Z5: 1 | AA5: 1 | AB5: 1 | AC5: 1 | AD5: 1 | AE5: 0 | AF5: 0 | AG5: 1 | AH5: 1 | AI5: 1 | AJ5: 0 | AK5: 0 | AL5: 1 | AM5: 0 | AN5: 0 | AO5: 0 | AP5: 1 | AQ5: 0 | AR5: 1 | AS5: =SUM(J5:Q5) -> 8 | AT5: =SUM(R5:AR5) -> 16 | AU5: 画面美术场景；动作打击手感；Boss战斗节奏；难度挑战；锁定视角；地图路线；空气墙可达性；探索隐藏支线；引导迷路单线；优化帧率；整体完成度；推荐价值判断；西游悟空符号；中国文化宗教语言审美；外部资料依赖；国产3A身份期待 | AV5: =IF(AT5>0,1,0) -> 1 | AW5: =IF(AT5=0,1,0) -> 0 | AX5: =IF(AT5>=8,1,0) -> 1 | AY5: 81.5 | AZ5: 正面 | BA5: P | BB5: 原文
A6: CN-P-005 | B6: 中文 | C6: 推荐 | D6: 48 | E6: 1 | F6: 128.4 | G6: 2024-08-20 | H6: 53小时，一周目完成，可以评测了。《黑神话：悟空》第九艺术，实至名归，美术之精良，音乐之精美，打斗之精彩...再多的溢美之词其实都不能表达它带给我的震撼。我从没有在其他游戏中如此频繁地打开拍照模式，部分关卡的美术资源真的是铺张到“令人发指”的地步。部分Boss设计如毒敌大王、大圣残躯、虎先锋、亢金龙...着实让人印象深刻，大开大合、见招拆招是真的做出了中式武侠过招的感觉，有的Boss真的算比较难的，但与魂类不同，这些Boss对我而言不会给人一种“我完全过不了”的坐牢感觉，很多时候都是感觉“差一点，应该马上就过了”。即使失误挨打，被一套带走，也会不由叹一句“这Boss设计好酷”。诚然，作为中国玩家，从2020年8月20日开始，我就带着各种光环来看待这个游戏，但是即使抛开国产、西游、第一部3A...在4年之后的今天，它依然是一款足够出色的游戏，一款足够“好玩”的游戏，一款足够“用心”的游戏，更是一款足够“有深度”的游戏。即使夸赞这么多，也不能说它就是“完美”的，相反，关卡设计，引导，还是体现出了不可忽视的短板，这类问题导致的割裂感，在第五、六章节极为明显。同时，与巨大体型Boss的战斗交互，也是需要加强的。这类需要靠经验积累的能力，还是稍显稚嫩，但也显得真实，毕竟这真的是中国3A单机市场的第一作，这种“不完美”，已经比我预想的好了太多。求其上者，得其中。能在全球范围内取得如今的口碑，我其实可以隐约感受到它在开发过程中所耗费的心血与煎熬。在国内，单机游戏这条路，依然是艰难的。但，这个世界需要“务实的理想主义者”，踏上西行之旅，比抵达灵山，更重要。感谢"游戏科学"带来的这场西游大梦，也希望更多的“游戏科学”拓宽这条刚开辟的小路，一步步百花齐放，给全球玩家带来更多的感动。 | I6: 53小时，一周目完成，可以评测了。《黑神话：悟空》第九艺术，实至名归，美术之精良，音乐之精美，打斗之精彩...再多的溢美之词其实都不能表达它带给我的震撼。我从没有在其他游戏中如此频繁地打开拍照模式，部分关卡的美术资源真的是铺张到“令人发指”的地步。部分Boss设计如毒敌大王、大圣残躯、虎先锋、亢金龙...着实让人印象深刻，大开大合、见招拆招是真的做出了中式武侠过招的感觉，有的Boss真的算比较难的，但与魂类不同，这些Boss对我而言不会给人一种“我完全过不了”的坐牢感觉，很多时候都是感觉“差一点，应该马上就过了”。即使失误挨打，被一套带走，也会不由叹一句“这Boss设计好酷”。诚然，作为中国玩家，从2020年8月20日开始，我就带着各种光环来看待这个游戏，但是即使抛开国产、西游、第一部3A...在4年之后的今天，它依然是一款足够出色的游戏，一款足够“好玩”的游戏，一款足够“用心”的游戏，更是一款足够“有深度”的游戏。即使夸赞这么多，也不能说它就是“完美”的，相反，关卡设计，引导，还是体现出了不可忽视的短板，这类问题导致的割裂感，在第五、六章节极为明显。同时，与巨大体型Boss的战斗交互，也是需要加强的。这类需要靠经验积累的能力，还是稍显稚嫩，但也显得真实，毕竟这真的是中国3A单机市场的第一作，这种“不完美”，已经比我预想的好了太多。求其上者，得其中。能在全球范围内取得如今的口碑，我其实可以隐约感受到它在开发过程中所耗费的心血与煎熬。在国内，单机游戏这条路，依然是艰难的。但，这个世界需要“务实的理想主义者”，踏上西行之旅，比抵达灵山，更重要。感谢"游戏科学"带来的这场西游大梦，也希望更多的“游戏科学”拓宽这条刚开辟的小路，一步步百花齐放，给全球玩家带来更多的感动。 | J6: =IF(SUM(R6:T6)>0,1,0) -> 1 | K6: =IF(SUM(U6:Y6)>0,1,0) -> 1 | L6: =IF(SUM(Z6:AC6)>0,1,0) -> 1 | M6: =IF(SUM(AD6:AF6)>0,1,0) -> 0 | N6: =IF(SUM(AG6:AH6)>0,1,0) -> 1 | O6: =IF(SUM(AI6:AL6)>0,1,0) -> 1 | P6: =IF(SUM(AM6:AQ6)>0,1,0) -> 0 | Q6: =IF(AR6>0,1,0) -> 1 | R6: 1 | S6: 1 | T6: 0 | U6: 0 | V6: 1 | W6: 0 | X6: 0 | Y6: 0 | Z6: 1 | AA6: 0 | AB6: 0 | AC6: 1 | AD6: 0 | AE6: 0 | AF6: 0 | AG6: 1 | AH6: 1 | AI6: 1 | AJ6: 0 | AK6: 0 | AL6: 0 | AM6: 0 | AN6: 0 | AO6: 0 | AP6: 0 | AQ6: 0 | AR6: 1 | AS6: =SUM(J6:Q6) -> 6 | AT6: =SUM(R6:AR6) -> 9 | AU6: 画面美术场景；音乐音效配音；Boss战斗节奏；地图路线；引导迷路单线；整体完成度；推荐价值判断；西游悟空符号；国产3A身份期待 | AV6: =IF(AT6>0,1,0) -> 1 | AW6: =IF(AT6=0,1,0) -> 0 | AX6: =IF(AT6>=8,1,0) -> 1 | AY6: 43 | AZ6: 正面 | BA6: P | BB6: 原文
A7: CN-P-006 | B7: 中文 | C7: 推荐 | D7: 51 | E7: 1 | F7: 20.1 | G7: 2024-08-20 | H7: 为了纪念这个游戏转眼间到了发售的日子，就让我想到了一个在这游戏发布的前前三天，正好是我一个朋友的生日。在2021年8月17日的时候，他说真希望能在我下一个生日之前发售，真希望能早点玩到国产魂类的3A游戏。因为2020年8月20日，游戏发布公布首段实机演示视频，拉满了他的期待。在2022年8月17日的时候，他说游戏用上新的引擎，也公示了更多信息，应该不久就要发售了吧。因为2021年8月20日开发团队再次释出一支12分钟的演示预告，由虚幻引擎5实机录制。在2023年8月17日的时候，我想他会说希望剧情能好一点，不要砸了这个招牌就好了。因为2022年8月20日，开发团队发布一支6分20秒剧情短片。在2023年8月17日的时候，我想他一定会带着我去杭州。因为2023年8月20日在杭州举办线下试玩会，体验内容包括多个首领挑战以及独立的关卡片段。时间一转而过就是五年，就想人们常说的，“你永远都不知道意外和明天到底哪一个会先来临”。可是到了游戏发售的日子，他却什么也说不了了。在去年迈入春天的时候，他却倒在了医院惨白的病床上，我当时就在一旁看着他的监护器的波纹逐渐趋近于水平，当什么都化为0的时候，我就知道和我随行那么多年的人，和我玩了那么久游戏的人，却还没能看到他期待的游戏上架就先离去。在2021年的时候，他检测出肺癌晚期，当时不相信自己长期不停的咳嗽居然是肺癌的症状。在2022年的时候，他辗转于医院的各个科室，会诊各个名医，只为了延续他的生命。在2023年的冬天，他给我看了他的病例报告单，上面写了19项病症，他说看到这么多癌转移，还有什么治疗的机会。于是他做了一个决定，他要把自己捐献给医学事业，当时我很震惊也很感动，我想他做了他能做的了吧。他很普通，也很平凡，但是在最后的那一刻，他得到了他主治医生的尊重。人生就是一场很大的舞台戏，如映画一般飘闪而过，并且不能用SL大法，无伤全成就。从认识他到现在，已经过去了十几年了，他走过那么多挫折和磨难，就像过九九八十一难一样，一个一个的度过，直到自己生命的尽头。我想也许他这个样子，就像孙猴子一样，上蹿下跳，总是在不断地折腾，最后也能在西天成为斗战胜佛…… | I7: 为了纪念这个游戏转眼间到了发售的日子，就让我想到了一个在这游戏发布的前前三天，正好是我一个朋友的生日。在2021年8月17日的时候，他说真希望能在我下一个生日之前发售，真希望能早点玩到国产魂类的3A游戏。因为2020年8月20日，游戏发布公布首段实机演示视频，拉满了他的期待。在2022年8月17日的时候，他说游戏用上新的引擎，也公示了更多信息，应该不久就要发售了吧。因为2021年8月20日开发团队再次释出一支12分钟的演示预告，由虚幻引擎5实机录制。在2023年8月17日的时候，我想他会说希望剧情能好一点，不要砸了这个招牌就好了。因为2022年8月20日，开发团队发布一支6分20秒剧情短片。在2023年8月17日的时候，我想他一定会带着我去杭州。因为2023年8月20日在杭州举办线下试玩会，体验内容包括多个首领挑战以及独立的关卡片段。时间一转而过就是五年，就想人们常说的，“你永远都不知道意外和明天到底哪一个会先来临”。可是到了游戏发售的日子，他却什么也说不了了。在去年迈入春天的时候，他却倒在了医院惨白的病床上，我当时就在一旁看着他的监护器的波纹逐渐趋近于水平，当什么都化为0的时候，我就知道和我随行那么多年的人，和我玩了那么久游戏的人，却还没能看到他期待的游戏上架就先离去。在2021年的时候，他检测出肺癌晚期，当时不相信自己长期不停的咳嗽居然是肺癌的症状。在2022年的时候，他辗转于医院的各个科室，会诊各个名医，只为了延续他的生命。在2023年的冬天，他给我看了他的病例报告单，上面写了19项病症，他说看到这么多癌转移，还有什么治疗的机会。于是他做了一个决定，他要把自己捐献给医学事业，当时我很震惊也很感动，我想他做了他能做的了吧。他很普通，也很平凡，但是在最后的那一刻，他得到了他主治医生的尊重。人生就是一场很大的舞台戏，如映画一般飘闪而过，并且不能用SL大法，无伤全成就。从认识他到现在，已经过去了十几年了，他走过那么多挫折和磨难，就像过九九八十一难一样，一个一个的度过，直到自己生命的尽头。我想也许他这个样子，就像孙猴子一样，上蹿下跳，总是在不断地折腾，最后也能在西天成为斗战胜佛…… | J7: =IF(SUM(R7:T7)>0,1,0) -> 0 | K7: =IF(SUM(U7:Y7)>0,1,0) -> 1 | L7: =IF(SUM(Z7:AC7)>0,1,0) -> 1 | M7: =IF(SUM(AD7:AF7)>0,1,0) -> 0 | N7: =IF(SUM(AG7:AH7)>0,1,0) -> 1 | O7: =IF(SUM(AI7:AL7)>0,1,0) -> 0 | P7: =IF(SUM(AM7:AQ7)>0,1,0) -> 0 | Q7: =IF(AR7>0,1,0) -> 1 | R7: 0 | S7: 0 | T7: 0 | U7: 0 | V7: 1 | W7: 1 | X7: 0 | Y7: 0 | Z7: 1 | AA7: 0 | AB7: 0 | AC7: 0 | AD7: 0 | AE7: 0 | AF7: 0 | AG7: 1 | AH7: 0 | AI7: 0 | AJ7: 0 | AK7: 0 | AL7: 0 | AM7: 0 | AN7: 0 | AO7: 0 | AP7: 0 | AQ7: 0 | AR7: 1 | AS7: =SUM(J7:Q7) -> 4 | AT7: =SUM(R7:AR7) -> 5 | AU7: Boss战斗节奏；难度挑战；地图路线；整体完成度；国产3A身份期待 | AV7: =IF(AT7>0,1,0) -> 1 | AW7: =IF(AT7=0,1,0) -> 0 | AX7: =IF(AT7>=8,1,0) -> 0 | AY7: 19.5 | AZ7: 正面 | BA7: P | BB7: 原文
A8: CN-P-007 | B8: 中文 | C8: 推荐 | D8: 20171 | E8: 545 | F8: 51.1 | G8: 2024-08-20 | H8: 一从大地起风雷，便有精生白骨堆。僧是愚氓犹可训，妖为鬼蜮必成灾。金猴奋起千钧棒，玉宇澄清万里埃。今日欢呼孙大圣，只缘妖雾又重来。 | I8: 一从大地起风雷，便有精生白骨堆。僧是愚氓犹可训，妖为鬼蜮必成灾。金猴奋起千钧棒，玉宇澄清万里埃。今日欢呼孙大圣，只缘妖雾又重来。 | J8: =IF(SUM(R8:T8)>0,1,0) -> 0 | K8: =IF(SUM(U8:Y8)>0,1,0) -> 0 | L8: =IF(SUM(Z8:AC8)>0,1,0) -> 0 | M8: =IF(SUM(AD8:AF8)>0,1,0) -> 0 | N8: =IF(SUM(AG8:AH8)>0,1,0) -> 0 | O8: =IF(SUM(AI8:AL8)>0,1,0) -> 1 | P8: =IF(SUM(AM8:AQ8)>0,1,0) -> 0 | Q8: =IF(AR8>0,1,0) -> 0 | R8: 0 | S8: 0 | T8: 0 | U8: 0 | V8: 0 | W8: 0 | X8: 0 | Y8: 0 | Z8: 0 | AA8: 0 | AB8: 0 | AC8: 0 | AD8: 0 | AE8: 0 | AF8: 0 | AG8: 0 | AH8: 0 | AI8: 1 | AJ8: 0 | AK8: 0 | AL8: 0 | AM8: 0 | AN8: 0 | AO8: 0 | AP8: 0 | AQ8: 0 | AR8: 0 | AS8: =SUM(J8:Q8) -> 1 | AT8: =SUM(R8:AR8) -> 1 | AU8: 西游悟空符号 | AV8: =IF(AT8>0,1,0) -> 1 | AW8: =IF(AT8=0,1,0) -> 0 | AX8: =IF(AT8>=8,1,0) -> 0 | AY8: 3 | AZ8: 正面 | BA8: P | BB8: 原文
A9: CN-P-008 | B9: 中文 | C9: 推荐 | D9: 19160 | E9: 8780 | F9: 52.3 | G9: 2024-08-20 | H9: 开服前：最多3天必定拿下杨戬开服打完第1个小boss：今天先拿下虎先锋吧开服后4小时：兄弟们 有没有会打大头的教一下 | I9: 开服前：最多3天必定拿下杨戬开服打完第1个小boss：今天先拿下虎先锋吧开服后4小时：兄弟们 有没有会打大头的教一下 | J9: =IF(SUM(R9:T9)>0,1,0) -> 0 | K9: =IF(SUM(U9:Y9)>0,1,0) -> 1 | L9: =IF(SUM(Z9:AC9)>0,1,0) -> 0 | M9: =IF(SUM(AD9:AF9)>0,1,0) -> 0 | N9: =IF(SUM(AG9:AH9)>0,1,0) -> 0 | O9: =IF(SUM(AI9:AL9)>0,1,0) -> 1 | P9: =IF(SUM(AM9:AQ9)>0,1,0) -> 0 | Q9: =IF(AR9>0,1,0) -> 0 | R9: 0 | S9: 0 | T9: 0 | U9: 0 | V9: 1 | W9: 0 | X9: 0 | Y9: 0 | Z9: 0 | AA9: 0 | AB9: 0 | AC9: 0 | AD9: 0 | AE9: 0 | AF9: 0 | AG9: 0 | AH9: 0 | AI9: 1 | AJ9: 0 | AK9: 0 | AL9: 0 | AM9: 0 | AN9: 0 | AO9: 0 | AP9: 0 | AQ9: 0 | AR9: 0 | AS9: =SUM(J9:Q9) -> 2 | AT9: =SUM(R9:AR9) -> 2 | AU9: Boss战斗节奏；西游悟空符号 | AV9: =IF(AT9>0,1,0) -> 1 | AW9: =IF(AT9=0,1,0) -> 0 | AX9: =IF(AT9>=8,1,0) -> 0 | AY9: 2 | AZ9: 正面 | BA9: P | BB9: 原文
A10: CN-P-009 | B10: 中文 | C10: 推荐 | D10: 12177 | E10: 250 | F10: 162.1 | G10: 2024-08-20 | H10: 回想四年前的今天，如同梦一场。扮演龙裔、猎魔人、刺客、勇者等等都很好，但你说可以当猴哥？这种来自血脉、历史、文化和童年记忆的加成，是过去多少年都不敢想象的。感谢游戏科学，让这场梦成真。全成就之后补充评测，画面、音乐、战斗都很棒，剧情有好有坏也还可以，整个游戏玩完我觉得挺开心，我喜欢玩，而且还要推荐别人玩。游戏看自己喜好，为啥要把自己的观点强加到别人身上，自己喜欢不喜欢友好评价就好，为何要跑到别人的评测下面刷自己怎么怎么破防，甚至破口大骂，和我有啥关系，这游戏又不是我做的。 | I10: 回想四年前的今天，如同梦一场。扮演龙裔、猎魔人、刺客、勇者等等都很好，但你说可以当猴哥？这种来自血脉、历史、文化和童年记忆的加成，是过去多少年都不敢想象的。感谢游戏科学，让这场梦成真。全成就之后补充评测，画面、音乐、战斗都很棒，剧情有好有坏也还可以，整个游戏玩完我觉得挺开心，我喜欢玩，而且还要推荐别人玩。游戏看自己喜好，为啥要把自己的观点强加到别人身上，自己喜欢不喜欢友好评价就好，为何要跑到别人的评测下面刷自己怎么怎么破防，甚至破口大骂，和我有啥关系，这游戏又不是我做的。 | J10: =IF(SUM(R10:T10)>0,1,0) -> 1 | K10: =IF(SUM(U10:Y10)>0,1,0) -> 1 | L10: =IF(SUM(Z10:AC10)>0,1,0) -> 0 | M10: =IF(SUM(AD10:AF10)>0,1,0) -> 0 | N10: =IF(SUM(AG10:AH10)>0,1,0) -> 1 | O10: =IF(SUM(AI10:AL10)>0,1,0) -> 1 | P10: =IF(SUM(AM10:AQ10)>0,1,0) -> 0 | Q10: =IF(AR10>0,1,0) -> 1 | R10: 1 | S10: 1 | T10: 0 | U10: 0 | V10: 1 | W10: 0 | X10: 0 | Y10: 0 | Z10: 0 | AA10: 0 | AB10: 0 | AC10: 0 | AD10: 0 | AE10: 0 | AF10: 0 | AG10: 0 | AH10: 1 | AI10: 1 | AJ10: 1 | AK10: 0 | AL10: 0 | AM10: 0 | AN10: 0 | AO10: 0 | AP10: 0 | AQ10: 0 | AR10: 1 | AS10: =SUM(J10:Q10) -> 5 | AT10: =SUM(R10:AR10) -> 7 | AU10: 画面美术场景；音乐音效配音；Boss战斗节奏；推荐价值判断；西游悟空符号；童年记忆情怀；国产3A身份期待 | AV10: =IF(AT10>0,1,0) -> 1 | AW10: =IF(AT10=0,1,0) -> 0 | AX10: =IF(AT10>=8,1,0) -> 0 | AY10: 10 | AZ10: 正面 | BA10: P | BB10: 原文
A11: CN-P-010 | B11: 中文 | C11: 推荐 | D11: 8886 | E11: 288 | F11: 20.9 | G11: 2024-08-20 | H11: 在正式开始玩之前，为了第一时间体验黑吗喽，今早惊醒了两次，却也迟迟不到开启的时间。最后快到的这半个小时却内心平静，感觉没有一丝波澜。我相信有许多跟我一样的人，第一次看到宣传片过后就热烈地期望着这一游戏，而一次次的实机预告过后又不断提升自己的期望值希望他走得更高更远，希望他能代表着我们国家的中华文化能够走出国门面向世界，告诉世界其他地区的玩家们中国也有一款优秀的中国3A游戏。我还记得第一次预告的时候大家伙讨论的还是黑神话是不是一款3A游戏，逐渐演变到后来他能对标哪款海外3A游戏再到后期的能不能TGA得奖。包括TGA得奖大家也从最开始觉得最佳美术稳了再到最佳音乐有希望再到希望获得年度最佳游戏。马上就要开启的旅程和长期以来的期望让我不希望黑神话会成为那种飞得越高摔得越惨的下场，同时也不希望优质国产游戏的未来落得个虎头蛇尾，伤仲永的结局。不过那些都是未来的事情了，未见未来，混沌与希望共存。到了最后，我由衷地希望黑神话能顺利地走完最后一步，在游玩的旅程当中能达到差强人意的地步就够了，完整地走完九九八十一难中的最后磨难，像流浪地球一样尝试着打开一扇新的通往未来的大门。也祝愿看到这条评论的大家能够玩得开心快乐，回归游戏带给我们快乐的初心。 | I11: 在正式开始玩之前，为了第一时间体验黑吗喽，今早惊醒了两次，却也迟迟不到开启的时间。最后快到的这半个小时却内心平静，感觉没有一丝波澜。我相信有许多跟我一样的人，第一次看到宣传片过后就热烈地期望着这一游戏，而一次次的实机预告过后又不断提升自己的期望值希望他走得更高更远，希望他能代表着我们国家的中华文化能够走出国门面向世界，告诉世界其他地区的玩家们中国也有一款优秀的中国3A游戏。我还记得第一次预告的时候大家伙讨论的还是黑神话是不是一款3A游戏，逐渐演变到后来他能对标哪款海外3A游戏再到后期的能不能TGA得奖。包括TGA得奖大家也从最开始觉得最佳美术稳了再到最佳音乐有希望再到希望获得年度最佳游戏。马上就要开启的旅程和长期以来的期望让我不希望黑神话会成为那种飞得越高摔得越惨的下场，同时也不希望优质国产游戏的未来落得个虎头蛇尾，伤仲永的结局。不过那些都是未来的事情了，未见未来，混沌与希望共存。到了最后，我由衷地希望黑神话能顺利地走完最后一步，在游玩的旅程当中能达到差强人意的地步就够了，完整地走完九九八十一难中的最后磨难，像流浪地球一样尝试着打开一扇新的通往未来的大门。也祝愿看到这条评论的大家能够玩得开心快乐，回归游戏带给我们快乐的初心。 | J11: =IF(SUM(R11:T11)>0,1,0) -> 1 | K11: =IF(SUM(U11:Y11)>0,1,0) -> 0 | L11: =IF(SUM(Z11:AC11)>0,1,0) -> 0 | M11: =IF(SUM(AD11:AF11)>0,1,0) -> 0 | N11: =IF(SUM(AG11:AH11)>0,1,0) -> 0 | O11: =IF(SUM(AI11:AL11)>0,1,0) -> 0 | P11: =IF(SUM(AM11:AQ11)>0,1,0) -> 0 | Q11: =IF(AR11>0,1,0) -> 1 | R11: 1 | S11: 1 | T11: 0 | U11: 0 | V11: 0 | W11: 0 | X11: 0 | Y11: 0 | Z11: 0 | AA11: 0 | AB11: 0 | AC11: 0 | AD11: 0 | AE11: 0 | AF11: 0 | AG11: 0 | AH11: 0 | AI11: 0 | AJ11: 0 | AK11: 0 | AL11: 0 | AM11: 0 | AN11: 0 | AO11: 0 | AP11: 0 | AQ11: 0 | AR11: 1 | AS11: =SUM(J11:Q11) -> 2 | AT11: =SUM(R11:AR11) -> 3 | AU11: 画面美术场景；音乐音效配音；国产3A身份期待 | AV11: =IF(AT11>0,1,0) -> 1 | AW11: =IF(AT11=0,1,0) -> 0 | AX11: =IF(AT11>=8,1,0) -> 0 | AY11: 30.5 | AZ11: 正面 | BA11: P | BB11: 原文
A12: CN-P-011 | B12: 中文 | C12: 推荐 | D12: 8705 | E12: 422 | F12: 132.2 | G12: 2024-08-20 | H12: 黑猴出世耀寰球，雄姿飒爽震九州。 无畏妖魔横空舞，一棍破敌尽风流。 惩恶扬善翻天覆，千古传说又重修。 踏平坎坷成大道，白骨之后再西游。 庚子年七月初二，余与常入哔哩哔哩，顾举界面求之，只见热门榜首标题亦生亦熟：黑神话？悟空？实机演示？即入观之，既而疑、动、喜至怖之情盈盈于胸，终日不释，观毕，始知涕泗横流矣。 余自幼嗜游，经手之数，浩如烟海，或单机或网游，神游于西土人情，鏖战在异域殊方。然随游龄之长，吾常觉心中空矣。至此方醒——从未游玩我中华文化背景之大型单机哉！黑神话之壁画、经幢、佛像、猢狲、妖魔、古建、对白、山水、民乐……纵不念，身心之烙印安能去乎？ 余如久旱而逢甘霖，他乡而遇故知，官方演示，反复观之，更不解瘾，剧情设定之解析、天下洋人之嗟叹，及其二创观之不止。吾虽知其未售，如此吹捧，是不智也，然心之终信：名为悟空者，必不欲令人失望。 四年间，游戏科学者，踏实实更动态、勤恳恳制游戏。正是：拨开云雾见天日，守得云开见月明，掸落吾之隐忧。暇时，购本著补读之，复寻童时之忆——八六年《西游记》。临售，吾心之期愿不减，反而益大。是再款《大圣归来》，抑犹“国游之光”“乡中第一大学士”，今将共见之。 终末，以八六年西游记，列《大圣歌》词曰： 腾云驾雾 追风逐电 一个跟头 哈哈哈 十万八千 火眼金睛 铜头铁肩 威风凛凛 哈哈哈 大圣齐天 说什么 艰险磨难 怕什么 鬼怪神仙 掣开如意金箍棒 打它个地覆天也翻！ 掣开如意金箍棒 打它个地覆天 也翻！ 【好大圣，把毫毛拔了一把，嚼得粉碎，每一个和尚与他一截，都教他：“捻在无名指甲里，捻着拳头，只情走路。无人敢拿你便罢；若有人拿你，攒紧了拳头，叫一声‘齐天大圣’，我就来护你。”（摘于本著）】 以上皆为余心路之历程，待深度赏玩，复与诸君共赏~ ================================================================= 历经十日，九九归真，难满功成，有诗为证： 取经得正果，愿归花果山。 本事遭天忌，尽除还心安。 紧箍藏于首，不教人作乱。 身陨成六器，海枯石不烂。 天命得所聚，方能寻齐全。 贪欲焚不尽，黑风又烧山。 佛妖本同源，盗圣皆一念。 倒乱因和果，极乐非长远。 寻常最长久，此事古难全。 空负平天志，大力难抗天。 百战相惜别，折梅赠心猿。 六根齐聚终，残躯炼成丹。 二心化一意，齐天归真返。 走脱轮回路，还教闹翻天！ “哥哥们，饮了这杯，我们一起打上凌霄宝殿！” | I12: 黑猴出世耀寰球，雄姿飒爽震九州。 无畏妖魔横空舞，一棍破敌尽风流。 惩恶扬善翻天覆，千古传说又重修。 踏平坎坷成大道，白骨之后再西游。 庚子年七月初二，余与常入哔哩哔哩，顾举界面求之，只见热门榜首标题亦生亦熟：黑神话？悟空？实机演示？即入观之，既而疑、动、喜至怖之情盈盈于胸，终日不释，观毕，始知涕泗横流矣。 余自幼嗜游，经手之数，浩如烟海，或单机或网游，神游于西土人情，鏖战在异域殊方。然随游龄之长，吾常觉心中空矣。至此方醒——从未游玩我中华文化背景之大型单机哉！黑神话之壁画、经幢、佛像、猢狲、妖魔、古建、对白、山水、民乐……纵不念，身心之烙印安能去乎？ 余如久旱而逢甘霖，他乡而遇故知，官方演示，反复观之，更不解瘾，剧情设定之解析、天下洋人之嗟叹，及其二创观之不止。吾虽知其未售，如此吹捧，是不智也，然心之终信：名为悟空者，必不欲令人失望。 四年间，游戏科学者，踏实实更动态、勤恳恳制游戏。正是：拨开云雾见天日，守得云开见月明，掸落吾之隐忧。暇时，购本著补读之，复寻童时之忆——八六年《西游记》。临售，吾心之期愿不减，反而益大。是再款《大圣归来》，抑犹“国游之光”“乡中第一大学士”，今将共见之。 终末，以八六年西游记，列《大圣歌》词曰： 腾云驾雾 追风逐电 一个跟头 哈哈哈 十万八千 火眼金睛 铜头铁肩 威风凛凛 哈哈哈 大圣齐天 说什么 艰险磨难 怕什么 鬼怪神仙 掣开如意金箍棒 打它个地覆天也翻！ 掣开如意金箍棒 打它个地覆天 也翻！ 【好大圣，把毫毛拔了一把，嚼得粉碎，每一个和尚与他一截，都教他：“捻在无名指甲里，捻着拳头，只情走路。无人敢拿你便罢；若有人拿你，攒紧了拳头，叫一声‘齐天大圣’，我就来护你。”（摘于本著）】 以上皆为余心路之历程，待深度赏玩，复与诸君共赏~ ================================================================= 历经十日，九九归真，难满功成，有诗为证： 取经得正果，愿归花果山。 本事遭天忌，尽除还心安。 紧箍藏于首，不教人作乱。 身陨成六器，海枯石不烂。 天命得所聚，方能寻齐全。 贪欲焚不尽，黑风又烧山。 佛妖本同源，盗圣皆一念。 倒乱因和果，极乐非长远。 寻常最长久，此事古难全。 空负平天志，大力难抗天。 百战相惜别，折梅赠心猿。 六根齐聚终，残躯炼成丹。 二心化一意，齐天归真返。 走脱轮回路，还教闹翻天！ “哥哥们，饮了这杯，我们一起打上凌霄宝殿！” | J12: =IF(SUM(R12:T12)>0,1,0) -> 1 | K12: =IF(SUM(U12:Y12)>0,1,0) -> 1 | L12: =IF(SUM(Z12:AC12)>0,1,0) -> 0 | M12: =IF(SUM(AD12:AF12)>0,1,0) -> 0 | N12: =IF(SUM(AG12:AH12)>0,1,0) -> 1 | O12: =IF(SUM(AI12:AL12)>0,1,0) -> 1 | P12: =IF(SUM(AM12:AQ12)>0,1,0) -> 1 | Q12: =IF(AR12>0,1,0) -> 0 | R12: 1 | S12: 0 | T12: 0 | U12: 1 | V12: 0 | W12: 0 | X12: 0 | Y12: 0 | Z12: 0 | AA12: 0 | AB12: 0 | AC12: 0 | AD12: 0 | AE12: 0 | AF12: 0 | AG12: 0 | AH12: 1 | AI12: 1 | AJ12: 0 | AK12: 0 | AL12: 0 | AM12: 0 | AN12: 1 | AO12: 0 | AP12: 0 | AQ12: 0 | AR12: 0 | AS12: =SUM(J12:Q12) -> 5 | AT12: =SUM(R12:AR12) -> 5 | AU12: 画面美术场景；动作打击手感；推荐价值判断；西游悟空符号；原典知识人物关系专名 | AV12: =IF(AT12>0,1,0) -> 1 | AW12: =IF(AT12=0,1,0) -> 0 | AX12: =IF(AT12>=8,1,0) -> 0 | AY12: 7.5 | AZ12: 正面 | BA12: P | BB12: 原文
A13: CN-P-012 | B13: 中文 | C13: 推荐 | D13: 6708 | E13: 163 | F13: 70.5 | G13: 2024-08-20 | H13: 我有一个梦想，将来的某一天，大家都能玩到蕴含着中国上下五千年本土文化的优质游戏大作。我有一个梦想，有一天，西游记能出ACT，让老外去体会中国文化西游记中”斗战胜佛”的打击快感，那一定比西方的动作巅峰之作《战神》《鬼泣》更加深邃。我有一个梦想，有一天，上海滩能出沙盒游戏，而不是玩《GTA》感受美国梦，亦或是玩着《热血无赖》体验国外公司强行塞给我们的“中国文化”。我有一个梦想，有一天，不少3A大作不需要汉化，因为是我们自己的游戏，配音是中文，文化也是中国的。我有一个梦想，将来的某一天，国产游戏能像中国的其他产业一样，以一个领跑者的姿态，面对全世界，面对全宇宙，器宇轩昂，扬眉吐气。这会是由我们一起去完成的梦想。我等着我们的好消息。 ——毛星云 R.I.P我们好像快要做到了，但是很遗憾您看不到了。 | I13: 我有一个梦想，将来的某一天，大家都能玩到蕴含着中国上下五千年本土文化的优质游戏大作。我有一个梦想，有一天，西游记能出ACT，让老外去体会中国文化西游记中”斗战胜佛”的打击快感，那一定比西方的动作巅峰之作《战神》《鬼泣》更加深邃。我有一个梦想，有一天，上海滩能出沙盒游戏，而不是玩《GTA》感受美国梦，亦或是玩着《热血无赖》体验国外公司强行塞给我们的“中国文化”。我有一个梦想，有一天，不少3A大作不需要汉化，因为是我们自己的游戏，配音是中文，文化也是中国的。我有一个梦想，将来的某一天，国产游戏能像中国的其他产业一样，以一个领跑者的姿态，面对全世界，面对全宇宙，器宇轩昂，扬眉吐气。这会是由我们一起去完成的梦想。我等着我们的好消息。 ——毛星云 R.I.P我们好像快要做到了，但是很遗憾您看不到了。 | J13: =IF(SUM(R13:T13)>0,1,0) -> 1 | K13: =IF(SUM(U13:Y13)>0,1,0) -> 1 | L13: =IF(SUM(Z13:AC13)>0,1,0) -> 0 | M13: =IF(SUM(AD13:AF13)>0,1,0) -> 0 | N13: =IF(SUM(AG13:AH13)>0,1,0) -> 0 | O13: =IF(SUM(AI13:AL13)>0,1,0) -> 1 | P13: =IF(SUM(AM13:AQ13)>0,1,0) -> 0 | Q13: =IF(AR13>0,1,0) -> 1 | R13: 0 | S13: 1 | T13: 0 | U13: 1 | V13: 0 | W13: 0 | X13: 0 | Y13: 0 | Z13: 0 | AA13: 0 | AB13: 0 | AC13: 0 | AD13: 0 | AE13: 0 | AF13: 0 | AG13: 0 | AH13: 0 | AI13: 1 | AJ13: 0 | AK13: 0 | AL13: 1 | AM13: 0 | AN13: 0 | AO13: 0 | AP13: 0 | AQ13: 0 | AR13: 1 | AS13: =SUM(J13:Q13) -> 4 | AT13: =SUM(R13:AR13) -> 5 | AU13: 音乐音效配音；动作打击手感；西游悟空符号；中国文化宗教语言审美；国产3A身份期待 | AV13: =IF(AT13>0,1,0) -> 1 | AW13: =IF(AT13=0,1,0) -> 0 | AX13: =IF(AT13>=8,1,0) -> 0 | AY13: 15 | AZ13: 正面 | BA13: P | BB13: 原文
... A16: CN-P-015 | B16: 中文 | C16: 推荐 | D16: 812 | E16: 19 | F16: 18.6 | G16: 2024-08-20 | H16: 2024年8月20日，黑神话悟空发行，侄子想玩，但他当时已经高三开始上课了，约好了考上一本线，就送侄子豪华版。如果一切走在正轨上，侄子也许刚好高考完，黑神话刚好也打折，买豪华版我还能省点钱。但在参加高考前侄子因为意外离世了，甚至没能看见他展现自己苦读12年的努力，侄子也是一个普通的热爱着游戏的年轻人，你期待着热爱着的游戏，叔叔只能替你去见证了。 | I16: 2024年8月20日，黑神话悟空发行，侄子想玩，但他当时已经高三开始上课了，约好了考上一本线，就送侄子豪华版。如果一切走在正轨上，侄子也许刚好高考完，黑神话刚好也打折，买豪华版我还能省点钱。但在参加高考前侄子因为意外离世了，甚至没能看见他展现自己苦读12年的努力，侄子也是一个普通的热爱着游戏的年轻人，你期待着热爱着的游戏，叔叔只能替你去见证了。 | J16: =IF(SUM(R16:T16)>0,1,0) -> 0 | K16: =IF(SUM(U16:Y16)>0,1,0) -> 0 | L16: =IF(SUM(Z16:AC16)>0,1,0) -> 0 | M16: =IF(SUM(AD16:AF16)>0,1,0) -> 0 | N16: =IF(SUM(AG16:AH16)>0,1,0) -> 1 | O16: =IF(SUM(AI16:AL16)>0,1,0) -> 1 | P16: =IF(SUM(AM16:AQ16)>0,1,0) -> 0 | Q16: =IF(AR16>0,1,0) -> 0 | R16: 0 | S16: 0 | T16: 0 | U16: 0 | V16: 0 | W16: 0 | X16: 0 | Y16: 0 | Z16: 0 | AA16: 0 | AB16: 0 | AC16: 0 | AD16: 0 | AE16: 0 | AF16: 0 | AG16: 0 | AH16: 1 | AI16: 1 | AJ16: 0 | AK16: 0 | AL16: 0 | AM16: 0 | AN16: 0 | AO16: 0 | AP16: 0 | AQ16: 0 | AR16: 0 | AS16: =SUM(J16:Q16) -> 2 | AT16: =SUM(R16:AR16) -> 2 | AU16: 推荐价值判断；西游悟空符号 | AV16: =IF(AT16>0,1,0) -> 1 | AW16: =IF(AT16=0,1,0) -> 0 | AX16: =IF(AT16>=8,1,0) -> 0 | AY16: 8.5 | AZ16: 正面 | BA16: P | BB16: 原文
A17: CN-P-016 | B17: 中文 | C17: 推荐 | D17: 0 | E17: 0 | F17: 23.9 小时 | G17: 2024-08-21 | H17: 除了画质其他的部分一言难尽，第二章的和第三章的地图设计简直就是重量级，怪物设计前面的感觉都挺不错的，从黄风开始就初现端倪。黄风也是重量级，已经看到有不少人骂了，作为关底boss待遇和普通怪一样，路过还以为是要顺手打的精英怪，定风丹一点引导都没有，但凡你在我似了几次后蹦出来一个npc让我去拿个丹，或者哪怕只是一个转场动画的tips告诉我还有这玩意我都能说你有引导，一点引导都没有真的是逆天了，别跟我提原著或者上网查，提原著的简直就是好笑，自己游戏一点引导没有指望玩家做攻略全都自己搞定？你游戏又没地图又没明确的引导，地图又做的逆天，群里迷路的一大堆，你跟我说是自己问题？还是说你要给我扯什么游戏的意义了？我欣赏不来这种艺术，哥们就想把boss都打了。地图方面真的无力吐槽，要来批判我自己不认真玩游戏的建议去看看各大主播的迷路率，第二章的地图标识物太少，没有路牌也没有什么记忆点，第三章无力吐槽，只能说玩了的懂得都懂。战斗设计上仁者见仁智者见智，有夸的有骂的，我感觉比较一般，无功无过。但boss设计真的是重量级，前面一二章的boss打的都挺爽的，但从第三章开始设计质量就是断崖式的下滑，难度不高但恶心程度极其逆天，喜欢我刮了10分钟被削了血量上限后被一招反杀吗，菜就多练？玩不过就别玩？不是打不打得过的问题，打亢金龙我也是两遍过，但战斗体验可以说差到了极致，然后跑图真实模拟坐大牢后遇到一个活全家的必打boss，前三章最粪boss没人有意见吧？视角乱的好像头被拧断了一样，血量上限减半就算了，这个战斗过程中各种无伤害强制打断动作。我就不明白了，虎先锋卡住了很多新手玩家但我寻思也没人在设计上骂他，让玩家战斗爽有那么难吗？各种小boss没有引导，明明看着有路却有空气墙，看着一眼空气墙的地方又可以走了。哥们没那么有钱，268对我来说不少了，哥们花这么多买了个游戏这么明显的缺点这么多，美术音乐确实是顶级，剧情我没看完不做评价。我说的很清楚了，游戏性上体验相当差，但除此之外的地方都很好，作为国产第一款3a我可以理解，但不好就是不好。给一些修改意见：1.修改索敌大体积怪物时的视角问题。2.增加地图引导，可以添加小地图道具，哪怕只是在背包中才能看也行。3.为地图增加有记忆点的地标，有效防止各种迷路。在tips中或者npc对话中添加关卡引导，把关底boss和一般boss做更加明显的区分。4.独木桥弓箭手活全家。5.建议第三章整体重做，我白天坐牢已经坐够了晚上真不想回家还沉浸式坐牢。 | I17: 除了画质其他的部分一言难尽，第二章的和第三章的地图设计简直就是重量级，怪物设计前面的感觉都挺不错的，从黄风开始就初现端倪。黄风也是重量级，已经看到有不少人骂了，作为关底boss待遇和普通怪一样，路过还以为是要顺手打的精英怪，定风丹一点引导都没有，但凡你在我似了几次后蹦出来一个npc让我去拿个丹，或者哪怕只是一个转场动画的tips告诉我还有这玩意我都能说你有引导，一点引导都没有真的是逆天了，别跟我提原著或者上网查，提原著的简直就是好笑，自己游戏一点引导没有指望玩家做攻略全都自己搞定？你游戏又没地图又没明确的引导，地图又做的逆天，群里迷路的一大堆，你跟我说是自己问题？还是说你要给我扯什么游戏的意义了？我欣赏不来这种艺术，哥们就想把boss都打了。地图方面真的无力吐槽，要来批判我自己不认真玩游戏的建议去看看各大主播的迷路率，第二章的地图标识物太少，没有路牌也没有什么记忆点，第三章无力吐槽，只能说玩了的懂得都懂。战斗设计上仁者见仁智者见智，有夸的有骂的，我感觉比较一般，无功无过。但boss设计真的是重量级，前面一二章的boss打的都挺爽的，但从第三章开始设计质量就是断崖式的下滑，难度不高但恶心程度极其逆天，喜欢我刮了10分钟被削了血量上限后被一招反杀吗，菜就多练？玩不过就别玩？不是打不打得过的问题，打亢金龙我也是两遍过，但战斗体验可以说差到了极致，然后跑图真实模拟坐大牢后遇到一个活全家的必打boss，前三章最粪boss没人有意见吧？视角乱的好像头被拧断了一样，血量上限减半就算了，这个战斗过程中各种无伤害强制打断动作。我就不明白了，虎先锋卡住了很多新手玩家但我寻思也没人在设计上骂他，让玩家战斗爽有那么难吗？各种小boss没有引导，明明看着有路却有空气墙，看着一眼空气墙的地方又可以走了。哥们没那么有钱，268对我来说不少了，哥们花这么多买了个游戏这么明显的缺点这么多，美术音乐确实是顶级，剧情我没看完不做评价。我说的很清楚了，游戏性上体验相当差，但除此之外的地方都很好，作为国产第一款3a我可以理解，但不好就是不好。给一些修改意见：1.修改索敌大体积怪物时的视角问题。2.增加地图引导，可以添加小地图道具，哪怕只是在背包中才能看也行。3.为地图增加有记忆点的地标，有效防止各种迷路。在tips中或者npc对话中添加关卡引导，把关底boss和一般boss做更加明显的区分。4.独木桥弓箭手活全家。5.建议第三章整体重做，我白天坐牢已经坐够了晚上真不想回家还沉浸式坐牢。 | J17: =IF(SUM(R17:T17)>0,1,0) -> 1 | K17: =IF(SUM(U17:Y17)>0,1,0) -> 1 | L17: =IF(SUM(Z17:AC17)>0,1,0) -> 1 | M17: =IF(SUM(AD17:AF17)>0,1,0) -> 0 | N17: =IF(SUM(AG17:AH17)>0,1,0) -> 1 | O17: =IF(SUM(AI17:AL17)>0,1,0) -> 1 | P17: =IF(SUM(AM17:AQ17)>0,1,0) -> 1 | Q17: =IF(AR17>0,1,0) -> 1 | R17: 1 | S17: 1 | T17: 1 | U17: 1 | V17: 1 | W17: 1 | X17: 1 | Y17: 0 | Z17: 1 | AA17: 1 | AB17: 1 | AC17: 1 | AD17: 0 | AE17: 0 | AF17: 0 | AG17: 1 | AH17: 1 | AI17: 0 | AJ17: 0 | AK17: 1 | AL17: 1 | AM17: 0 | AN17: 0 | AO17: 0 | AP17: 1 | AQ17: 0 | AR17: 1 | AS17: =SUM(J17:Q17) -> 7 | AT17: =SUM(R17:AR17) -> 17 | AU17: 画面美术场景；音乐音效配音；演出角色怪物设计；动作打击手感；Boss战斗节奏；难度挑战；锁定视角；地图路线；空气墙可达性；探索隐藏支线；引导迷路单线；整体完成度；推荐价值判断；本国媒介路径；中国文化宗教语言审美；外部资料依赖；国产3A身份期待 | AV17: =IF(AT17>0,1,0) -> 1 | AW17: =IF(AT17=0,1,0) -> 0 | AX17: =IF(AT17>=8,1,0) -> 1 | AY17: 4.5 | AZ17: 正面 | BA17: P | BB17: 原文
A18: CN-P-017 | B18: 中文 | C18: 推荐 | D18: 303 | E18: 6 | F18: 36.3 | G18: 2024-08-20 | H18: 黑神话作为3A游戏是不完美的，甚至是不太成熟的，但是对于中国玩家他是目前最好的3A游戏 对国内玩家而言，今天是一个值得铭记的一天。但是我不想谈情怀，而是理性看待游戏。抛开立场，冷静分析后，我相信各位游戏爱好者在体验了许多成熟的3A作品后，会发现《黑神话》确实存在不少不足之处。就像A9评测说的那样：”它不需要被包容，也不需要被捧上神坛“ 指出这些不足，才能推动国内游戏的发展更快更好！《黑神话》的美术水平无疑达到了全球顶尖，但是我建议游科开除关卡策划（我感觉大概率是因为美术主导才导致的）。 其实我的个人期望最开始就没有拉到很高，希望能和《仁王》一个水平即可。随着发售日期的临近，官方尚未发布玩家试玩Demo，我开始感到一些不安。最终体验下来，整体可玩性确实不及《仁王》。更严苛地评价的话，我感觉它更像是2024年的《教团1886》的升级版，美术水平和设计能力严重不匹配。比如，大家以及评测媒体都提到的“地图迷路”问题 小地图可以解决部分问题，但是会可能影响沉浸感 。虽然有人认为“迷路”只是一个小瑕疵，但是在重复十几次之后一定会产生强烈的负面情绪。因为这本身就是关卡设计中的一大忌讳。《黑神话》在关卡设计上不应与魂类游戏相比，因为魂类游戏注重小型箱庭地图的通路设计，包括捷径、隐藏奖励、稀有敌人等一整套系统，能够有效地使玩家的情绪产生反馈。如果拿传统线性游戏做参考，则可以通过场景中的材质变化提示、可交互或可破坏物的引导等方式，减少迷路的可能性，虽然这些可能会影响场景的氛围，但它们确实能粗暴地解决一些问题。这让我不禁想起顽皮狗的关卡设计，其巧妙的指引方式，包括环境解谜、狭窄通路设计和角色互动等，充分展示了优秀的关卡设计理念。 感兴趣可以看看这个，顽皮狗关卡设计师的分享 [www.bilibili.com]这些问题充分说明，《黑神话》在设计层面仍显得不够成熟，无法和美术能力做匹配，给我的感觉更像是由美术主导完成的关卡设计。黑神话可能拿不到今年的Glory，但是它绝对是中国游戏的Glory。 即便它撼动不了资本的地位，若能让国家政策开始倾斜的话，结果会更好！隔壁韩国游戏行业能发展壮大起来，我们一定也没问题的！ | I18: 黑神话作为3A游戏是不完美的，甚至是不太成熟的，但是对于中国玩家他是目前最好的3A游戏 对国内玩家而言，今天是一个值得铭记的一天。但是我不想谈情怀，而是理性看待游戏。抛开立场，冷静分析后，我相信各位游戏爱好者在体验了许多成熟的3A作品后，会发现《黑神话》确实存在不少不足之处。就像A9评测说的那样：”它不需要被包容，也不需要被捧上神坛“ 指出这些不足，才能推动国内游戏的发展更快更好！《黑神话》的美术水平无疑达到了全球顶尖，但是我建议游科开除关卡策划（我感觉大概率是因为美术主导才导致的）。 其实我的个人期望最开始就没有拉到很高，希望能和《仁王》一个水平即可。随着发售日期的临近，官方尚未发布玩家试玩Demo，我开始感到一些不安。最终体验下来，整体可玩性确实不及《仁王》。更严苛地评价的话，我感觉它更像是2024年的《教团1886》的升级版，美术水平和设计能力严重不匹配。比如，大家以及评测媒体都提到的“地图迷路”问题 小地图可以解决部分问题，但是会可能影响沉浸感 。虽然有人认为“迷路”只是一个小瑕疵，但是在重复十几次之后一定会产生强烈的负面情绪。因为这本身就是关卡设计中的一大忌讳。《黑神话》在关卡设计上不应与魂类游戏相比，因为魂类游戏注重小型箱庭地图的通路设计，包括捷径、隐藏奖励、稀有敌人等一整套系统，能够有效地使玩家的情绪产生反馈。如果拿传统线性游戏做参考，则可以通过场景中的材质变化提示、可交互或可破坏物的引导等方式，减少迷路的可能性，虽然这些可能会影响场景的氛围，但它们确实能粗暴地解决一些问题。这让我不禁想起顽皮狗的关卡设计，其巧妙的指引方式，包括环境解谜、狭窄通路设计和角色互动等，充分展示了优秀的关卡设计理念。 感兴趣可以看看这个，顽皮狗关卡设计师的分享 [www.bilibili.com]这些问题充分说明，《黑神话》在设计层面仍显得不够成熟，无法和美术能力做匹配，给我的感觉更像是由美术主导完成的关卡设计。黑神话可能拿不到今年的Glory，但是它绝对是中国游戏的Glory。 即便它撼动不了资本的地位，若能让国家政策开始倾斜的话，结果会更好！隔壁韩国游戏行业能发展壮大起来，我们一定也没问题的！ | J18: =IF(SUM(R18:T18)>0,1,0) -> 1 | K18: =IF(SUM(U18:Y18)>0,1,0) -> 1 | L18: =IF(SUM(Z18:AC18)>0,1,0) -> 1 | M18: =IF(SUM(AD18:AF18)>0,1,0) -> 0 | N18: =IF(SUM(AG18:AH18)>0,1,0) -> 1 | O18: =IF(SUM(AI18:AL18)>0,1,0) -> 1 | P18: =IF(SUM(AM18:AQ18)>0,1,0) -> 0 | Q18: =IF(AR18>0,1,0) -> 1 | R18: 1 | S18: 0 | T18: 1 | U18: 0 | V18: 0 | W18: 0 | X18: 0 | Y18: 1 | Z18: 1 | AA18: 0 | AB18: 1 | AC18: 1 | AD18: 0 | AE18: 0 | AF18: 0 | AG18: 1 | AH18: 1 | AI18: 0 | AJ18: 1 | AK18: 0 | AL18: 0 | AM18: 0 | AN18: 0 | AO18: 0 | AP18: 0 | AQ18: 0 | AR18: 1 | AS18: =SUM(J18:Q18) -> 6 | AT18: =SUM(R18:AR18) -> 10 | AU18: 画面美术场景；演出角色怪物设计；判定反馈；地图路线；探索隐藏支线；引导迷路单线；整体完成度；推荐价值判断；童年记忆情怀；国产3A身份期待 | AV18: =IF(AT18>0,1,0) -> 1 | AW18: =IF(AT18=0,1,0) -> 0 | AX18: =IF(AT18>=8,1,0) -> 1 | AY18: 15.5 | AZ18: 正面 | BA18: P | BB18: 原文
A19: CN-P-018 | B19: 中文 | C19: 推荐 | D19: 286 | E19: 2 | F19: 17.4 | G19: 2024-08-20 | H19: 作为国产第一款3a游戏我认为这个表现相当可以了，这是我玩了三个小时的真心感受。我看大家都在夸我就说几个我在意的地方供大伙以及游科参考。第一点，在打灵虚子的时候他在我身边跑动，出现了丢失视野的情况。就是锁定还在但是屏幕里没有BOSS，我认为是BOSS跑得太快以及镜头运转太慢导致的。等BOSS停下来了之后镜头又正常了。不过不是什么大问题，BOSS这个时候不会偷袭，况且灵虚子是前面最菜的一个BOSS第二点，游戏里面场景做的太好了，有些不能走的地方经常会让我撞得满头包，还有有的地方可以跳过去有的类似的地形就不可以，但地图是真大啊。第三点，我认为可以出一个保存加点的机制。没有死亡惩罚以及有偿洗点对我来讲已经非常非常棒了，但这个加点如果能作为一个范式保留的话就更好了总而言之，这款游戏没有辜负大伙四年的等待，纵使有一些瑕疵但是瑕不掩瑜，在做的好的地方已经足够好了，我会继续玩下去，后面会继续更新 | I19: 作为国产第一款3a游戏我认为这个表现相当可以了，这是我玩了三个小时的真心感受。我看大家都在夸我就说几个我在意的地方供大伙以及游科参考。第一点，在打灵虚子的时候他在我身边跑动，出现了丢失视野的情况。就是锁定还在但是屏幕里没有BOSS，我认为是BOSS跑得太快以及镜头运转太慢导致的。等BOSS停下来了之后镜头又正常了。不过不是什么大问题，BOSS这个时候不会偷袭，况且灵虚子是前面最菜的一个BOSS第二点，游戏里面场景做的太好了，有些不能走的地方经常会让我撞得满头包，还有有的地方可以跳过去有的类似的地形就不可以，但地图是真大啊。第三点，我认为可以出一个保存加点的机制。没有死亡惩罚以及有偿洗点对我来讲已经非常非常棒了，但这个加点如果能作为一个范式保留的话就更好了总而言之，这款游戏没有辜负大伙四年的等待，纵使有一些瑕疵但是瑕不掩瑜，在做的好的地方已经足够好了，我会继续玩下去，后面会继续更新 | J19: =IF(SUM(R19:T19)>0,1,0) -> 1 | K19: =IF(SUM(U19:Y19)>0,1,0) -> 1 | L19: =IF(SUM(Z19:AC19)>0,1,0) -> 1 | M19: =IF(SUM(AD19:AF19)>0,1,0) -> 0 | N19: =IF(SUM(AG19:AH19)>0,1,0) -> 0 | O19: =IF(SUM(AI19:AL19)>0,1,0) -> 0 | P19: =IF(SUM(AM19:AQ19)>0,1,0) -> 0 | Q19: =IF(AR19>0,1,0) -> 1 | R19: 1 | S19: 0 | T19: 0 | U19: 0 | V19: 1 | W19: 1 | X19: 1 | Y19: 0 | Z19: 1 | AA19: 1 | AB19: 0 | AC19: 0 | AD19: 0 | AE19: 0 | AF19: 0 | AG19: 0 | AH19: 0 | AI19: 0 | AJ19: 0 | AK19: 0 | AL19: 0 | AM19: 0 | AN19: 0 | AO19: 0 | AP19: 0 | AQ19: 0 | AR19: 1 | AS19: =SUM(J19:Q19) -> 4 | AT19: =SUM(R19:AR19) -> 7 | AU19: 画面美术场景；Boss战斗节奏；难度挑战；锁定视角；地图路线；空气墙可达性；国产3A身份期待 | AV19: =IF(AT19>0,1,0) -> 1 | AW19: =IF(AT19=0,1,0) -> 0 | AX19: =IF(AT19>=8,1,0) -> 0 | AY19: 14 | AZ19: 正面 | BA19: P | BB19: 原文
A20: CN-P-019 | B20: 中文 | C20: 不推荐 | D20: 259 | E20: 19 | F20: 46.7 | G20: 2024-08-20 | H20: 好评没两个说游戏怎么样的，就是无脑好评，饭圈滚出steam | I20: 好评没两个说游戏怎么样的，就是无脑好评，饭圈滚出steam | J20: =IF(SUM(R20:T20)>0,1,0) -> 0 | K20: =IF(SUM(U20:Y20)>0,1,0) -> 0 | L20: =IF(SUM(Z20:AC20)>0,1,0) -> 0 | M20: =IF(SUM(AD20:AF20)>0,1,0) -> 0 | N20: =IF(SUM(AG20:AH20)>0,1,0) -> 0 | O20: =IF(SUM(AI20:AL20)>0,1,0) -> 0 | P20: =IF(SUM(AM20:AQ20)>0,1,0) -> 0 | Q20: =IF(AR20>0,1,0) -> 0 | R20: 0 | S20: 0 | T20: 0 | U20: 0 | V20: 0 | W20: 0 | X20: 0 | Y20: 0 | Z20: 0 | AA20: 0 | AB20: 0 | AC20: 0 | AD20: 0 | AE20: 0 | AF20: 0 | AG20: 0 | AH20: 0 | AI20: 0 | AJ20: 0 | AK20: 0 | AL20: 0 | AM20: 0 | AN20: 0 | AO20: 0 | AP20: 0 | AQ20: 0 | AR20: 0 | AS20: =SUM(J20:Q20) -> 0 | AT20: =SUM(R20:AR20) -> 0 | AV20: =IF(AT20>0,1,0) -> 0 | AW20: =IF(AT20=0,1,0) -> 1 | AX20: =IF(AT20>=8,1,0) -> 0 | AY20: 3 | AZ20: 正面 | BA20: P | BB20: 原文
A21: CN-P-020 | B21: 中文 | C21: 不推荐 | D21: 245 | E21: 70 | F21: 3.3 | G21: 2024-08-20 | H21: 一坨不好惹的屎可以完美的概括这款游戏 | I21: 一坨不好惹的屎可以完美的概括这款游戏 | J21: =IF(SUM(R21:T21)>0,1,0) -> 0 | K21: =IF(SUM(U21:Y21)>0,1,0) -> 0 | L21: =IF(SUM(Z21:AC21)>0,1,0) -> 0 | M21: =IF(SUM(AD21:AF21)>0,1,0) -> 0 | N21: =IF(SUM(AG21:AH21)>0,1,0) -> 0 | O21: =IF(SUM(AI21:AL21)>0,1,0) -> 0 | P21: =IF(SUM(AM21:AQ21)>0,1,0) -> 0 | Q21: =IF(AR21>0,1,0) -> 0 | R21: 0 | S21: 0 | T21: 0 | U21: 0 | V21: 0 | W21: 0 | X21: 0 | Y21: 0 | Z21: 0 | AA21: 0 | AB21: 0 | AC21: 0 | AD21: 0 | AE21: 0 | AF21: 0 | AG21: 0 | AH21: 0 | AI21: 0 | AJ21: 0 | AK21: 0 | AL21: 0 | AM21: 0 | AN21: 0 | AO21: 0 | AP21: 0 | AQ21: 0 | AR21: 0 | AS21: =SUM(J21:Q21) -> 0 | AT21: =SUM(R21:AR21) -> 0 | AV21: =IF(AT21>0,1,0) -> 0 | AW21: =IF(AT21=0,1,0) -> 1 | AX21: =IF(AT21>=8,1,0) -> 0 | AY21: 1 | AZ21: 正面 | BA21: P | BB21: 原文
A22: CN-P-021 | B22: 中文 | C22: 推荐 | D22: 227 | E22: 4 | F22: 45.9 | G22: 2024-08-20 | H22: 豪玩但是！我需要：1：手柄自定义键位！！！！！！2：短按闪避长按奔跑3：奔跑跳跃后保持奔跑状态 | I22: 豪玩但是！我需要：1：手柄自定义键位！！！！！！2：短按闪避长按奔跑3：奔跑跳跃后保持奔跑状态 | J22: =IF(SUM(R22:T22)>0,1,0) -> 0 | K22: =IF(SUM(U22:Y22)>0,1,0) -> 1 | L22: =IF(SUM(Z22:AC22)>0,1,0) -> 0 | M22: =IF(SUM(AD22:AF22)>0,1,0) -> 0 | N22: =IF(SUM(AG22:AH22)>0,1,0) -> 0 | O22: =IF(SUM(AI22:AL22)>0,1,0) -> 0 | P22: =IF(SUM(AM22:AQ22)>0,1,0) -> 0 | Q22: =IF(AR22>0,1,0) -> 0 | R22: 0 | S22: 0 | T22: 0 | U22: 1 | V22: 0 | W22: 0 | X22: 0 | Y22: 0 | Z22: 0 | AA22: 0 | AB22: 0 | AC22: 0 | AD22: 0 | AE22: 0 | AF22: 0 | AG22: 0 | AH22: 0 | AI22: 0 | AJ22: 0 | AK22: 0 | AL22: 0 | AM22: 0 | AN22: 0 | AO22: 0 | AP22: 0 | AQ22: 0 | AR22: 0 | AS22: =SUM(J22:Q22) -> 1 | AT22: =SUM(R22:AR22) -> 1 | AU22: 动作打击手感 | AV22: =IF(AT22>0,1,0) -> 1 | AW22: =IF(AT22=0,1,0) -> 0 | AX22: =IF(AT22>=8,1,0) -> 0 | AY22: 2 | AZ22: 正面 | BA22: P | BB22: 原文
A23: CN-P-022 | B23: 中文 | C23: 不推荐 | D23: 212 | E23: 15 | F23: 67.3 | G23: 2024-08-20 | H23: 请问第三章真的是人设计的吗？？是脑子有什么病吗？很好玩吗？很有趣吗？你们玩过吗？你们很喜欢吗？？我不理解。全成就了，现在感觉能正常且系统性的来评价这款游戏了。对于我来说，一周目的第一章的体验是极其美好的，不算复杂的地图设计就没有地图与指引全收集也不是难事，但是在第二章的大规模地图的设计下就开始变味儿。因为没有地图与指引，人物就像乱转的苍蝇，再加上游科也确确实实喜欢在地图里藏物品和任务，导致玩家只能把看到的位置都探索一遍，然后产生了一种灾难性的体验，就是探索空气墙，这一点在第三章尤为体现。随后而来的第四章的地图设计我反而更能接受，个人认为第四章地图的辨识度比第三章高很多，且比起大平面的地图个人也更喜欢纵向的地图设计。能感觉到游科在制作游戏的时候想给玩家呈现不同的地图设计但是我并不认为不给玩家地图功能是一个能忽略的缺点。说回让我破防的第三章的浮屠牢，我深深地感到来自于制作人的恶意，确确实实是真实的坐牢体验。在人物没有靠谱的远程手段且前期法力并不可再生只能去土地庙才能回复的条件下，给我的游戏体验是极其糟糕的，经典的斜坡或者独木桥旁放远程和让你坠机飞天小怪，再搭配上每隔几分钟人物血量减半的debuff，堪称折磨。就算经历万险，爬出牢笼，别忘了头上可有个还能给你带来糟糕体验的boss。说句实话，黑神话给我与boss的战斗体验也是扣分的，基本上每个boss都会有一到两个招数他会飞到空中而你只能在地面一边疯狂逃窜一边干瞪眼。boss会一边在空中跳舞一边免疫你引以为豪的定身术。我能理解游科的部分想法，那就是法宝克制，比如说收集到第二章的隐藏法宝，确确实实就能跳过boss的跳舞阶段，这设计思路我觉得很棒，很喜欢，但是其他的boss呢，一周目能像这样跳过阶段的boss又有几个呢？除了强制对舞pk以外，再就是快慢刀了，这点在二郎神身上算是体现到了极致。一道金光二郎显圣真君瞬移到你头上举起自己的开山斧，而你选择铜墙铁壁硬挡这一斧，但很遗憾直到你的铜墙铁壁结束，二郎神的斧才会劈下来。我本来期望会有酣畅淋漓，大开大合的一场战斗，可打着打着，只能一边嘴巴上爆着粗口一边祭出卑鄙的芭蕉扇。等打完也不会是与强敌对战后的意犹未竟而是感觉出了一口恶气。其实战斗方面还有很多可以聊的，糟糕的锁定，我打巨人的脚，锁左脚往裆下打，锁右脚还是往裆下打。部分敌人的韧性极高，而我们主角被一把小刀划到可能就会被打断，更别提我主玩的劈棍好不容易攒好豆被打断伴随始终。不过劈棍更大问题还是距离太短太容易空，被体型大一点的模型碰撞一下就会登龙失败，其他的流派做得到吗？还有预输入，个人还是更倾向于有预输入的战斗体验。对我来说，黑神话悟空是一款优点缺点都极其明显的游戏，他有着让人着迷的美术音乐设计和头目演出，对于出现过的神人妖都会有专门的游记进行记载，既丰富了世界观也满足了玩家对于剧情探索的需求，更别提是基于国人耳熟能详的西游记的再创作。但同时他又有着略偏同质化的战斗及部分糟糕的boss战体验，个别章节的地图设计恶意满满，还有绝对应该有却没有的地图功能以及指引。这种优缺点明显的游戏让我觉得在互联网上夸的骂的，都很正常。但是只让人骂见不得夸的，或者只让人夸见不得骂的，除了云玩家、串子再就是一些我不太好说的饭圈团体了。不过看了看大家给我的留言，互联网上的大家绝大部分还是很温和的正常人。最后就是，我也是第一次写这种长评测，当时破防也是确确实实被游戏设计震惊且觉得恶心，现在刚刚白金也是感概万千，真实的取经体验，苦甜参半，个中滋味也确实令人回味。脑子乱糟糟也写得也是乱糟糟但这也算是我黑神话之旅最真实的感受了。也希望游科能够重视这次黑神话的部分糟糕体验，在后续dlc及作品里做出改善。另外二周目是真的爽，如果一周目让你玩的不开心这不是你心中的大圣，二周目绝对会满足你对大圣的幻想。 | I23: 请问第三章真的是人设计的吗？？是脑子有什么病吗？很好玩吗？很有趣吗？你们玩过吗？你们很喜欢吗？？我不理解。全成就了，现在感觉能正常且系统性的来评价这款游戏了。对于我来说，一周目的第一章的体验是极其美好的，不算复杂的地图设计就没有地图与指引全收集也不是难事，但是在第二章的大规模地图的设计下就开始变味儿。因为没有地图与指引，人物就像乱转的苍蝇，再加上游科也确确实实喜欢在地图里藏物品和任务，导致玩家只能把看到的位置都探索一遍，然后产生了一种灾难性的体验，就是探索空气墙，这一点在第三章尤为体现。随后而来的第四章的地图设计我反而更能接受，个人认为第四章地图的辨识度比第三章高很多，且比起大平面的地图个人也更喜欢纵向的地图设计。能感觉到游科在制作游戏的时候想给玩家呈现不同的地图设计但是我并不认为不给玩家地图功能是一个能忽略的缺点。说回让我破防的第三章的浮屠牢，我深深地感到来自于制作人的恶意，确确实实是真实的坐牢体验。在人物没有靠谱的远程手段且前期法力并不可再生只能去土地庙才能回复的条件下，给我的游戏体验是极其糟糕的，经典的斜坡或者独木桥旁放远程和让你坠机飞天小怪，再搭配上每隔几分钟人物血量减半的debuff，堪称折磨。就算经历万险，爬出牢笼，别忘了头上可有个还能给你带来糟糕体验的boss。说句实话，黑神话给我与boss的战斗体验也是扣分的，基本上每个boss都会有一到两个招数他会飞到空中而你只能在地面一边疯狂逃窜一边干瞪眼。boss会一边在空中跳舞一边免疫你引以为豪的定身术。我能理解游科的部分想法，那就是法宝克制，比如说收集到第二章的隐藏法宝，确确实实就能跳过boss的跳舞阶段，这设计思路我觉得很棒，很喜欢，但是其他的boss呢，一周目能像这样跳过阶段的boss又有几个呢？除了强制对舞pk以外，再就是快慢刀了，这点在二郎神身上算是体现到了极致。一道金光二郎显圣真君瞬移到你头上举起自己的开山斧，而你选择铜墙铁壁硬挡这一斧，但很遗憾直到你的铜墙铁壁结束，二郎神的斧才会劈下来。我本来期望会有酣畅淋漓，大开大合的一场战斗，可打着打着，只能一边嘴巴上爆着粗口一边祭出卑鄙的芭蕉扇。等打完也不会是与强敌对战后的意犹未竟而是感觉出了一口恶气。其实战斗方面还有很多可以聊的，糟糕的锁定，我打巨人的脚，锁左脚往裆下打，锁右脚还是往裆下打。部分敌人的韧性极高，而我们主角被一把小刀划到可能就会被打断，更别提我主玩的劈棍好不容易攒好豆被打断伴随始终。不过劈棍更大问题还是距离太短太容易空，被体型大一点的模型碰撞一下就会登龙失败，其他的流派做得到吗？还有预输入，个人还是更倾向于有预输入的战斗体验。对我来说，黑神话悟空是一款优点缺点都极其明显的游戏，他有着让人着迷的美术音乐设计和头目演出，对于出现过的神人妖都会有专门的游记进行记载，既丰富了世界观也满足了玩家对于剧情探索的需求，更别提是基于国人耳熟能详的西游记的再创作。但同时他又有着略偏同质化的战斗及部分糟糕的boss战体验，个别章节的地图设计恶意满满，还有绝对应该有却没有的地图功能以及指引。这种优缺点明显的游戏让我觉得在互联网上夸的骂的，都很正常。但是只让人骂见不得夸的，或者只让人夸见不得骂的，除了云玩家、串子再就是一些我不太好说的饭圈团体了。不过看了看大家给我的留言，互联网上的大家绝大部分还是很温和的正常人。最后就是，我也是第一次写这种长评测，当时破防也是确确实实被游戏设计震惊且觉得恶心，现在刚刚白金也是感概万千，真实的取经体验，苦甜参半，个中滋味也确实令人回味。脑子乱糟糟也写得也是乱糟糟但这也算是我黑神话之旅最真实的感受了。也希望游科能够重视这次黑神话的部分糟糕体验，在后续dlc及作品里做出改善。另外二周目是真的爽，如果一周目让你玩的不开心这不是你心中的大圣，二周目绝对会满足你对大圣的幻想。 | J23: =IF(SUM(R23:T23)>0,1,0) -> 1 | K23: =IF(SUM(U23:Y23)>0,1,0) -> 1 | L23: =IF(SUM(Z23:AC23)>0,1,0) -> 1 | M23: =IF(SUM(AD23:AF23)>0,1,0) -> 0 | N23: =IF(SUM(AG23:AH23)>0,1,0) -> 1 | O23: =IF(SUM(AI23:AL23)>0,1,0) -> 1 | P23: =IF(SUM(AM23:AQ23)>0,1,0) -> 1 | Q23: =IF(AR23>0,1,0) -> 0 | R23: 1 | S23: 1 | T23: 1 | U23: 1 | V23: 1 | W23: 1 | X23: 1 | Y23: 1 | Z23: 1 | AA23: 1 | AB23: 1 | AC23: 1 | AD23: 0 | AE23: 0 | AF23: 0 | AG23: 0 | AH23: 1 | AI23: 1 | AJ23: 0 | AK23: 0 | AL23: 0 | AM23: 0 | AN23: 0 | AO23: 0 | AP23: 0 | AQ23: 1 | AR23: 0 | AS23: =SUM(J23:Q23) -> 6 | AT23: =SUM(R23:AR23) -> 15 | AU23: 画面美术场景；音乐音效配音；演出角色怪物设计；动作打击手感；Boss战斗节奏；难度挑战；锁定视角；判定反馈；地图路线；空气墙可达性；探索隐藏支线；引导迷路单线；推荐价值判断；西游悟空符号；角色期待意义偏移 | AV23: =IF(AT23>0,1,0) -> 1 | AW23: =IF(AT23=0,1,0) -> 0 | AX23: =IF(AT23>=8,1,0) -> 1 | AY23: 65.5 | AZ23: 正面 | BA23: P | BB23: 原文
A24: CN-P-023 | B24: 中文 | C24: 推荐 | D24: 188 | E24: 228 | F24: 41.2 | G24: 2024-08-20 | H24: 免费获取的产品 给兄弟口了一整天才给买的，好玩 | I24: 免费获取的产品 给兄弟口了一整天才给买的，好玩 | J24: =IF(SUM(R24:T24)>0,1,0) -> 0 | K24: =IF(SUM(U24:Y24)>0,1,0) -> 0 | L24: =IF(SUM(Z24:AC24)>0,1,0) -> 0 | M24: =IF(SUM(AD24:AF24)>0,1,0) -> 0 | N24: =IF(SUM(AG24:AH24)>0,1,0) -> 1 | O24: =IF(SUM(AI24:AL24)>0,1,0) -> 0 | P24: =IF(SUM(AM24:AQ24)>0,1,0) -> 0 | Q24: =IF(AR24>0,1,0) -> 0 | R24: 0 | S24: 0 | T24: 0 | U24: 0 | V24: 0 | W24: 0 | X24: 0 | Y24: 0 | Z24: 0 | AA24: 0 | AB24: 0 | AC24: 0 | AD24: 0 | AE24: 0 | AF24: 0 | AG24: 0 | AH24: 1 | AI24: 0 | AJ24: 0 | AK24: 0 | AL24: 0 | AM24: 0 | AN24: 0 | AO24: 0 | AP24: 0 | AQ24: 0 | AR24: 0 | AS24: =SUM(J24:Q24) -> 1 | AT24: =SUM(R24:AR24) -> 1 | AU24: 推荐价值判断 | AV24: =IF(AT24>0,1,0) -> 1 | AW24: =IF(AT24=0,1,0) -> 0 | AX24: =IF(AT24>=8,1,0) -> 0 | AY24: 3 | AZ24: 正面 | BA24: P | BB24: 原文
A25: CN-N-024 | B25: 中文 | C25: 不推荐 | D25: 186 | E25: 15 | F25: 6.5 | G25: 2024-08-20 | H25: 免费获取的产品 目前不推荐任何不喜欢魂游受虐模式的轻度路人玩家跟风买这个游戏。（这不是差评，是基于目前宣发狂热氛围下对轻度玩家的谨慎购入建议，别那么二极管/狭隘排外自卑）能做出来个没难度选项的纯背板的魂游我是真没想过的，前面大头娃起码背板个80%打过了，现在打个白衣居士被打到道心破碎，真没想到是个纯背板才能打得过的魂游，继承魂的体力条机制，365里路跑图，延迟滚，翻滚窗口滞连第二次，UI弄得贼小打起来根本没空注视体力条（要求熟练背板），武器机制要求 背死板，不然一点收益都吃不到，一点容错都没有，翻滚延迟考背板，要垫轻击的重击GP要背板，两个都TM有前摇延迟，判定窗口还贼短，打个BOSS要考跳跃、完美闪避、连招窗口，背板背板背得道心破碎了，但凡TM的翻滚没前摇都能爽起来，这一点起码加了90%的难度，傻逼玩意好学不学学TM魂游搞翻滚前摇延迟，我背完怪物出招时间点，背连招逻辑就算了，我还得背自己的输入延迟，TMD完美闪避的判定还TMD终极诡异，我纯战士翻滚打完1.0法环白金都没这么难受，法环那延迟滚都没这个诡异，考试也不上来就高强度考全科目，日NM的难度翻倍，不背板根本不能正常过关，要降难度只能去刷小怪攒经验升级加点，策划真要做魂游为什么不写明白，BOSS不仅性能碾压玩家，还会读指令，一些远程攻击还带穿模穿墙穿透的，还搞那么多地形凹凸，初见我被幽魂那穿墙射线整笑了还有那个独立的移动重击蓄力系统，我都搞不懂策划是怎么想出来这么割裂的招式，这游戏动作衔接就僵硬，因为没有招式取消后摇，必须播完动画帧，而单重击霸体没无敌时间，伤害能吃到饱，还得讲究背板输出窗口，那重击点攒起来就费劲，打空直接血亏，更别说那个要垫轻击的重击GP，我就没见过如此多施展条件的逆天招式，不是自由态施展，要垫刀，而轻击分5下，每下前后摇逐步增长，而闪避和衔接招式都要等攻击动作帧播完了才能派生下一招，而这个派生窗口还极短，还不能闪避打断/被打断（闪避继承连招拆进后期技能树了），导致凹一个重击GP，我先要费力完美闪避+蹭轻击攒一个重击点，然后还得专注背板读招在怪物身上找机会垫一刀轻击，然后再赌怪物会打我延迟重击的一瞬间，千辛万苦遇到窗口重击到了，那收益还不如不打GP直接平A攒重击点直接派生凹GP砸灌伤害，而怪物大概率快打完连招即将进入自由态，那很可能读指令后撤步，重击还是罚站原地释放的，攻击距离还短，而那些BOSS机动高，抬手还快，空GP砸棍直接血压拉满，而且觉得和连招系统巨割裂，仿佛这重击纯属是个偶尔放一下的战技。说是ARPG，但前期这个角色性能差得离谱，技能树一眼望到头，基本上玩死一种招式，战斗体验毫无深度，重击太割裂难用又要用，只能一直找输出窗口平A偷刀，而怪物性能却强到考全科目，装备类别也是经典木棍打小龙虾迭代，打得跟类魂一样，根本不能很爽的交互，这种机制数值不对等的难，游科有在乎过轻度玩家的体验？真觉得魂游市场很大？还是说宣发足够后“自有大儒为你辩经”？还有手柄震动几乎没有，锁定视角转速跟不上游戏里的BOSS各种飘逸移速然后是这个地图，问题可太大了，没有标志物，怪物貌似没掉落伤害但玩家有掉落伤害，而且一些在其他游戏中看着出去就死亡的场景，比如悬崖，一些边缘，河流，放这里面可能是另一条能走的岔路，而且还分不清是不是主线路还是支线路，十有八九还往里面藏BOSS，在线性箱庭里面藏大线性箱庭岔路，对于有经验的玩家极其不友好，谁知道你能不能走，是不是主线，有没有漏关键道具，谁知道你是惊喜还是惊吓，只能指望那个“防跌落”的空气墙动作去试探，然而真有落差却能过去的地方，却能把玩家摔掉血，指引只有在篝火点附近的主线一本道有光点指引，探图体验太晕了，这还是个有跑图压力的魂游，提心吊胆摸路还摸到迷路，虽说堆料，但游戏体验非常不舒服还好没脑子热跟风买，本以为是个爽快ACT，没想到是个没难度选项的纯纯背板受苦魂游，假如游科明说了是难度很高的类魂，那我不会在忙碌中挤出一天假期，但游科说这玩意是ARPG，网络宣发也说是类战神，再不济也是仁王，早起本以为能爽玩，没想到是坐大牢，有落差+状态不佳直接干到道心破碎，我不是不会练，而是在这个时间点我没这个心态给你凹，但凡你说是类魂，我就找周末静心来练，某些狭隘孝子，真觉得世界上就只有一种玩家？狭隘地认为自家第一个打响世界的神坛只配小部分高端精英玩家玩？这种人比单机婆罗门还恶臭，环境里的真正的搅屎棍，记住，你玩某个游戏时间长，很厉害，那只会证明你是一个很闲的闲人罢了，游戏里的你，再强大都是虚拟的。但游戏质量真是目前国内3A巅峰水准，极致的堆料，村里出来的第一个大学生，第一次肯定是有点缺点，国内游戏历程是有目共睹的，如今在落后世界好几年的畸形环境里终于诞生出一个，我是真心包容支持的，真心祝愿这游戏能吸纳玩家反馈优化不良体验变得更好，中国单机游戏能诞生更多优秀的作品，喜欢这游戏的天命人能游戏愉快。（这社媒宣发真离谱，一个个博主生怕吃不到流量，全在蹭热度，游戏还没出一天，就仗着先玩先录的素材争先恐后地把各种剧透各种攻略发上来，网都没法上了）（还有这边玩家群体的风气也离谱，一个游戏难玩，玩不爽，那应该先去质疑策划，提出游戏缺点，要求合理合法的游戏体验，游戏公司不妥协再考虑看攻略找轮椅/开挂降难度或者别玩，而不是第一时间下意识想到走捷径开挂作弊，把游戏厂商和其作品当成完全不容置疑的神） | I25: 免费获取的产品 目前不推荐任何不喜欢魂游受虐模式的轻度路人玩家跟风买这个游戏。（这不是差评，是基于目前宣发狂热氛围下对轻度玩家的谨慎购入建议，别那么二极管/狭隘排外自卑）能做出来个没难度选项的纯背板的魂游我是真没想过的，前面大头娃起码背板个80%打过了，现在打个白衣居士被打到道心破碎，真没想到是个纯背板才能打得过的魂游，继承魂的体力条机制，365里路跑图，延迟滚，翻滚窗口滞连第二次，UI弄得贼小打起来根本没空注视体力条（要求熟练背板），武器机制要求 背死板，不然一点收益都吃不到，一点容错都没有，翻滚延迟考背板，要垫轻击的重击GP要背板，两个都TM有前摇延迟，判定窗口还贼短，打个BOSS要考跳跃、完美闪避、连招窗口，背板背板背得道心破碎了，但凡TM的翻滚没前摇都能爽起来，这一点起码加了90%的难度，傻逼玩意好学不学学TM魂游搞翻滚前摇延迟，我背完怪物出招时间点，背连招逻辑就算了，我还得背自己的输入延迟，TMD完美闪避的判定还TMD终极诡异，我纯战士翻滚打完1.0法环白金都没这么难受，法环那延迟滚都没这个诡异，考试也不上来就高强度考全科目，日NM的难度翻倍，不背板根本不能正常过关，要降难度只能去刷小怪攒经验升级加点，策划真要做魂游为什么不写明白，BOSS不仅性能碾压玩家，还会读指令，一些远程攻击还带穿模穿墙穿透的，还搞那么多地形凹凸，初见我被幽魂那穿墙射线整笑了还有那个独立的移动重击蓄力系统，我都搞不懂策划是怎么想出来这么割裂的招式，这游戏动作衔接就僵硬，因为没有招式取消后摇，必须播完动画帧，而单重击霸体没无敌时间，伤害能吃到饱，还得讲究背板输出窗口，那重击点攒起来就费劲，打空直接血亏，更别说那个要垫轻击的重击GP，我就没见过如此多施展条件的逆天招式，不是自由态施展，要垫刀，而轻击分5下，每下前后摇逐步增长，而闪避和衔接招式都要等攻击动作帧播完了才能派生下一招，而这个派生窗口还极短，还不能闪避打断/被打断（闪避继承连招拆进后期技能树了），导致凹一个重击GP，我先要费力完美闪避+蹭轻击攒一个重击点，然后还得专注背板读招在怪物身上找机会垫一刀轻击，然后再赌怪物会打我延迟重击的一瞬间，千辛万苦遇到窗口重击到了，那收益还不如不打GP直接平A攒重击点直接派生凹GP砸灌伤害，而怪物大概率快打完连招即将进入自由态，那很可能读指令后撤步，重击还是罚站原地释放的，攻击距离还短，而那些BOSS机动高，抬手还快，空GP砸棍直接血压拉满，而且觉得和连招系统巨割裂，仿佛这重击纯属是个偶尔放一下的战技。说是ARPG，但前期这个角色性能差得离谱，技能树一眼望到头，基本上玩死一种招式，战斗体验毫无深度，重击太割裂难用又要用，只能一直找输出窗口平A偷刀，而怪物性能却强到考全科目，装备类别也是经典木棍打小龙虾迭代，打得跟类魂一样，根本不能很爽的交互，这种机制数值不对等的难，游科有在乎过轻度玩家的体验？真觉得魂游市场很大？还是说宣发足够后“自有大儒为你辩经”？还有手柄震动几乎没有，锁定视角转速跟不上游戏里的BOSS各种飘逸移速然后是这个地图，问题可太大了，没有标志物，怪物貌似没掉落伤害但玩家有掉落伤害，而且一些在其他游戏中看着出去就死亡的场景，比如悬崖，一些边缘，河流，放这里面可能是另一条能走的岔路，而且还分不清是不是主线路还是支线路，十有八九还往里面藏BOSS，在线性箱庭里面藏大线性箱庭岔路，对于有经验的玩家极其不友好，谁知道你能不能走，是不是主线，有没有漏关键道具，谁知道你是惊喜还是惊吓，只能指望那个“防跌落”的空气墙动作去试探，然而真有落差却能过去的地方，却能把玩家摔掉血，指引只有在篝火点附近的主线一本道有光点指引，探图体验太晕了，这还是个有跑图压力的魂游，提心吊胆摸路还摸到迷路，虽说堆料，但游戏体验非常不舒服还好没脑子热跟风买，本以为是个爽快ACT，没想到是个没难度选项的纯纯背板受苦魂游，假如游科明说了是难度很高的类魂，那我不会在忙碌中挤出一天假期，但游科说这玩意是ARPG，网络宣发也说是类战神，再不济也是仁王，早起本以为能爽玩，没想到是坐大牢，有落差+状态不佳直接干到道心破碎，我不是不会练，而是在这个时间点我没这个心态给你凹，但凡你说是类魂，我就找周末静心来练，某些狭隘孝子，真觉得世界上就只有一种玩家？狭隘地认为自家第一个打响世界的神坛只配小部分高端精英玩家玩？这种人比单机婆罗门还恶臭，环境里的真正的搅屎棍，记住，你玩某个游戏时间长，很厉害，那只会证明你是一个很闲的闲人罢了，游戏里的你，再强大都是虚拟的。但游戏质量真是目前国内3A巅峰水准，极致的堆料，村里出来的第一个大学生，第一次肯定是有点缺点，国内游戏历程是有目共睹的，如今在落后世界好几年的畸形环境里终于诞生出一个，我是真心包容支持的，真心祝愿这游戏能吸纳玩家反馈优化不良体验变得更好，中国单机游戏能诞生更多优秀的作品，喜欢这游戏的天命人能游戏愉快。（这社媒宣发真离谱，一个个博主生怕吃不到流量，全在蹭热度，游戏还没出一天，就仗着先玩先录的素材争先恐后地把各种剧透各种攻略发上来，网都没法上了）（还有这边玩家群体的风气也离谱，一个游戏难玩，玩不爽，那应该先去质疑策划，提出游戏缺点，要求合理合法的游戏体验，游戏公司不妥协再考虑看攻略找轮椅/开挂降难度或者别玩，而不是第一时间下意识想到走捷径开挂作弊，把游戏厂商和其作品当成完全不容置疑的神） | J25: =IF(SUM(R25:T25)>0,1,0) -> 1 | K25: =IF(SUM(U25:Y25)>0,1,0) -> 1 | L25: =IF(SUM(Z25:AC25)>0,1,0) -> 1 | M25: =IF(SUM(AD25:AF25)>0,1,0) -> 1 | N25: =IF(SUM(AG25:AH25)>0,1,0) -> 1 | O25: =IF(SUM(AI25:AL25)>0,1,0) -> 1 | P25: =IF(SUM(AM25:AQ25)>0,1,0) -> 1 | Q25: =IF(AR25>0,1,0) -> 0 | R25: 1 | S25: 0 | T25: 1 | U25: 1 | V25: 1 | W25: 1 | X25: 1 | Y25: 1 | Z25: 1 | AA25: 1 | AB25: 1 | AC25: 1 | AD25: 1 | AE25: 0 | AF25: 0 | AG25: 1 | AH25: 1 | AI25: 1 | AJ25: 0 | AK25: 1 | AL25: 0 | AM25: 0 | AN25: 0 | AO25: 0 | AP25: 1 | AQ25: 0 | AR25: 0 | AS25: =SUM(J25:Q25) -> 7 | AT25: =SUM(R25:AR25) -> 17 | AU25: 画面美术场景；演出角色怪物设计；动作打击手感；Boss战斗节奏；难度挑战；锁定视角；判定反馈；地图路线；空气墙可达性；探索隐藏支线；引导迷路单线；优化帧率；整体完成度；推荐价值判断；西游悟空符号；本国媒介路径；外部资料依赖 | AV25: =IF(AT25>0,1,0) -> 1 | AW25: =IF(AT25=0,1,0) -> 0 | AX25: =IF(AT25>=8,1,0) -> 1 | AY25: -3.5 | AZ25: 负面 | BA25: N | BB25: 原文
A26: CN-N-025 | B26: 中文 | C26: 不推荐 | D26: 144 | E26: 11 | F26: 12.2 | G26: 2024-08-20 | H26: 为什么不能自定义手柄键位？ 首先，也是我打差评的重要原因，为什么不能改手柄键位，我玩过的那么多游戏中，第一次遇到不能改键位的游戏就是黑神话了，如果给游戏加一个自定义键位的功能很难，我会撤回这个差评的，毕竟游科的工作人员也是打工人，打工人的命也是命。我不希望原本游玩游戏的时间要腾出一段时间去适应新的键位习惯。 地图设计为了给美术让步，设置了很多无用的空气墙，减弱了引导，导致我在地图中游玩时不时就会迷路，即使每场boss战都让人那么激动人心，但是其中找路的负反馈还是冲淡了体验，况且我菜，boss那么能打，让我法环都是摇铃铛过来的人很为难。 还有就是视角锁定，锁定到某些boss（说的就是黑熊精。）视角飘忽的跟着boss飞来飞去，出招都看不清楚，还有，有时候锁定敌人的时候回突然锁定到更远的敌人，怪一多，视角就很怪。 即便如此，我也觉得黑神话悟空给我带来的体验和我玩法环dlc的体验一样，惊艳的boss，优秀的美术，但是绝对不是所谓的无暇之作，希望游科下一部作品千万要加自定义键位，（末尾叠甲，要骂就骂，如果从骂人升级到线下开盒，我立马删差评，加好评，真是怕了一些人。还有还有，如果后续加了自定义键位，我也马上删差评，先玩完再说，时间有限。） | I26: 为什么不能自定义手柄键位？ 首先，也是我打差评的重要原因，为什么不能改手柄键位，我玩过的那么多游戏中，第一次遇到不能改键位的游戏就是黑神话了，如果给游戏加一个自定义键位的功能很难，我会撤回这个差评的，毕竟游科的工作人员也是打工人，打工人的命也是命。我不希望原本游玩游戏的时间要腾出一段时间去适应新的键位习惯。 地图设计为了给美术让步，设置了很多无用的空气墙，减弱了引导，导致我在地图中游玩时不时就会迷路，即使每场boss战都让人那么激动人心，但是其中找路的负反馈还是冲淡了体验，况且我菜，boss那么能打，让我法环都是摇铃铛过来的人很为难。 还有就是视角锁定，锁定到某些boss（说的就是黑熊精。）视角飘忽的跟着boss飞来飞去，出招都看不清楚，还有，有时候锁定敌人的时候回突然锁定到更远的敌人，怪一多，视角就很怪。 即便如此，我也觉得黑神话悟空给我带来的体验和我玩法环dlc的体验一样，惊艳的boss，优秀的美术，但是绝对不是所谓的无暇之作，希望游科下一部作品千万要加自定义键位，（末尾叠甲，要骂就骂，如果从骂人升级到线下开盒，我立马删差评，加好评，真是怕了一些人。还有还有，如果后续加了自定义键位，我也马上删差评，先玩完再说，时间有限。） | J26: =IF(SUM(R26:T26)>0,1,0) -> 1 | K26: =IF(SUM(U26:Y26)>0,1,0) -> 1 | L26: =IF(SUM(Z26:AC26)>0,1,0) -> 1 | M26: =IF(SUM(AD26:AF26)>0,1,0) -> 0 | N26: =IF(SUM(AG26:AH26)>0,1,0) -> 1 | O26: =IF(SUM(AI26:AL26)>0,1,0) -> 1 | P26: =IF(SUM(AM26:AQ26)>0,1,0) -> 0 | Q26: =IF(AR26>0,1,0) -> 0 | R26: 1 | S26: 0 | T26: 0 | U26: 0 | V26: 1 | W26: 1 | X26: 1 | Y26: 1 | Z26: 1 | AA26: 1 | AB26: 0 | AC26: 1 | AD26: 0 | AE26: 0 | AF26: 0 | AG26: 0 | AH26: 1 | AI26: 1 | AJ26: 0 | AK26: 0 | AL26: 0 | AM26: 0 | AN26: 0 | AO26: 0 | AP26: 0 | AQ26: 0 | AR26: 0 | AS26: =SUM(J26:Q26) -> 5 | AT26: =SUM(R26:AR26) -> 10 | AU26: 画面美术场景；Boss战斗节奏；难度挑战；锁定视角；判定反馈；地图路线；空气墙可达性；引导迷路单线；推荐价值判断；西游悟空符号 | AV26: =IF(AT26>0,1,0) -> 1 | AW26: =IF(AT26=0,1,0) -> 0 | AX26: =IF(AT26>=8,1,0) -> 1 | AY26: -1 | AZ26: 负面 | BA26: N | BB26: 原文
A27: CN-P-026 | B27: 中文 | C27: 推荐 | D27: 122 | E27: 1 | F27: 218.1 | G27: 2024-08-20 | H27: 都是二十多的人了，一想到大圣还能给我们这些玩家这么多感动，真着有点泪目了，中国玩家等这一天太久了，真的。能看到国产游戏有这样的质量，我真的已经非常满足了，音乐美术完美，boss战，棍花的设计，线性的成长，齐天大圣的刻画，建模精良，我steamdeck和pc都有在玩，还是很流畅的，deck也能全程高贴图，除了雪山区域有所掉帧。 大圣最后一战，真的很难绷，看着大圣用定身法，弹反我的立棍，抢我的葫芦，猴子猴孙圈踢我，还是把金箍棒给我踢过来叫我继续打，继续战斗，那一刻我鸡皮疙瘩都起来了。这才是大圣，我打其他游戏的boss只想快速打死他，但跟大圣打，我很享受，我在最后我也很不舍得结束。 大圣在我心中永存，那个中国小男孩小的时候没有金箍棒呢。剧情有些许欠缺。最后两章感觉有点赶工。 （我他妈只想打如来和玉帝，跪求天庭DLC，最后戴上紧箍咒我心态有点小崩我说实话。） 哪怕是没有小地图，空气墙，但我真的觉得完成度已经很高了。能感觉的到是真正用心做的游戏，每一个建模，每一个细节，一张一弛。 踏平坎坷成大道，历代驰名第一妖大道已成，又何须那袈裟来证游戏科学牛逼 | I27: 都是二十多的人了，一想到大圣还能给我们这些玩家这么多感动，真着有点泪目了，中国玩家等这一天太久了，真的。能看到国产游戏有这样的质量，我真的已经非常满足了，音乐美术完美，boss战，棍花的设计，线性的成长，齐天大圣的刻画，建模精良，我steamdeck和pc都有在玩，还是很流畅的，deck也能全程高贴图，除了雪山区域有所掉帧。 大圣最后一战，真的很难绷，看着大圣用定身法，弹反我的立棍，抢我的葫芦，猴子猴孙圈踢我，还是把金箍棒给我踢过来叫我继续打，继续战斗，那一刻我鸡皮疙瘩都起来了。这才是大圣，我打其他游戏的boss只想快速打死他，但跟大圣打，我很享受，我在最后我也很不舍得结束。 大圣在我心中永存，那个中国小男孩小的时候没有金箍棒呢。剧情有些许欠缺。最后两章感觉有点赶工。 （我他妈只想打如来和玉帝，跪求天庭DLC，最后戴上紧箍咒我心态有点小崩我说实话。） 哪怕是没有小地图，空气墙，但我真的觉得完成度已经很高了。能感觉的到是真正用心做的游戏，每一个建模，每一个细节，一张一弛。 踏平坎坷成大道，历代驰名第一妖大道已成，又何须那袈裟来证游戏科学牛逼 | J27: =IF(SUM(R27:T27)>0,1,0) -> 1 | K27: =IF(SUM(U27:Y27)>0,1,0) -> 1 | L27: =IF(SUM(Z27:AC27)>0,1,0) -> 1 | M27: =IF(SUM(AD27:AF27)>0,1,0) -> 1 | N27: =IF(SUM(AG27:AH27)>0,1,0) -> 1 | O27: =IF(SUM(AI27:AL27)>0,1,0) -> 1 | P27: =IF(SUM(AM27:AQ27)>0,1,0) -> 0 | Q27: =IF(AR27>0,1,0) -> 1 | R27: 1 | S27: 1 | T27: 0 | U27: 1 | V27: 1 | W27: 1 | X27: 0 | Y27: 0 | Z27: 1 | AA27: 1 | AB27: 0 | AC27: 1 | AD27: 1 | AE27: 0 | AF27: 1 | AG27: 1 | AH27: 0 | AI27: 1 | AJ27: 0 | AK27: 0 | AL27: 1 | AM27: 0 | AN27: 0 | AO27: 0 | AP27: 0 | AQ27: 0 | AR27: 1 | AS27: =SUM(J27:Q27) -> 7 | AT27: =SUM(R27:AR27) -> 14 | AU27: 画面美术场景；音乐音效配音；动作打击手感；Boss战斗节奏；难度挑战；地图路线；空气墙可达性；引导迷路单线；优化帧率；Bug兼容硬件；整体完成度；西游悟空符号；中国文化宗教语言审美；国产3A身份期待 | AV27: =IF(AT27>0,1,0) -> 1 | AW27: =IF(AT27=0,1,0) -> 0 | AX27: =IF(AT27>=8,1,0) -> 1 | AY27: 22 | AZ27: 正面 | BA27: P | BB27: 原文
A28: CN-P-027 | B28: 中文 | C28: 推荐 | D28: 113 | E28: 0 | F28: 42.3 | G28: 2024-08-20 | H28: 这样的事情，终归需要有人来做！ 《黑神话：悟空》作为我国第一款3A作品，以如此火爆的姿势风靡全球着实是让国人大大的长脸，也狠狠的给国内那些只愿做赚快钱氪金手游的所谓大厂扇一个大耳光，实属快哉！谁说我大天朝就制作不出3A大作？一是不愿，二依然是不愿而已！（请细品！） 欢迎关注 网易UU鉴赏家培养计划 关注UU加速器VX公众号，回复“steam”，获得专属玩家群邀请。 齐天大圣的呐喊，举世皆惊！ 所谓“3A大作”其实就是A Lot Of Monet(大量的金钱)、A Lot Of Resources(大量的资源）”和A Lot Of Time(大量的时间）制作而成的大型单机游戏。这类游戏往往在画面、音效音乐、剧情和玩法上都达到业界的顶尖水准。在之前市面上的3A游戏都是国外公司制作，《黑神话：悟空》由游戏科学团队历经俩轮融资耗费4亿历时6年制作而成，其中花费的精力和承受的压力难以想象，但该团队秉承心中的信仰，硬生生扛了过去，在2024年8月20日这天，一经发售就打破各种记录，以傲人的成绩成功的向世人发出了齐天大圣不畏艰难所向披靡的呐喊！ 无畏ZZZQ的优秀建模！ 《黑神话：悟空》采用了最新的虚幻5引擎制作，在机器配置足够的前提下，那画面简直无与伦比，各种以现实实景为基础的环境画面，加上光追效果的加持，如梦似幻之下，让玩家忙碌的一天之后享受一份心灵的空灵。 角色建模也是如此，本身原著《西游记》里对各路妖怪就有着详细至极绘声绘色的形象描绘，《黑神话：悟空》只需要借鉴一二，制作出来的妖怪必然活灵活现，熟悉《西游记》的小伙伴还能直接就在脑海里将之对比一二，徒增几分熟悉感。特别是那些蜘蛛精四妹和小狐狸萍萍更是让众多小伙伴激动的流下口水！多少被国外ZZZQ摧残审美多年的外国小伙伴也是流下来羡慕的泪水！大伙为坚持正确审美的制作组鼓掌欢呼吧！ 不过有一说一，晕3D的世纪难题依然存在，习惯边走边左右摇晃周边场景的小伙伴感觉尤为明显，这点可能还得制作组加强优化才行，能通过优化让吾等晕3D的天命人减缓一分是一分哇！当然，有些时候也是可以存档下线休息一会再玩，这个时候就可以考虑使用UU云存档，一键自动备份存档，还能锁定关键存档，实在打不过到存档超市下载大神存档也行，关键是还能免费使用，相当给力！ 当年一猴一棍尚且敢直面漫天神佛，何况如今有千万天命人！ 《黑神话：悟空》的故事改编自我大天朝四大名著之一的《西游记》，其中不乏一些我们耳熟能详的仙魔人物，当然，游戏故事既然以“黑神话”的形式展现，角色形象自然有着另一种不同的演绎，但大圣终究是大圣，十万天兵天将和漫天神佛都不放在眼里，又何畏再一次八十一难？（坊间笑谈：目前一千来万的销量，一千多万的天命人，十万天兵天将平均每人要面对100个天命人，该瑟瑟发抖的是天兵天将才对！） 让人发指的探索深度 《黑神话：悟空》在内容上也秉承了《西游记》让人深思让人探索的深度，许多内容和剧情都需要我们进行认真的探索后才能顺利通过，很多BOSS的通过契机其实也是在探索之后获得某样法宝道具后就能轻松打败。众多前期的开荒玩家各种失败其实就是为了速通探索不足没获得对应法宝道具导致。毕竟是神话题材，辟火罩、定风珠等法宝所具有的神通相当给力（对国外友人来说也许就有点匪夷所思了）。深度的探索，细细的品味，用心体验游戏带给我们不一样的黑神话传说！（我是不会告诉你不细心探索和思考对白的话，甚至锻造功能都会错过解锁的） 接俺老孙一棍！ 作为一款类魂动作游戏，《黑神话：悟空》的战斗系统也是制作得极为出色。当然，对许多游戏苦手（比如本人）来说，难度也是不低的，不过操作着猴哥闻名西游天下的各种技能，什么金刚不坏身（铜头铁臂）、七十二变（变身术）、定身术、毫毛分身等等应有尽有，加上那充满力量的几棍连击，立棍暴击等等，要不是本人实在手残，没法畅快淋漓的轻松收拾各路妖怪，真想在一套连击后问问这些敢当阻挡吾等天命人的妖怪：俺老孙这一棍一万三千五百斤，汝等妖怪受死！！！（可惜这些妖怪可能多少都有点背景，俺老孙是真的打不过哇！） 希望这是辉煌的起点！ 按游戏目前的热度（连外交部都被惊动了），相信很快就会有漫天遍野的通关攻略、视频面世，游戏里许多需要细心探索后才能发现的隐藏要素肯定也会被一点点揭秘，一个BOSS卡玩家几天的情况也会因此逐渐减少，也许对许多高手来说会减少许多乐趣，但相对的，对许多游戏苦手来说这可都是利好消息，这里友情提示下哦！《黑神话：悟空》可是一个有多结局的，各位天命人终归需要多来几周目才行的！熟能生巧之下，也许真能成就战无不胜的齐天大圣哦！ | I28: 这样的事情，终归需要有人来做！ 《黑神话：悟空》作为我国第一款3A作品，以如此火爆的姿势风靡全球着实是让国人大大的长脸，也狠狠的给国内那些只愿做赚快钱氪金手游的所谓大厂扇一个大耳光，实属快哉！谁说我大天朝就制作不出3A大作？一是不愿，二依然是不愿而已！（请细品！） 欢迎关注 网易UU鉴赏家培养计划 关注UU加速器VX公众号，回复“steam”，获得专属玩家群邀请。 齐天大圣的呐喊，举世皆惊！ 所谓“3A大作”其实就是A Lot Of Monet(大量的金钱)、A Lot Of Resources(大量的资源）”和A Lot Of Time(大量的时间）制作而成的大型单机游戏。这类游戏往往在画面、音效音乐、剧情和玩法上都达到业界的顶尖水准。在之前市面上的3A游戏都是国外公司制作，《黑神话：悟空》由游戏科学团队历经俩轮融资耗费4亿历时6年制作而成，其中花费的精力和承受的压力难以想象，但该团队秉承心中的信仰，硬生生扛了过去，在2024年8月20日这天，一经发售就打破各种记录，以傲人的成绩成功的向世人发出了齐天大圣不畏艰难所向披靡的呐喊！ 无畏ZZZQ的优秀建模！ 《黑神话：悟空》采用了最新的虚幻5引擎制作，在机器配置足够的前提下，那画面简直无与伦比，各种以现实实景为基础的环境画面，加上光追效果的加持，如梦似幻之下，让玩家忙碌的一天之后享受一份心灵的空灵。 角色建模也是如此，本身原著《西游记》里对各路妖怪就有着详细至极绘声绘色的形象描绘，《黑神话：悟空》只需要借鉴一二，制作出来的妖怪必然活灵活现，熟悉《西游记》的小伙伴还能直接就在脑海里将之对比一二，徒增几分熟悉感。特别是那些蜘蛛精四妹和小狐狸萍萍更是让众多小伙伴激动的流下口水！多少被国外ZZZQ摧残审美多年的外国小伙伴也是流下来羡慕的泪水！大伙为坚持正确审美的制作组鼓掌欢呼吧！ 不过有一说一，晕3D的世纪难题依然存在，习惯边走边左右摇晃周边场景的小伙伴感觉尤为明显，这点可能还得制作组加强优化才行，能通过优化让吾等晕3D的天命人减缓一分是一分哇！当然，有些时候也是可以存档下线休息一会再玩，这个时候就可以考虑使用UU云存档，一键自动备份存档，还能锁定关键存档，实在打不过到存档超市下载大神存档也行，关键是还能免费使用，相当给力！ 当年一猴一棍尚且敢直面漫天神佛，何况如今有千万天命人！ 《黑神话：悟空》的故事改编自我大天朝四大名著之一的《西游记》，其中不乏一些我们耳熟能详的仙魔人物，当然，游戏故事既然以“黑神话”的形式展现，角色形象自然有着另一种不同的演绎，但大圣终究是大圣，十万天兵天将和漫天神佛都不放在眼里，又何畏再一次八十一难？（坊间笑谈：目前一千来万的销量，一千多万的天命人，十万天兵天将平均每人要面对100个天命人，该瑟瑟发抖的是天兵天将才对！） 让人发指的探索深度 《黑神话：悟空》在内容上也秉承了《西游记》让人深思让人探索的深度，许多内容和剧情都需要我们进行认真的探索后才能顺利通过，很多BOSS的通过契机其实也是在探索之后获得某样法宝道具后就能轻松打败。众多前期的开荒玩家各种失败其实就是为了速通探索不足没获得对应法宝道具导致。毕竟是神话题材，辟火罩、定风珠等法宝所具有的神通相当给力（对国外友人来说也许就有点匪夷所思了）。深度的探索，细细的品味，用心体验游戏带给我们不一样的黑神话传说！（我是不会告诉你不细心探索和思考对白的话，甚至锻造功能都会错过解锁的） 接俺老孙一棍！ 作为一款类魂动作游戏，《黑神话：悟空》的战斗系统也是制作得极为出色。当然，对许多游戏苦手（比如本人）来说，难度也是不低的，不过操作着猴哥闻名西游天下的各种技能，什么金刚不坏身（铜头铁臂）、七十二变（变身术）、定身术、毫毛分身等等应有尽有，加上那充满力量的几棍连击，立棍暴击等等，要不是本人实在手残，没法畅快淋漓的轻松收拾各路妖怪，真想在一套连击后问问这些敢当阻挡吾等天命人的妖怪：俺老孙这一棍一万三千五百斤，汝等妖怪受死！！！（可惜这些妖怪可能多少都有点背景，俺老孙是真的打不过哇！） 希望这是辉煌的起点！ 按游戏目前的热度（连外交部都被惊动了），相信很快就会有漫天遍野的通关攻略、视频面世，游戏里许多需要细心探索后才能发现的隐藏要素肯定也会被一点点揭秘，一个BOSS卡玩家几天的情况也会因此逐渐减少，也许对许多高手来说会减少许多乐趣，但相对的，对许多游戏苦手来说这可都是利好消息，这里友情提示下哦！《黑神话：悟空》可是一个有多结局的，各位天命人终归需要多来几周目才行的！熟能生巧之下，也许真能成就战无不胜的齐天大圣哦！ | J28: =IF(SUM(R28:T28)>0,1,0) -> 1 | K28: =IF(SUM(U28:Y28)>0,1,0) -> 1 | L28: =IF(SUM(Z28:AC28)>0,1,0) -> 1 | M28: =IF(SUM(AD28:AF28)>0,1,0) -> 1 | N28: =IF(SUM(AG28:AH28)>0,1,0) -> 1 | O28: =IF(SUM(AI28:AL28)>0,1,0) -> 1 | P28: =IF(SUM(AM28:AQ28)>0,1,0) -> 1 | Q28: =IF(AR28>0,1,0) -> 1 | R28: 1 | S28: 1 | T28: 0 | U28: 1 | V28: 1 | W28: 1 | X28: 1 | Y28: 0 | Z28: 0 | AA28: 0 | AB28: 1 | AC28: 0 | AD28: 1 | AE28: 0 | AF28: 1 | AG28: 1 | AH28: 0 | AI28: 1 | AJ28: 0 | AK28: 0 | AL28: 1 | AM28: 0 | AN28: 0 | AO28: 0 | AP28: 1 | AQ28: 1 | AR28: 1 | AS28: =SUM(J28:Q28) -> 8 | AT28: =SUM(R28:AR28) -> 15 | AU28: 画面美术场景；音乐音效配音；动作打击手感；Boss战斗节奏；难度挑战；锁定视角；探索隐藏支线；优化帧率；Bug兼容硬件；整体完成度；西游悟空符号；中国文化宗教语言审美；外部资料依赖；角色期待意义偏移；国产3A身份期待 | AV28: =IF(AT28>0,1,0) -> 1 | AW28: =IF(AT28=0,1,0) -> 0 | AX28: =IF(AT28>=8,1,0) -> 1 | AY28: 107.5 | AZ28: 正面 | BA28: P | BB28: 原文
A29: CN-M-028 | B29: 中文 | C29: 推荐 | D29: 105 | E29: 11 | F29: 52 | G29: 2024-08-20 | H29: 不是，哥，加个地图吧，真不认路。我对着地图左拐右拐都找不到该找的地 | I29: 不是，哥，加个地图吧，真不认路。我对着地图左拐右拐都找不到该找的地 | J29: =IF(SUM(R29:T29)>0,1,0) -> 0 | K29: =IF(SUM(U29:Y29)>0,1,0) -> 0 | L29: =IF(SUM(Z29:AC29)>0,1,0) -> 1 | M29: =IF(SUM(AD29:AF29)>0,1,0) -> 0 | N29: =IF(SUM(AG29:AH29)>0,1,0) -> 0 | O29: =IF(SUM(AI29:AL29)>0,1,0) -> 0 | P29: =IF(SUM(AM29:AQ29)>0,1,0) -> 0 | Q29: =IF(AR29>0,1,0) -> 0 | R29: 0 | S29: 0 | T29: 0 | U29: 0 | V29: 0 | W29: 0 | X29: 0 | Y29: 0 | Z29: 1 | AA29: 0 | AB29: 0 | AC29: 0 | AD29: 0 | AE29: 0 | AF29: 0 | AG29: 0 | AH29: 0 | AI29: 0 | AJ29: 0 | AK29: 0 | AL29: 0 | AM29: 0 | AN29: 0 | AO29: 0 | AP29: 0 | AQ29: 0 | AR29: 0 | AS29: =SUM(J29:Q29) -> 1 | AT29: =SUM(R29:AR29) -> 1 | AU29: 地图路线 | AV29: =IF(AT29>0,1,0) -> 1 | AW29: =IF(AT29=0,1,0) -> 0 | AX29: =IF(AT29>=8,1,0) -> 0 | AY29: 0 | AZ29: 中性 | BA29: M | BB29: 原文
A30: CN-P-029 | B30: 中文 | C30: 推荐 | D30: 105 | E30: 6 | F30: 55.9 | G30: 2024-08-20 | H30: 十四年前，我还是个小屁孩的时候，接触到了斗战神这款游戏，当时的我不懂什么是配装，哪个职业最好玩，哪个流派最牛逼，只知道每天没日没夜的推进剧情。虽然当时的我对剧情也是懵懵懂懂，但优秀的演出、丰富的配音、动人的故事是支撑着我玩下去的动力。第三章之后，主线剧情肉眼可见的下滑，我便慢慢失去了玩下去的动力......十年之后，游戏科学的第一个视频火爆全网，当我知道这是当年开发斗战神前三章内容的主创团队时，立马引起了我的兴趣，也知道了当年团队存在的苦衷。如果是他们的话，或许真的能弥补当年的遗憾。苦等四年，今日终得发售，白骨之后，重走西游！游戏的质量和体量大大超出了我的预期。我相信这只是中国单机游戏市场百花齐放的第一步，我们中国人有能力做好自己的游戏，有能力讲好属于自己的故事，这就是我心目中的年度最佳。 | I30: 十四年前，我还是个小屁孩的时候，接触到了斗战神这款游戏，当时的我不懂什么是配装，哪个职业最好玩，哪个流派最牛逼，只知道每天没日没夜的推进剧情。虽然当时的我对剧情也是懵懵懂懂，但优秀的演出、丰富的配音、动人的故事是支撑着我玩下去的动力。第三章之后，主线剧情肉眼可见的下滑，我便慢慢失去了玩下去的动力......十年之后，游戏科学的第一个视频火爆全网，当我知道这是当年开发斗战神前三章内容的主创团队时，立马引起了我的兴趣，也知道了当年团队存在的苦衷。如果是他们的话，或许真的能弥补当年的遗憾。苦等四年，今日终得发售，白骨之后，重走西游！游戏的质量和体量大大超出了我的预期。我相信这只是中国单机游戏市场百花齐放的第一步，我们中国人有能力做好自己的游戏，有能力讲好属于自己的故事，这就是我心目中的年度最佳。 | J30: =IF(SUM(R30:T30)>0,1,0) -> 1 | K30: =IF(SUM(U30:Y30)>0,1,0) -> 1 | L30: =IF(SUM(Z30:AC30)>0,1,0) -> 0 | M30: =IF(SUM(AD30:AF30)>0,1,0) -> 0 | N30: =IF(SUM(AG30:AH30)>0,1,0) -> 1 | O30: =IF(SUM(AI30:AL30)>0,1,0) -> 1 | P30: =IF(SUM(AM30:AQ30)>0,1,0) -> 1 | Q30: =IF(AR30>0,1,0) -> 1 | R30: 0 | S30: 1 | T30: 1 | U30: 1 | V30: 0 | W30: 0 | X30: 0 | Y30: 0 | Z30: 0 | AA30: 0 | AB30: 0 | AC30: 0 | AD30: 0 | AE30: 0 | AF30: 0 | AG30: 1 | AH30: 1 | AI30: 1 | AJ30: 0 | AK30: 0 | AL30: 0 | AM30: 0 | AN30: 1 | AO30: 0 | AP30: 0 | AQ30: 0 | AR30: 1 | AS30: =SUM(J30:Q30) -> 6 | AT30: =SUM(R30:AR30) -> 8 | AU30: 音乐音效配音；演出角色怪物设计；动作打击手感；整体完成度；推荐价值判断；西游悟空符号；原典知识人物关系专名；国产3A身份期待 | AV30: =IF(AT30>0,1,0) -> 1 | AW30: =IF(AT30=0,1,0) -> 0 | AX30: =IF(AT30>=8,1,0) -> 1 | AY30: 15.5 | AZ30: 正面 | BA30: P | BB30: 原文
A31: CN-P-030 | B31: 中文 | C31: 推荐 | D31: 100 | E31: 3 | F31: 50.6 | G31: 2024-08-20 | H31: 踏上取经路，比抵达灵山更难——冯骥事实证明，只有觉得不够好，想要做的更好，才会有做出好游戏的可能；事实证明，战斗是没法黑的，切手技需要一些理解和熟练，但真的比弹反好玩太多了；事实证明，精妙的BOSS设计，哪怕是连续的大小BOSS也不带腻的；事实证明，传统国乐很多时候适宜且美妙；事实证明，国色古香味的场景，就是山川湖泊的味道；事实证明，剧情还没看完，看完再说！友情提醒DLSS之类的别开低了小心锯齿和穿模可能场景和技能特效的设计，会让战斗视角些微难受，也算是瑕疵了。 | I31: 踏上取经路，比抵达灵山更难——冯骥事实证明，只有觉得不够好，想要做的更好，才会有做出好游戏的可能；事实证明，战斗是没法黑的，切手技需要一些理解和熟练，但真的比弹反好玩太多了；事实证明，精妙的BOSS设计，哪怕是连续的大小BOSS也不带腻的；事实证明，传统国乐很多时候适宜且美妙；事实证明，国色古香味的场景，就是山川湖泊的味道；事实证明，剧情还没看完，看完再说！友情提醒DLSS之类的别开低了小心锯齿和穿模可能场景和技能特效的设计，会让战斗视角些微难受，也算是瑕疵了。 | J31: =IF(SUM(R31:T31)>0,1,0) -> 1 | K31: =IF(SUM(U31:Y31)>0,1,0) -> 1 | L31: =IF(SUM(Z31:AC31)>0,1,0) -> 0 | M31: =IF(SUM(AD31:AF31)>0,1,0) -> 1 | N31: =IF(SUM(AG31:AH31)>0,1,0) -> 1 | O31: =IF(SUM(AI31:AL31)>0,1,0) -> 0 | P31: =IF(SUM(AM31:AQ31)>0,1,0) -> 0 | Q31: =IF(AR31>0,1,0) -> 0 | R31: 1 | S31: 0 | T31: 1 | U31: 0 | V31: 1 | W31: 0 | X31: 1 | Y31: 0 | Z31: 0 | AA31: 0 | AB31: 0 | AC31: 0 | AD31: 0 | AE31: 0 | AF31: 1 | AG31: 0 | AH31: 1 | AI31: 0 | AJ31: 0 | AK31: 0 | AL31: 0 | AM31: 0 | AN31: 0 | AO31: 0 | AP31: 0 | AQ31: 0 | AR31: 0 | AS31: =SUM(J31:Q31) -> 4 | AT31: =SUM(R31:AR31) -> 6 | AU31: 画面美术场景；演出角色怪物设计；Boss战斗节奏；锁定视角；Bug兼容硬件；推荐价值判断 | AV31: =IF(AT31>0,1,0) -> 1 | AW31: =IF(AT31=0,1,0) -> 0 | AX31: =IF(AT31>=8,1,0) -> 0 | AY31: 11 | AZ31: 正面 | BA31: P | BB31: 原文
A32: CN-P-031 | B32: 中文 | C32: 推荐 | D32: 84 | E32: 5 | F32: 252.2 | G32: 2024-08-20 | H32: 希望国产优质游戏能够越走越远，越来越多，越来越好！ | I32: 希望国产优质游戏能够越走越远，越来越多，越来越好！ | J32: =IF(SUM(R32:T32)>0,1,0) -> 0 | K32: =IF(SUM(U32:Y32)>0,1,0) -> 0 | L32: =IF(SUM(Z32:AC32)>0,1,0) -> 0 | M32: =IF(SUM(AD32:AF32)>0,1,0) -> 0 | N32: =IF(SUM(AG32:AH32)>0,1,0) -> 0 | O32: =IF(SUM(AI32:AL32)>0,1,0) -> 0 | P32: =IF(SUM(AM32:AQ32)>0,1,0) -> 0 | Q32: =IF(AR32>0,1,0) -> 1 | R32: 0 | S32: 0 | T32: 0 | U32: 0 | V32: 0 | W32: 0 | X32: 0 | Y32: 0 | Z32: 0 | AA32: 0 | AB32: 0 | AC32: 0 | AD32: 0 | AE32: 0 | AF32: 0 | AG32: 0 | AH32: 0 | AI32: 0 | AJ32: 0 | AK32: 0 | AL32: 0 | AM32: 0 | AN32: 0 | AO32: 0 | AP32: 0 | AQ32: 0 | AR32: 1 | AS32: =SUM(J32:Q32) -> 1 | AT32: =SUM(R32:AR32) -> 1 | AU32: 国产3A身份期待 | AV32: =IF(AT32>0,1,0) -> 1 | AW32: =IF(AT32=0,1,0) -> 0 | AX32: =IF(AT32>=8,1,0) -> 0 | AY32: 3.5 | AZ32: 正面 | BA32: P | BB32: 原文
A33: CN-P-032 | B33: 中文 | C33: 推荐 | D33: 79 | E33: 1 | F33: 64.5 | G33: 2024-08-20 | H33: 甲辰岁七月既望，余有故交生辰，幼时尝为余述其往昔之奇闻异事，遂成余心中之首出庶物之英雄也。岁序递迁，而关彼之传说，犹自流传于人，未尝稍息。吾终悟之，彼非独吾辈中华之人之旧交，实为普天之炎黄子孙共仰之英豪也！ 谨以此作献给我们的超级英雄。大圣，生日快乐！ 欢迎关注 网易UU鉴赏家培养计划 关注UU加速器VX公众号，回复“steam”，获得专属玩家群邀请。 金猴奋起千钧棒，玉宇澄清万里埃 依然记得小时候蹲守在电视机前等待86版《西游记》的美好时光，那时“资源匮乏”，该片成为了中流砥柱般的存在。可谁又能想到，在影视作品琳琅满目的今天，86版《西游记》的播放量依然无可撼动：大闹天宫、三打白骨精、车迟国斗法·······大圣的一段段传奇故事陪伴着每一位炎黄子孙的成长。 2024年8月20，甲辰年七月十七，大圣回来了！随着《黑神话 悟空》开场动画的进行，他再次独自面对天兵天将的围剿，杨戬的三尖两刃枪迎面袭来，大圣再展神通，电光火石间天地撼、乾坤震，我们的故事就此展开。 重拾棍棒，直面天命，探寻昔日传说的真相。 金猴奋起千钧棒，这一棒，定叫世间邪祟灰飞烟灭！ 真墨隐现，笔精墨妙 《黑神话 悟空》为玩家带来了一场极致的视觉盛宴，它巧妙地将中国古典美学的韵味与现代游戏技术的精湛相融合，尤其是每一话结束后老者说书式的剧情回顾，配合上精美的画卷，每一帧画面都如同精心雕琢的艺术品。 在场景设计方面，《黑神话 悟空》展现出了非凡的创造力与想象力。无论是云雾缭绕的灵山仙境、还是沧桑古朴的庙宇楼阁，这一个个场景保留传统水墨画的淡雅与留白的同时，又巧妙地融入了更加丰富的色彩层次。游戏中的一草一木、一砖一瓦都经过精心设计与布置：谁又能想到，路边随手采摘的草药竟是妖精伪装。 “黑猴——你适合的初恋” 作为一款动作冒险游戏，《黑神话 悟空》的难度最为直观地影响力玩家的游戏体验。犹记得23年820的试玩直播，众多天命人们跃跃欲试却被虎先锋打得苦不堪言，被众多up主成为“最黑暗的时光”，向我这样的手残党适合玩这款游戏吗？重走西游之路真的是在受苦受难吗？ 游戏正式解锁之后这种顾虑烟消云散。基于RPG的核心玩法，玩家通过战斗可以积攒经验，获取技能点并进行相应的强化，碰到打不过的敌人时不妨回去刷刷经验，进行充分的准备后再进行挑战。 第一话难度是最低的，也是玩家的入门第一课。第一话的小妖大家莽就完了，打得他毫无还手之力；头目和妖王虽然略有些棘手，但他们招式固定，找准时机上去一顿输出也可轻松拿下。在这里善意提醒一下大家，切忌贪刀，否则定会生死道消。 除了敌人本身强度相对不高之外，大圣的各项神通也能助玩家一臂之力。首先是棍势，玩家通过有效击打、闪避等操作可以积攒棍势，通过重攻击释放棍势打出高额伤害；同时游戏中的棍法分为劈棍，立棍和戳棍，每种棍法都有独属于自己的重击，合理切换棍法重击可以实现躲避地面伤害、减伤、爆发伤害、打出硬直等一系列奇效。 此外法术、变身、法宝也是战斗利器，定身术给玩家疯狂灌伤的时间，瞬身术则能化解危急情况并打出爆发伤害，玩家亦可进行化身，打出效果伤害的同时避免自身血量的扣减······游戏中的变身系统也是丰富多彩，当玩家击败特定的精英怪后可以吸收其精魄从而获得相应的变身能力：远程雷电消耗，毒势积攒，抑或是更为暴力直接的打出一个硬直。 游戏中的炼丹、装备打造等系统也同样十分出色。根据收集到的材料炼制丹药获得增益buff，或是对装备进行强化，这一些列操作在深化游戏自身玩法的同时也一定程度上起到了降低游戏难度的作用。 路，就在脚下 四年的等待，游客不负众望，为所有玩家奉献上了一封骇世之作，波澜壮阔的游戏画面，大开大合的战斗场景，这就是齐天大圣！ 不可否认游戏存在弱引导等不足之处，但精心设计的BOSS，各有特点的小妖，丰富的战斗系统以及角色成长系统，设计组的良苦用心让《黑神话 悟空》成为了游戏史上浓墨重彩的一笔。 路遥人困驴嘶，觅机惆怅徘徊 “黄粱一梦非真传，三藏只在此中求”，取经路之艰险无需多言，那时的唐僧师徒只知要前往西天取经，具体的路线根本无从得知。 《黑神话 悟空》中没有场景地图这一点为许多玩家所诟病。确实，对于我这样的路痴尚且分不清东南西北，更不要谈在游戏中记忆路线了；一路妖怪阻挠不断，在第一话中小怪的伤害不高，尚且不会成为前进的障碍，待到第二话小怪实力陡增，稍有不慎便会“死于非命”，复活到上一个土地庙重走来时的路；同时游戏中山路宛转，岔路横生，稍有不慎便会迷失方向。不过值得庆幸的是游戏中的场景虽然大多波澜壮阔，但悬崖、山峰等地方存在许多空气墙，“撞了南墙”便可回头。一次次的探索、一次次的战斗，到头来却又绕回了起点，最初的我也多少有些恼火，可这是西游啊，取经之路困难重重，谈何容易？此次的游戏主题又是探寻昔日传说的真相，若是地图在手，真相何须探索。 游戏虽然精彩，可别让游戏外的事情扫了兴！无论是换电脑玩时存档误覆盖，还是各种问题导致存档损坏。相信这样惨痛的经历依然时常发生，但这次决不能。所以，使用「UU云存档」来为你的存档上个保险吧，使用起来简单方便：打开UU，一键开启就能用全程自动保存，无需手动操作，不干扰你的游戏体验不影响原平台正常存储档，UU与平台云存档同步运行一键备份存档，一键锁定存档，重要的档要保存好。 没有场景地图，较弱的游戏引导，这些因素固然会导致游戏难度的增加，但不断探索，发掘宝物、秘密，从而发现真相的过程不正是此次“重走取经之路”的浪漫之处吗。 路，就在脚下！这一棒，定叫世间邪祟灰飞烟灭！ | I33: 甲辰岁七月既望，余有故交生辰，幼时尝为余述其往昔之奇闻异事，遂成余心中之首出庶物之英雄也。岁序递迁，而关彼之传说，犹自流传于人，未尝稍息。吾终悟之，彼非独吾辈中华之人之旧交，实为普天之炎黄子孙共仰之英豪也！ 谨以此作献给我们的超级英雄。大圣，生日快乐！ 欢迎关注 网易UU鉴赏家培养计划 关注UU加速器VX公众号，回复“steam”，获得专属玩家群邀请。 金猴奋起千钧棒，玉宇澄清万里埃 依然记得小时候蹲守在电视机前等待86版《西游记》的美好时光，那时“资源匮乏”，该片成为了中流砥柱般的存在。可谁又能想到，在影视作品琳琅满目的今天，86版《西游记》的播放量依然无可撼动：大闹天宫、三打白骨精、车迟国斗法·······大圣的一段段传奇故事陪伴着每一位炎黄子孙的成长。 2024年8月20，甲辰年七月十七，大圣回来了！随着《黑神话 悟空》开场动画的进行，他再次独自面对天兵天将的围剿，杨戬的三尖两刃枪迎面袭来，大圣再展神通，电光火石间天地撼、乾坤震，我们的故事就此展开。 重拾棍棒，直面天命，探寻昔日传说的真相。 金猴奋起千钧棒，这一棒，定叫世间邪祟灰飞烟灭！ 真墨隐现，笔精墨妙 《黑神话 悟空》为玩家带来了一场极致的视觉盛宴，它巧妙地将中国古典美学的韵味与现代游戏技术的精湛相融合，尤其是每一话结束后老者说书式的剧情回顾，配合上精美的画卷，每一帧画面都如同精心雕琢的艺术品。 在场景设计方面，《黑神话 悟空》展现出了非凡的创造力与想象力。无论是云雾缭绕的灵山仙境、还是沧桑古朴的庙宇楼阁，这一个个场景保留传统水墨画的淡雅与留白的同时，又巧妙地融入了更加丰富的色彩层次。游戏中的一草一木、一砖一瓦都经过精心设计与布置：谁又能想到，路边随手采摘的草药竟是妖精伪装。 “黑猴——你适合的初恋” 作为一款动作冒险游戏，《黑神话 悟空》的难度最为直观地影响力玩家的游戏体验。犹记得23年820的试玩直播，众多天命人们跃跃欲试却被虎先锋打得苦不堪言，被众多up主成为“最黑暗的时光”，向我这样的手残党适合玩这款游戏吗？重走西游之路真的是在受苦受难吗？ 游戏正式解锁之后这种顾虑烟消云散。基于RPG的核心玩法，玩家通过战斗可以积攒经验，获取技能点并进行相应的强化，碰到打不过的敌人时不妨回去刷刷经验，进行充分的准备后再进行挑战。 第一话难度是最低的，也是玩家的入门第一课。第一话的小妖大家莽就完了，打得他毫无还手之力；头目和妖王虽然略有些棘手，但他们招式固定，找准时机上去一顿输出也可轻松拿下。在这里善意提醒一下大家，切忌贪刀，否则定会生死道消。 除了敌人本身强度相对不高之外，大圣的各项神通也能助玩家一臂之力。首先是棍势，玩家通过有效击打、闪避等操作可以积攒棍势，通过重攻击释放棍势打出高额伤害；同时游戏中的棍法分为劈棍，立棍和戳棍，每种棍法都有独属于自己的重击，合理切换棍法重击可以实现躲避地面伤害、减伤、爆发伤害、打出硬直等一系列奇效。 此外法术、变身、法宝也是战斗利器，定身术给玩家疯狂灌伤的时间，瞬身术则能化解危急情况并打出爆发伤害，玩家亦可进行化身，打出效果伤害的同时避免自身血量的扣减······游戏中的变身系统也是丰富多彩，当玩家击败特定的精英怪后可以吸收其精魄从而获得相应的变身能力：远程雷电消耗，毒势积攒，抑或是更为暴力直接的打出一个硬直。 游戏中的炼丹、装备打造等系统也同样十分出色。根据收集到的材料炼制丹药获得增益buff，或是对装备进行强化，这一些列操作在深化游戏自身玩法的同时也一定程度上起到了降低游戏难度的作用。 路，就在脚下 四年的等待，游客不负众望，为所有玩家奉献上了一封骇世之作，波澜壮阔的游戏画面，大开大合的战斗场景，这就是齐天大圣！ 不可否认游戏存在弱引导等不足之处，但精心设计的BOSS，各有特点的小妖，丰富的战斗系统以及角色成长系统，设计组的良苦用心让《黑神话 悟空》成为了游戏史上浓墨重彩的一笔。 路遥人困驴嘶，觅机惆怅徘徊 “黄粱一梦非真传，三藏只在此中求”，取经路之艰险无需多言，那时的唐僧师徒只知要前往西天取经，具体的路线根本无从得知。 《黑神话 悟空》中没有场景地图这一点为许多玩家所诟病。确实，对于我这样的路痴尚且分不清东南西北，更不要谈在游戏中记忆路线了；一路妖怪阻挠不断，在第一话中小怪的伤害不高，尚且不会成为前进的障碍，待到第二话小怪实力陡增，稍有不慎便会“死于非命”，复活到上一个土地庙重走来时的路；同时游戏中山路宛转，岔路横生，稍有不慎便会迷失方向。不过值得庆幸的是游戏中的场景虽然大多波澜壮阔，但悬崖、山峰等地方存在许多空气墙，“撞了南墙”便可回头。一次次的探索、一次次的战斗，到头来却又绕回了起点，最初的我也多少有些恼火，可这是西游啊，取经之路困难重重，谈何容易？此次的游戏主题又是探寻昔日传说的真相，若是地图在手，真相何须探索。 游戏虽然精彩，可别让游戏外的事情扫了兴！无论是换电脑玩时存档误覆盖，还是各种问题导致存档损坏。相信这样惨痛的经历依然时常发生，但这次决不能。所以，使用「UU云存档」来为你的存档上个保险吧，使用起来简单方便：打开UU，一键开启就能用全程自动保存，无需手动操作，不干扰你的游戏体验不影响原平台正常存储档，UU与平台云存档同步运行一键备份存档，一键锁定存档，重要的档要保存好。 没有场景地图，较弱的游戏引导，这些因素固然会导致游戏难度的增加，但不断探索，发掘宝物、秘密，从而发现真相的过程不正是此次“重走取经之路”的浪漫之处吗。 路，就在脚下！这一棒，定叫世间邪祟灰飞烟灭！ | J33: =IF(SUM(R33:T33)>0,1,0) -> 1 | K33: =IF(SUM(U33:Y33)>0,1,0) -> 1 | L33: =IF(SUM(Z33:AC33)>0,1,0) -> 1 | M33: =IF(SUM(AD33:AF33)>0,1,0) -> 1 | N33: =IF(SUM(AG33:AH33)>0,1,0) -> 1 | O33: =IF(SUM(AI33:AL33)>0,1,0) -> 1 | P33: =IF(SUM(AM33:AQ33)>0,1,0) -> 0 | Q33: =IF(AR33>0,1,0) -> 0 | R33: 1 | S33: 0 | T33: 1 | U33: 1 | V33: 1 | W33: 1 | X33: 1 | Y33: 0 | Z33: 1 | AA33: 1 | AB33: 1 | AC33: 1 | AD33: 1 | AE33: 0 | AF33: 0 | AG33: 0 | AH33: 1 | AI33: 1 | AJ33: 1 | AK33: 1 | AL33: 1 | AM33: 0 | AN33: 0 | AO33: 0 | AP33: 0 | AQ33: 0 | AR33: 0 | AS33: =SUM(J33:Q33) -> 6 | AT33: =SUM(R33:AR33) -> 16 | AU33: 画面美术场景；演出角色怪物设计；动作打击手感；Boss战斗节奏；难度挑战；锁定视角；地图路线；空气墙可达性；探索隐藏支线；引导迷路单线；优化帧率；推荐价值判断；西游悟空符号；童年记忆情怀；本国媒介路径；中国文化宗教语言审美 | AV33: =IF(AT33>0,1,0) -> 1 | AW33: =IF(AT33=0,1,0) -> 0 | AX33: =IF(AT33>=8,1,0) -> 1 | AY33: 91.5 | AZ33: 正面 | BA33: P | BB33: 原文
... A39: CN-P-038 | B39: 中文 | C39: 推荐 | D39: 52 | E39: 11 | F39: 2.1 | G39: 2024-08-20 | H39: 非常好，使我的金箍棒旋转，爱来自中国。 | I39: 非常好，使我的金箍棒旋转，爱来自中国。 | J39: =IF(SUM(R39:T39)>0,1,0) -> 0 | K39: =IF(SUM(U39:Y39)>0,1,0) -> 1 | L39: =IF(SUM(Z39:AC39)>0,1,0) -> 0 | M39: =IF(SUM(AD39:AF39)>0,1,0) -> 0 | N39: =IF(SUM(AG39:AH39)>0,1,0) -> 0 | O39: =IF(SUM(AI39:AL39)>0,1,0) -> 1 | P39: =IF(SUM(AM39:AQ39)>0,1,0) -> 0 | Q39: =IF(AR39>0,1,0) -> 0 | R39: 0 | S39: 0 | T39: 0 | U39: 1 | V39: 0 | W39: 0 | X39: 0 | Y39: 0 | Z39: 0 | AA39: 0 | AB39: 0 | AC39: 0 | AD39: 0 | AE39: 0 | AF39: 0 | AG39: 0 | AH39: 0 | AI39: 1 | AJ39: 0 | AK39: 0 | AL39: 0 | AM39: 0 | AN39: 0 | AO39: 0 | AP39: 0 | AQ39: 0 | AR39: 0 | AS39: =SUM(J39:Q39) -> 2 | AT39: =SUM(R39:AR39) -> 2 | AU39: 动作打击手感；西游悟空符号 | AV39: =IF(AT39>0,1,0) -> 1 | AW39: =IF(AT39=0,1,0) -> 0 | AX39: =IF(AT39>=8,1,0) -> 0 | AY39: 2.5 | AZ39: 正面 | BA39: P | BB39: 原文
A40: CN-P-039 | B40: 中文 | C40: 推荐 | D40: 50 | E40: 2 | F40: 3.9 | G40: 2024-08-20 | H40: 出门在外旅游拿着1660ti的笔记本都能畅玩 那些sb差评如果不是收钱了真的活全家了 | I40: 出门在外旅游拿着1660ti的笔记本都能畅玩 那些sb差评如果不是收钱了真的活全家了 | J40: =IF(SUM(R40:T40)>0,1,0) -> 0 | K40: =IF(SUM(U40:Y40)>0,1,0) -> 0 | L40: =IF(SUM(Z40:AC40)>0,1,0) -> 0 | M40: =IF(SUM(AD40:AF40)>0,1,0) -> 0 | N40: =IF(SUM(AG40:AH40)>0,1,0) -> 0 | O40: =IF(SUM(AI40:AL40)>0,1,0) -> 0 | P40: =IF(SUM(AM40:AQ40)>0,1,0) -> 0 | Q40: =IF(AR40>0,1,0) -> 0 | R40: 0 | S40: 0 | T40: 0 | U40: 0 | V40: 0 | W40: 0 | X40: 0 | Y40: 0 | Z40: 0 | AA40: 0 | AB40: 0 | AC40: 0 | AD40: 0 | AE40: 0 | AF40: 0 | AG40: 0 | AH40: 0 | AI40: 0 | AJ40: 0 | AK40: 0 | AL40: 0 | AM40: 0 | AN40: 0 | AO40: 0 | AP40: 0 | AQ40: 0 | AR40: 0 | AS40: =SUM(J40:Q40) -> 0 | AT40: =SUM(R40:AR40) -> 0 | AV40: =IF(AT40>0,1,0) -> 0 | AW40: =IF(AT40=0,1,0) -> 1 | AX40: =IF(AT40>=8,1,0) -> 0 | AY40: 1 | AZ40: 正面 | BA40: P | BB40: 原文
A41: CN-P-040 | B41: 中文 | C41: 推荐 | D41: 50 | E41: 1 | F41: 88.9 | G41: 2024-08-20 | H41: 当过苇名城的修罗，也当过交界地的褪色者；当过战国时期的美少女阿秀，也当过克拉特的匹诺曹；当过痞里痞气的但丁，也当过成熟稳重的绝地。但是这次，我想当回猴哥 | I41: 当过苇名城的修罗，也当过交界地的褪色者；当过战国时期的美少女阿秀，也当过克拉特的匹诺曹；当过痞里痞气的但丁，也当过成熟稳重的绝地。但是这次，我想当回猴哥 | J41: =IF(SUM(R41:T41)>0,1,0) -> 0 | K41: =IF(SUM(U41:Y41)>0,1,0) -> 0 | L41: =IF(SUM(Z41:AC41)>0,1,0) -> 0 | M41: =IF(SUM(AD41:AF41)>0,1,0) -> 0 | N41: =IF(SUM(AG41:AH41)>0,1,0) -> 1 | O41: =IF(SUM(AI41:AL41)>0,1,0) -> 1 | P41: =IF(SUM(AM41:AQ41)>0,1,0) -> 0 | Q41: =IF(AR41>0,1,0) -> 0 | R41: 0 | S41: 0 | T41: 0 | U41: 0 | V41: 0 | W41: 0 | X41: 0 | Y41: 0 | Z41: 0 | AA41: 0 | AB41: 0 | AC41: 0 | AD41: 0 | AE41: 0 | AF41: 0 | AG41: 1 | AH41: 0 | AI41: 1 | AJ41: 0 | AK41: 0 | AL41: 0 | AM41: 0 | AN41: 0 | AO41: 0 | AP41: 0 | AQ41: 0 | AR41: 0 | AS41: =SUM(J41:Q41) -> 2 | AT41: =SUM(R41:AR41) -> 2 | AU41: 整体完成度；西游悟空符号 | AV41: =IF(AT41>0,1,0) -> 1 | AW41: =IF(AT41=0,1,0) -> 0 | AX41: =IF(AT41>=8,1,0) -> 0 | AY41: 7 | AZ41: 正面 | BA41: P | BB41: 原文
A42: CN-M-041 | B42: 中文 | C42: 推荐 | D42: 49 | E42: 0 | F42: 74.6 | G42: 2024-08-20 | H42: 伟大，无需多言。IGN不要脸的东西，游戏好不让投是吧，你们自己玩去吧 | I42: 伟大，无需多言。IGN不要脸的东西，游戏好不让投是吧，你们自己玩去吧 | J42: =IF(SUM(R42:T42)>0,1,0) -> 0 | K42: =IF(SUM(U42:Y42)>0,1,0) -> 0 | L42: =IF(SUM(Z42:AC42)>0,1,0) -> 0 | M42: =IF(SUM(AD42:AF42)>0,1,0) -> 0 | N42: =IF(SUM(AG42:AH42)>0,1,0) -> 0 | O42: =IF(SUM(AI42:AL42)>0,1,0) -> 0 | P42: =IF(SUM(AM42:AQ42)>0,1,0) -> 0 | Q42: =IF(AR42>0,1,0) -> 0 | R42: 0 | S42: 0 | T42: 0 | U42: 0 | V42: 0 | W42: 0 | X42: 0 | Y42: 0 | Z42: 0 | AA42: 0 | AB42: 0 | AC42: 0 | AD42: 0 | AE42: 0 | AF42: 0 | AG42: 0 | AH42: 0 | AI42: 0 | AJ42: 0 | AK42: 0 | AL42: 0 | AM42: 0 | AN42: 0 | AO42: 0 | AP42: 0 | AQ42: 0 | AR42: 0 | AS42: =SUM(J42:Q42) -> 0 | AT42: =SUM(R42:AR42) -> 0 | AV42: =IF(AT42>0,1,0) -> 0 | AW42: =IF(AT42=0,1,0) -> 1 | AX42: =IF(AT42>=8,1,0) -> 0 | AY42: 0 | AZ42: 中性 | BA42: M | BB42: 原文
A43: CN-P-042 | B43: 中文 | C43: 推荐 | D43: 49 | E43: 0 | F43: 77.8 | G43: 2024-08-20 | H43: 更适合中国宝宝体质，玩到这忍不住评论一手，打完金池给我小高潮了，在我看来他完全不输于任何同类型作品，硬要说的话就是优化和关卡设计上有些小瑕疵，但是依然挡不住它本身的优秀，完全有资格入选tga | I43: 更适合中国宝宝体质，玩到这忍不住评论一手，打完金池给我小高潮了，在我看来他完全不输于任何同类型作品，硬要说的话就是优化和关卡设计上有些小瑕疵，但是依然挡不住它本身的优秀，完全有资格入选tga | J43: =IF(SUM(R43:T43)>0,1,0) -> 0 | K43: =IF(SUM(U43:Y43)>0,1,0) -> 0 | L43: =IF(SUM(Z43:AC43)>0,1,0) -> 1 | M43: =IF(SUM(AD43:AF43)>0,1,0) -> 1 | N43: =IF(SUM(AG43:AH43)>0,1,0) -> 0 | O43: =IF(SUM(AI43:AL43)>0,1,0) -> 0 | P43: =IF(SUM(AM43:AQ43)>0,1,0) -> 0 | Q43: =IF(AR43>0,1,0) -> 0 | R43: 0 | S43: 0 | T43: 0 | U43: 0 | V43: 0 | W43: 0 | X43: 0 | Y43: 0 | Z43: 1 | AA43: 0 | AB43: 0 | AC43: 0 | AD43: 1 | AE43: 0 | AF43: 0 | AG43: 0 | AH43: 0 | AI43: 0 | AJ43: 0 | AK43: 0 | AL43: 0 | AM43: 0 | AN43: 0 | AO43: 0 | AP43: 0 | AQ43: 0 | AR43: 0 | AS43: =SUM(J43:Q43) -> 2 | AT43: =SUM(R43:AR43) -> 2 | AU43: 地图路线；优化帧率 | AV43: =IF(AT43>0,1,0) -> 1 | AW43: =IF(AT43=0,1,0) -> 0 | AX43: =IF(AT43>=8,1,0) -> 0 | AY43: 9.5 | AZ43: 正面 | BA43: P | BB43: 原文
A44: CN-N-043 | B44: 中文 | C44: 推荐 | D44: 44 | E44: 1 | F44: 58 | G44: 2024-08-20 | H44: 作为一款boss战为核心买点的游戏蛮好的 就是地图设计缺乏构思 空气墙太频繁 | I44: 作为一款boss战为核心买点的游戏蛮好的 就是地图设计缺乏构思 空气墙太频繁 | J44: =IF(SUM(R44:T44)>0,1,0) -> 0 | K44: =IF(SUM(U44:Y44)>0,1,0) -> 1 | L44: =IF(SUM(Z44:AC44)>0,1,0) -> 1 | M44: =IF(SUM(AD44:AF44)>0,1,0) -> 0 | N44: =IF(SUM(AG44:AH44)>0,1,0) -> 1 | O44: =IF(SUM(AI44:AL44)>0,1,0) -> 0 | P44: =IF(SUM(AM44:AQ44)>0,1,0) -> 0 | Q44: =IF(AR44>0,1,0) -> 0 | R44: 0 | S44: 0 | T44: 0 | U44: 0 | V44: 1 | W44: 0 | X44: 0 | Y44: 0 | Z44: 1 | AA44: 1 | AB44: 0 | AC44: 0 | AD44: 0 | AE44: 0 | AF44: 0 | AG44: 0 | AH44: 1 | AI44: 0 | AJ44: 0 | AK44: 0 | AL44: 0 | AM44: 0 | AN44: 0 | AO44: 0 | AP44: 0 | AQ44: 0 | AR44: 0 | AS44: =SUM(J44:Q44) -> 3 | AT44: =SUM(R44:AR44) -> 4 | AU44: Boss战斗节奏；地图路线；空气墙可达性；推荐价值判断 | AV44: =IF(AT44>0,1,0) -> 1 | AW44: =IF(AT44=0,1,0) -> 0 | AX44: =IF(AT44>=8,1,0) -> 0 | AY44: -1 | AZ44: 负面 | BA44: N | BB44: 原文
A45: CN-P-044 | B45: 中文 | C45: 推荐 | D45: 44 | E45: 0 | F45: 18.3 | G45: 2024-08-20 | H45: 爽！真的太爽了！开头序幕的演出就已经给我刺激到了，后面正式开始以天命人的身份游玩之后，爽感也没有怎么降低，从动作到画面再到配乐，在我心中都已经是顶尖水平，游科在四年前为我们展示了一场美梦，而在四年后的今天，美梦终于成真了。这只猴子曾拯救过花果山，拯救过取经路，现在，他又来拯救中国游戏界了。 | I45: 爽！真的太爽了！开头序幕的演出就已经给我刺激到了，后面正式开始以天命人的身份游玩之后，爽感也没有怎么降低，从动作到画面再到配乐，在我心中都已经是顶尖水平，游科在四年前为我们展示了一场美梦，而在四年后的今天，美梦终于成真了。这只猴子曾拯救过花果山，拯救过取经路，现在，他又来拯救中国游戏界了。 | J45: =IF(SUM(R45:T45)>0,1,0) -> 1 | K45: =IF(SUM(U45:Y45)>0,1,0) -> 1 | L45: =IF(SUM(Z45:AC45)>0,1,0) -> 0 | M45: =IF(SUM(AD45:AF45)>0,1,0) -> 0 | N45: =IF(SUM(AG45:AH45)>0,1,0) -> 1 | O45: =IF(SUM(AI45:AL45)>0,1,0) -> 1 | P45: =IF(SUM(AM45:AQ45)>0,1,0) -> 0 | Q45: =IF(AR45>0,1,0) -> 1 | R45: 1 | S45: 1 | T45: 1 | U45: 1 | V45: 0 | W45: 0 | X45: 0 | Y45: 0 | Z45: 0 | AA45: 0 | AB45: 0 | AC45: 0 | AD45: 0 | AE45: 0 | AF45: 0 | AG45: 1 | AH45: 0 | AI45: 1 | AJ45: 0 | AK45: 0 | AL45: 0 | AM45: 0 | AN45: 0 | AO45: 0 | AP45: 0 | AQ45: 0 | AR45: 1 | AS45: =SUM(J45:Q45) -> 5 | AT45: =SUM(R45:AR45) -> 7 | AU45: 画面美术场景；音乐音效配音；演出角色怪物设计；动作打击手感；整体完成度；西游悟空符号；国产3A身份期待 | AV45: =IF(AT45>0,1,0) -> 1 | AW45: =IF(AT45=0,1,0) -> 0 | AX45: =IF(AT45>=8,1,0) -> 0 | AY45: 14 | AZ45: 正面 | BA45: P | BB45: 原文
A46: CN-P-045 | B46: 中文 | C46: 推荐 | D46: 42 | E46: 2 | F46: 52.6 | G46: 2024-08-20 | H46: 确实好玩，配乐和美术都是顶级。战斗比仁王好，绝对算的上好玩。地图设计有点绕，但瑕不掩瑜，毕竟主要内容是打BOSS，反馈和手感都不错。 | I46: 确实好玩，配乐和美术都是顶级。战斗比仁王好，绝对算的上好玩。地图设计有点绕，但瑕不掩瑜，毕竟主要内容是打BOSS，反馈和手感都不错。 | J46: =IF(SUM(R46:T46)>0,1,0) -> 1 | K46: =IF(SUM(U46:Y46)>0,1,0) -> 1 | L46: =IF(SUM(Z46:AC46)>0,1,0) -> 1 | M46: =IF(SUM(AD46:AF46)>0,1,0) -> 0 | N46: =IF(SUM(AG46:AH46)>0,1,0) -> 1 | O46: =IF(SUM(AI46:AL46)>0,1,0) -> 0 | P46: =IF(SUM(AM46:AQ46)>0,1,0) -> 0 | Q46: =IF(AR46>0,1,0) -> 0 | R46: 1 | S46: 1 | T46: 0 | U46: 1 | V46: 1 | W46: 0 | X46: 0 | Y46: 1 | Z46: 1 | AA46: 0 | AB46: 0 | AC46: 0 | AD46: 0 | AE46: 0 | AF46: 0 | AG46: 0 | AH46: 1 | AI46: 0 | AJ46: 0 | AK46: 0 | AL46: 0 | AM46: 0 | AN46: 0 | AO46: 0 | AP46: 0 | AQ46: 0 | AR46: 0 | AS46: =SUM(J46:Q46) -> 4 | AT46: =SUM(R46:AR46) -> 7 | AU46: 画面美术场景；音乐音效配音；动作打击手感；Boss战斗节奏；判定反馈；地图路线；推荐价值判断 | AV46: =IF(AT46>0,1,0) -> 1 | AW46: =IF(AT46=0,1,0) -> 0 | AX46: =IF(AT46>=8,1,0) -> 0 | AY46: 9.5 | AZ46: 正面 | BA46: P | BB46: 原文
A47: CN-P-046 | B47: 中文 | C47: 推荐 | D47: 38 | E47: 0 | F47: 33.7 | G47: 2024-08-20 | H47: 发售前看评测视频说指引不明确，我玩第一章这个感觉不明显，第二章有点明显了，第三章 上了龟背之后 感觉更强烈了，直到 变成白狐 ，我就有一点点玩不下去了，游戏是真的好游戏，听着国语配音、感受中国文化是真的舒服，，但是于我个人而言有两个需要改进的：第一点是确确实实需要指引，第二点是小怪的名字希望可以显示 | I47: 发售前看评测视频说指引不明确，我玩第一章这个感觉不明显，第二章有点明显了，第三章 上了龟背之后 感觉更强烈了，直到 变成白狐 ，我就有一点点玩不下去了，游戏是真的好游戏，听着国语配音、感受中国文化是真的舒服，，但是于我个人而言有两个需要改进的：第一点是确确实实需要指引，第二点是小怪的名字希望可以显示 | J47: =IF(SUM(R47:T47)>0,1,0) -> 1 | K47: =IF(SUM(U47:Y47)>0,1,0) -> 0 | L47: =IF(SUM(Z47:AC47)>0,1,0) -> 1 | M47: =IF(SUM(AD47:AF47)>0,1,0) -> 0 | N47: =IF(SUM(AG47:AH47)>0,1,0) -> 1 | O47: =IF(SUM(AI47:AL47)>0,1,0) -> 1 | P47: =IF(SUM(AM47:AQ47)>0,1,0) -> 0 | Q47: =IF(AR47>0,1,0) -> 0 | R47: 0 | S47: 1 | T47: 0 | U47: 0 | V47: 0 | W47: 0 | X47: 0 | Y47: 0 | Z47: 0 | AA47: 0 | AB47: 0 | AC47: 1 | AD47: 0 | AE47: 0 | AF47: 0 | AG47: 0 | AH47: 1 | AI47: 0 | AJ47: 0 | AK47: 0 | AL47: 1 | AM47: 0 | AN47: 0 | AO47: 0 | AP47: 0 | AQ47: 0 | AR47: 0 | AS47: =SUM(J47:Q47) -> 4 | AT47: =SUM(R47:AR47) -> 4 | AU47: 音乐音效配音；引导迷路单线；推荐价值判断；中国文化宗教语言审美 | AV47: =IF(AT47>0,1,0) -> 1 | AW47: =IF(AT47=0,1,0) -> 0 | AX47: =IF(AT47>=8,1,0) -> 0 | AY47: 2.5 | AZ47: 正面 | BA47: P | BB47: 原文
A48: CN-P-047 | B48: 中文 | C48: 推荐 | D48: 37 | E48: 1 | F48: 38.1 | G48: 2024-08-20 | H48: 古色古香的好游戏，适合中国宝宝的体质，看小怪图鉴真好玩 | I48: 古色古香的好游戏，适合中国宝宝的体质，看小怪图鉴真好玩 | J48: =IF(SUM(R48:T48)>0,1,0) -> 0 | K48: =IF(SUM(U48:Y48)>0,1,0) -> 0 | L48: =IF(SUM(Z48:AC48)>0,1,0) -> 0 | M48: =IF(SUM(AD48:AF48)>0,1,0) -> 0 | N48: =IF(SUM(AG48:AH48)>0,1,0) -> 1 | O48: =IF(SUM(AI48:AL48)>0,1,0) -> 0 | P48: =IF(SUM(AM48:AQ48)>0,1,0) -> 0 | Q48: =IF(AR48>0,1,0) -> 0 | R48: 0 | S48: 0 | T48: 0 | U48: 0 | V48: 0 | W48: 0 | X48: 0 | Y48: 0 | Z48: 0 | AA48: 0 | AB48: 0 | AC48: 0 | AD48: 0 | AE48: 0 | AF48: 0 | AG48: 0 | AH48: 1 | AI48: 0 | AJ48: 0 | AK48: 0 | AL48: 0 | AM48: 0 | AN48: 0 | AO48: 0 | AP48: 0 | AQ48: 0 | AR48: 0 | AS48: =SUM(J48:Q48) -> 1 | AT48: =SUM(R48:AR48) -> 1 | AU48: 推荐价值判断 | AV48: =IF(AT48>0,1,0) -> 1 | AW48: =IF(AT48=0,1,0) -> 0 | AX48: =IF(AT48>=8,1,0) -> 0 | AY48: 4 | AZ48: 正面 | BA48: P | BB48: 原文
A49: CN-N-048 | B49: 中文 | C49: 推荐 | D49: 37 | E49: 2 | F49: 65.4 | G49: 2024-08-20 | H49: 也是终于在垃圾氪金手游荼毒的国游环境中玩上国产3A了 | I49: 也是终于在垃圾氪金手游荼毒的国游环境中玩上国产3A了 | J49: =IF(SUM(R49:T49)>0,1,0) -> 1 | K49: =IF(SUM(U49:Y49)>0,1,0) -> 0 | L49: =IF(SUM(Z49:AC49)>0,1,0) -> 0 | M49: =IF(SUM(AD49:AF49)>0,1,0) -> 0 | N49: =IF(SUM(AG49:AH49)>0,1,0) -> 1 | O49: =IF(SUM(AI49:AL49)>0,1,0) -> 0 | P49: =IF(SUM(AM49:AQ49)>0,1,0) -> 0 | Q49: =IF(AR49>0,1,0) -> 1 | R49: 1 | S49: 0 | T49: 0 | U49: 0 | V49: 0 | W49: 0 | X49: 0 | Y49: 0 | Z49: 0 | AA49: 0 | AB49: 0 | AC49: 0 | AD49: 0 | AE49: 0 | AF49: 0 | AG49: 0 | AH49: 1 | AI49: 0 | AJ49: 0 | AK49: 0 | AL49: 0 | AM49: 0 | AN49: 0 | AO49: 0 | AP49: 0 | AQ49: 0 | AR49: 1 | AS49: =SUM(J49:Q49) -> 3 | AT49: =SUM(R49:AR49) -> 3 | AU49: 画面美术场景；推荐价值判断；国产3A身份期待 | AV49: =IF(AT49>0,1,0) -> 1 | AW49: =IF(AT49=0,1,0) -> 0 | AX49: =IF(AT49>=8,1,0) -> 0 | AY49: -2 | AZ49: 负面 | BA49: N | BB49: 原文
A50: CN-P-049 | B50: 中文 | C50: 推荐 | D50: 35 | E50: 1 | F50: 39.9 | G50: 2024-08-20 | H50: 除了容易迷路和一些sm小怪（鼠鼠我啊 真的要红温了）堪称完美战斗超爽 风景优美 美术到位 猴哥性能拉满甚至感觉有点简单 前两章头目和妖王的体验都很好千言万语化成两个字：好玩 只恨我的电脑比较差 不能更好的体验黑猴这次预购没上当------------------------------你说的对！但是：叶隐朔风如刀飘零扫尘冲天！接住了！六丁六甲，从不吃素！比其他你还是差远了 | I50: 除了容易迷路和一些sm小怪（鼠鼠我啊 真的要红温了）堪称完美战斗超爽 风景优美 美术到位 猴哥性能拉满甚至感觉有点简单 前两章头目和妖王的体验都很好千言万语化成两个字：好玩 只恨我的电脑比较差 不能更好的体验黑猴这次预购没上当------------------------------你说的对！但是：叶隐朔风如刀飘零扫尘冲天！接住了！六丁六甲，从不吃素！比其他你还是差远了 | J50: =IF(SUM(R50:T50)>0,1,0) -> 1 | K50: =IF(SUM(U50:Y50)>0,1,0) -> 1 | L50: =IF(SUM(Z50:AC50)>0,1,0) -> 1 | M50: =IF(SUM(AD50:AF50)>0,1,0) -> 1 | N50: =IF(SUM(AG50:AH50)>0,1,0) -> 1 | O50: =IF(SUM(AI50:AL50)>0,1,0) -> 1 | P50: =IF(SUM(AM50:AQ50)>0,1,0) -> 0 | Q50: =IF(AR50>0,1,0) -> 0 | R50: 1 | S50: 0 | T50: 0 | U50: 0 | V50: 1 | W50: 1 | X50: 0 | Y50: 0 | Z50: 0 | AA50: 0 | AB50: 0 | AC50: 1 | AD50: 1 | AE50: 0 | AF50: 0 | AG50: 0 | AH50: 1 | AI50: 1 | AJ50: 0 | AK50: 0 | AL50: 0 | AM50: 0 | AN50: 0 | AO50: 0 | AP50: 0 | AQ50: 0 | AR50: 0 | AS50: =SUM(J50:Q50) -> 6 | AT50: =SUM(R50:AR50) -> 7 | AU50: 画面美术场景；Boss战斗节奏；难度挑战；引导迷路单线；优化帧率；推荐价值判断；西游悟空符号 | AV50: =IF(AT50>0,1,0) -> 1 | AW50: =IF(AT50=0,1,0) -> 0 | AX50: =IF(AT50>=8,1,0) -> 0 | AY50: 4.5 | AZ50: 正面 | BA50: P | BB50: 原文
A51: CN-M-050 | B51: 中文 | C51: 推荐 | D51: 35 | E51: 1 | F51: 36.2 | G51: 2024-08-20 | H51: 第一章已过，没有什么可说的，画面电影级别，动作不是完美，但已经可以和其他3A差不多，剧情不用说了（中国人都看哭）大国正在崛起，前方路虽遥远，我辈直面天命。 | I51: 第一章已过，没有什么可说的，画面电影级别，动作不是完美，但已经可以和其他3A差不多，剧情不用说了（中国人都看哭）大国正在崛起，前方路虽遥远，我辈直面天命。 | J51: =IF(SUM(R51:T51)>0,1,0) -> 1 | K51: =IF(SUM(U51:Y51)>0,1,0) -> 1 | L51: =IF(SUM(Z51:AC51)>0,1,0) -> 0 | M51: =IF(SUM(AD51:AF51)>0,1,0) -> 0 | N51: =IF(SUM(AG51:AH51)>0,1,0) -> 0 | O51: =IF(SUM(AI51:AL51)>0,1,0) -> 0 | P51: =IF(SUM(AM51:AQ51)>0,1,0) -> 0 | Q51: =IF(AR51>0,1,0) -> 1 | R51: 1 | S51: 0 | T51: 0 | U51: 1 | V51: 0 | W51: 0 | X51: 0 | Y51: 0 | Z51: 0 | AA51: 0 | AB51: 0 | AC51: 0 | AD51: 0 | AE51: 0 | AF51: 0 | AG51: 0 | AH51: 0 | AI51: 0 | AJ51: 0 | AK51: 0 | AL51: 0 | AM51: 0 | AN51: 0 | AO51: 0 | AP51: 0 | AQ51: 0 | AR51: 1 | AS51: =SUM(J51:Q51) -> 3 | AT51: =SUM(R51:AR51) -> 3 | AU51: 画面美术场景；动作打击手感；国产3A身份期待 | AV51: =IF(AT51>0,1,0) -> 1 | AW51: =IF(AT51=0,1,0) -> 0 | AX51: =IF(AT51>=8,1,0) -> 0 | AY51: 0 | AZ51: 中性 | BA51: M | BB51: 原文
A52: CN-P-051 | B52: 中文 | C52: 推荐 | D52: 34 | E52: 27 | F52: 394.9 | G52: 2024-08-20 | H52: 我把虎先锋喂饱了(༎ຶ⌑༎ຶ) | I52: 我把虎先锋喂饱了(༎ຶ⌑༎ຶ) | J52: =IF(SUM(R52:T52)>0,1,0) -> 0 | K52: =IF(SUM(U52:Y52)>0,1,0) -> 0 | L52: =IF(SUM(Z52:AC52)>0,1,0) -> 0 | M52: =IF(SUM(AD52:AF52)>0,1,0) -> 0 | N52: =IF(SUM(AG52:AH52)>0,1,0) -> 0 | O52: =IF(SUM(AI52:AL52)>0,1,0) -> 0 | P52: =IF(SUM(AM52:AQ52)>0,1,0) -> 0 | Q52: =IF(AR52>0,1,0) -> 0 | R52: 0 | S52: 0 | T52: 0 | U52: 0 | V52: 0 | W52: 0 | X52: 0 | Y52: 0 | Z52: 0 | AA52: 0 | AB52: 0 | AC52: 0 | AD52: 0 | AE52: 0 | AF52: 0 | AG52: 0 | AH52: 0 | AI52: 0 | AJ52: 0 | AK52: 0 | AL52: 0 | AM52: 0 | AN52: 0 | AO52: 0 | AP52: 0 | AQ52: 0 | AR52: 0 | AS52: =SUM(J52:Q52) -> 0 | AT52: =SUM(R52:AR52) -> 0 | AV52: =IF(AT52>0,1,0) -> 0 | AW52: =IF(AT52=0,1,0) -> 1 | AX52: =IF(AT52>=8,1,0) -> 0 | AY52: 1 | AZ52: 正面 | BA52: P | BB52: 原文
A53: CN-M-052 | B53: 中文 | C53: 推荐 | D53: 34 | E53: 4 | F53: 61.4 | G53: 2024-08-20 | H53: 终于不用进游戏找setting-language了 | I53: 终于不用进游戏找setting-language了 | J53: =IF(SUM(R53:T53)>0,1,0) -> 0 | K53: =IF(SUM(U53:Y53)>0,1,0) -> 0 | L53: =IF(SUM(Z53:AC53)>0,1,0) -> 0 | M53: =IF(SUM(AD53:AF53)>0,1,0) -> 0 | N53: =IF(SUM(AG53:AH53)>0,1,0) -> 0 | O53: =IF(SUM(AI53:AL53)>0,1,0) -> 0 | P53: =IF(SUM(AM53:AQ53)>0,1,0) -> 0 | Q53: =IF(AR53>0,1,0) -> 0 | R53: 0 | S53: 0 | T53: 0 | U53: 0 | V53: 0 | W53: 0 | X53: 0 | Y53: 0 | Z53: 0 | AA53: 0 | AB53: 0 | AC53: 0 | AD53: 0 | AE53: 0 | AF53: 0 | AG53: 0 | AH53: 0 | AI53: 0 | AJ53: 0 | AK53: 0 | AL53: 0 | AM53: 0 | AN53: 0 | AO53: 0 | AP53: 0 | AQ53: 0 | AR53: 0 | AS53: =SUM(J53:Q53) -> 0 | AT53: =SUM(R53:AR53) -> 0 | AV53: =IF(AT53>0,1,0) -> 0 | AW53: =IF(AT53=0,1,0) -> 1 | AX53: =IF(AT53>=8,1,0) -> 0 | AY53: 0 | AZ53: 中性 | BA53: M | BB53: 原文
A54: CN-P-053 | B54: 中文 | C54: 推荐 | D54: 34 | E54: 2 | F54: 114.7 | G54: 2024-08-20 | H54: 游戏科学牛逼！玩的太爽快了！不知不觉8个多小时了！你们继续。我休息一下。 | I54: 游戏科学牛逼！玩的太爽快了！不知不觉8个多小时了！你们继续。我休息一下。 | J54: =IF(SUM(R54:T54)>0,1,0) -> 0 | K54: =IF(SUM(U54:Y54)>0,1,0) -> 0 | L54: =IF(SUM(Z54:AC54)>0,1,0) -> 0 | M54: =IF(SUM(AD54:AF54)>0,1,0) -> 0 | N54: =IF(SUM(AG54:AH54)>0,1,0) -> 0 | O54: =IF(SUM(AI54:AL54)>0,1,0) -> 0 | P54: =IF(SUM(AM54:AQ54)>0,1,0) -> 0 | Q54: =IF(AR54>0,1,0) -> 0 | R54: 0 | S54: 0 | T54: 0 | U54: 0 | V54: 0 | W54: 0 | X54: 0 | Y54: 0 | Z54: 0 | AA54: 0 | AB54: 0 | AC54: 0 | AD54: 0 | AE54: 0 | AF54: 0 | AG54: 0 | AH54: 0 | AI54: 0 | AJ54: 0 | AK54: 0 | AL54: 0 | AM54: 0 | AN54: 0 | AO54: 0 | AP54: 0 | AQ54: 0 | AR54: 0 | AS54: =SUM(J54:Q54) -> 0 | AT54: =SUM(R54:AR54) -> 0 | AV54: =IF(AT54>0,1,0) -> 0 | AW54: =IF(AT54=0,1,0) -> 1 | AX54: =IF(AT54>=8,1,0) -> 0 | AY54: 0.5 | AZ54: 正面 | BA54: P | BB54: 原文
A55: CN-P-054 | B55: 中文 | C55: 推荐 | D55: 14 | E55: 0 | F55: 64.7 小时 | G55: 2024-09-07 | H55: 未竟 看了影神图，听完结尾曲，这冯骥莫不是游戏界的姜文和许嵩？ 试问有谁，再打破顽空，不堕轮回万古传！ 一千个人眼里就有一千个哈姆雷特，游戏优点很多我这边就不说了，只讲讲个人主观上认为的不足之处：一、因制作经验的不足，大型BOSS战视角锁定体验不是很好；二、因制作工期赶，游科对原规划删减后，妥协做出的第六章，地图内容真的空洞；三、比较怨念的掉落物收集（特指采集植物所得）；四、不能自选存档位置，如果可以自选，那便可在自己喜欢的BOSS房前存好档，供日后多多把玩。 以上四条仅是我个人目前所感，日后若有新的想法，日后更新出来。 毕竟这是游科第一次涉猎大型单机大作的制作，有不足之处不是很正常？难不成那些国际大厂的作品各个都是无暇之物？有缺点我们努力改正，日后赶上不就行了。也有人拿《黑神话：悟空》对标那些一流大作，说这也不行那也不行，问题你是想看到一个属于国人的，一个带有冯骥团队色彩的《黑神话：悟空》，还是纯国外风格的《黑神话：悟空》？都说打破顽空须悟空，总在别人的框架下怎么施展自己的拳脚。“曲唱成歌，最怕平凡”警惕把《黑神话：悟空》往神作捧的，这就如同当年教员被人捧的高高的，结果就是现在把你捧的高，把你奉为“无害神像”，日后便把你摔的粉碎，因为你已经是完美无瑕的了，怎么会出现这些问题呢，肯定是你也不过如此，拒绝你的平凡后，你做的事对与错不就成他人一念之间的事。 乾卦六爻皆阳，上九爻爻辞却是“亢龙有悔”，坤卦六爻皆阴，上六爻爻辞却是“龙战在野，其血玄黄”，凡是事物发展到极端了，必要向着反面发展，只希望多多理解游科的不足，能给予这个团队回转的余地，而不是一味的捧高，要接受“你我原是有情有欲人”，是人那就一定有缺点，或多或少、或大或小，但只看缺点不看优点，那不就成了泼皮无赖了吗。 还有近期网友吐槽的大圣形象问题，从《西游记》的诞生到现在，大圣的形象是慢慢丰满起来的，真闹完天宫后善终的，怕也只有1961年上美出的这部《大闹天宫》了，其余时候都是在取真经得果位的路上，游科这次创作的大圣形象是经典的延续，更有自己的想法，有影神图中与八戒的问答还有自身设局，以身死换后人继承意志跳出轮回，这不是一个好的现象吗，怎么会是乱编呢。我觉得《黑神话：悟空》就是一款瑕不掩瑜的作品，是冯骥团队献给我们国人的一份大礼。总之思绪万千写的很乱，这条评测观感肯定不甚舒服，希望读者见谅。 | I55: 未竟 看了影神图，听完结尾曲，这冯骥莫不是游戏界的姜文和许嵩？ 试问有谁，再打破顽空，不堕轮回万古传！ 一千个人眼里就有一千个哈姆雷特，游戏优点很多我这边就不说了，只讲讲个人主观上认为的不足之处：一、因制作经验的不足，大型BOSS战视角锁定体验不是很好；二、因制作工期赶，游科对原规划删减后，妥协做出的第六章，地图内容真的空洞；三、比较怨念的掉落物收集（特指采集植物所得）；四、不能自选存档位置，如果可以自选，那便可在自己喜欢的BOSS房前存好档，供日后多多把玩。 以上四条仅是我个人目前所感，日后若有新的想法，日后更新出来。 毕竟这是游科第一次涉猎大型单机大作的制作，有不足之处不是很正常？难不成那些国际大厂的作品各个都是无暇之物？有缺点我们努力改正，日后赶上不就行了。也有人拿《黑神话：悟空》对标那些一流大作，说这也不行那也不行，问题你是想看到一个属于国人的，一个带有冯骥团队色彩的《黑神话：悟空》，还是纯国外风格的《黑神话：悟空》？都说打破顽空须悟空，总在别人的框架下怎么施展自己的拳脚。“曲唱成歌，最怕平凡”警惕把《黑神话：悟空》往神作捧的，这就如同当年教员被人捧的高高的，结果就是现在把你捧的高，把你奉为“无害神像”，日后便把你摔的粉碎，因为你已经是完美无瑕的了，怎么会出现这些问题呢，肯定是你也不过如此，拒绝你的平凡后，你做的事对与错不就成他人一念之间的事。 乾卦六爻皆阳，上九爻爻辞却是“亢龙有悔”，坤卦六爻皆阴，上六爻爻辞却是“龙战在野，其血玄黄”，凡是事物发展到极端了，必要向着反面发展，只希望多多理解游科的不足，能给予这个团队回转的余地，而不是一味的捧高，要接受“你我原是有情有欲人”，是人那就一定有缺点，或多或少、或大或小，但只看缺点不看优点，那不就成了泼皮无赖了吗。 还有近期网友吐槽的大圣形象问题，从《西游记》的诞生到现在，大圣的形象是慢慢丰满起来的，真闹完天宫后善终的，怕也只有1961年上美出的这部《大闹天宫》了，其余时候都是在取真经得果位的路上，游科这次创作的大圣形象是经典的延续，更有自己的想法，有影神图中与八戒的问答还有自身设局，以身死换后人继承意志跳出轮回，这不是一个好的现象吗，怎么会是乱编呢。我觉得《黑神话：悟空》就是一款瑕不掩瑜的作品，是冯骥团队献给我们国人的一份大礼。总之思绪万千写的很乱，这条评测观感肯定不甚舒服，希望读者见谅。 | J55: =IF(SUM(R55:T55)>0,1,0) -> 0 | K55: =IF(SUM(U55:Y55)>0,1,0) -> 1 | L55: =IF(SUM(Z55:AC55)>0,1,0) -> 1 | M55: =IF(SUM(AD55:AF55)>0,1,0) -> 0 | N55: =IF(SUM(AG55:AH55)>0,1,0) -> 1 | O55: =IF(SUM(AI55:AL55)>0,1,0) -> 1 | P55: =IF(SUM(AM55:AQ55)>0,1,0) -> 1 | Q55: =IF(AR55>0,1,0) -> 0 | R55: 0 | S55: 0 | T55: 0 | U55: 0 | V55: 1 | W55: 0 | X55: 1 | Y55: 0 | Z55: 1 | AA55: 0 | AB55: 1 | AC55: 0 | AD55: 0 | AE55: 0 | AF55: 0 | AG55: 0 | AH55: 1 | AI55: 1 | AJ55: 0 | AK55: 0 | AL55: 0 | AM55: 0 | AN55: 1 | AO55: 0 | AP55: 0 | AQ55: 1 | AR55: 0 | AS55: =SUM(J55:Q55) -> 5 | AT55: =SUM(R55:AR55) -> 8 | AU55: Boss战斗节奏；锁定视角；地图路线；探索隐藏支线；推荐价值判断；西游悟空符号；原典知识人物关系专名；角色期待意义偏移 | AV55: =IF(AT55>0,1,0) -> 1 | AW55: =IF(AT55=0,1,0) -> 0 | AX55: =IF(AT55>=8,1,0) -> 1 | AY55: 12 | AZ55: 正面 | BA55: P | BB55: 原文
A56: CN-N-055 | B56: 中文 | C56: 推荐 | D56: 31 | E56: 8 | F56: 50.1 | G56: 2024-08-20 | H56: 你买了游戏，大圣很开心，因为他知道你很喜欢他。你开风林月影，大圣很高兴，因为这本来就是他的本领。你没买，大圣也理解，因为他知道你也有自己的八十一难。你玩盗版，大圣也只会淡然一笑，毕竟哪个猴子猴孙没有一个齐天梦？ 如果你花钱玩盗版，大圣会开心，因为他感觉看到了他的二师弟…但是如果你以一个购买者去嘲笑，贬低，谩骂，道德绑架其他人，那么大圣就会不高兴了，因为他仿佛看到了，西天和天庭那帮道貌岸然，以强权压迫弱小的那帮家伙。 | I56: 你买了游戏，大圣很开心，因为他知道你很喜欢他。你开风林月影，大圣很高兴，因为这本来就是他的本领。你没买，大圣也理解，因为他知道你也有自己的八十一难。你玩盗版，大圣也只会淡然一笑，毕竟哪个猴子猴孙没有一个齐天梦？ 如果你花钱玩盗版，大圣会开心，因为他感觉看到了他的二师弟…但是如果你以一个购买者去嘲笑，贬低，谩骂，道德绑架其他人，那么大圣就会不高兴了，因为他仿佛看到了，西天和天庭那帮道貌岸然，以强权压迫弱小的那帮家伙。 | J56: =IF(SUM(R56:T56)>0,1,0) -> 0 | K56: =IF(SUM(U56:Y56)>0,1,0) -> 0 | L56: =IF(SUM(Z56:AC56)>0,1,0) -> 0 | M56: =IF(SUM(AD56:AF56)>0,1,0) -> 0 | N56: =IF(SUM(AG56:AH56)>0,1,0) -> 1 | O56: =IF(SUM(AI56:AL56)>0,1,0) -> 1 | P56: =IF(SUM(AM56:AQ56)>0,1,0) -> 0 | Q56: =IF(AR56>0,1,0) -> 0 | R56: 0 | S56: 0 | T56: 0 | U56: 0 | V56: 0 | W56: 0 | X56: 0 | Y56: 0 | Z56: 0 | AA56: 0 | AB56: 0 | AC56: 0 | AD56: 0 | AE56: 0 | AF56: 0 | AG56: 0 | AH56: 1 | AI56: 1 | AJ56: 0 | AK56: 0 | AL56: 1 | AM56: 0 | AN56: 0 | AO56: 0 | AP56: 0 | AQ56: 0 | AR56: 0 | AS56: =SUM(J56:Q56) -> 2 | AT56: =SUM(R56:AR56) -> 3 | AU56: 推荐价值判断；西游悟空符号；中国文化宗教语言审美 | AV56: =IF(AT56>0,1,0) -> 1 | AW56: =IF(AT56=0,1,0) -> 0 | AX56: =IF(AT56>=8,1,0) -> 0 | AY56: -4.5 | AZ56: 负面 | BA56: N | BB56: 原文
A57: CN-P-056 | B57: 中文 | C57: 推荐 | D57: 30 | E57: 1 | F57: 63.1 | G57: 2024-08-20 | H57: 非常好玩，空气墙问题没有想象中的那么严重，甚至有的时候我个人感觉都无伤大雅。玩了8小时没碰到bug也没有闪退，优化很好。但是我怎么打不出劈棍法示里那么帅的连招马上前两章全收集了，说一下游戏不足的地方，希望后续能改进，一个是视角锁定的问题，boss战太容易丢失锁定了，好几次都要重新手动锁定。第二个就是希望内置一个收集度提示的功能，这样就不用玩家一个个去比照攻略网站看有没有收集完了，没有这个功能真不太方便 | I57: 非常好玩，空气墙问题没有想象中的那么严重，甚至有的时候我个人感觉都无伤大雅。玩了8小时没碰到bug也没有闪退，优化很好。但是我怎么打不出劈棍法示里那么帅的连招马上前两章全收集了，说一下游戏不足的地方，希望后续能改进，一个是视角锁定的问题，boss战太容易丢失锁定了，好几次都要重新手动锁定。第二个就是希望内置一个收集度提示的功能，这样就不用玩家一个个去比照攻略网站看有没有收集完了，没有这个功能真不太方便 | J57: =IF(SUM(R57:T57)>0,1,0) -> 0 | K57: =IF(SUM(U57:Y57)>0,1,0) -> 1 | L57: =IF(SUM(Z57:AC57)>0,1,0) -> 1 | M57: =IF(SUM(AD57:AF57)>0,1,0) -> 1 | N57: =IF(SUM(AG57:AH57)>0,1,0) -> 1 | O57: =IF(SUM(AI57:AL57)>0,1,0) -> 0 | P57: =IF(SUM(AM57:AQ57)>0,1,0) -> 1 | Q57: =IF(AR57>0,1,0) -> 0 | R57: 0 | S57: 0 | T57: 0 | U57: 1 | V57: 1 | W57: 1 | X57: 1 | Y57: 0 | Z57: 0 | AA57: 1 | AB57: 1 | AC57: 0 | AD57: 1 | AE57: 1 | AF57: 1 | AG57: 0 | AH57: 1 | AI57: 0 | AJ57: 0 | AK57: 0 | AL57: 0 | AM57: 0 | AN57: 0 | AO57: 0 | AP57: 1 | AQ57: 0 | AR57: 0 | AS57: =SUM(J57:Q57) -> 5 | AT57: =SUM(R57:AR57) -> 11 | AU57: 动作打击手感；Boss战斗节奏；难度挑战；锁定视角；空气墙可达性；探索隐藏支线；优化帧率；崩溃闪退；Bug兼容硬件；推荐价值判断；外部资料依赖 | AV57: =IF(AT57>0,1,0) -> 1 | AW57: =IF(AT57=0,1,0) -> 0 | AX57: =IF(AT57>=8,1,0) -> 1 | AY57: 3 | AZ57: 正面 | BA57: P | BB57: 原文
A58: CN-P-057 | B58: 中文 | C58: 推荐 | D58: 29 | E58: 0 | F58: 98.8 | G58: 2024-08-20 | H58: 终于出现这么个游戏值得我写有生以来第一个STEAM评测了无敌好吧我此刻无比骄傲自豪 | I58: 终于出现这么个游戏值得我写有生以来第一个STEAM评测了无敌好吧我此刻无比骄傲自豪 | J58: =IF(SUM(R58:T58)>0,1,0) -> 0 | K58: =IF(SUM(U58:Y58)>0,1,0) -> 0 | L58: =IF(SUM(Z58:AC58)>0,1,0) -> 0 | M58: =IF(SUM(AD58:AF58)>0,1,0) -> 0 | N58: =IF(SUM(AG58:AH58)>0,1,0) -> 1 | O58: =IF(SUM(AI58:AL58)>0,1,0) -> 0 | P58: =IF(SUM(AM58:AQ58)>0,1,0) -> 0 | Q58: =IF(AR58>0,1,0) -> 0 | R58: 0 | S58: 0 | T58: 0 | U58: 0 | V58: 0 | W58: 0 | X58: 0 | Y58: 0 | Z58: 0 | AA58: 0 | AB58: 0 | AC58: 0 | AD58: 0 | AE58: 0 | AF58: 0 | AG58: 0 | AH58: 1 | AI58: 0 | AJ58: 0 | AK58: 0 | AL58: 0 | AM58: 0 | AN58: 0 | AO58: 0 | AP58: 0 | AQ58: 0 | AR58: 0 | AS58: =SUM(J58:Q58) -> 1 | AT58: =SUM(R58:AR58) -> 1 | AU58: 推荐价值判断 | AV58: =IF(AT58>0,1,0) -> 1 | AW58: =IF(AT58=0,1,0) -> 0 | AX58: =IF(AT58>=8,1,0) -> 0 | AY58: 5 | AZ58: 正面 | BA58: P | BB58: 原文
A59: CN-M-058 | B59: 中文 | C59: 推荐 | D59: 28 | E59: 1 | F59: 21.9 | G59: 2024-08-20 | H59: 我曾有过很多身份，我曾驾驶过泰坦BT7274，在反抗军中是一名以一敌千的铁驭，我也曾在北美西部的荒野里燃起篝火，一把左轮，除暴安良。我还在古老的江户时期，成为“独臂之狼”的忍者大师，不畏死亡。我也曾在洛圣都中，快意恩仇，一辆超跑，无限嚣张。在诺曼底海岸成为一名普通士兵匍匐冲刺，一身破军服，浴血荣光。在中欧大地我是刺客大师藏起袖剑，隐秘角落，杀人无形。但是这次我谁也不是，我只想回到我的家乡。这一次，我只想在属于我们的神话世界里，当一回齐天大圣。——来自小黑盒用户春日野_悠的评价 | I59: 我曾有过很多身份，我曾驾驶过泰坦BT7274，在反抗军中是一名以一敌千的铁驭，我也曾在北美西部的荒野里燃起篝火，一把左轮，除暴安良。我还在古老的江户时期，成为“独臂之狼”的忍者大师，不畏死亡。我也曾在洛圣都中，快意恩仇，一辆超跑，无限嚣张。在诺曼底海岸成为一名普通士兵匍匐冲刺，一身破军服，浴血荣光。在中欧大地我是刺客大师藏起袖剑，隐秘角落，杀人无形。但是这次我谁也不是，我只想回到我的家乡。这一次，我只想在属于我们的神话世界里，当一回齐天大圣。——来自小黑盒用户春日野_悠的评价 | J59: =IF(SUM(R59:T59)>0,1,0) -> 0 | K59: =IF(SUM(U59:Y59)>0,1,0) -> 1 | L59: =IF(SUM(Z59:AC59)>0,1,0) -> 0 | M59: =IF(SUM(AD59:AF59)>0,1,0) -> 0 | N59: =IF(SUM(AG59:AH59)>0,1,0) -> 0 | O59: =IF(SUM(AI59:AL59)>0,1,0) -> 1 | P59: =IF(SUM(AM59:AQ59)>0,1,0) -> 0 | Q59: =IF(AR59>0,1,0) -> 0 | R59: 0 | S59: 0 | T59: 0 | U59: 0 | V59: 0 | W59: 1 | X59: 0 | Y59: 0 | Z59: 0 | AA59: 0 | AB59: 0 | AC59: 0 | AD59: 0 | AE59: 0 | AF59: 0 | AG59: 0 | AH59: 0 | AI59: 1 | AJ59: 0 | AK59: 0 | AL59: 0 | AM59: 0 | AN59: 0 | AO59: 0 | AP59: 0 | AQ59: 0 | AR59: 0 | AS59: =SUM(J59:Q59) -> 2 | AT59: =SUM(R59:AR59) -> 2 | AU59: 难度挑战；西游悟空符号 | AV59: =IF(AT59>0,1,0) -> 1 | AW59: =IF(AT59=0,1,0) -> 0 | AX59: =IF(AT59>=8,1,0) -> 0 | AY59: 0 | AZ59: 中性 | BA59: M | BB59: 原文
A60: CN-P-059 | B60: 中文 | C60: 推荐 | D60: 27 | E60: 0 | F60: 63.3 | G60: 2024-08-20 | H60: 作为国产第一部3A来说，做的比较优秀了 | I60: 作为国产第一部3A来说，做的比较优秀了 | J60: =IF(SUM(R60:T60)>0,1,0) -> 0 | K60: =IF(SUM(U60:Y60)>0,1,0) -> 0 | L60: =IF(SUM(Z60:AC60)>0,1,0) -> 0 | M60: =IF(SUM(AD60:AF60)>0,1,0) -> 0 | N60: =IF(SUM(AG60:AH60)>0,1,0) -> 0 | O60: =IF(SUM(AI60:AL60)>0,1,0) -> 0 | P60: =IF(SUM(AM60:AQ60)>0,1,0) -> 0 | Q60: =IF(AR60>0,1,0) -> 1 | R60: 0 | S60: 0 | T60: 0 | U60: 0 | V60: 0 | W60: 0 | X60: 0 | Y60: 0 | Z60: 0 | AA60: 0 | AB60: 0 | AC60: 0 | AD60: 0 | AE60: 0 | AF60: 0 | AG60: 0 | AH60: 0 | AI60: 0 | AJ60: 0 | AK60: 0 | AL60: 0 | AM60: 0 | AN60: 0 | AO60: 0 | AP60: 0 | AQ60: 0 | AR60: 1 | AS60: =SUM(J60:Q60) -> 1 | AT60: =SUM(R60:AR60) -> 1 | AU60: 国产3A身份期待 | AV60: =IF(AT60>0,1,0) -> 1 | AW60: =IF(AT60=0,1,0) -> 0 | AX60: =IF(AT60>=8,1,0) -> 0 | AY60: 1 | AZ60: 正面 | BA60: P | BB60: 原文
A61: CN-P-060 | B61: 中文 | C61: 推荐 | D61: 26 | E61: 7 | F61: 43.6 | G61: 2024-08-20 | H61: 4年啊！我等了4年！不说了，猿神！！！！启动！！！！！！！！ | I61: 4年啊！我等了4年！不说了，猿神！！！！启动！！！！！！！！ | J61: =IF(SUM(R61:T61)>0,1,0) -> 0 | K61: =IF(SUM(U61:Y61)>0,1,0) -> 0 | L61: =IF(SUM(Z61:AC61)>0,1,0) -> 0 | M61: =IF(SUM(AD61:AF61)>0,1,0) -> 0 | N61: =IF(SUM(AG61:AH61)>0,1,0) -> 0 | O61: =IF(SUM(AI61:AL61)>0,1,0) -> 0 | P61: =IF(SUM(AM61:AQ61)>0,1,0) -> 0 | Q61: =IF(AR61>0,1,0) -> 0 | R61: 0 | S61: 0 | T61: 0 | U61: 0 | V61: 0 | W61: 0 | X61: 0 | Y61: 0 | Z61: 0 | AA61: 0 | AB61: 0 | AC61: 0 | AD61: 0 | AE61: 0 | AF61: 0 | AG61: 0 | AH61: 0 | AI61: 0 | AJ61: 0 | AK61: 0 | AL61: 0 | AM61: 0 | AN61: 0 | AO61: 0 | AP61: 0 | AQ61: 0 | AR61: 0 | AS61: =SUM(J61:Q61) -> 0 | AT61: =SUM(R61:AR61) -> 0 | AV61: =IF(AT61>0,1,0) -> 0 | AW61: =IF(AT61=0,1,0) -> 1 | AX61: =IF(AT61>=8,1,0) -> 0 | AY61: 1 | AZ61: 正面 | BA61: P | BB61: 原文
A62: CN-P-061 | B62: 中文 | C62: 推荐 | D62: 24 | E62: 2 | F62: 47.5 | G62: 2024-08-20 | H62: 比战神好，没解密，有打击感，牛逼 | I62: 比战神好，没解密，有打击感，牛逼 | J62: =IF(SUM(R62:T62)>0,1,0) -> 0 | K62: =IF(SUM(U62:Y62)>0,1,0) -> 1 | L62: =IF(SUM(Z62:AC62)>0,1,0) -> 0 | M62: =IF(SUM(AD62:AF62)>0,1,0) -> 0 | N62: =IF(SUM(AG62:AH62)>0,1,0) -> 0 | O62: =IF(SUM(AI62:AL62)>0,1,0) -> 0 | P62: =IF(SUM(AM62:AQ62)>0,1,0) -> 0 | Q62: =IF(AR62>0,1,0) -> 0 | R62: 0 | S62: 0 | T62: 0 | U62: 1 | V62: 0 | W62: 0 | X62: 0 | Y62: 0 | Z62: 0 | AA62: 0 | AB62: 0 | AC62: 0 | AD62: 0 | AE62: 0 | AF62: 0 | AG62: 0 | AH62: 0 | AI62: 0 | AJ62: 0 | AK62: 0 | AL62: 0 | AM62: 0 | AN62: 0 | AO62: 0 | AP62: 0 | AQ62: 0 | AR62: 0 | AS62: =SUM(J62:Q62) -> 1 | AT62: =SUM(R62:AR62) -> 1 | AU62: 动作打击手感 | AV62: =IF(AT62>0,1,0) -> 1 | AW62: =IF(AT62=0,1,0) -> 0 | AX62: =IF(AT62>=8,1,0) -> 0 | AY62: 2 | AZ62: 正面 | BA62: P | BB62: 原文
A63: CN-P-062 | B63: 中文 | C63: 推荐 | D63: 24 | E63: 0 | F63: 96.9 | G63: 2024-08-20 | H63: “当你想做一个能打动自己的事情的时候，他大概率能打动跟你相似的人”“第一次做，完成比完美重要”“你可以试试”“吴承恩和莎士比亚没有那么大差别”“不光关注孙悟空，还会关注对手，能不能把敌人也塑造好”“经典的东西并不是一个束缚""国内出现75分产品的时候，只是因为我们承载了大家对这个国家这个民族朴素的热爱”“从自己出发，务实一点地考量，只作为一个不带这些标签（国产3A）的产品的时候是不是也能达到那个标准”“产品应该是先自然地打动本地的文化族群，当品质足够高，会自然辐射到海外”“不是因为盖了国风的标签就有了免死金牌或者可以低品质，而是应该要有更大的责任感，应该如履薄冰”“老祖宗赏饭吃自己不肯吃”“踏上取经路，比抵达灵山更重要”——游戏科学创始人冯骥天都这么冷了，多一件袈裟，它也不嫌多 | I63: “当你想做一个能打动自己的事情的时候，他大概率能打动跟你相似的人”“第一次做，完成比完美重要”“你可以试试”“吴承恩和莎士比亚没有那么大差别”“不光关注孙悟空，还会关注对手，能不能把敌人也塑造好”“经典的东西并不是一个束缚""国内出现75分产品的时候，只是因为我们承载了大家对这个国家这个民族朴素的热爱”“从自己出发，务实一点地考量，只作为一个不带这些标签（国产3A）的产品的时候是不是也能达到那个标准”“产品应该是先自然地打动本地的文化族群，当品质足够高，会自然辐射到海外”“不是因为盖了国风的标签就有了免死金牌或者可以低品质，而是应该要有更大的责任感，应该如履薄冰”“老祖宗赏饭吃自己不肯吃”“踏上取经路，比抵达灵山更重要”——游戏科学创始人冯骥天都这么冷了，多一件袈裟，它也不嫌多 | J63: =IF(SUM(R63:T63)>0,1,0) -> 0 | K63: =IF(SUM(U63:Y63)>0,1,0) -> 0 | L63: =IF(SUM(Z63:AC63)>0,1,0) -> 0 | M63: =IF(SUM(AD63:AF63)>0,1,0) -> 0 | N63: =IF(SUM(AG63:AH63)>0,1,0) -> 1 | O63: =IF(SUM(AI63:AL63)>0,1,0) -> 1 | P63: =IF(SUM(AM63:AQ63)>0,1,0) -> 0 | Q63: =IF(AR63>0,1,0) -> 1 | R63: 0 | S63: 0 | T63: 0 | U63: 0 | V63: 0 | W63: 0 | X63: 0 | Y63: 0 | Z63: 0 | AA63: 0 | AB63: 0 | AC63: 0 | AD63: 0 | AE63: 0 | AF63: 0 | AG63: 1 | AH63: 0 | AI63: 1 | AJ63: 0 | AK63: 0 | AL63: 0 | AM63: 0 | AN63: 0 | AO63: 0 | AP63: 0 | AQ63: 0 | AR63: 1 | AS63: =SUM(J63:Q63) -> 3 | AT63: =SUM(R63:AR63) -> 3 | AU63: 整体完成度；西游悟空符号；国产3A身份期待 | AV63: =IF(AT63>0,1,0) -> 1 | AW63: =IF(AT63=0,1,0) -> 0 | AX63: =IF(AT63>=8,1,0) -> 0 | AY63: 29 | AZ63: 正面 | BA63: P | BB63: 原文
A64: CN-P-063 | B64: 中文 | C64: 推荐 | D64: 23 | E64: 0 | F64: 23.5 | G64: 2024-08-20 | H64: 个人感觉文化氛围浓郁，作为中国人很喜欢这样的画风，就是难度偏高，希望游戏有难度选项，照顾一下魂类新手玩家。希望加入对超宽屏 带鱼屏的分辨率支持，加入更多的养成DLC要素。 | I64: 个人感觉文化氛围浓郁，作为中国人很喜欢这样的画风，就是难度偏高，希望游戏有难度选项，照顾一下魂类新手玩家。希望加入对超宽屏 带鱼屏的分辨率支持，加入更多的养成DLC要素。 | J64: =IF(SUM(R64:T64)>0,1,0) -> 1 | K64: =IF(SUM(U64:Y64)>0,1,0) -> 1 | L64: =IF(SUM(Z64:AC64)>0,1,0) -> 0 | M64: =IF(SUM(AD64:AF64)>0,1,0) -> 0 | N64: =IF(SUM(AG64:AH64)>0,1,0) -> 0 | O64: =IF(SUM(AI64:AL64)>0,1,0) -> 0 | P64: =IF(SUM(AM64:AQ64)>0,1,0) -> 0 | Q64: =IF(AR64>0,1,0) -> 1 | R64: 1 | S64: 0 | T64: 0 | U64: 0 | V64: 0 | W64: 1 | X64: 0 | Y64: 0 | Z64: 0 | AA64: 0 | AB64: 0 | AC64: 0 | AD64: 0 | AE64: 0 | AF64: 0 | AG64: 0 | AH64: 0 | AI64: 0 | AJ64: 0 | AK64: 0 | AL64: 0 | AM64: 0 | AN64: 0 | AO64: 0 | AP64: 0 | AQ64: 0 | AR64: 1 | AS64: =SUM(J64:Q64) -> 3 | AT64: =SUM(R64:AR64) -> 3 | AU64: 画面美术场景；难度挑战；国产3A身份期待 | AV64: =IF(AT64>0,1,0) -> 1 | AW64: =IF(AT64=0,1,0) -> 0 | AX64: =IF(AT64>=8,1,0) -> 0 | AY64: 5.5 | AZ64: 正面 | BA64: P | BB64: 原文
A65: CN-P-064 | B65: 中文 | C65: 推荐 | D65: 23 | E65: 0 | F65: 45.2 | G65: 2024-08-20 | H65: 爽玩了第一章，应该说这游戏达到了我的预期。猴哥性能太强了，各种神通，血还很厚，挺容易上手的。第一章打完后的cg让我想起了小时候看的动画，希望国内以后能有更多这样优秀的作品 | I65: 爽玩了第一章，应该说这游戏达到了我的预期。猴哥性能太强了，各种神通，血还很厚，挺容易上手的。第一章打完后的cg让我想起了小时候看的动画，希望国内以后能有更多这样优秀的作品 | J65: =IF(SUM(R65:T65)>0,1,0) -> 1 | K65: =IF(SUM(U65:Y65)>0,1,0) -> 1 | L65: =IF(SUM(Z65:AC65)>0,1,0) -> 0 | M65: =IF(SUM(AD65:AF65)>0,1,0) -> 1 | N65: =IF(SUM(AG65:AH65)>0,1,0) -> 0 | O65: =IF(SUM(AI65:AL65)>0,1,0) -> 1 | P65: =IF(SUM(AM65:AQ65)>0,1,0) -> 0 | Q65: =IF(AR65>0,1,0) -> 0 | R65: 0 | S65: 0 | T65: 1 | U65: 0 | V65: 0 | W65: 1 | X65: 0 | Y65: 0 | Z65: 0 | AA65: 0 | AB65: 0 | AC65: 0 | AD65: 1 | AE65: 0 | AF65: 0 | AG65: 0 | AH65: 0 | AI65: 1 | AJ65: 1 | AK65: 1 | AL65: 0 | AM65: 0 | AN65: 0 | AO65: 0 | AP65: 0 | AQ65: 0 | AR65: 0 | AS65: =SUM(J65:Q65) -> 4 | AT65: =SUM(R65:AR65) -> 6 | AU65: 演出角色怪物设计；难度挑战；优化帧率；西游悟空符号；童年记忆情怀；本国媒介路径 | AV65: =IF(AT65>0,1,0) -> 1 | AW65: =IF(AT65=0,1,0) -> 0 | AX65: =IF(AT65>=8,1,0) -> 0 | AY65: 7.5 | AZ65: 正面 | BA65: P | BB65: 原文
A66: CN-P-065 | B66: 中文 | C66: 推荐 | D66: 2121 | E66: 55 | F66: 72.1 | G66: 2024-08-21 | H66: 金猴奋起千钧棒，玉宇澄清万古埃 毫无疑问，黑猴打破了这些年发售前呼声高昂，发售后掉轨的魔咒。 有一说一，文化争夺想在西方语境下的围剿进行突围，是有难度。 话说回来，今年的对手将将。咱就说：“什么年度不年度的，天命人无所畏惧！” 欢迎关注 网易UU鉴赏家培养计划 关注UU加速器VX公众号，回复“steam”，获得专属玩家群邀请。 前言： 问题①：《黑神话：悟空》让国人玩家们狂热的根本是什么？ 问题②：《黑神话：悟空》到底是一款什么样的游戏？（跟预告片有多大差异？） 对于观望的玩家，这篇内容是推荐文，也是“祛魅文”，还是一名玩家的游玩心得。 推荐：为何痴迷，为何上头？ 我们知道本作并不完美，有些地方还显得稚嫩。可为什么我们依旧为其痴迷，玩起来那么的上头？ 答案很显而易见，只是被大家忽略了。情怀只是其中很小一部分，只是初因。而玩起来上头，上头后为其打Call点赞，这主要原因还是“打铁还需自身硬”。 游戏玩家们并不会只因为情怀而买单，这一切都需要游戏本身够硬，它不需要金刚不坏（不需要完美），但它要足够硬，硬到经得起玩家们的三味真火的考验。俗话说，真金不怕火炼。 推荐：预告片可靠吗？ 预料之中，这几年的预告片中的少许内容并未全部出现在游戏中。其中些许演出环节，还有明显的变动，如果你对过去的每一个视频都看过，在游戏时你会发现这些变动的。 情理之中，游戏实际质感与预告片中的效果保持一致，不存在所谓的“预告骗”。你在视频中看到的那种成熟游戏气质，在实际游戏中依然如此，游戏的视听体验令人满意。 推荐：黑猴是款什么样的游戏？ 《黑神话：悟空》其实更像是包含了角色扮演元素的动作冒险游戏，也是一款含有魂元素的Boss rush游戏。 注意：魂元素，不是类魂。就像一部电影包含惊悚元素，这并不能代表这是部惊悚电影。 游戏中的部分魂元素：“缩地青符”的效果。还有土地庙（类似篝火），当然黑猴在这方面做了创新优化，玩家与土地庙互动不会立马刷新地图，玩家可以自行整备物资，选择“调息”后才会刷新地图和恢复状态。 Boss rush：游戏每个关卡提供了大量的Boss战，其中好些Boss是国人玩家耳熟能详的存在，同时也带来全新的解读与设计，某些Boss更是从外观到战斗设计都非常有特色。 游戏难度综合而言尚可，极难的Boss少见（推荐手柄游玩）。对于没有动作游戏经验的玩家来说，多少得受点苦了，当然稍加练习后，也可以较快上手，因为战斗的操作逻辑并不复杂。对于有动作游戏经验的玩家而言，只要热热身，就可以战个痛快了。 “祛魅”：遇到的问题，未来的成长 这部份内容是以客观的视角来看待品质。 正如前文所说，《黑神话：悟空》不需要金刚不坏，但它要够硬。是的，黑猴它够硬，只是不完美。其中游戏时你会遇到一些可忽略的小问题，也可能遇到一直伴随着你的问题。 一些小问题，暂举几个例子。 初次跟二郎神对战时，蓄力攻击（按Y）有丢失特效和音效的情况。偶尔打坐时的配乐跟打坐结束后的环境音衔接不到位，导致两种音乐的冲突。跟土地庙的互动，土地庙显示了互动图标（右扳机RT），但按下时却是释放技能和使用物品的窗口。以上问题非必现。 可能一直伴随你的问题。 遗憾的是，游戏地图的表现成为最大的短板。一方面是设计原因，使地图路径的编排不够巧妙。二方面或许是开发周期紧张，又或许是经验不足，让地图上的可活动区域与非活动区域的界限不够清晰，同时（可能）为了避免场景bug，开发组在场景中放置了大量的空气墙。这让一些区域看似可以前往，其实并非可探索区域，为了避免错过重要道具，玩家会在每个类似路径处尝试探索，于是更加容易碰到空气墙，最终让玩家的体验体验遭受到挑战。显然这是开发组在未来需要成长的环节。 幸运的是，场景设计是完美的。那种氛围感只有中式美学才能办到，那些到实地取景的佛像与建筑，非常令人震撼。今年上半年还提前看了其中的某取景地，怕的就是黑神话大火后景点迎来旅游高峰。 当前的部分大小问题，未来应该能够得到处理，这一点个人不太担心。实话实说，这些问题基本在可接受范围内，游戏发售至今，没有大量极其恶劣的优化问题或者BUG问题，例如：像2077首发那样的灾难。能做到这一点，属实不易。 游戏体验和心得 个人游玩方式 比起速通，个人更喜欢事无巨细的探索，把章节里的每个BOSS都打败，每个蒲团都收集到，还要尽可能的拿到各种成就。这种情况下额外的云存档就显得格外重要，无论是换电脑玩时存档误覆盖，还是各种问题导致存档损坏，UU云存档能给你的存档上个保险。 主要是操作方便，启动即用，不会影响原平台正常存储档，UU与平台云存档同步运行。而且全程自动保存，无需手动操作，不干扰你的游戏体验。还能一键备份存档，一键锁定存档，锁定剧情分支点关键存档，一周目也能打多结局。到时也别错过UU存档市集，为你提供多种存档，多种攻略，如：知名主播存档，做成就做收集的各种存档，还有手把手教学的攻略。最重要的是免费！现在还能参与活动赢奖品。 敌人数值选择 敌人数值采用的是固定数值，而非动态数值，例如：前期有难度的敌人，在后期对于玩家来说就是杂兵，顶多是算是个精英怪。 固定数值与动态数值，有优劣但并无对错，这只是一种选择。是选择固定数值，还是选择动态数值，这在于开发商想给玩家什么样的体验。个人是两者数值体系都能接受的，但对于一款包含了角色扮演的动作冒险游戏而言，敌人是固定数值的好处，让玩家的成长体验更好，可以利用属性成长来弥补技艺上的欠缺，不至于持续处于吃闭门羹的状态。 死亡惩罚刚刚好 角色死亡后，大多数敌人会重新刷新，除特殊敌人或特殊地点敌人外，如：土地庙处或重要物品处的敌人初次击杀后不会再刷新。最重要的是玩家角色死亡后，重要资源不会掉落，使玩家战斗压力最小化。重要资源如“灵韵”，游戏中的一种重要类货币要素。 角色死亡后的跑路设计也很人性化。特别是一些需要转场，需要载入才能抵达的隐藏Boss区域，玩家在这里被Boss击杀后并不需要跑很远，也不需要重新载入区域。玩家会在区域入口处复活，这里会有一个临时复活点，这大大降低了玩家战败后的挫败感，以及节约了玩家反复挑战的时间成本。 推图驱动力足够 场景中会有放置的灵韵，涉取灵韵不仅增加灵韵点数，还能恢复若干酒葫芦使用次数，这无疑是增加了玩家在探索地图时的续航能力。 地图很大，敌人数量不算多，好在敌人与道具的放置摆放合理，在探索的过程中乐意继续往前推进。这些重要道具正是在探索关卡中拾取，或者击杀关卡中的Boss获取，这是一种正向的游戏体验。例如：酒葫芦，不仅仅是一种恢复手段，也是游戏BD的玩法之一，这让酒葫芦相关的道具成为了探索搜集的重要驱动力之一。 关于游戏BD 套装BD：套装非恒强，装备不一定要穿整套。是否要凑套装效果，要看效果情况。只要数值相差不是特别大，在最多保证2件套装效果下，优先穿戴有“独门妙用”（也就是装备特性）的装备，一般这类装备都有战斗强化，如改变招式或增伤等特性。 酒葫芦BD：葫芦本身有被动效果，获得的酒类也带有特殊效果，其中泡酒的道具还有特殊效果。所以当酒葫芦一口下肚就能有3种buff加成，好不快活！ 为何没有提起招式BD，因为迟早你是要水桶号的。 写在最后的话 由于文化差异原因，文化话语权争夺的原因，《黑神话：悟空》想要在西方语境下的围剿进行突围，可以说还是很有难度的。 从当前在海外的媒体评测与MC综合评分来看，正是如此——“难”。外媒是很难理解西游记这一文化对于国人的影响，何况中式文学在翻译后会流失大量原本的的韵味，他们更难理解这款游戏的诞生对于中国单机游戏圈（开发者和玩家）代表着什么。所以他们更多是只能关注游戏玩法和开发技术，在褪去那一层层的情怀光环下，还顶着他们对多元化要求的有色眼镜的苛责下，综合评分能够达到80分往上，可以说这一成绩不可小觑！ 话说回来，今年的对手将将够看。黑神话这样的品质和热度，争取争取年度提名问题不大。至于其它的事情就复杂很多，这是文化话语权的争夺，最终角逐如何，交给天命吧！ 最后感谢各位天命人的阅读！ | I66: 金猴奋起千钧棒，玉宇澄清万古埃 毫无疑问，黑猴打破了这些年发售前呼声高昂，发售后掉轨的魔咒。 有一说一，文化争夺想在西方语境下的围剿进行突围，是有难度。 话说回来，今年的对手将将。咱就说：“什么年度不年度的，天命人无所畏惧！” 欢迎关注 网易UU鉴赏家培养计划 关注UU加速器VX公众号，回复“steam”，获得专属玩家群邀请。 前言： 问题①：《黑神话：悟空》让国人玩家们狂热的根本是什么？ 问题②：《黑神话：悟空》到底是一款什么样的游戏？（跟预告片有多大差异？） 对于观望的玩家，这篇内容是推荐文，也是“祛魅文”，还是一名玩家的游玩心得。 推荐：为何痴迷，为何上头？ 我们知道本作并不完美，有些地方还显得稚嫩。可为什么我们依旧为其痴迷，玩起来那么的上头？ 答案很显而易见，只是被大家忽略了。情怀只是其中很小一部分，只是初因。而玩起来上头，上头后为其打Call点赞，这主要原因还是“打铁还需自身硬”。 游戏玩家们并不会只因为情怀而买单，这一切都需要游戏本身够硬，它不需要金刚不坏（不需要完美），但它要足够硬，硬到经得起玩家们的三味真火的考验。俗话说，真金不怕火炼。 推荐：预告片可靠吗？ 预料之中，这几年的预告片中的少许内容并未全部出现在游戏中。其中些许演出环节，还有明显的变动，如果你对过去的每一个视频都看过，在游戏时你会发现这些变动的。 情理之中，游戏实际质感与预告片中的效果保持一致，不存在所谓的“预告骗”。你在视频中看到的那种成熟游戏气质，在实际游戏中依然如此，游戏的视听体验令人满意。 推荐：黑猴是款什么样的游戏？ 《黑神话：悟空》其实更像是包含了角色扮演元素的动作冒险游戏，也是一款含有魂元素的Boss rush游戏。 注意：魂元素，不是类魂。就像一部电影包含惊悚元素，这并不能代表这是部惊悚电影。 游戏中的部分魂元素：“缩地青符”的效果。还有土地庙（类似篝火），当然黑猴在这方面做了创新优化，玩家与土地庙互动不会立马刷新地图，玩家可以自行整备物资，选择“调息”后才会刷新地图和恢复状态。 Boss rush：游戏每个关卡提供了大量的Boss战，其中好些Boss是国人玩家耳熟能详的存在，同时也带来全新的解读与设计，某些Boss更是从外观到战斗设计都非常有特色。 游戏难度综合而言尚可，极难的Boss少见（推荐手柄游玩）。对于没有动作游戏经验的玩家来说，多少得受点苦了，当然稍加练习后，也可以较快上手，因为战斗的操作逻辑并不复杂。对于有动作游戏经验的玩家而言，只要热热身，就可以战个痛快了。 “祛魅”：遇到的问题，未来的成长 这部份内容是以客观的视角来看待品质。 正如前文所说，《黑神话：悟空》不需要金刚不坏，但它要够硬。是的，黑猴它够硬，只是不完美。其中游戏时你会遇到一些可忽略的小问题，也可能遇到一直伴随着你的问题。 一些小问题，暂举几个例子。 初次跟二郎神对战时，蓄力攻击（按Y）有丢失特效和音效的情况。偶尔打坐时的配乐跟打坐结束后的环境音衔接不到位，导致两种音乐的冲突。跟土地庙的互动，土地庙显示了互动图标（右扳机RT），但按下时却是释放技能和使用物品的窗口。以上问题非必现。 可能一直伴随你的问题。 遗憾的是，游戏地图的表现成为最大的短板。一方面是设计原因，使地图路径的编排不够巧妙。二方面或许是开发周期紧张，又或许是经验不足，让地图上的可活动区域与非活动区域的界限不够清晰，同时（可能）为了避免场景bug，开发组在场景中放置了大量的空气墙。这让一些区域看似可以前往，其实并非可探索区域，为了避免错过重要道具，玩家会在每个类似路径处尝试探索，于是更加容易碰到空气墙，最终让玩家的体验体验遭受到挑战。显然这是开发组在未来需要成长的环节。 幸运的是，场景设计是完美的。那种氛围感只有中式美学才能办到，那些到实地取景的佛像与建筑，非常令人震撼。今年上半年还提前看了其中的某取景地，怕的就是黑神话大火后景点迎来旅游高峰。 当前的部分大小问题，未来应该能够得到处理，这一点个人不太担心。实话实说，这些问题基本在可接受范围内，游戏发售至今，没有大量极其恶劣的优化问题或者BUG问题，例如：像2077首发那样的灾难。能做到这一点，属实不易。 游戏体验和心得 个人游玩方式 比起速通，个人更喜欢事无巨细的探索，把章节里的每个BOSS都打败，每个蒲团都收集到，还要尽可能的拿到各种成就。这种情况下额外的云存档就显得格外重要，无论是换电脑玩时存档误覆盖，还是各种问题导致存档损坏，UU云存档能给你的存档上个保险。 主要是操作方便，启动即用，不会影响原平台正常存储档，UU与平台云存档同步运行。而且全程自动保存，无需手动操作，不干扰你的游戏体验。还能一键备份存档，一键锁定存档，锁定剧情分支点关键存档，一周目也能打多结局。到时也别错过UU存档市集，为你提供多种存档，多种攻略，如：知名主播存档，做成就做收集的各种存档，还有手把手教学的攻略。最重要的是免费！现在还能参与活动赢奖品。 敌人数值选择 敌人数值采用的是固定数值，而非动态数值，例如：前期有难度的敌人，在后期对于玩家来说就是杂兵，顶多是算是个精英怪。 固定数值与动态数值，有优劣但并无对错，这只是一种选择。是选择固定数值，还是选择动态数值，这在于开发商想给玩家什么样的体验。个人是两者数值体系都能接受的，但对于一款包含了角色扮演的动作冒险游戏而言，敌人是固定数值的好处，让玩家的成长体验更好，可以利用属性成长来弥补技艺上的欠缺，不至于持续处于吃闭门羹的状态。 死亡惩罚刚刚好 角色死亡后，大多数敌人会重新刷新，除特殊敌人或特殊地点敌人外，如：土地庙处或重要物品处的敌人初次击杀后不会再刷新。最重要的是玩家角色死亡后，重要资源不会掉落，使玩家战斗压力最小化。重要资源如“灵韵”，游戏中的一种重要类货币要素。 角色死亡后的跑路设计也很人性化。特别是一些需要转场，需要载入才能抵达的隐藏Boss区域，玩家在这里被Boss击杀后并不需要跑很远，也不需要重新载入区域。玩家会在区域入口处复活，这里会有一个临时复活点，这大大降低了玩家战败后的挫败感，以及节约了玩家反复挑战的时间成本。 推图驱动力足够 场景中会有放置的灵韵，涉取灵韵不仅增加灵韵点数，还能恢复若干酒葫芦使用次数，这无疑是增加了玩家在探索地图时的续航能力。 地图很大，敌人数量不算多，好在敌人与道具的放置摆放合理，在探索的过程中乐意继续往前推进。这些重要道具正是在探索关卡中拾取，或者击杀关卡中的Boss获取，这是一种正向的游戏体验。例如：酒葫芦，不仅仅是一种恢复手段，也是游戏BD的玩法之一，这让酒葫芦相关的道具成为了探索搜集的重要驱动力之一。 关于游戏BD 套装BD：套装非恒强，装备不一定要穿整套。是否要凑套装效果，要看效果情况。只要数值相差不是特别大，在最多保证2件套装效果下，优先穿戴有“独门妙用”（也就是装备特性）的装备，一般这类装备都有战斗强化，如改变招式或增伤等特性。 酒葫芦BD：葫芦本身有被动效果，获得的酒类也带有特殊效果，其中泡酒的道具还有特殊效果。所以当酒葫芦一口下肚就能有3种buff加成，好不快活！ 为何没有提起招式BD，因为迟早你是要水桶号的。 写在最后的话 由于文化差异原因，文化话语权争夺的原因，《黑神话：悟空》想要在西方语境下的围剿进行突围，可以说还是很有难度的。 从当前在海外的媒体评测与MC综合评分来看，正是如此——“难”。外媒是很难理解西游记这一文化对于国人的影响，何况中式文学在翻译后会流失大量原本的的韵味，他们更难理解这款游戏的诞生对于中国单机游戏圈（开发者和玩家）代表着什么。所以他们更多是只能关注游戏玩法和开发技术，在褪去那一层层的情怀光环下，还顶着他们对多元化要求的有色眼镜的苛责下，综合评分能够达到80分往上，可以说这一成绩不可小觑！ 话说回来，今年的对手将将够看。黑神话这样的品质和热度，争取争取年度提名问题不大。至于其它的事情就复杂很多，这是文化话语权的争夺，最终角逐如何，交给天命吧！ 最后感谢各位天命人的阅读！ | J66: =IF(SUM(R66:T66)>0,1,0) -> 1 | K66: =IF(SUM(U66:Y66)>0,1,0) -> 1 | L66: =IF(SUM(Z66:AC66)>0,1,0) -> 1 | M66: =IF(SUM(AD66:AF66)>0,1,0) -> 1 | N66: =IF(SUM(AG66:AH66)>0,1,0) -> 1 | O66: =IF(SUM(AI66:AL66)>0,1,0) -> 1 | P66: =IF(SUM(AM66:AQ66)>0,1,0) -> 1 | Q66: =IF(AR66>0,1,0) -> 0 | R66: 1 | S66: 1 | T66: 1 | U66: 1 | V66: 1 | W66: 1 | X66: 1 | Y66: 0 | Z66: 1 | AA66: 1 | AB66: 1 | AC66: 0 | AD66: 1 | AE66: 0 | AF66: 1 | AG66: 1 | AH66: 1 | AI66: 1 | AJ66: 1 | AK66: 0 | AL66: 0 | AM66: 0 | AN66: 0 | AO66: 0 | AP66: 1 | AQ66: 0 | AR66: 0 | AS66: =SUM(J66:Q66) -> 7 | AT66: =SUM(R66:AR66) -> 17 | AU66: 画面美术场景；音乐音效配音；演出角色怪物设计；动作打击手感；Boss战斗节奏；难度挑战；锁定视角；地图路线；空气墙可达性；探索隐藏支线；优化帧率；Bug兼容硬件；整体完成度；推荐价值判断；西游悟空符号；童年记忆情怀；外部资料依赖 | AV66: =IF(AT66>0,1,0) -> 1 | AW66: =IF(AT66=0,1,0) -> 0 | AX66: =IF(AT66>=8,1,0) -> 1 | AY66: 116.5 | AZ66: 正面 | BA66: P | BB66: 原文
A67: CN-P-066 | B67: 中文 | C67: 推荐 | D67: 1653 | E67: 93 | F67: 64.6 | G67: 2024-08-21 | H67: 十分确实吹的太过了，这个游戏要是满分十分，那他的地图设计扣一分还少了。这游戏的地图主打一个让你不知所措。很多地方喜欢把死路做的又宽又大又长，把正确的路做的又隐秘又窄。很多岔口还是互相绕远路串起来的。基本没有引导怎么走全凭感觉。走远了你连你自己在哪都不知道了。还有这个游戏地图大多数情况下都得和空气墙打交道，不是说这个游戏空气墙有多么多，而是他的地图做的你根本无法判断到底能不能走，必须去得去试探一下才能确定这个区域的可活动范围。没错空气墙没有挡你路而是给你排除了个错误选项。尤其是第二章地图简直就是得摸墙走。游科赶紧把地图指引功能给安排上吧，要不然指南针也行。就目前这个地图设计就是纯纯的折磨，打完第二章不觉得爽反而是感觉终于解脱了。10分还是不客观了，8分确实合理分割——————————————————我平时没怎么加好友突然来了那么多好友申请我还奇怪，原来是我被团建了。先说第一，这个评价仅仅是我认为这个游戏体验上不足的地方。评分也是我的标准评的，我不是任何媒体机构，评价也仅仅代表个人。其次，我寻思我也没给差评吧。如果是因为我打了差评来团建我还能理解，好评还来团建我真不理解。有些人拿法环和黑魂的地图拐我，其一我不是魂类玩家，也不喜欢魂。我也听说过魂类有多折磨，但我不是抖m也没有斯德哥尔摩。你让我去玩魂我只会给比黑神话更低的分数，你拿别的游戏拐我证明不了其他游戏有多优秀，只能让我知道那个游戏体验可能比这个还烂。其次，我说地图有问题可没说其他的地方都不行，相反其他的都很行。但是这个地图的设计带来的负反馈基本上摧毁了相当多其他优点建立的正反馈。空气墙的问题根本不在于多而是你根本没办法判断到底哪里有空气墙哪里没有，基本上是逼着你模墙探索才能对可活动范围的大小有概念。在整体都很优秀的情况下，严重的缺点会把问题暴露的更加彻底。我专门提地图问题就是因为这个地图设计基本把我的探索欲望和正反馈给干了个稀碎。至于我没提到了那基本就是我认为这个游戏都没有问题的地方。再来，我判断游戏该不该买的的时候一般都优先看一些刺眼的缺点再看优点。一个游戏再好也存在有一些玩家无法接受的地方，我强调地图恰恰是我最不能接受的地方就是这个地图设计。我的评价只是告诉打算买的人这游戏存在的缺点有个清晰的认知而已。再来团建我对你们也没好处，会影响这游戏的好评率吗？还是影响你去拿tga大奖？影响这个游戏的销量？还是你们我谈缺点扫了你们的兴让你们看着不好受？我的评分就那么重要？ | I67: 十分确实吹的太过了，这个游戏要是满分十分，那他的地图设计扣一分还少了。这游戏的地图主打一个让你不知所措。很多地方喜欢把死路做的又宽又大又长，把正确的路做的又隐秘又窄。很多岔口还是互相绕远路串起来的。基本没有引导怎么走全凭感觉。走远了你连你自己在哪都不知道了。还有这个游戏地图大多数情况下都得和空气墙打交道，不是说这个游戏空气墙有多么多，而是他的地图做的你根本无法判断到底能不能走，必须去得去试探一下才能确定这个区域的可活动范围。没错空气墙没有挡你路而是给你排除了个错误选项。尤其是第二章地图简直就是得摸墙走。游科赶紧把地图指引功能给安排上吧，要不然指南针也行。就目前这个地图设计就是纯纯的折磨，打完第二章不觉得爽反而是感觉终于解脱了。10分还是不客观了，8分确实合理分割——————————————————我平时没怎么加好友突然来了那么多好友申请我还奇怪，原来是我被团建了。先说第一，这个评价仅仅是我认为这个游戏体验上不足的地方。评分也是我的标准评的，我不是任何媒体机构，评价也仅仅代表个人。其次，我寻思我也没给差评吧。如果是因为我打了差评来团建我还能理解，好评还来团建我真不理解。有些人拿法环和黑魂的地图拐我，其一我不是魂类玩家，也不喜欢魂。我也听说过魂类有多折磨，但我不是抖m也没有斯德哥尔摩。你让我去玩魂我只会给比黑神话更低的分数，你拿别的游戏拐我证明不了其他游戏有多优秀，只能让我知道那个游戏体验可能比这个还烂。其次，我说地图有问题可没说其他的地方都不行，相反其他的都很行。但是这个地图的设计带来的负反馈基本上摧毁了相当多其他优点建立的正反馈。空气墙的问题根本不在于多而是你根本没办法判断到底哪里有空气墙哪里没有，基本上是逼着你模墙探索才能对可活动范围的大小有概念。在整体都很优秀的情况下，严重的缺点会把问题暴露的更加彻底。我专门提地图问题就是因为这个地图设计基本把我的探索欲望和正反馈给干了个稀碎。至于我没提到了那基本就是我认为这个游戏都没有问题的地方。再来，我判断游戏该不该买的的时候一般都优先看一些刺眼的缺点再看优点。一个游戏再好也存在有一些玩家无法接受的地方，我强调地图恰恰是我最不能接受的地方就是这个地图设计。我的评价只是告诉打算买的人这游戏存在的缺点有个清晰的认知而已。再来团建我对你们也没好处，会影响这游戏的好评率吗？还是影响你去拿tga大奖？影响这个游戏的销量？还是你们我谈缺点扫了你们的兴让你们看着不好受？我的评分就那么重要？ | J67: =IF(SUM(R67:T67)>0,1,0) -> 0 | K67: =IF(SUM(U67:Y67)>0,1,0) -> 1 | L67: =IF(SUM(Z67:AC67)>0,1,0) -> 1 | M67: =IF(SUM(AD67:AF67)>0,1,0) -> 0 | N67: =IF(SUM(AG67:AH67)>0,1,0) -> 1 | O67: =IF(SUM(AI67:AL67)>0,1,0) -> 0 | P67: =IF(SUM(AM67:AQ67)>0,1,0) -> 0 | Q67: =IF(AR67>0,1,0) -> 0 | R67: 0 | S67: 0 | T67: 0 | U67: 0 | V67: 0 | W67: 0 | X67: 0 | Y67: 1 | Z67: 1 | AA67: 1 | AB67: 1 | AC67: 1 | AD67: 0 | AE67: 0 | AF67: 0 | AG67: 0 | AH67: 1 | AI67: 0 | AJ67: 0 | AK67: 0 | AL67: 0 | AM67: 0 | AN67: 0 | AO67: 0 | AP67: 0 | AQ67: 0 | AR67: 0 | AS67: =SUM(J67:Q67) -> 3 | AT67: =SUM(R67:AR67) -> 6 | AU67: 判定反馈；地图路线；空气墙可达性；探索隐藏支线；引导迷路单线；推荐价值判断 | AV67: =IF(AT67>0,1,0) -> 1 | AW67: =IF(AT67=0,1,0) -> 0 | AX67: =IF(AT67>=8,1,0) -> 0 | AY67: 6 | AZ67: 正面 | BA67: P | BB67: 原文
A68: CN-N-067 | B68: 中文 | C68: 不推荐 | D68: 562 | E68: 48 | F68: 113 | G68: 2024-08-21 | H68: 我目前玩到小西天，总结目前为止，浮屠界你们设计的是认真的？什么屎啊？就这个边缘机制能统一吗？自主移动包括奔跑跳跃，到了边缘空气墙。被攻击可以落下，自主攻击也可以落下，到底会不会做边缘机制，然后一个强力近战兵旁边来一个高台上的弓箭手，请问你给了角色远程处理敌人的能力了吗？就一个棍花防御，最傻逼的顶着弓箭的强硬直杀气近战兵之后，也完全没手段上高台击杀远程，然后你还要在旁边放个宝箱。其他游戏也有这种阴间的屎图，但是又臭又香，你这个纯臭，说不会做游戏，游戏做得还可以，说会做，让这个关卡设计师n+1滚蛋吧。 | I68: 我目前玩到小西天，总结目前为止，浮屠界你们设计的是认真的？什么屎啊？就这个边缘机制能统一吗？自主移动包括奔跑跳跃，到了边缘空气墙。被攻击可以落下，自主攻击也可以落下，到底会不会做边缘机制，然后一个强力近战兵旁边来一个高台上的弓箭手，请问你给了角色远程处理敌人的能力了吗？就一个棍花防御，最傻逼的顶着弓箭的强硬直杀气近战兵之后，也完全没手段上高台击杀远程，然后你还要在旁边放个宝箱。其他游戏也有这种阴间的屎图，但是又臭又香，你这个纯臭，说不会做游戏，游戏做得还可以，说会做，让这个关卡设计师n+1滚蛋吧。 | J68: =IF(SUM(R68:T68)>0,1,0) -> 0 | K68: =IF(SUM(U68:Y68)>0,1,0) -> 1 | L68: =IF(SUM(Z68:AC68)>0,1,0) -> 1 | M68: =IF(SUM(AD68:AF68)>0,1,0) -> 0 | N68: =IF(SUM(AG68:AH68)>0,1,0) -> 0 | O68: =IF(SUM(AI68:AL68)>0,1,0) -> 0 | P68: =IF(SUM(AM68:AQ68)>0,1,0) -> 0 | Q68: =IF(AR68>0,1,0) -> 0 | R68: 0 | S68: 0 | T68: 0 | U68: 1 | V68: 0 | W68: 0 | X68: 0 | Y68: 0 | Z68: 1 | AA68: 1 | AB68: 1 | AC68: 0 | AD68: 0 | AE68: 0 | AF68: 0 | AG68: 0 | AH68: 0 | AI68: 0 | AJ68: 0 | AK68: 0 | AL68: 0 | AM68: 0 | AN68: 0 | AO68: 0 | AP68: 0 | AQ68: 0 | AR68: 0 | AS68: =SUM(J68:Q68) -> 2 | AT68: =SUM(R68:AR68) -> 4 | AU68: 动作打击手感；地图路线；空气墙可达性；探索隐藏支线 | AV68: =IF(AT68>0,1,0) -> 1 | AW68: =IF(AT68=0,1,0) -> 0 | AX68: =IF(AT68>=8,1,0) -> 0 | AY68: -1.5 | AZ68: 负面 | BA68: N | BB68: 原文
A69: CN-P-068 | B69: 中文 | C69: 推荐 | D69: 309 | E69: 7 | F69: 119.5 | G69: 2024-08-21 | H69: 抛开国产滤镜也能给9分的品质，但游戏中的文化氛围那代入感是别的游戏给不了的。满分！！！ | I69: 抛开国产滤镜也能给9分的品质，但游戏中的文化氛围那代入感是别的游戏给不了的。满分！！！ | J69: =IF(SUM(R69:T69)>0,1,0) -> 0 | K69: =IF(SUM(U69:Y69)>0,1,0) -> 0 | L69: =IF(SUM(Z69:AC69)>0,1,0) -> 0 | M69: =IF(SUM(AD69:AF69)>0,1,0) -> 0 | N69: =IF(SUM(AG69:AH69)>0,1,0) -> 1 | O69: =IF(SUM(AI69:AL69)>0,1,0) -> 0 | P69: =IF(SUM(AM69:AQ69)>0,1,0) -> 0 | Q69: =IF(AR69>0,1,0) -> 1 | R69: 0 | S69: 0 | T69: 0 | U69: 0 | V69: 0 | W69: 0 | X69: 0 | Y69: 0 | Z69: 0 | AA69: 0 | AB69: 0 | AC69: 0 | AD69: 0 | AE69: 0 | AF69: 0 | AG69: 1 | AH69: 1 | AI69: 0 | AJ69: 0 | AK69: 0 | AL69: 0 | AM69: 0 | AN69: 0 | AO69: 0 | AP69: 0 | AQ69: 0 | AR69: 1 | AS69: =SUM(J69:Q69) -> 2 | AT69: =SUM(R69:AR69) -> 3 | AU69: 整体完成度；推荐价值判断；国产3A身份期待 | AV69: =IF(AT69>0,1,0) -> 1 | AW69: =IF(AT69=0,1,0) -> 0 | AX69: =IF(AT69>=8,1,0) -> 0 | AY69: 2 | AZ69: 正面 | BA69: P | BB69: 原文
A70: CN-P-069 | B70: 中文 | C70: 不推荐 | D70: 236 | E70: 15 | F70: 30.3 | G70: 2024-08-21 | H70: 打差评是为了提醒想入手的兄弟们，不要相信某些up主说“闭眼买”，“最值得一玩的游戏”，你得掂量掂量自己，自己是不是手残，自己喜不喜欢这种有点难度，手残起来还是会坐牢的“简化魂类”（他们都说这不能算是“魂类”游戏）游戏，boss的难度更像是怪物猎人世界（单人）。这游戏是arpg（他们如是说），上手有一点门槛，有难度，不喜欢这种类型，可以去支持自己感兴趣的优质国产独立游戏，例如，喜欢推理选《山河旅探》，喜欢经营建造可以选《戴森球计划》，喜欢悬疑恐怖的可以选《烟火》、《三伏》，不要脑子一热就来原价买一个自己不一定喜欢玩的3a游戏，好的游戏不只是3a。 | I70: 打差评是为了提醒想入手的兄弟们，不要相信某些up主说“闭眼买”，“最值得一玩的游戏”，你得掂量掂量自己，自己是不是手残，自己喜不喜欢这种有点难度，手残起来还是会坐牢的“简化魂类”（他们都说这不能算是“魂类”游戏）游戏，boss的难度更像是怪物猎人世界（单人）。这游戏是arpg（他们如是说），上手有一点门槛，有难度，不喜欢这种类型，可以去支持自己感兴趣的优质国产独立游戏，例如，喜欢推理选《山河旅探》，喜欢经营建造可以选《戴森球计划》，喜欢悬疑恐怖的可以选《烟火》、《三伏》，不要脑子一热就来原价买一个自己不一定喜欢玩的3a游戏，好的游戏不只是3a。 | J70: =IF(SUM(R70:T70)>0,1,0) -> 0 | K70: =IF(SUM(U70:Y70)>0,1,0) -> 1 | L70: =IF(SUM(Z70:AC70)>0,1,0) -> 0 | M70: =IF(SUM(AD70:AF70)>0,1,0) -> 0 | N70: =IF(SUM(AG70:AH70)>0,1,0) -> 1 | O70: =IF(SUM(AI70:AL70)>0,1,0) -> 0 | P70: =IF(SUM(AM70:AQ70)>0,1,0) -> 0 | Q70: =IF(AR70>0,1,0) -> 1 | R70: 0 | S70: 0 | T70: 0 | U70: 0 | V70: 1 | W70: 1 | X70: 0 | Y70: 0 | Z70: 0 | AA70: 0 | AB70: 0 | AC70: 0 | AD70: 0 | AE70: 0 | AF70: 0 | AG70: 0 | AH70: 1 | AI70: 0 | AJ70: 0 | AK70: 0 | AL70: 0 | AM70: 0 | AN70: 0 | AO70: 0 | AP70: 0 | AQ70: 0 | AR70: 1 | AS70: =SUM(J70:Q70) -> 3 | AT70: =SUM(R70:AR70) -> 4 | AU70: Boss战斗节奏；难度挑战；推荐价值判断；国产3A身份期待 | AV70: =IF(AT70>0,1,0) -> 1 | AW70: =IF(AT70=0,1,0) -> 0 | AX70: =IF(AT70>=8,1,0) -> 0 | AY70: 5.5 | AZ70: 正面 | BA70: P | BB70: 原文
A71: CN-P-070 | B71: 中文 | C71: 不推荐 | D71: 213 | E71: 64 | F71: 23.5 | G71: 2024-08-21 | H71: 你是一名猿神玩家，最喜欢的事就是去steam和各大论坛看有没有诋毁猿神的评论，双标是你作为猿神玩家的独特体制，因为每次刷到有关猿神的视频和帖子，你都会发了疯一样冲进评论区，搜查辱骂猿神的言论，逮住一个就说：“你买游戏了吗？云玩家，这么高的销售量还堵不了你的嘴吗？”遇到关于游戏性的问题便会嗦起那几个赛博奶嘴说到“xx也干了。“此时你就像猿神附体一样铜头铁臂，仿佛任何人都不能伤你半分。在评论区维护玩你那销量高的、剧情好的、被打压的猿神后你便美滋滋的打开另一个帖子如同寻血猎犬般继续搜寻下一个猎物。”wow！这种犹如疯狗一样的打法，让人根本无法反应，即便的陷入劣势也能通过身外法身召唤其他猴子猴孙瞬间将局势逆转，你才是新一代孙悟空。有没有一种可能他只是一款82分的游戏却被你们当成宗教一样成为赛博华为，销量高只是因为很多人去支持”村里第一个大学生“。而这赛博奶嘴则是你最后的一道防线，除了画质也许猿神都没问题了吧。所以你才是游戏领域大神，对吗？孩子。 | I71: 你是一名猿神玩家，最喜欢的事就是去steam和各大论坛看有没有诋毁猿神的评论，双标是你作为猿神玩家的独特体制，因为每次刷到有关猿神的视频和帖子，你都会发了疯一样冲进评论区，搜查辱骂猿神的言论，逮住一个就说：“你买游戏了吗？云玩家，这么高的销售量还堵不了你的嘴吗？”遇到关于游戏性的问题便会嗦起那几个赛博奶嘴说到“xx也干了。“此时你就像猿神附体一样铜头铁臂，仿佛任何人都不能伤你半分。在评论区维护玩你那销量高的、剧情好的、被打压的猿神后你便美滋滋的打开另一个帖子如同寻血猎犬般继续搜寻下一个猎物。”wow！这种犹如疯狗一样的打法，让人根本无法反应，即便的陷入劣势也能通过身外法身召唤其他猴子猴孙瞬间将局势逆转，你才是新一代孙悟空。有没有一种可能他只是一款82分的游戏却被你们当成宗教一样成为赛博华为，销量高只是因为很多人去支持”村里第一个大学生“。而这赛博奶嘴则是你最后的一道防线，除了画质也许猿神都没问题了吧。所以你才是游戏领域大神，对吗？孩子。 | J71: =IF(SUM(R71:T71)>0,1,0) -> 1 | K71: =IF(SUM(U71:Y71)>0,1,0) -> 0 | L71: =IF(SUM(Z71:AC71)>0,1,0) -> 0 | M71: =IF(SUM(AD71:AF71)>0,1,0) -> 0 | N71: =IF(SUM(AG71:AH71)>0,1,0) -> 1 | O71: =IF(SUM(AI71:AL71)>0,1,0) -> 1 | P71: =IF(SUM(AM71:AQ71)>0,1,0) -> 0 | Q71: =IF(AR71>0,1,0) -> 0 | R71: 1 | S71: 0 | T71: 0 | U71: 0 | V71: 0 | W71: 0 | X71: 0 | Y71: 0 | Z71: 0 | AA71: 0 | AB71: 0 | AC71: 0 | AD71: 0 | AE71: 0 | AF71: 0 | AG71: 0 | AH71: 1 | AI71: 1 | AJ71: 0 | AK71: 0 | AL71: 1 | AM71: 0 | AN71: 0 | AO71: 0 | AP71: 0 | AQ71: 0 | AR71: 0 | AS71: =SUM(J71:Q71) -> 3 | AT71: =SUM(R71:AR71) -> 4 | AU71: 画面美术场景；推荐价值判断；西游悟空符号；中国文化宗教语言审美 | AV71: =IF(AT71>0,1,0) -> 1 | AW71: =IF(AT71=0,1,0) -> 0 | AX71: =IF(AT71>=8,1,0) -> 0 | AY71: 10.5 | AZ71: 正面 | BA71: P | BB71: 原文
A72: CN-P-071 | B72: 中文 | C72: 不推荐 | D72: 151 | E72: 9 | F72: 20.1 | G72: 2024-08-21 | H72: 唱唱反调先说说结论，我个人对黑话空的评价，是一群全球顶尖的技美经过志同道合的讨论后弄出来的自娱自乐的大项目。其实这个评价有失公允，假定了他们不想把其他部分做好，但这个评价描述的画面描述是准确的。首先，美术评分上，技美能打100分，并且是因为满分只有一百分。但其他地方就乏善可陈了，不论是光脚的大圣失去了他的藕丝步云履，还是天兵在云端平铺列阵，场景美如画却很难在游戏中捕捉到一个与流程交互起来的惊艳画面，看起来这些顶级的美术资源制作能力被很多都被浪费在了蹩脚主美功力了，这就是我想说的，主美欠缺带来了审美灵魂缺失，主美为整个作品提供审美水平与审美灵魂，他能把开头的天兵天将编织成画，能将画面与流程串在一起，能变废为宝，更别说这么多宝贵的顶级资源。但遗憾的是，没有这样的主美。然后，游戏性上，勉强能踏过平均线，在一些设计上可以拿到不错的成绩，但整体问题太多了，甚至一个短评描述不完，除了boss战本身，其他几乎只要是一个系统就存在致命的缺陷，这其实同样也反应在制作人员的问题上，玩法策划数值策划关卡策划水平远远不行。根本支撑不起来这么多技美带来的顶级素材，在这种水平下这些东西难以用游戏性串联起来，更别提融入玩法里去了。最后，是剧情，从开篇尴尬的台词就能看出来，是个游科绑在一起，也难以写出小学超纲的台词。整个游戏像没有主编剧一样，故事过于简单，哪怕是找b站水平最差的阴谋论西游up，都不至于蹩脚至此。与魂叙事对比，他的话太多了，与其他演绎型线性游戏对比，他的话又太少了。如果你有心能看我骂骂咧咧写到这里，那么你一定值得我给你描述真正的问题。以上这些问题，是很典型的技美组成的团队会诞生的问题，他们技术好，但审美能力有限，又因为技术全球领先而看不起其他工作者，很难听进去他们的意见，我不少技美朋友都有这样的问题。但是，这依然不是问题的根源。你觉得，游科不想把它做好吗？他不想尝试解决这些问题吗？他不会克服技美的自身局限吗？这个问题，回归到一个本初问题，为什么是一群技美攒在一起做了这么个游戏，答案已经呼之欲出了，因为我们只有技美，中国游戏行业，只有技美能达到全球领先水平。所以他们积累了财富，有了能力去实现自己想做的东西，上述所有问题，只有一个原因，游科如果想找一个能胜任的人，在国内能找到吗？一个能力匹配他们技美水平的主美？一个能力能驾驭这些素材的玩法策划？一个能做好叙事与玩法结合的主编剧？这样的人如果存在，那么也早与这些技美一样，积累了财富与技术资本，去做自己想做的事了。问题如此之多，但黑话空绝对是一个非常好的开始，我们开始做了。给游科一些小建议，试着去培养一些上述问题中缺位的从业者吧，也许能有一天看到中国真正3A，真正的齐天大圣！ | I72: 唱唱反调先说说结论，我个人对黑话空的评价，是一群全球顶尖的技美经过志同道合的讨论后弄出来的自娱自乐的大项目。其实这个评价有失公允，假定了他们不想把其他部分做好，但这个评价描述的画面描述是准确的。首先，美术评分上，技美能打100分，并且是因为满分只有一百分。但其他地方就乏善可陈了，不论是光脚的大圣失去了他的藕丝步云履，还是天兵在云端平铺列阵，场景美如画却很难在游戏中捕捉到一个与流程交互起来的惊艳画面，看起来这些顶级的美术资源制作能力被很多都被浪费在了蹩脚主美功力了，这就是我想说的，主美欠缺带来了审美灵魂缺失，主美为整个作品提供审美水平与审美灵魂，他能把开头的天兵天将编织成画，能将画面与流程串在一起，能变废为宝，更别说这么多宝贵的顶级资源。但遗憾的是，没有这样的主美。然后，游戏性上，勉强能踏过平均线，在一些设计上可以拿到不错的成绩，但整体问题太多了，甚至一个短评描述不完，除了boss战本身，其他几乎只要是一个系统就存在致命的缺陷，这其实同样也反应在制作人员的问题上，玩法策划数值策划关卡策划水平远远不行。根本支撑不起来这么多技美带来的顶级素材，在这种水平下这些东西难以用游戏性串联起来，更别提融入玩法里去了。最后，是剧情，从开篇尴尬的台词就能看出来，是个游科绑在一起，也难以写出小学超纲的台词。整个游戏像没有主编剧一样，故事过于简单，哪怕是找b站水平最差的阴谋论西游up，都不至于蹩脚至此。与魂叙事对比，他的话太多了，与其他演绎型线性游戏对比，他的话又太少了。如果你有心能看我骂骂咧咧写到这里，那么你一定值得我给你描述真正的问题。以上这些问题，是很典型的技美组成的团队会诞生的问题，他们技术好，但审美能力有限，又因为技术全球领先而看不起其他工作者，很难听进去他们的意见，我不少技美朋友都有这样的问题。但是，这依然不是问题的根源。你觉得，游科不想把它做好吗？他不想尝试解决这些问题吗？他不会克服技美的自身局限吗？这个问题，回归到一个本初问题，为什么是一群技美攒在一起做了这么个游戏，答案已经呼之欲出了，因为我们只有技美，中国游戏行业，只有技美能达到全球领先水平。所以他们积累了财富，有了能力去实现自己想做的东西，上述所有问题，只有一个原因，游科如果想找一个能胜任的人，在国内能找到吗？一个能力匹配他们技美水平的主美？一个能力能驾驭这些素材的玩法策划？一个能做好叙事与玩法结合的主编剧？这样的人如果存在，那么也早与这些技美一样，积累了财富与技术资本，去做自己想做的事了。问题如此之多，但黑话空绝对是一个非常好的开始，我们开始做了。给游科一些小建议，试着去培养一些上述问题中缺位的从业者吧，也许能有一天看到中国真正3A，真正的齐天大圣！ | J72: =IF(SUM(R72:T72)>0,1,0) -> 1 | K72: =IF(SUM(U72:Y72)>0,1,0) -> 1 | L72: =IF(SUM(Z72:AC72)>0,1,0) -> 1 | M72: =IF(SUM(AD72:AF72)>0,1,0) -> 0 | N72: =IF(SUM(AG72:AH72)>0,1,0) -> 1 | O72: =IF(SUM(AI72:AL72)>0,1,0) -> 1 | P72: =IF(SUM(AM72:AQ72)>0,1,0) -> 0 | Q72: =IF(AR72>0,1,0) -> 1 | R72: 1 | S72: 0 | T72: 0 | U72: 0 | V72: 1 | W72: 1 | X72: 0 | Y72: 0 | Z72: 1 | AA72: 0 | AB72: 0 | AC72: 1 | AD72: 0 | AE72: 0 | AF72: 0 | AG72: 1 | AH72: 1 | AI72: 1 | AJ72: 0 | AK72: 0 | AL72: 0 | AM72: 0 | AN72: 0 | AO72: 0 | AP72: 0 | AQ72: 0 | AR72: 1 | AS72: =SUM(J72:Q72) -> 6 | AT72: =SUM(R72:AR72) -> 9 | AU72: 画面美术场景；Boss战斗节奏；难度挑战；地图路线；引导迷路单线；整体完成度；推荐价值判断；西游悟空符号；国产3A身份期待 | AV72: =IF(AT72>0,1,0) -> 1 | AW72: =IF(AT72=0,1,0) -> 0 | AX72: =IF(AT72>=8,1,0) -> 1 | AY72: 14 | AZ72: 正面 | BA72: P | BB72: 原文
A73: CN-P-072 | B73: 中文 | C73: 推荐 | D73: 134 | E73: 7 | F73: 111.1 | G73: 2024-08-21 | H73: 直接爆论年度最佳，手残不要怕，非常简单，已114514周目 | I73: 直接爆论年度最佳，手残不要怕，非常简单，已114514周目 | J73: =IF(SUM(R73:T73)>0,1,0) -> 0 | K73: =IF(SUM(U73:Y73)>0,1,0) -> 1 | L73: =IF(SUM(Z73:AC73)>0,1,0) -> 0 | M73: =IF(SUM(AD73:AF73)>0,1,0) -> 0 | N73: =IF(SUM(AG73:AH73)>0,1,0) -> 0 | O73: =IF(SUM(AI73:AL73)>0,1,0) -> 0 | P73: =IF(SUM(AM73:AQ73)>0,1,0) -> 0 | Q73: =IF(AR73>0,1,0) -> 0 | R73: 0 | S73: 0 | T73: 0 | U73: 0 | V73: 0 | W73: 1 | X73: 0 | Y73: 0 | Z73: 0 | AA73: 0 | AB73: 0 | AC73: 0 | AD73: 0 | AE73: 0 | AF73: 0 | AG73: 0 | AH73: 0 | AI73: 0 | AJ73: 0 | AK73: 0 | AL73: 0 | AM73: 0 | AN73: 0 | AO73: 0 | AP73: 0 | AQ73: 0 | AR73: 0 | AS73: =SUM(J73:Q73) -> 1 | AT73: =SUM(R73:AR73) -> 1 | AU73: 难度挑战 | AV73: =IF(AT73>0,1,0) -> 1 | AW73: =IF(AT73=0,1,0) -> 0 | AX73: =IF(AT73>=8,1,0) -> 0 | AY73: 2 | AZ73: 正面 | BA73: P | BB73: 原文
... A79: CN-M-078 | B79: 中文 | C79: 推荐 | D79: 49 | E79: 0 | F79: 54.6 | G79: 2024-08-21 | H79: 总的来说这游戏是真上头，就觉得指令输入延迟有点大。 | I79: 总的来说这游戏是真上头，就觉得指令输入延迟有点大。 | J79: =IF(SUM(R79:T79)>0,1,0) -> 0 | K79: =IF(SUM(U79:Y79)>0,1,0) -> 0 | L79: =IF(SUM(Z79:AC79)>0,1,0) -> 0 | M79: =IF(SUM(AD79:AF79)>0,1,0) -> 1 | N79: =IF(SUM(AG79:AH79)>0,1,0) -> 0 | O79: =IF(SUM(AI79:AL79)>0,1,0) -> 0 | P79: =IF(SUM(AM79:AQ79)>0,1,0) -> 0 | Q79: =IF(AR79>0,1,0) -> 0 | R79: 0 | S79: 0 | T79: 0 | U79: 0 | V79: 0 | W79: 0 | X79: 0 | Y79: 0 | Z79: 0 | AA79: 0 | AB79: 0 | AC79: 0 | AD79: 1 | AE79: 0 | AF79: 0 | AG79: 0 | AH79: 0 | AI79: 0 | AJ79: 0 | AK79: 0 | AL79: 0 | AM79: 0 | AN79: 0 | AO79: 0 | AP79: 0 | AQ79: 0 | AR79: 0 | AS79: =SUM(J79:Q79) -> 1 | AT79: =SUM(R79:AR79) -> 1 | AU79: 优化帧率 | AV79: =IF(AT79>0,1,0) -> 1 | AW79: =IF(AT79=0,1,0) -> 0 | AX79: =IF(AT79>=8,1,0) -> 0 | AY79: 0 | AZ79: 中性 | BA79: M | BB79: 原文
A80: CN-N-079 | B80: 中文 | C80: 推荐 | D80: 48 | E80: 1 | F80: 95.5 | G80: 2024-08-21 | H80: 太他妈牛逼了！不想睡觉！想一口气通关 | I80: 太他妈牛逼了！不想睡觉！想一口气通关 | J80: =IF(SUM(R80:T80)>0,1,0) -> 0 | K80: =IF(SUM(U80:Y80)>0,1,0) -> 0 | L80: =IF(SUM(Z80:AC80)>0,1,0) -> 0 | M80: =IF(SUM(AD80:AF80)>0,1,0) -> 0 | N80: =IF(SUM(AG80:AH80)>0,1,0) -> 0 | O80: =IF(SUM(AI80:AL80)>0,1,0) -> 0 | P80: =IF(SUM(AM80:AQ80)>0,1,0) -> 0 | Q80: =IF(AR80>0,1,0) -> 0 | R80: 0 | S80: 0 | T80: 0 | U80: 0 | V80: 0 | W80: 0 | X80: 0 | Y80: 0 | Z80: 0 | AA80: 0 | AB80: 0 | AC80: 0 | AD80: 0 | AE80: 0 | AF80: 0 | AG80: 0 | AH80: 0 | AI80: 0 | AJ80: 0 | AK80: 0 | AL80: 0 | AM80: 0 | AN80: 0 | AO80: 0 | AP80: 0 | AQ80: 0 | AR80: 0 | AS80: =SUM(J80:Q80) -> 0 | AT80: =SUM(R80:AR80) -> 0 | AV80: =IF(AT80>0,1,0) -> 0 | AW80: =IF(AT80=0,1,0) -> 1 | AX80: =IF(AT80>=8,1,0) -> 0 | AY80: -1.5 | AZ80: 负面 | BA80: N | BB80: 原文
A81: CN-P-080 | B81: 中文 | C81: 推荐 | D81: 47 | E81: 0 | F81: 91.4 | G81: 2024-08-21 | H81: 踏上取经路，比抵达灵山更重要。怀揣单机梦想，再绎西游神话！ | I81: 踏上取经路，比抵达灵山更重要。怀揣单机梦想，再绎西游神话！ | J81: =IF(SUM(R81:T81)>0,1,0) -> 0 | K81: =IF(SUM(U81:Y81)>0,1,0) -> 0 | L81: =IF(SUM(Z81:AC81)>0,1,0) -> 0 | M81: =IF(SUM(AD81:AF81)>0,1,0) -> 0 | N81: =IF(SUM(AG81:AH81)>0,1,0) -> 0 | O81: =IF(SUM(AI81:AL81)>0,1,0) -> 1 | P81: =IF(SUM(AM81:AQ81)>0,1,0) -> 0 | Q81: =IF(AR81>0,1,0) -> 0 | R81: 0 | S81: 0 | T81: 0 | U81: 0 | V81: 0 | W81: 0 | X81: 0 | Y81: 0 | Z81: 0 | AA81: 0 | AB81: 0 | AC81: 0 | AD81: 0 | AE81: 0 | AF81: 0 | AG81: 0 | AH81: 0 | AI81: 1 | AJ81: 0 | AK81: 0 | AL81: 0 | AM81: 0 | AN81: 0 | AO81: 0 | AP81: 0 | AQ81: 0 | AR81: 0 | AS81: =SUM(J81:Q81) -> 1 | AT81: =SUM(R81:AR81) -> 1 | AU81: 西游悟空符号 | AV81: =IF(AT81>0,1,0) -> 1 | AW81: =IF(AT81=0,1,0) -> 0 | AX81: =IF(AT81>=8,1,0) -> 0 | AY81: 3.5 | AZ81: 正面 | BA81: P | BB81: 原文
A82: CN-P-081 | B82: 中文 | C82: 推荐 | D82: 9 | E82: 0 | F82: 75.9 小时 | G82: 2025-08-10 | H82: 奶GN：8/10 +画质上乘（3060卡），但是很多精美的地方无法放大仔细揣摩细节+打完第一章，过场动画和故事相辅相成作画优良，打完后反而有种圣人模式的感觉+卓越且符合中国审美的游戏百科，以山海经画风勾勒，加以小诗简介，最终伴随一则小故事来简述来龙去脉，给玩家带了无与伦比的沉浸体验+优秀的配音，配乐±以动作游戏而言，难度略高，以魂系游戏而已难度略低，但是对于手残的玩家来说还是略有挑战难度±丰富的怪物设置，每个boss和小怪拥有多样的技能与模型，无疑给西游之行带来很多沉浸感，但是对手残玩家而已无疑容易带来挫败感，需要多次尝试来通关，甚至需要做好无法通关准备-空气墙的处理让人失望，空气墙的处理方式应该是制作组并没有太多经验，一下子会让人出戏，像部分地区完全可以做到让猴哥摔下去然后再用尾巴把自己拉起来，而不是急刹-全屛无大UI的方式让人感觉到沉浸感十足，但是没有地图只能靠不断地碰撞空气墙来找路，如果能添加一个自定义地图UI显然是不错的，目前游科已经添加沉浸感拉满的地图，故此隐藏-个别小怪机制存在问题，典型远程怪，隔着十万八千里开始射杀玩家，架势如果不点技能完全只能站在挡箭雨，而前期技能点稀缺完全不应该放在这里，导致玩家不得不硬冲过去强杀-游戏指引堪忧，在缺乏地图和指引的情况下，玩家容易成为无头苍蝇乱窜错失许多支线以及boss-较差的奖励机制，玩家在游戏中并不能发现许多装备（逃课用）加之地图缺失无疑降低探索热情，进一步无法体验更多隐藏的剧情，而在战斗中，闪避机制奖励反馈略低，攻击连造无法快速闪避（第二段攻击会有僵直）简而言之，如果以3A游戏的标准来衡量，《黑神话》仅为中间水准，许多地方可以优化以及后续改进，价格完全对得起268元，不以道德绑架为基础，个人是推荐购买，如果你是不以魂系游戏为长项，请需谨慎购买。私货环节，就上文而已，黑神话以新晋公司第一款且国内唯一一款3A，能做到bug较少，画风优质，配乐满分，战斗精彩，设定沉浸，怪物众多实属不易，游戏科学冯骥、杨奇等先生以殉道者之势撬开国产3A能成大门，无疑告诉后来者此路能通，让更多资金与人才投入其中。在游玩过程中，个别剧情并没有看到画面而是仅听语音都可以感受到浓郁的氛围，尽管如此，3A制作周期长，资金压力大（尽管有腾子和游科手游等支撑依旧不得不砍掉项目），可见未来五至十年，国产3A可能仅黑神话一只独苗。因此牛奶个人感情评分最终为10分。 | I82: 奶GN：8/10 +画质上乘（3060卡），但是很多精美的地方无法放大仔细揣摩细节+打完第一章，过场动画和故事相辅相成作画优良，打完后反而有种圣人模式的感觉+卓越且符合中国审美的游戏百科，以山海经画风勾勒，加以小诗简介，最终伴随一则小故事来简述来龙去脉，给玩家带了无与伦比的沉浸体验+优秀的配音，配乐±以动作游戏而言，难度略高，以魂系游戏而已难度略低，但是对于手残的玩家来说还是略有挑战难度±丰富的怪物设置，每个boss和小怪拥有多样的技能与模型，无疑给西游之行带来很多沉浸感，但是对手残玩家而已无疑容易带来挫败感，需要多次尝试来通关，甚至需要做好无法通关准备-空气墙的处理让人失望，空气墙的处理方式应该是制作组并没有太多经验，一下子会让人出戏，像部分地区完全可以做到让猴哥摔下去然后再用尾巴把自己拉起来，而不是急刹-全屛无大UI的方式让人感觉到沉浸感十足，但是没有地图只能靠不断地碰撞空气墙来找路，如果能添加一个自定义地图UI显然是不错的，目前游科已经添加沉浸感拉满的地图，故此隐藏-个别小怪机制存在问题，典型远程怪，隔着十万八千里开始射杀玩家，架势如果不点技能完全只能站在挡箭雨，而前期技能点稀缺完全不应该放在这里，导致玩家不得不硬冲过去强杀-游戏指引堪忧，在缺乏地图和指引的情况下，玩家容易成为无头苍蝇乱窜错失许多支线以及boss-较差的奖励机制，玩家在游戏中并不能发现许多装备（逃课用）加之地图缺失无疑降低探索热情，进一步无法体验更多隐藏的剧情，而在战斗中，闪避机制奖励反馈略低，攻击连造无法快速闪避（第二段攻击会有僵直）简而言之，如果以3A游戏的标准来衡量，《黑神话》仅为中间水准，许多地方可以优化以及后续改进，价格完全对得起268元，不以道德绑架为基础，个人是推荐购买，如果你是不以魂系游戏为长项，请需谨慎购买。私货环节，就上文而已，黑神话以新晋公司第一款且国内唯一一款3A，能做到bug较少，画风优质，配乐满分，战斗精彩，设定沉浸，怪物众多实属不易，游戏科学冯骥、杨奇等先生以殉道者之势撬开国产3A能成大门，无疑告诉后来者此路能通，让更多资金与人才投入其中。在游玩过程中，个别剧情并没有看到画面而是仅听语音都可以感受到浓郁的氛围，尽管如此，3A制作周期长，资金压力大（尽管有腾子和游科手游等支撑依旧不得不砍掉项目），可见未来五至十年，国产3A可能仅黑神话一只独苗。因此牛奶个人感情评分最终为10分。 | J82: =IF(SUM(R82:T82)>0,1,0) -> 1 | K82: =IF(SUM(U82:Y82)>0,1,0) -> 1 | L82: =IF(SUM(Z82:AC82)>0,1,0) -> 1 | M82: =IF(SUM(AD82:AF82)>0,1,0) -> 1 | N82: =IF(SUM(AG82:AH82)>0,1,0) -> 1 | O82: =IF(SUM(AI82:AL82)>0,1,0) -> 1 | P82: =IF(SUM(AM82:AQ82)>0,1,0) -> 1 | Q82: =IF(AR82>0,1,0) -> 1 | R82: 1 | S82: 1 | T82: 1 | U82: 1 | V82: 1 | W82: 1 | X82: 0 | Y82: 1 | Z82: 1 | AA82: 1 | AB82: 1 | AC82: 1 | AD82: 1 | AE82: 0 | AF82: 1 | AG82: 1 | AH82: 1 | AI82: 1 | AJ82: 0 | AK82: 1 | AL82: 0 | AM82: 0 | AN82: 0 | AO82: 0 | AP82: 1 | AQ82: 0 | AR82: 1 | AS82: =SUM(J82:Q82) -> 8 | AT82: =SUM(R82:AR82) -> 19 | AU82: 画面美术场景；音乐音效配音；演出角色怪物设计；动作打击手感；Boss战斗节奏；难度挑战；判定反馈；地图路线；空气墙可达性；探索隐藏支线；引导迷路单线；优化帧率；Bug兼容硬件；整体完成度；推荐价值判断；西游悟空符号；本国媒介路径；外部资料依赖；国产3A身份期待 | AV82: =IF(AT82>0,1,0) -> 1 | AW82: =IF(AT82=0,1,0) -> 0 | AX82: =IF(AT82>=8,1,0) -> 1 | AY82: 30.5 | AZ82: 正面 | BA82: P | BB82: 原文
A83: CN-P-082 | B83: 中文 | C83: 推荐 | D83: 39 | E83: 2 | F83: 41.6 | G83: 2024-08-21 | H83: 可能不是动作游戏的里程碑，但绝对是中国游戏的里程碑，人生中玩过最好玩的“类魂”游戏。作为第一款国产3A游戏，他完美的不能再完美，影视级别的配音，充满文化魅力的UI，十分还原的故事，引人入胜的动作表现，电影级别的画面，优秀的剧情，黑神话悟空简直是我玩过最震惊我的游戏，当然了，这份震惊当中有一部分BUFF叫“同文化带来的浪漫” 以及魅力。每个中国人都知道齐天大圣，它是属于我们中国人的“超级英雄”，但是用超英来形容大圣简直就是诋毁，大圣是神，不是普通的超级英雄。我从来没有在任何一款游戏里见过把一个国家的文化展现的如此的淋漓尽致，浪漫切富有魅力，黑神话悟空绝对算的上我心目中的2024年度最佳，只有玩过其他同类封神的游戏，战神 艾尔登法环才能理解，黑神话悟空这个游戏的底层逻辑和底层元素非常清晰明了，所有的底层攻击和游戏设定都是一环扣一环，天赋可以无限重置，意味着每一个boss都有不一样的打法，这是我在其他游戏从未见到过的。 在其他同样优秀的游戏对比看来，例如战神4 艾尔登法环 只狼，我能给黑神话悟空85—90分，而上述我说的这些具有里程碑式和引领同类游戏的优秀游戏，在95—100分。 黑神话悟空已经封神，哪怕作为玩家在游戏层面，并非一味的吹捧，站在游戏公司的角度考虑，黑神话悟空已经完完全全的封神了，而且是大获全胜。 首先，为什么我上述提到了战神4 艾尔登法环 只狼，因为我多多少少在黑神话悟空里是看到了这些游戏的影子的，最起码主创和游戏公司是有意想吸取这些游戏的优点的，黑神话悟空大体像战神4，战神4是完完全全的线性剧情半开放世界，黑神话悟空并没有像艾尔登法环一样有如此庞大的地图，其次黑神话悟空的打斗跟招数我看到了有战神的的影子，毕竟当年的战神的打斗已经足够封神，所以说在玩家的视角里，黑神话悟空就应该像战神一样，足够爽，足够痛快，毕竟大家都知道题材是西游记，大家都想扮演齐天大圣，但是到了8.20号早上10点大家才意识到，我们玩的根本就不是齐天大圣，我们玩的只是一个平平无奇稍微有点修为的普通猴子，就像当年齐天大圣大闹天宫一样，十万天兵天将全是精英中的精英，但是只有精英中的精英才配见到齐天大圣，玩到现在我就感觉我只是一个稍微修炼了十几年的一个小土神仙一样，我原本以为会像战神一样痛快的杀，但是并没有，黑神话悟空融入了法环的风格，他的打boss底层逻辑就是像法环一样砍一刀翻滚闪避一下，所以这点跟玩家对黑神话悟空的印象是冲突的。这就是为什么我觉得有点失望的原因，如果黑神话悟空出一个难度选项，他可能不会跟战神一样多牛逼，但是他绝对可以跟杀的跟战神一样爽快。 黑神话悟空从来都不是魂类游戏，他甚至不是类魂游戏，他只有类魂的元素在里面，打怪升级养成，自己去探索招式之间的配合，自己去研究打法，正是黑神话悟空的魅力，同时还能感受西游世界的魅力，在国人玩家眼里，他绝对是超越艾尔登法环 战神4的封神游戏，因为他所讲述的故事是我们自己的故事，我们能够去感同身受的故事，不要开风灵月影，慢慢去体验，感受。两天二十四小时游戏时长，20号玩了15个小时，21号10个小时，他已经足够有魅力了，起码对于我来说。现在是2024年8月23号晚上9:56，历时四天39小时完美通关黑神话悟空，所有隐藏关卡隐藏boss全部都打了，也是顺利的达成了好结局，也是我比较满意的一个结局，我个人玩到现在，对结局有一些个人的看法和猜测，毕竟现在网上众说纷纭，有许多没玩过游戏的，甚至连电脑都没有的都在造谣，搞一堆黑神话悟空烟雾弹，以下是我个人通关后对黑神话悟空的理解和后续预测，会有剧透，谨慎观看。=====================================================================================首先剧情方面，网上众说纷纭，但是我可以告诉你，结局就只有两个，没有所谓的联妖破佛，大闹天宫，大圣复活，剧情方面从一开始序章所有人都认为大圣只是败了，后面才知道是死了，此时大部分玩家会本能的认为是二郎神杀的大圣，好结局跟坏结局唯一的不同就是戴上紧箍咒，和去找二郎神决战然后二郎神会告诉你真相，首先原著里二郎神跟悟空的关系还是很好的，实际上，二郎神是跟孙悟空演的一出戏，黑神话悟空的故事是在师徒四人取经过后，悟空被封为斗战胜佛，但是想回花果山还乡，但是却被整个天庭忌惮，甚至派出天兵天将围杀花果山，悟空无奈二次大闹天宫，跟二郎神商量好演一出戏骗过天庭，如果后面你打赢二郎神了，二郎神会说，没人能杀死齐天大圣，就连我也不行，能杀他的只有他自己，我个人主观理解，首先孙悟空是有配音的，但全游戏流程走完悟空的配音几乎不到20句话，而天命人全程没有配音，天命人就是孙悟空转世又成为的一只猕猴，但是丢失了所有的记忆，天命人天命人，不仅被上天选中，也被齐天大圣本人选中，其次第一章的土地公在详情介绍里有讲，教给土地公定身数等小魔法的是一位道士，通过详情得知，那位道士就是菩提老祖，特地教给土地公让土地公传授给天命人，也就是说跟二郎神演这一出戏就是孙悟空为了摆脱天庭的掌控，轮回就是为了脱下紧箍咒，要不然永世沦为天庭的奴隶，而坏结局就在于天命人没有去找二郎神，不知道是跟二郎神演的一出戏，打败齐天大圣怨气化为的躯壳后又被老猴子戴上了紧箍咒，又一次轮回，并且这次就连大圣转生成为的天命人也被再一次戴上了紧箍咒，也就是一结局大圣是失败了的，但是如果你打了二结局，天命人不会戴上紧箍咒，虽然再一次轮回，但是这一次，天命人不再是孙悟空，而是齐天大圣，戴上紧箍咒永远是孙悟空，而脱下紧箍咒才能成为齐天大圣。好的，剧情聊完，我个人往后的推测是，天命人就是大圣的转世，因为二级局打败二郎神后，二郎神把所有大圣的记忆全部还给了天命人，天命人本身就是大圣的转世，不存在夺舍之说，所以我推测往后的剧情，天命人会逐渐找回曾经齐天大圣的自己，大圣，会找回他自己。二结局非常震撼，绝对值得上天命人这次的旅程，我非常期待游科的DLC或者是悟空的续作，我知道一部分玩家对结局相当失望，大圣没有复活，没有大闹天庭，但是实际上现在的二结局是非常非常合适了已经，如果连妖破佛，天庭那么多神人，那接下来该如何收场？续作将如何讲述，黑神话悟空没有留下悬念，反而是给了玩家一剂定心丸，结尾的老猴子说了，大圣绝无复活的可能，代表了大圣的肉身，从话中也稍微有点隐喻，其实天命人就是大圣的转世，大师兄就藏在天命人的身体里，所谓的继承，不过是大圣为了重新做自己而去寻找上一世的肉身，并且游戏闪回时二郎神还说，你现在做这一出戏，天命人未必能有你现在的修行。 | I83: 可能不是动作游戏的里程碑，但绝对是中国游戏的里程碑，人生中玩过最好玩的“类魂”游戏。作为第一款国产3A游戏，他完美的不能再完美，影视级别的配音，充满文化魅力的UI，十分还原的故事，引人入胜的动作表现，电影级别的画面，优秀的剧情，黑神话悟空简直是我玩过最震惊我的游戏，当然了，这份震惊当中有一部分BUFF叫“同文化带来的浪漫” 以及魅力。每个中国人都知道齐天大圣，它是属于我们中国人的“超级英雄”，但是用超英来形容大圣简直就是诋毁，大圣是神，不是普通的超级英雄。我从来没有在任何一款游戏里见过把一个国家的文化展现的如此的淋漓尽致，浪漫切富有魅力，黑神话悟空绝对算的上我心目中的2024年度最佳，只有玩过其他同类封神的游戏，战神 艾尔登法环才能理解，黑神话悟空这个游戏的底层逻辑和底层元素非常清晰明了，所有的底层攻击和游戏设定都是一环扣一环，天赋可以无限重置，意味着每一个boss都有不一样的打法，这是我在其他游戏从未见到过的。 在其他同样优秀的游戏对比看来，例如战神4 艾尔登法环 只狼，我能给黑神话悟空85—90分，而上述我说的这些具有里程碑式和引领同类游戏的优秀游戏，在95—100分。 黑神话悟空已经封神，哪怕作为玩家在游戏层面，并非一味的吹捧，站在游戏公司的角度考虑，黑神话悟空已经完完全全的封神了，而且是大获全胜。 首先，为什么我上述提到了战神4 艾尔登法环 只狼，因为我多多少少在黑神话悟空里是看到了这些游戏的影子的，最起码主创和游戏公司是有意想吸取这些游戏的优点的，黑神话悟空大体像战神4，战神4是完完全全的线性剧情半开放世界，黑神话悟空并没有像艾尔登法环一样有如此庞大的地图，其次黑神话悟空的打斗跟招数我看到了有战神的的影子，毕竟当年的战神的打斗已经足够封神，所以说在玩家的视角里，黑神话悟空就应该像战神一样，足够爽，足够痛快，毕竟大家都知道题材是西游记，大家都想扮演齐天大圣，但是到了8.20号早上10点大家才意识到，我们玩的根本就不是齐天大圣，我们玩的只是一个平平无奇稍微有点修为的普通猴子，就像当年齐天大圣大闹天宫一样，十万天兵天将全是精英中的精英，但是只有精英中的精英才配见到齐天大圣，玩到现在我就感觉我只是一个稍微修炼了十几年的一个小土神仙一样，我原本以为会像战神一样痛快的杀，但是并没有，黑神话悟空融入了法环的风格，他的打boss底层逻辑就是像法环一样砍一刀翻滚闪避一下，所以这点跟玩家对黑神话悟空的印象是冲突的。这就是为什么我觉得有点失望的原因，如果黑神话悟空出一个难度选项，他可能不会跟战神一样多牛逼，但是他绝对可以跟杀的跟战神一样爽快。 黑神话悟空从来都不是魂类游戏，他甚至不是类魂游戏，他只有类魂的元素在里面，打怪升级养成，自己去探索招式之间的配合，自己去研究打法，正是黑神话悟空的魅力，同时还能感受西游世界的魅力，在国人玩家眼里，他绝对是超越艾尔登法环 战神4的封神游戏，因为他所讲述的故事是我们自己的故事，我们能够去感同身受的故事，不要开风灵月影，慢慢去体验，感受。两天二十四小时游戏时长，20号玩了15个小时，21号10个小时，他已经足够有魅力了，起码对于我来说。现在是2024年8月23号晚上9:56，历时四天39小时完美通关黑神话悟空，所有隐藏关卡隐藏boss全部都打了，也是顺利的达成了好结局，也是我比较满意的一个结局，我个人玩到现在，对结局有一些个人的看法和猜测，毕竟现在网上众说纷纭，有许多没玩过游戏的，甚至连电脑都没有的都在造谣，搞一堆黑神话悟空烟雾弹，以下是我个人通关后对黑神话悟空的理解和后续预测，会有剧透，谨慎观看。=====================================================================================首先剧情方面，网上众说纷纭，但是我可以告诉你，结局就只有两个，没有所谓的联妖破佛，大闹天宫，大圣复活，剧情方面从一开始序章所有人都认为大圣只是败了，后面才知道是死了，此时大部分玩家会本能的认为是二郎神杀的大圣，好结局跟坏结局唯一的不同就是戴上紧箍咒，和去找二郎神决战然后二郎神会告诉你真相，首先原著里二郎神跟悟空的关系还是很好的，实际上，二郎神是跟孙悟空演的一出戏，黑神话悟空的故事是在师徒四人取经过后，悟空被封为斗战胜佛，但是想回花果山还乡，但是却被整个天庭忌惮，甚至派出天兵天将围杀花果山，悟空无奈二次大闹天宫，跟二郎神商量好演一出戏骗过天庭，如果后面你打赢二郎神了，二郎神会说，没人能杀死齐天大圣，就连我也不行，能杀他的只有他自己，我个人主观理解，首先孙悟空是有配音的，但全游戏流程走完悟空的配音几乎不到20句话，而天命人全程没有配音，天命人就是孙悟空转世又成为的一只猕猴，但是丢失了所有的记忆，天命人天命人，不仅被上天选中，也被齐天大圣本人选中，其次第一章的土地公在详情介绍里有讲，教给土地公定身数等小魔法的是一位道士，通过详情得知，那位道士就是菩提老祖，特地教给土地公让土地公传授给天命人，也就是说跟二郎神演这一出戏就是孙悟空为了摆脱天庭的掌控，轮回就是为了脱下紧箍咒，要不然永世沦为天庭的奴隶，而坏结局就在于天命人没有去找二郎神，不知道是跟二郎神演的一出戏，打败齐天大圣怨气化为的躯壳后又被老猴子戴上了紧箍咒，又一次轮回，并且这次就连大圣转生成为的天命人也被再一次戴上了紧箍咒，也就是一结局大圣是失败了的，但是如果你打了二结局，天命人不会戴上紧箍咒，虽然再一次轮回，但是这一次，天命人不再是孙悟空，而是齐天大圣，戴上紧箍咒永远是孙悟空，而脱下紧箍咒才能成为齐天大圣。好的，剧情聊完，我个人往后的推测是，天命人就是大圣的转世，因为二级局打败二郎神后，二郎神把所有大圣的记忆全部还给了天命人，天命人本身就是大圣的转世，不存在夺舍之说，所以我推测往后的剧情，天命人会逐渐找回曾经齐天大圣的自己，大圣，会找回他自己。二结局非常震撼，绝对值得上天命人这次的旅程，我非常期待游科的DLC或者是悟空的续作，我知道一部分玩家对结局相当失望，大圣没有复活，没有大闹天庭，但是实际上现在的二结局是非常非常合适了已经，如果连妖破佛，天庭那么多神人，那接下来该如何收场？续作将如何讲述，黑神话悟空没有留下悬念，反而是给了玩家一剂定心丸，结尾的老猴子说了，大圣绝无复活的可能，代表了大圣的肉身，从话中也稍微有点隐喻，其实天命人就是大圣的转世，大师兄就藏在天命人的身体里，所谓的继承，不过是大圣为了重新做自己而去寻找上一世的肉身，并且游戏闪回时二郎神还说，你现在做这一出戏，天命人未必能有你现在的修行。 | J83: =IF(SUM(R83:T83)>0,1,0) -> 1 | K83: =IF(SUM(U83:Y83)>0,1,0) -> 1 | L83: =IF(SUM(Z83:AC83)>0,1,0) -> 1 | M83: =IF(SUM(AD83:AF83)>0,1,0) -> 0 | N83: =IF(SUM(AG83:AH83)>0,1,0) -> 1 | O83: =IF(SUM(AI83:AL83)>0,1,0) -> 1 | P83: =IF(SUM(AM83:AQ83)>0,1,0) -> 1 | Q83: =IF(AR83>0,1,0) -> 1 | R83: 1 | S83: 1 | T83: 0 | U83: 1 | V83: 1 | W83: 1 | X83: 1 | Y83: 0 | Z83: 1 | AA83: 0 | AB83: 1 | AC83: 1 | AD83: 0 | AE83: 0 | AF83: 0 | AG83: 0 | AH83: 1 | AI83: 1 | AJ83: 0 | AK83: 1 | AL83: 1 | AM83: 0 | AN83: 1 | AO83: 0 | AP83: 0 | AQ83: 1 | AR83: 1 | AS83: =SUM(J83:Q83) -> 7 | AT83: =SUM(R83:AR83) -> 16 | AU83: 画面美术场景；音乐音效配音；动作打击手感；Boss战斗节奏；难度挑战；锁定视角；地图路线；探索隐藏支线；引导迷路单线；推荐价值判断；西游悟空符号；本国媒介路径；中国文化宗教语言审美；原典知识人物关系专名；角色期待意义偏移；国产3A身份期待 | AV83: =IF(AT83>0,1,0) -> 1 | AW83: =IF(AT83=0,1,0) -> 0 | AX83: =IF(AT83>=8,1,0) -> 1 | AY83: 26.5 | AZ83: 正面 | BA83: P | BB83: 原文
A84: CN-M-083 | B84: 中文 | C84: 推荐 | D84: 35 | E84: 0 | F84: 85.6 | G84: 2024-08-21 | H84: 黑猴YYDS——来自小黑盒用户随风飘扬123的评价 | I84: 黑猴YYDS——来自小黑盒用户随风飘扬123的评价 | J84: =IF(SUM(R84:T84)>0,1,0) -> 0 | K84: =IF(SUM(U84:Y84)>0,1,0) -> 0 | L84: =IF(SUM(Z84:AC84)>0,1,0) -> 0 | M84: =IF(SUM(AD84:AF84)>0,1,0) -> 0 | N84: =IF(SUM(AG84:AH84)>0,1,0) -> 0 | O84: =IF(SUM(AI84:AL84)>0,1,0) -> 0 | P84: =IF(SUM(AM84:AQ84)>0,1,0) -> 0 | Q84: =IF(AR84>0,1,0) -> 0 | R84: 0 | S84: 0 | T84: 0 | U84: 0 | V84: 0 | W84: 0 | X84: 0 | Y84: 0 | Z84: 0 | AA84: 0 | AB84: 0 | AC84: 0 | AD84: 0 | AE84: 0 | AF84: 0 | AG84: 0 | AH84: 0 | AI84: 0 | AJ84: 0 | AK84: 0 | AL84: 0 | AM84: 0 | AN84: 0 | AO84: 0 | AP84: 0 | AQ84: 0 | AR84: 0 | AS84: =SUM(J84:Q84) -> 0 | AT84: =SUM(R84:AR84) -> 0 | AV84: =IF(AT84>0,1,0) -> 0 | AW84: =IF(AT84=0,1,0) -> 1 | AX84: =IF(AT84>=8,1,0) -> 0 | AY84: 0 | AZ84: 中性 | BA84: M | BB84: 原文
A85: CN-P-084 | B85: 中文 | C85: 推荐 | D85: 34 | E85: 3 | F85: 44.8 | G85: 2024-08-21 | H85: 美术顶音乐顶战斗顶地图设计不顶浮屠塔太恶心人了但是瑕不掩瑜，佳作！！！章节后的小动画和帛画真的太有意境了！！！绝对的好游戏，希望国产游戏越来越好 | I85: 美术顶音乐顶战斗顶地图设计不顶浮屠塔太恶心人了但是瑕不掩瑜，佳作！！！章节后的小动画和帛画真的太有意境了！！！绝对的好游戏，希望国产游戏越来越好 | J85: =IF(SUM(R85:T85)>0,1,0) -> 1 | K85: =IF(SUM(U85:Y85)>0,1,0) -> 1 | L85: =IF(SUM(Z85:AC85)>0,1,0) -> 1 | M85: =IF(SUM(AD85:AF85)>0,1,0) -> 0 | N85: =IF(SUM(AG85:AH85)>0,1,0) -> 1 | O85: =IF(SUM(AI85:AL85)>0,1,0) -> 1 | P85: =IF(SUM(AM85:AQ85)>0,1,0) -> 0 | Q85: =IF(AR85>0,1,0) -> 1 | R85: 1 | S85: 1 | T85: 1 | U85: 0 | V85: 1 | W85: 0 | X85: 0 | Y85: 0 | Z85: 1 | AA85: 0 | AB85: 0 | AC85: 0 | AD85: 0 | AE85: 0 | AF85: 0 | AG85: 0 | AH85: 1 | AI85: 0 | AJ85: 0 | AK85: 1 | AL85: 0 | AM85: 0 | AN85: 0 | AO85: 0 | AP85: 0 | AQ85: 0 | AR85: 1 | AS85: =SUM(J85:Q85) -> 6 | AT85: =SUM(R85:AR85) -> 8 | AU85: 画面美术场景；音乐音效配音；演出角色怪物设计；Boss战斗节奏；地图路线；推荐价值判断；本国媒介路径；国产3A身份期待 | AV85: =IF(AT85>0,1,0) -> 1 | AW85: =IF(AT85=0,1,0) -> 0 | AX85: =IF(AT85>=8,1,0) -> 1 | AY85: 7.5 | AZ85: 正面 | BA85: P | BB85: 原文
A86: CN-P-085 | B86: 中文 | C86: 推荐 | D86: 32 | E86: 2 | F86: 56.2 | G86: 2024-08-21 | H86: 啥也不说了，牛逼就完事，就喜欢看黑子跳脚 | I86: 啥也不说了，牛逼就完事，就喜欢看黑子跳脚 | J86: =IF(SUM(R86:T86)>0,1,0) -> 0 | K86: =IF(SUM(U86:Y86)>0,1,0) -> 0 | L86: =IF(SUM(Z86:AC86)>0,1,0) -> 0 | M86: =IF(SUM(AD86:AF86)>0,1,0) -> 0 | N86: =IF(SUM(AG86:AH86)>0,1,0) -> 0 | O86: =IF(SUM(AI86:AL86)>0,1,0) -> 0 | P86: =IF(SUM(AM86:AQ86)>0,1,0) -> 0 | Q86: =IF(AR86>0,1,0) -> 0 | R86: 0 | S86: 0 | T86: 0 | U86: 0 | V86: 0 | W86: 0 | X86: 0 | Y86: 0 | Z86: 0 | AA86: 0 | AB86: 0 | AC86: 0 | AD86: 0 | AE86: 0 | AF86: 0 | AG86: 0 | AH86: 0 | AI86: 0 | AJ86: 0 | AK86: 0 | AL86: 0 | AM86: 0 | AN86: 0 | AO86: 0 | AP86: 0 | AQ86: 0 | AR86: 0 | AS86: =SUM(J86:Q86) -> 0 | AT86: =SUM(R86:AR86) -> 0 | AV86: =IF(AT86>0,1,0) -> 0 | AW86: =IF(AT86=0,1,0) -> 1 | AX86: =IF(AT86>=8,1,0) -> 0 | AY86: 1 | AZ86: 正面 | BA86: P | BB86: 原文
A87: CN-P-086 | B87: 中文 | C87: 推荐 | D87: 31 | E87: 2 | F87: 34.1 | G87: 2024-08-21 | H87: 真的特别好玩，就是艺术——来自小黑盒用户玩家25007924的评价 | I87: 真的特别好玩，就是艺术——来自小黑盒用户玩家25007924的评价 | J87: =IF(SUM(R87:T87)>0,1,0) -> 0 | K87: =IF(SUM(U87:Y87)>0,1,0) -> 0 | L87: =IF(SUM(Z87:AC87)>0,1,0) -> 0 | M87: =IF(SUM(AD87:AF87)>0,1,0) -> 0 | N87: =IF(SUM(AG87:AH87)>0,1,0) -> 1 | O87: =IF(SUM(AI87:AL87)>0,1,0) -> 0 | P87: =IF(SUM(AM87:AQ87)>0,1,0) -> 0 | Q87: =IF(AR87>0,1,0) -> 0 | R87: 0 | S87: 0 | T87: 0 | U87: 0 | V87: 0 | W87: 0 | X87: 0 | Y87: 0 | Z87: 0 | AA87: 0 | AB87: 0 | AC87: 0 | AD87: 0 | AE87: 0 | AF87: 0 | AG87: 0 | AH87: 1 | AI87: 0 | AJ87: 0 | AK87: 0 | AL87: 0 | AM87: 0 | AN87: 0 | AO87: 0 | AP87: 0 | AQ87: 0 | AR87: 0 | AS87: =SUM(J87:Q87) -> 1 | AT87: =SUM(R87:AR87) -> 1 | AU87: 推荐价值判断 | AV87: =IF(AT87>0,1,0) -> 1 | AW87: =IF(AT87=0,1,0) -> 0 | AX87: =IF(AT87>=8,1,0) -> 0 | AY87: 3.5 | AZ87: 正面 | BA87: P | BB87: 原文
A88: CN-P-087 | B88: 中文 | C88: 推荐 | D88: 29 | E88: 1 | F88: 95.2 | G88: 2024-08-21 | H88: 今日欢呼孙大圣，只源妖雾又重来。村里第一个大学生，好好培养！美术表现、文化沉淀、动作设计、就连小怪故事都诚意满满，在我心里就是当之无愧的十分，当然问题也有，比如空气墙不明显，没地图一直迷路，没引导错过一堆隐藏，部分场景光影渲染有问题。但是，瑕不掩瑜，上乘佳作，情怀加持下直接化身满分神作，这就是文化认同的力量吧 | I88: 今日欢呼孙大圣，只源妖雾又重来。村里第一个大学生，好好培养！美术表现、文化沉淀、动作设计、就连小怪故事都诚意满满，在我心里就是当之无愧的十分，当然问题也有，比如空气墙不明显，没地图一直迷路，没引导错过一堆隐藏，部分场景光影渲染有问题。但是，瑕不掩瑜，上乘佳作，情怀加持下直接化身满分神作，这就是文化认同的力量吧 | J88: =IF(SUM(R88:T88)>0,1,0) -> 1 | K88: =IF(SUM(U88:Y88)>0,1,0) -> 1 | L88: =IF(SUM(Z88:AC88)>0,1,0) -> 1 | M88: =IF(SUM(AD88:AF88)>0,1,0) -> 0 | N88: =IF(SUM(AG88:AH88)>0,1,0) -> 1 | O88: =IF(SUM(AI88:AL88)>0,1,0) -> 1 | P88: =IF(SUM(AM88:AQ88)>0,1,0) -> 0 | Q88: =IF(AR88>0,1,0) -> 0 | R88: 1 | S88: 0 | T88: 0 | U88: 1 | V88: 0 | W88: 0 | X88: 0 | Y88: 0 | Z88: 1 | AA88: 1 | AB88: 1 | AC88: 1 | AD88: 0 | AE88: 0 | AF88: 0 | AG88: 1 | AH88: 1 | AI88: 1 | AJ88: 1 | AK88: 0 | AL88: 0 | AM88: 0 | AN88: 0 | AO88: 0 | AP88: 0 | AQ88: 0 | AR88: 0 | AS88: =SUM(J88:Q88) -> 5 | AT88: =SUM(R88:AR88) -> 10 | AU88: 画面美术场景；动作打击手感；地图路线；空气墙可达性；探索隐藏支线；引导迷路单线；整体完成度；推荐价值判断；西游悟空符号；童年记忆情怀 | AV88: =IF(AT88>0,1,0) -> 1 | AW88: =IF(AT88=0,1,0) -> 0 | AX88: =IF(AT88>=8,1,0) -> 1 | AY88: 7 | AZ88: 正面 | BA88: P | BB88: 原文
A89: CN-M-088 | B89: 中文 | C89: 推荐 | D89: 29 | E89: 1 | F89: 68.5 | G89: 2024-08-21 | H89: 空气墙是较多，小地图啥的，个人反而无所谓，剩下的，全是优点吧 | I89: 空气墙是较多，小地图啥的，个人反而无所谓，剩下的，全是优点吧 | J89: =IF(SUM(R89:T89)>0,1,0) -> 0 | K89: =IF(SUM(U89:Y89)>0,1,0) -> 0 | L89: =IF(SUM(Z89:AC89)>0,1,0) -> 1 | M89: =IF(SUM(AD89:AF89)>0,1,0) -> 0 | N89: =IF(SUM(AG89:AH89)>0,1,0) -> 0 | O89: =IF(SUM(AI89:AL89)>0,1,0) -> 0 | P89: =IF(SUM(AM89:AQ89)>0,1,0) -> 0 | Q89: =IF(AR89>0,1,0) -> 0 | R89: 0 | S89: 0 | T89: 0 | U89: 0 | V89: 0 | W89: 0 | X89: 0 | Y89: 0 | Z89: 1 | AA89: 1 | AB89: 0 | AC89: 0 | AD89: 0 | AE89: 0 | AF89: 0 | AG89: 0 | AH89: 0 | AI89: 0 | AJ89: 0 | AK89: 0 | AL89: 0 | AM89: 0 | AN89: 0 | AO89: 0 | AP89: 0 | AQ89: 0 | AR89: 0 | AS89: =SUM(J89:Q89) -> 1 | AT89: =SUM(R89:AR89) -> 2 | AU89: 地图路线；空气墙可达性 | AV89: =IF(AT89>0,1,0) -> 1 | AW89: =IF(AT89=0,1,0) -> 0 | AX89: =IF(AT89>=8,1,0) -> 0 | AY89: 0 | AZ89: 中性 | BA89: M | BB89: 原文
A90: CN-P-089 | B90: 中文 | C90: 推荐 | D90: 27 | E90: 0 | F90: 38.8 | G90: 2024-08-21 | H90: 游科做到这个地步真的厉害，美术顶级，演出效果非常好。 | I90: 游科做到这个地步真的厉害，美术顶级，演出效果非常好。 | J90: =IF(SUM(R90:T90)>0,1,0) -> 1 | K90: =IF(SUM(U90:Y90)>0,1,0) -> 0 | L90: =IF(SUM(Z90:AC90)>0,1,0) -> 0 | M90: =IF(SUM(AD90:AF90)>0,1,0) -> 0 | N90: =IF(SUM(AG90:AH90)>0,1,0) -> 0 | O90: =IF(SUM(AI90:AL90)>0,1,0) -> 0 | P90: =IF(SUM(AM90:AQ90)>0,1,0) -> 0 | Q90: =IF(AR90>0,1,0) -> 0 | R90: 1 | S90: 0 | T90: 1 | U90: 0 | V90: 0 | W90: 0 | X90: 0 | Y90: 0 | Z90: 0 | AA90: 0 | AB90: 0 | AC90: 0 | AD90: 0 | AE90: 0 | AF90: 0 | AG90: 0 | AH90: 0 | AI90: 0 | AJ90: 0 | AK90: 0 | AL90: 0 | AM90: 0 | AN90: 0 | AO90: 0 | AP90: 0 | AQ90: 0 | AR90: 0 | AS90: =SUM(J90:Q90) -> 1 | AT90: =SUM(R90:AR90) -> 2 | AU90: 画面美术场景；演出角色怪物设计 | AV90: =IF(AT90>0,1,0) -> 1 | AW90: =IF(AT90=0,1,0) -> 0 | AX90: =IF(AT90>=8,1,0) -> 0 | AY90: 2.5 | AZ90: 正面 | BA90: P | BB90: 原文
A91: CN-P-090 | B91: 中文 | C91: 推荐 | D91: 23 | E91: 6 | F91: 54.2 | G91: 2024-08-21 | H91: 什么？劈棍？什么劈棍？这游戏不是只有立棍吗？🐒丨丨丨 呔！ 🐯妖食我一棍！！！唉 🤓👆 我还有定身 😏 定！！！🤪 再接两棍丨丨！！！唉 🤓👆 我还有大头！！ 大头重击😡😡😡！唉 🤓👆 我还有广智！！ 将大局逆转吧😤😤！被虎哥打了一拳😨 不慌，我还有酒😠😠！！虎哥拔刀了😰😰😰 我躲😜 我躲🤪 棍气满了😦 ！ 立棍！！！！🥵🐒丨丨丨 呔！ 💨🐯 被躲了😨？🐯🤜🤜🤜🐒🐯：🐵留着下酒。。 | I91: 什么？劈棍？什么劈棍？这游戏不是只有立棍吗？🐒丨丨丨 呔！ 🐯妖食我一棍！！！唉 🤓👆 我还有定身 😏 定！！！🤪 再接两棍丨丨！！！唉 🤓👆 我还有大头！！ 大头重击😡😡😡！唉 🤓👆 我还有广智！！ 将大局逆转吧😤😤！被虎哥打了一拳😨 不慌，我还有酒😠😠！！虎哥拔刀了😰😰😰 我躲😜 我躲🤪 棍气满了😦 ！ 立棍！！！！🥵🐒丨丨丨 呔！ 💨🐯 被躲了😨？🐯🤜🤜🤜🐒🐯：🐵留着下酒。。 | J91: =IF(SUM(R91:T91)>0,1,0) -> 0 | K91: =IF(SUM(U91:Y91)>0,1,0) -> 0 | L91: =IF(SUM(Z91:AC91)>0,1,0) -> 0 | M91: =IF(SUM(AD91:AF91)>0,1,0) -> 0 | N91: =IF(SUM(AG91:AH91)>0,1,0) -> 0 | O91: =IF(SUM(AI91:AL91)>0,1,0) -> 0 | P91: =IF(SUM(AM91:AQ91)>0,1,0) -> 0 | Q91: =IF(AR91>0,1,0) -> 0 | R91: 0 | S91: 0 | T91: 0 | U91: 0 | V91: 0 | W91: 0 | X91: 0 | Y91: 0 | Z91: 0 | AA91: 0 | AB91: 0 | AC91: 0 | AD91: 0 | AE91: 0 | AF91: 0 | AG91: 0 | AH91: 0 | AI91: 0 | AJ91: 0 | AK91: 0 | AL91: 0 | AM91: 0 | AN91: 0 | AO91: 0 | AP91: 0 | AQ91: 0 | AR91: 0 | AS91: =SUM(J91:Q91) -> 0 | AT91: =SUM(R91:AR91) -> 0 | AV91: =IF(AT91>0,1,0) -> 0 | AW91: =IF(AT91=0,1,0) -> 1 | AX91: =IF(AT91>=8,1,0) -> 0 | AY91: 2 | AZ91: 正面 | BA91: P | BB91: 原文
A92: CN-P-091 | B92: 中文 | C92: 推荐 | D92: 22 | E92: 1 | F92: 87.7 | G92: 2024-08-21 | H92: 打了一晚上很上头，跟朋友挂着语音，一边打一边聊游戏，虽然两个人进度不同，但相同都是对国产游戏未来的美好愿景。 | I92: 打了一晚上很上头，跟朋友挂着语音，一边打一边聊游戏，虽然两个人进度不同，但相同都是对国产游戏未来的美好愿景。 | J92: =IF(SUM(R92:T92)>0,1,0) -> 1 | K92: =IF(SUM(U92:Y92)>0,1,0) -> 0 | L92: =IF(SUM(Z92:AC92)>0,1,0) -> 0 | M92: =IF(SUM(AD92:AF92)>0,1,0) -> 0 | N92: =IF(SUM(AG92:AH92)>0,1,0) -> 0 | O92: =IF(SUM(AI92:AL92)>0,1,0) -> 0 | P92: =IF(SUM(AM92:AQ92)>0,1,0) -> 0 | Q92: =IF(AR92>0,1,0) -> 1 | R92: 0 | S92: 1 | T92: 0 | U92: 0 | V92: 0 | W92: 0 | X92: 0 | Y92: 0 | Z92: 0 | AA92: 0 | AB92: 0 | AC92: 0 | AD92: 0 | AE92: 0 | AF92: 0 | AG92: 0 | AH92: 0 | AI92: 0 | AJ92: 0 | AK92: 0 | AL92: 0 | AM92: 0 | AN92: 0 | AO92: 0 | AP92: 0 | AQ92: 0 | AR92: 1 | AS92: =SUM(J92:Q92) -> 2 | AT92: =SUM(R92:AR92) -> 2 | AU92: 音乐音效配音；国产3A身份期待 | AV92: =IF(AT92>0,1,0) -> 1 | AW92: =IF(AT92=0,1,0) -> 0 | AX92: =IF(AT92>=8,1,0) -> 0 | AY92: 3 | AZ92: 正面 | BA92: P | BB92: 原文
A93: CN-P-092 | B93: 中文 | C93: 推荐 | D93: 1046 | E93: 937 | F93: 42.8 | G93: 2024-08-22 | H93: 若干年后游戏科学经过不断发展终于成为了世界顶尖ARPG开发商，当颁奖主持人呼唤杨奇上台领奖的时候，杨奇流下了激动的泪水向前走去，结果发现面前的台阶有一堵空气墙，于是打算绕一圈从幕后进，结果因为台上的灯导致过大的场景明暗对比度把杨奇闪晕了，最后兜兜转转终于走到后台，结果发现门不能从这一侧打开（——来自小黑盒用户她的女友的评价 | I93: 若干年后游戏科学经过不断发展终于成为了世界顶尖ARPG开发商，当颁奖主持人呼唤杨奇上台领奖的时候，杨奇流下了激动的泪水向前走去，结果发现面前的台阶有一堵空气墙，于是打算绕一圈从幕后进，结果因为台上的灯导致过大的场景明暗对比度把杨奇闪晕了，最后兜兜转转终于走到后台，结果发现门不能从这一侧打开（——来自小黑盒用户她的女友的评价 | J93: =IF(SUM(R93:T93)>0,1,0) -> 1 | K93: =IF(SUM(U93:Y93)>0,1,0) -> 0 | L93: =IF(SUM(Z93:AC93)>0,1,0) -> 1 | M93: =IF(SUM(AD93:AF93)>0,1,0) -> 0 | N93: =IF(SUM(AG93:AH93)>0,1,0) -> 0 | O93: =IF(SUM(AI93:AL93)>0,1,0) -> 0 | P93: =IF(SUM(AM93:AQ93)>0,1,0) -> 0 | Q93: =IF(AR93>0,1,0) -> 0 | R93: 1 | S93: 0 | T93: 0 | U93: 0 | V93: 0 | W93: 0 | X93: 0 | Y93: 0 | Z93: 0 | AA93: 1 | AB93: 0 | AC93: 0 | AD93: 0 | AE93: 0 | AF93: 0 | AG93: 0 | AH93: 0 | AI93: 0 | AJ93: 0 | AK93: 0 | AL93: 0 | AM93: 0 | AN93: 0 | AO93: 0 | AP93: 0 | AQ93: 0 | AR93: 0 | AS93: =SUM(J93:Q93) -> 2 | AT93: =SUM(R93:AR93) -> 2 | AU93: 画面美术场景；空气墙可达性 | AV93: =IF(AT93>0,1,0) -> 1 | AW93: =IF(AT93=0,1,0) -> 0 | AX93: =IF(AT93>=8,1,0) -> 0 | AY93: 3 | AZ93: 正面 | BA93: P | BB93: 原文
A94: CN-P-093 | B94: 中文 | C94: 不推荐 | D94: 451 | E94: 15 | F94: 50.6 | G94: 2024-08-22 | H94: 目前通关了，说真的除了第一回还可以，到了第二回的后半段就开始犯病，各种恶心设计交相辉映啊。先说这游戏优点吧，首先美术和画面很顶，其次塑造的文化氛围感很浓，游戏本身体量很大，一些boss设计的还可以，演出还可以，剩下开始吐槽缺点：1.堆怪：很多地方都是几个地面配一俩个甚至更多的远程敌人，这些远程敌人很多都是上不去的地形，这种情况下本身也没远程打击手段，只能跑路，如果附近有东西还不能停下来捡东西，仇恨导致拉火车，而且有时候会在一些狭小的地形安排这套配置，且后边一些小怪的血量和机动性提升的很明显，这种情况下只能隐身，什么？你说在之前舔图过程中已经和敌人消耗的蓝量见底了？那对不起，你只能开始“享受”制作组精心给你设计的惊喜啦。2.地图设计：本身就没有地图，还是弱引导（仅能从npc那获得只言片语），加上制作组没有设计此类游戏的经验，导致地图结构设计的也很糟糕，景色没有很明显区分，还有离谱的空气墙等等，从而导致各种迷路问题。3.土地庙放置问题：本来想放到上边地图编辑那一条，但这个问题很恶心所以单拎出来说，很多图两个庙之间距离很远（如果只是偶尔存在那么极个别的情况我也就不吐槽了，但事实相反存在很多这种情况），加上上面提到的两个问题他们混合在一起产生的这一坨东西真是给玩家的赛博“福报”，还有为什么要在快探索到下一座新庙的地方跟前放几个敌人，而且越到后边越严重，这游戏本来就存在着地图烂+堆怪的问题，有些想探索舔图且技术一般的玩家到达一个新的土地庙之前可能就没啥资源了，想赶紧恢复资源保存进度，这下到好成了葬身地了（上边提到了后边一些小怪血量和机动性都提升不少，没资源硬刚不了一点），而且在庙前挂了负反馈拉满，从上个庙复活以后又开始365里路长途奔袭……真的建议看一下其他做得好的竞品是咋设计的，建议学习一下。4.战斗体验：系统方面有一点像卧龙，战斗交互方面本作之前宣传的是非魂类游戏，但游戏有些怪打起来还是回合制（ps：这游戏为啥搞低精力槽+低法力槽绑定，你可以限定但是限定太多了，这也是导致有些怪很粪的原因之一。魂系这么设计是为了迎合系统，魂系动作相对来说简单，大部分战斗节奏偏慢，它主要玩的就是资源分配，我选择躲避、攻击、格挡要大概考虑一下剩下的血量、精力或者法力条消耗，这些是促成魂系列使用回合制打法合理的原因）。这游戏靠大多数时候要靠aaaa段子攒豆子，当定身用过进入cd时，而且已经消耗掉通过第一次aaaa积攒的豆子的情况下，就要进入boss回合了（有些boss定不了而且进p2会消减精力条上限，不带法宝难上天，说的就是你百眼！），到boss回合后，没豆子情况下你只能通过aaaa、喝药攒豆子或者找时机劈棍（立棍）蓄力，但一些疯狗boss连绵不绝的攻击让你蓄力机会很稀少，更多情况是普通轻攻击，但问题是普通轻攻击除了最后跳劈那一下有些boss会踉跄一下，剩下的打在他们身上真的不痛不痒，你本质上还是要靠消耗豆子的棍技去打血量或者踉跄以及积累倒地值，轻攻击第四段动作完成前取消不了反击，还有在你耍棍的途中大概率打不到最后一下跳劈，甚至可能因为有时候取消不了翻滚挨打，轻攻击前几段好像也无法积攒倒地值，而且单靠系统的话，攒豆和反制boss手段很单一，导致在你的视角里你和boss回合制，但在boss视角里一直是我的回合，还有就是打断boss出招的手段很多都得用攒的豆（蓄力也是攒豆子一种），所以很多玩家基本选择就是开局定身攒豆子或者进战斗前蓄力来一棍，定型文一样，当然也有别的套路比如禁字流之类的，但真正能用的流派与同行相比真不算多吧。其次这游戏反击也是有点问题，反击收益会不会太小了，头两次成功反击以后怪会踉跄但这时来不及补上后续伤害他就恢复了，这踉跄时间难道不可以长一点吗，让玩家稍微喝口药或者恢复一下精力，哪怕能普通aaaa连段打一套让自己资源变得有优势也行啊，现在来看除了做出来踉跄这个动画告诉你怪被你打踉跄了还有啥意义？这游戏反击多次命中积累倒地槽才能进入倒地硬直，虽然卧龙很多方面也是一坨，但它那个化解成功的爽度和收益绝对比黑猴强。黑猴动作模组数量一般，所以花活玩法偏少，游戏越到后面玩家方的手段越发固定越单调，加上上述所提到所有缺点杂糅在一起会让一些玩家产生疲劳的感觉，最后战斗系统总结就是门槛低，但深度一般；说到战斗体验了就顺便提一嘴boss战，游戏内boss数量很多，但大部分你打你的我打我的突出一个各打各的没有交互，一些boss真的堪比黄金树的粪怪，很多boss投技0帧起手无视距离，无前摇动作或者说很隐蔽，即使你集中注意力很多时候也躲不了。让boss战体验感进一步下降的问题是在第三回后开始存在大量boss频繁读指令（例如读到你蓄力完成打出劈棍一刻直接后跳）以及hitbox判定框反直觉（觉得能经常打到，由于受击框窄而打不到）。玩下来感觉制作组对boss战视觉效果比较注重，而玩家与boss战斗过程中的游戏体验却很少顾及。还是游戏中后期开始大量boss存在全屏或大范围的地板技能或者飞行道具，说白了就是机制检测，拥有这种机制的boss数量比远比同类游戏多，机制检测持续时间也比同类游戏久，而且游戏的视角锁定本来就有问题，这让玩家在过机制时候失误率大大提升，如果躲避失误一次，轻则半条命，重则从头再来（主要原因除了伤害高，还有挨打后硬直很久，很容易吃到boss的后续技能，同样的问题在远程小怪身上也存在，飞行道具打到你会硬直很久，如果他有同伴，那么接下来他同伴的飞行道具接踵而来，这时候只能罚站硬吃），一次失误可能就下一回了。然后说一下劈棍，中期开始的运动战中劈棍你不用隐身蓄力很容易空，越到后边越发现立棍和戳棍适用场景的数量遥遥领先劈棍，这样导致战斗手段又变得单调了一些。boss剩下的问题但不限于中后期人均霸体快慢刀，光污染场景和大招，锁定视角在乱飘（高机动性和大体积boss表现的尤为明显）；吐槽完上面两个战斗点最后说一下最为重量级的点，就是当属我们按键问题，按键是有延迟帧的。还有翻滚等操作没有预输入，进而让躲避时机变得随缘了起来，很多时候你不知道提前多少按，还有这按键判定是不是有问题？我接的ps5手柄，按幽魂技总是出不来原地罚站，最后就是手柄这法宝的按键布局战斗紧张的时候很容易误触，希望改一下。5.家园系统解锁时机：这一点很好改，先说问题吧，六六村这种类似传火祭祀场的功能性的场地是不是解锁的有点晚？并且有一部分玩家不舔图不看攻略可能都找不到，一些玩家得知有这样的地方时候已经第四、第五回了。然后是为啥说他解锁晚？很简单里面有一个铁匠，可以升级防具的品质，这个游戏用来给装备铸造、升级的高品质材料比较少，地图设计和某些隐藏的任务奖励不看攻略导致很难拿全材料，最主要的问题是中前期为了提升防御，或者看到了套装效果，并且一看这个防具品质很高就直接锻造了，这样就给人一种错觉，防具是随用随造，过了特定时间段就扔然后锻造下一件，但是像刚才提到的那样，这游戏是有给低阶防具升阶的系统，但是给的时间太晚，结果就是中期前很多玩家用一些稀有素材造了几件临时的过度装备来应付当下关卡的战斗场景，随着游玩的深入觉得自己输出、防御越发疲软，开始翻找攻略，就产生了组bulid的这个概念，这时遇到bulid中所需的防具材料不够，材料都消耗在锻造临时过度的装备了，试错成本有点高。给制作组一个建议，如果你们不想改变解锁家园系统的时机，可以给铁匠加一个分解防具的功能，钱不用返还，材料多少返还一些吧，这样让玩家起试错成本少一些，方便他们找到更适合自己的build。6.剧情体验：在不剧透情况下说一下，剧情非常迷的（稍微云了一下后面的剧情），发售前采访中说是遵循原著设定，真的是吗？尤其是这第四第五章，如果发售前没有一直强调原著的事，你改编成啥样即使我不喜欢也尊重你，但现在这处境只能说自找的，现在还有很多黑猴粉丝说真结局反转之类的，如果真像这一部分粉丝所说非得达成很多条件或者很苛刻的条件才能开启隐藏真结局，那有多少玩家会达成这些条件？你做出来前面这剧情不就恶心正常普通结局的玩家吗？这不纯纯设计问题？隐藏结局肯定可以有，但他的作用是拔高作品立意的，是站得住脚的，是用来锦上添花的，起码我是这么认为。以上是我作为玩家非常主观的评价，人和人的体验肯定是不一样的，人人都有发表自己看法的权利，可能有些人不认同我的观点，不同观点这很正常，我尊重你的观点，但不应该通过各种手段网暴从而堵嘴。最后我再说一点主观的看法，消费者花了真金白银买了游戏没有退款这难道不是对支持厂商吗？提出问题是为了让他变得更好，如果我真想让厂商死我就惯着他，时间久了自然病入膏肓，死的更透彻，所以为了他好建议就别当厂商孝子（那些拿钱办事的人除外），那真的小丑好吧，而且再伟大的作品他也有不喜欢的人不是吗？写的有些乱，都是想到哪写到哪，如果制作组以后通过更新解决掉这些问题会改好评。 | I94: 目前通关了，说真的除了第一回还可以，到了第二回的后半段就开始犯病，各种恶心设计交相辉映啊。先说这游戏优点吧，首先美术和画面很顶，其次塑造的文化氛围感很浓，游戏本身体量很大，一些boss设计的还可以，演出还可以，剩下开始吐槽缺点：1.堆怪：很多地方都是几个地面配一俩个甚至更多的远程敌人，这些远程敌人很多都是上不去的地形，这种情况下本身也没远程打击手段，只能跑路，如果附近有东西还不能停下来捡东西，仇恨导致拉火车，而且有时候会在一些狭小的地形安排这套配置，且后边一些小怪的血量和机动性提升的很明显，这种情况下只能隐身，什么？你说在之前舔图过程中已经和敌人消耗的蓝量见底了？那对不起，你只能开始“享受”制作组精心给你设计的惊喜啦。2.地图设计：本身就没有地图，还是弱引导（仅能从npc那获得只言片语），加上制作组没有设计此类游戏的经验，导致地图结构设计的也很糟糕，景色没有很明显区分，还有离谱的空气墙等等，从而导致各种迷路问题。3.土地庙放置问题：本来想放到上边地图编辑那一条，但这个问题很恶心所以单拎出来说，很多图两个庙之间距离很远（如果只是偶尔存在那么极个别的情况我也就不吐槽了，但事实相反存在很多这种情况），加上上面提到的两个问题他们混合在一起产生的这一坨东西真是给玩家的赛博“福报”，还有为什么要在快探索到下一座新庙的地方跟前放几个敌人，而且越到后边越严重，这游戏本来就存在着地图烂+堆怪的问题，有些想探索舔图且技术一般的玩家到达一个新的土地庙之前可能就没啥资源了，想赶紧恢复资源保存进度，这下到好成了葬身地了（上边提到了后边一些小怪血量和机动性都提升不少，没资源硬刚不了一点），而且在庙前挂了负反馈拉满，从上个庙复活以后又开始365里路长途奔袭……真的建议看一下其他做得好的竞品是咋设计的，建议学习一下。4.战斗体验：系统方面有一点像卧龙，战斗交互方面本作之前宣传的是非魂类游戏，但游戏有些怪打起来还是回合制（ps：这游戏为啥搞低精力槽+低法力槽绑定，你可以限定但是限定太多了，这也是导致有些怪很粪的原因之一。魂系这么设计是为了迎合系统，魂系动作相对来说简单，大部分战斗节奏偏慢，它主要玩的就是资源分配，我选择躲避、攻击、格挡要大概考虑一下剩下的血量、精力或者法力条消耗，这些是促成魂系列使用回合制打法合理的原因）。这游戏靠大多数时候要靠aaaa段子攒豆子，当定身用过进入cd时，而且已经消耗掉通过第一次aaaa积攒的豆子的情况下，就要进入boss回合了（有些boss定不了而且进p2会消减精力条上限，不带法宝难上天，说的就是你百眼！），到boss回合后，没豆子情况下你只能通过aaaa、喝药攒豆子或者找时机劈棍（立棍）蓄力，但一些疯狗boss连绵不绝的攻击让你蓄力机会很稀少，更多情况是普通轻攻击，但问题是普通轻攻击除了最后跳劈那一下有些boss会踉跄一下，剩下的打在他们身上真的不痛不痒，你本质上还是要靠消耗豆子的棍技去打血量或者踉跄以及积累倒地值，轻攻击第四段动作完成前取消不了反击，还有在你耍棍的途中大概率打不到最后一下跳劈，甚至可能因为有时候取消不了翻滚挨打，轻攻击前几段好像也无法积攒倒地值，而且单靠系统的话，攒豆和反制boss手段很单一，导致在你的视角里你和boss回合制，但在boss视角里一直是我的回合，还有就是打断boss出招的手段很多都得用攒的豆（蓄力也是攒豆子一种），所以很多玩家基本选择就是开局定身攒豆子或者进战斗前蓄力来一棍，定型文一样，当然也有别的套路比如禁字流之类的，但真正能用的流派与同行相比真不算多吧。其次这游戏反击也是有点问题，反击收益会不会太小了，头两次成功反击以后怪会踉跄但这时来不及补上后续伤害他就恢复了，这踉跄时间难道不可以长一点吗，让玩家稍微喝口药或者恢复一下精力，哪怕能普通aaaa连段打一套让自己资源变得有优势也行啊，现在来看除了做出来踉跄这个动画告诉你怪被你打踉跄了还有啥意义？这游戏反击多次命中积累倒地槽才能进入倒地硬直，虽然卧龙很多方面也是一坨，但它那个化解成功的爽度和收益绝对比黑猴强。黑猴动作模组数量一般，所以花活玩法偏少，游戏越到后面玩家方的手段越发固定越单调，加上上述所提到所有缺点杂糅在一起会让一些玩家产生疲劳的感觉，最后战斗系统总结就是门槛低，但深度一般；说到战斗体验了就顺便提一嘴boss战，游戏内boss数量很多，但大部分你打你的我打我的突出一个各打各的没有交互，一些boss真的堪比黄金树的粪怪，很多boss投技0帧起手无视距离，无前摇动作或者说很隐蔽，即使你集中注意力很多时候也躲不了。让boss战体验感进一步下降的问题是在第三回后开始存在大量boss频繁读指令（例如读到你蓄力完成打出劈棍一刻直接后跳）以及hitbox判定框反直觉（觉得能经常打到，由于受击框窄而打不到）。玩下来感觉制作组对boss战视觉效果比较注重，而玩家与boss战斗过程中的游戏体验却很少顾及。还是游戏中后期开始大量boss存在全屏或大范围的地板技能或者飞行道具，说白了就是机制检测，拥有这种机制的boss数量比远比同类游戏多，机制检测持续时间也比同类游戏久，而且游戏的视角锁定本来就有问题，这让玩家在过机制时候失误率大大提升，如果躲避失误一次，轻则半条命，重则从头再来（主要原因除了伤害高，还有挨打后硬直很久，很容易吃到boss的后续技能，同样的问题在远程小怪身上也存在，飞行道具打到你会硬直很久，如果他有同伴，那么接下来他同伴的飞行道具接踵而来，这时候只能罚站硬吃），一次失误可能就下一回了。然后说一下劈棍，中期开始的运动战中劈棍你不用隐身蓄力很容易空，越到后边越发现立棍和戳棍适用场景的数量遥遥领先劈棍，这样导致战斗手段又变得单调了一些。boss剩下的问题但不限于中后期人均霸体快慢刀，光污染场景和大招，锁定视角在乱飘（高机动性和大体积boss表现的尤为明显）；吐槽完上面两个战斗点最后说一下最为重量级的点，就是当属我们按键问题，按键是有延迟帧的。还有翻滚等操作没有预输入，进而让躲避时机变得随缘了起来，很多时候你不知道提前多少按，还有这按键判定是不是有问题？我接的ps5手柄，按幽魂技总是出不来原地罚站，最后就是手柄这法宝的按键布局战斗紧张的时候很容易误触，希望改一下。5.家园系统解锁时机：这一点很好改，先说问题吧，六六村这种类似传火祭祀场的功能性的场地是不是解锁的有点晚？并且有一部分玩家不舔图不看攻略可能都找不到，一些玩家得知有这样的地方时候已经第四、第五回了。然后是为啥说他解锁晚？很简单里面有一个铁匠，可以升级防具的品质，这个游戏用来给装备铸造、升级的高品质材料比较少，地图设计和某些隐藏的任务奖励不看攻略导致很难拿全材料，最主要的问题是中前期为了提升防御，或者看到了套装效果，并且一看这个防具品质很高就直接锻造了，这样就给人一种错觉，防具是随用随造，过了特定时间段就扔然后锻造下一件，但是像刚才提到的那样，这游戏是有给低阶防具升阶的系统，但是给的时间太晚，结果就是中期前很多玩家用一些稀有素材造了几件临时的过度装备来应付当下关卡的战斗场景，随着游玩的深入觉得自己输出、防御越发疲软，开始翻找攻略，就产生了组bulid的这个概念，这时遇到bulid中所需的防具材料不够，材料都消耗在锻造临时过度的装备了，试错成本有点高。给制作组一个建议，如果你们不想改变解锁家园系统的时机，可以给铁匠加一个分解防具的功能，钱不用返还，材料多少返还一些吧，这样让玩家起试错成本少一些，方便他们找到更适合自己的build。6.剧情体验：在不剧透情况下说一下，剧情非常迷的（稍微云了一下后面的剧情），发售前采访中说是遵循原著设定，真的是吗？尤其是这第四第五章，如果发售前没有一直强调原著的事，你改编成啥样即使我不喜欢也尊重你，但现在这处境只能说自找的，现在还有很多黑猴粉丝说真结局反转之类的，如果真像这一部分粉丝所说非得达成很多条件或者很苛刻的条件才能开启隐藏真结局，那有多少玩家会达成这些条件？你做出来前面这剧情不就恶心正常普通结局的玩家吗？这不纯纯设计问题？隐藏结局肯定可以有，但他的作用是拔高作品立意的，是站得住脚的，是用来锦上添花的，起码我是这么认为。以上是我作为玩家非常主观的评价，人和人的体验肯定是不一样的，人人都有发表自己看法的权利，可能有些人不认同我的观点，不同观点这很正常，我尊重你的观点，但不应该通过各种手段网暴从而堵嘴。最后我再说一点主观的看法，消费者花了真金白银买了游戏没有退款这难道不是对支持厂商吗？提出问题是为了让他变得更好，如果我真想让厂商死我就惯着他，时间久了自然病入膏肓，死的更透彻，所以为了他好建议就别当厂商孝子（那些拿钱办事的人除外），那真的小丑好吧，而且再伟大的作品他也有不喜欢的人不是吗？写的有些乱，都是想到哪写到哪，如果制作组以后通过更新解决掉这些问题会改好评。 | J94: =IF(SUM(R94:T94)>0,1,0) -> 1 | K94: =IF(SUM(U94:Y94)>0,1,0) -> 1 | L94: =IF(SUM(Z94:AC94)>0,1,0) -> 1 | M94: =IF(SUM(AD94:AF94)>0,1,0) -> 1 | N94: =IF(SUM(AG94:AH94)>0,1,0) -> 1 | O94: =IF(SUM(AI94:AL94)>0,1,0) -> 1 | P94: =IF(SUM(AM94:AQ94)>0,1,0) -> 1 | Q94: =IF(AR94>0,1,0) -> 0 | R94: 1 | S94: 0 | T94: 1 | U94: 1 | V94: 1 | W94: 1 | X94: 1 | Y94: 1 | Z94: 1 | AA94: 1 | AB94: 1 | AC94: 1 | AD94: 1 | AE94: 0 | AF94: 1 | AG94: 1 | AH94: 1 | AI94: 0 | AJ94: 0 | AK94: 1 | AL94: 1 | AM94: 0 | AN94: 0 | AO94: 0 | AP94: 1 | AQ94: 1 | AR94: 0 | AS94: =SUM(J94:Q94) -> 7 | AT94: =SUM(R94:AR94) -> 19 | AU94: 画面美术场景；演出角色怪物设计；动作打击手感；Boss战斗节奏；难度挑战；锁定视角；判定反馈；地图路线；空气墙可达性；探索隐藏支线；引导迷路单线；优化帧率；Bug兼容硬件；整体完成度；推荐价值判断；本国媒介路径；中国文化宗教语言审美；外部资料依赖；角色期待意义偏移 | AV94: =IF(AT94>0,1,0) -> 1 | AW94: =IF(AT94=0,1,0) -> 0 | AX94: =IF(AT94>=8,1,0) -> 1 | AY94: 36.5 | AZ94: 正面 | BA94: P | BB94: 原文
A95: CN-P-094 | B95: 中文 | C95: 推荐 | D95: 355 | E95: 12 | F95: 68.8 | G95: 2024-08-22 | H95: 以为会凭着国产吃情怀，但实际玩下来只能说amazing great game 可玩性实在太高了 机制十分新颖 无论是跑图还是BOSS的场景都是史诗级的 每一丝一线都能够看出制作的良心用苦 简直细节狂魔好吧 ！并且正因为没有地图的缘故 使得游戏可以隐藏巨多东西 也都影响着诸多史诗级剧情的分支发展 非常好玩 非常有趣 都来玩！ 玩！ 玩！ 玩！ | I95: 以为会凭着国产吃情怀，但实际玩下来只能说amazing great game 可玩性实在太高了 机制十分新颖 无论是跑图还是BOSS的场景都是史诗级的 每一丝一线都能够看出制作的良心用苦 简直细节狂魔好吧 ！并且正因为没有地图的缘故 使得游戏可以隐藏巨多东西 也都影响着诸多史诗级剧情的分支发展 非常好玩 非常有趣 都来玩！ 玩！ 玩！ 玩！ | J95: =IF(SUM(R95:T95)>0,1,0) -> 1 | K95: =IF(SUM(U95:Y95)>0,1,0) -> 1 | L95: =IF(SUM(Z95:AC95)>0,1,0) -> 1 | M95: =IF(SUM(AD95:AF95)>0,1,0) -> 0 | N95: =IF(SUM(AG95:AH95)>0,1,0) -> 1 | O95: =IF(SUM(AI95:AL95)>0,1,0) -> 1 | P95: =IF(SUM(AM95:AQ95)>0,1,0) -> 1 | Q95: =IF(AR95>0,1,0) -> 1 | R95: 1 | S95: 0 | T95: 0 | U95: 0 | V95: 1 | W95: 0 | X95: 0 | Y95: 0 | Z95: 1 | AA95: 0 | AB95: 1 | AC95: 0 | AD95: 0 | AE95: 0 | AF95: 0 | AG95: 0 | AH95: 1 | AI95: 0 | AJ95: 1 | AK95: 0 | AL95: 0 | AM95: 0 | AN95: 0 | AO95: 0 | AP95: 0 | AQ95: 1 | AR95: 1 | AS95: =SUM(J95:Q95) -> 7 | AT95: =SUM(R95:AR95) -> 8 | AU95: 画面美术场景；Boss战斗节奏；地图路线；探索隐藏支线；推荐价值判断；童年记忆情怀；角色期待意义偏移；国产3A身份期待 | AV95: =IF(AT95>0,1,0) -> 1 | AW95: =IF(AT95=0,1,0) -> 0 | AX95: =IF(AT95>=8,1,0) -> 1 | AY95: 4.5 | AZ95: 正面 | BA95: P | BB95: 原文
A96: CN-P-095 | B96: 中文 | C96: 不推荐 | D96: 258 | E96: 12 | F96: 7.3 | G96: 2024-08-22 | H96: 奔着中国人自己的第一款3a拿下的预购豪华版，没想到四年磨一剑磨了这么个玩意。先说优点，美术 音乐 文案全是一等一水平，每一条单拿出来都可以获奖的那种，大到妖王小到小怪，每只怪物都有自己的神话风立绘 故事介绍和高质量配音，就连背包里的采集物 装备材料 饰品都有介绍，并且保质保量，文案编辑的文学造诣一定相当高。美术方面独树一帜，西游之后的破败景象，重走西游路，重看西游人，颇有韵味。其次就是战斗动作设计，很难想象一款以猴类角色为主角的游戏能把动作做得这么帅，又帅又干练，各种招式和技能虽然不花哨，但创意无限，三种棍法各有其可圈可点之处，值得称赞最后就是原著还原了，第一章一上手就感觉西游回来了，那股神怪又庄严的感觉，文案美术和音乐全部紧扣原著，就连各种神通都有还原，不过听说游戏后面改编也不少，所以这方面见仁见智了现在来谈谈这款游戏的缺点，首先就是游戏内没有内置活点地图，我想知道我现在在哪里，不行，只能去存档点查看自己当前的大致方位，并且这个方位非常大致，你旁边有什么建筑物有什么东西还是不知道，并且基本没有引导，我下一步该去做什么不知道，这种迷茫感与没有地图一结合，就诞生出了一款玩家走着走着迷路好不容易找到路发现自己缺少钥匙打不开门只能回去继续迷路的游戏，就是退一步来讲，没有地图和引导是为了鼓励玩家自由探索，那么好，你这个傻逼空气墙是要干什么，看着能过去的地方我给你拦着，看着明显就过不去的地方放几个隐藏关卡，很幽默是吗，一面要开放探索，一面又要线性通关，知道的是在做3A，不知道的还以为哪家根本不懂游戏的公司做出来卖情怀圈钱的然后就是这游戏的战斗系统，作为一款动作游戏，你不集中一个点做好做出特色而是老想着缝那几个大牌动作游戏干什么？想研究搓招你就学鬼泣搞得花一点，想上难度你就学黑魂只狼，几个游戏缝来缝去缝出一个四不像，打怪爽感也不够压迫也不够，攻击大前摇大后摇，唯一值得称道的就是你那BOSS战氛围还算好最后要谈谈这游戏的玩家群体，游戏有问题不让说？天天像个傻逼一样维护你的厂商跌，抛开国产滤镜这黑神话最多拿75分，还有一群傻逼在那狗叫，什么第一次做没经验，什么你不喜欢可以不玩。你没做过游戏还没玩过游戏？我国作为游戏copy大国平时猛猛抄到了为国争光的时候又要自己乱搞创新？最后，我付了钱并请了一天假来玩，我有权利提出意见，这个质量完全可以继续优化打磨，把引导系统做的更好，把地图加进来，别成为中国人自己的赛博朋克2077修改至2024年8月22日12：43 留言每条都认真查看并思考过，有正常人也有猴孝子，有理智者也有无脑骂，恶意留言不会改变这游戏是三流作品的事实，只会使你那可悲的极端民族主义和开除国籍的行为持续膨胀，直至压过你的大脑和理性 | I96: 奔着中国人自己的第一款3a拿下的预购豪华版，没想到四年磨一剑磨了这么个玩意。先说优点，美术 音乐 文案全是一等一水平，每一条单拿出来都可以获奖的那种，大到妖王小到小怪，每只怪物都有自己的神话风立绘 故事介绍和高质量配音，就连背包里的采集物 装备材料 饰品都有介绍，并且保质保量，文案编辑的文学造诣一定相当高。美术方面独树一帜，西游之后的破败景象，重走西游路，重看西游人，颇有韵味。其次就是战斗动作设计，很难想象一款以猴类角色为主角的游戏能把动作做得这么帅，又帅又干练，各种招式和技能虽然不花哨，但创意无限，三种棍法各有其可圈可点之处，值得称赞最后就是原著还原了，第一章一上手就感觉西游回来了，那股神怪又庄严的感觉，文案美术和音乐全部紧扣原著，就连各种神通都有还原，不过听说游戏后面改编也不少，所以这方面见仁见智了现在来谈谈这款游戏的缺点，首先就是游戏内没有内置活点地图，我想知道我现在在哪里，不行，只能去存档点查看自己当前的大致方位，并且这个方位非常大致，你旁边有什么建筑物有什么东西还是不知道，并且基本没有引导，我下一步该去做什么不知道，这种迷茫感与没有地图一结合，就诞生出了一款玩家走着走着迷路好不容易找到路发现自己缺少钥匙打不开门只能回去继续迷路的游戏，就是退一步来讲，没有地图和引导是为了鼓励玩家自由探索，那么好，你这个傻逼空气墙是要干什么，看着能过去的地方我给你拦着，看着明显就过不去的地方放几个隐藏关卡，很幽默是吗，一面要开放探索，一面又要线性通关，知道的是在做3A，不知道的还以为哪家根本不懂游戏的公司做出来卖情怀圈钱的然后就是这游戏的战斗系统，作为一款动作游戏，你不集中一个点做好做出特色而是老想着缝那几个大牌动作游戏干什么？想研究搓招你就学鬼泣搞得花一点，想上难度你就学黑魂只狼，几个游戏缝来缝去缝出一个四不像，打怪爽感也不够压迫也不够，攻击大前摇大后摇，唯一值得称道的就是你那BOSS战氛围还算好最后要谈谈这游戏的玩家群体，游戏有问题不让说？天天像个傻逼一样维护你的厂商跌，抛开国产滤镜这黑神话最多拿75分，还有一群傻逼在那狗叫，什么第一次做没经验，什么你不喜欢可以不玩。你没做过游戏还没玩过游戏？我国作为游戏copy大国平时猛猛抄到了为国争光的时候又要自己乱搞创新？最后，我付了钱并请了一天假来玩，我有权利提出意见，这个质量完全可以继续优化打磨，把引导系统做的更好，把地图加进来，别成为中国人自己的赛博朋克2077修改至2024年8月22日12：43 留言每条都认真查看并思考过，有正常人也有猴孝子，有理智者也有无脑骂，恶意留言不会改变这游戏是三流作品的事实，只会使你那可悲的极端民族主义和开除国籍的行为持续膨胀，直至压过你的大脑和理性 | J96: =IF(SUM(R96:T96)>0,1,0) -> 1 | K96: =IF(SUM(U96:Y96)>0,1,0) -> 1 | L96: =IF(SUM(Z96:AC96)>0,1,0) -> 1 | M96: =IF(SUM(AD96:AF96)>0,1,0) -> 1 | N96: =IF(SUM(AG96:AH96)>0,1,0) -> 1 | O96: =IF(SUM(AI96:AL96)>0,1,0) -> 1 | P96: =IF(SUM(AM96:AQ96)>0,1,0) -> 1 | Q96: =IF(AR96>0,1,0) -> 1 | R96: 1 | S96: 1 | T96: 0 | U96: 1 | V96: 1 | W96: 1 | X96: 0 | Y96: 0 | Z96: 1 | AA96: 1 | AB96: 1 | AC96: 1 | AD96: 1 | AE96: 0 | AF96: 0 | AG96: 1 | AH96: 1 | AI96: 1 | AJ96: 1 | AK96: 0 | AL96: 1 | AM96: 0 | AN96: 0 | AO96: 0 | AP96: 0 | AQ96: 1 | AR96: 1 | AS96: =SUM(J96:Q96) -> 8 | AT96: =SUM(R96:AR96) -> 17 | AU96: 画面美术场景；音乐音效配音；动作打击手感；Boss战斗节奏；难度挑战；地图路线；空气墙可达性；探索隐藏支线；引导迷路单线；优化帧率；整体完成度；推荐价值判断；西游悟空符号；童年记忆情怀；中国文化宗教语言审美；角色期待意义偏移；国产3A身份期待 | AV96: =IF(AT96>0,1,0) -> 1 | AW96: =IF(AT96=0,1,0) -> 0 | AX96: =IF(AT96>=8,1,0) -> 1 | AY96: 15 | AZ96: 正面 | BA96: P | BB96: 原文
A97: CN-P-096 | B97: 中文 | C97: 不推荐 | D97: 211 | E97: 8 | F97: 12.5 | G97: 2024-08-22 | H97: 1.黑神话的现象级大热是中国游戏史上最重要的里程碑之一，它代表中国已经具备比肩国际一线水准的，供游戏制作的资源。社会主义初级阶段的中国是社资混淆的中国，在自由市场的环境中，黑神话的现象级爆火大热无疑已经给自营资本清晰测出了单机游戏的市场潜力。所以黑神话是一部非常重要的作品，它的成功预示着中国单机游戏产业正式踏入国际竞争行列，同时它的成功又不完全来源于游戏科学一家制作公司的努力，而更多来自10余年来中国游戏制作环境的进步与社会环境（对游戏看法）的改变。2.“天地不仁以万物为刍狗”的意思是，自然界没有好恶倾向，因此对人对狗对万物都一视同仁，人与狗平等，万物不分高低尊卑贵贱，而非游戏中蜘蛛精师兄所取的隐喻等级之意。这算是个经典谬误了，所以大概提一下。3.反传统、反主流的目的是批判旧的不合理的东西，不是因为成王败寇今天好运没轮到我所以鼓吹“我命由我不由天”。石猴大闹天宫是出于对天庭蔑视自己，自我价值被他人否定，潜能被浪费，不被人尊重的愤慨，这与黑神话中佛道相争，天界动荡于是三界四洲不得安生的封建史观是南辕北辙的两码事。历史是由多数人书写的，不是极少数的几个英雄/精英，推动时代改变的也是历史的趋势，而非英雄/精英史观下一神几人的四两拨千斤。人有欲，有贪嗔痴，欲望是驱使人行为的源动力，是人的自由意志，是“因为无聊，所以想要做点啥”的具体表现，所以欲望本是中性的，可为什么人又会有贪嗔痴呢？如果人性是恶的，人性中就没有善的部分了吗？人本来只是在特定方面才有所长的高级动物，是社会塑造了人，人性就是社会性，是社会关系的集合共同塑造了人性。无论是金池长老的贪、黄眉与金蝉子的赌注，又或是沟槽的玉帝嫦娥偷情这种宫廷史观的市侩野史；只摒弃后西游时代能让妖魔当道的社会黑暗现实，不批判造就如此后西游时代黑暗现实的社会结构、社会制度，反把一切过错全部简单归因到“人性”这个虚无缥缈的概念上，就是黑神话这部作品对严肃议题的敷衍与谬论了。人为什么革命？因为分赃不均；为什么朝不保夕？因为人性使然。解构解构，抓不住后现代稀释权威性还权利于大众的精髓，只学了个资本主义下消费重点元素进行扁平矮化娱乐化的臭皮囊。封建时代的农民起义大呼王侯将相宁有种乎，是对自身不平等待遇的愤慨，上个世纪政治领袖感慨王侯将相宁有种乎，是对封建制度吃人现实的反思与批判，而今天黑神话质疑天、反对天、与天斗的主旨，却又绕了个大弯重新回到封建时代屠龙因为自己不是龙的陈词老调上来。只有干翻天庭才能安生，拳头大的才配说话，三界四洲到处是家破人亡的零和博弈。起义因为自己不是当权者，革命因为自己不是既得利益者。革命的正义性被消解，现实的不合理被接纳，达官显赫里也有好人，穷苦贫民窟里钻出来的多是人心不古的贱民，一切问题回答到最后又重复落入老生常谈且低能的人性论，这样的糟粕就是从二十年前就已经盛产的文化遗毒了。戏说不是胡说，改编不是乱编。中美合拍说的这句话理是不糙的，可人是糙的，因为中美合拍将自己与孙悟空的形象绑定，垄断了形象，所以任何对孙悟空形象的“二次创作”，无论好坏其实都在把观众心中孙悟空形象与中美合拍解绑，这是砸人饭碗了，于是有了他 “~戏说~胡说~” 的名言。这个事例也同时说明，影响力本身是中性的，而具备影响力事物的好坏，也同时可能在其触及领域造成长久的好或坏的潜在影响。人糙理不糙，如果就事论事，中美合拍说的 “孙悟空到底谈了几个妖精女朋友” 这样的市侩庸俗描述确实是对《西游记》这样一部集合了元明两代百姓创作智慧结晶的庸俗矮化。当把“无关好坏，只有立场”这种折中主义+功利主义的论调拿来当成理论中心，故事中正义性的确立、好坏的区分也不再是必要的了，反正站在我这边的就是好的，挡我路的都是坏的，对具体事物的批判自然也名存实亡，剩下的就只有 “你到底站哪边” 如此的二极世界。标新立异真不是这么标的。民族的就是世界的，对外文化输出如果是输出的糟粕，那该改个名叫文化入侵、文化污染。黑神话的黑如果只是黑深残的黑，是厚黑学的黑，是对“存在即合理”，客观现实造就的具体情况的唯心主义反对+批判，说实话这样的黑神话也真不是我等了4年的中国式3A单机了。4.我自己个人是一直这么看：一部作品受限于创作时代、作者身平，必定会有相当的局限性。而作为未来的作者（对比作品创作年代），职责的其中之一就是突破过往的限制，在原有的基础上突破局限性给出新时代视角的答案。所以客观来说，一部作品在未来的改编，必定是受到所在未来的时代（环境）因素所制约的，但同时突破这两层制约与限制（原作品的时代局限，当下的时代局限）又正是改编作者的重要历史担当。革命的重点从来都有两个，一个是暴力的革命，一个是暴力革命后第二天的从新建设。可惜全世界的文艺作品从来大都只突出第一个问题而忽视第二个问题。黑神话开了个头，无论好坏与否这个头是及其重要且必要的，至于下一章如何，只有未来才能见真章了。 | I97: 1.黑神话的现象级大热是中国游戏史上最重要的里程碑之一，它代表中国已经具备比肩国际一线水准的，供游戏制作的资源。社会主义初级阶段的中国是社资混淆的中国，在自由市场的环境中，黑神话的现象级爆火大热无疑已经给自营资本清晰测出了单机游戏的市场潜力。所以黑神话是一部非常重要的作品，它的成功预示着中国单机游戏产业正式踏入国际竞争行列，同时它的成功又不完全来源于游戏科学一家制作公司的努力，而更多来自10余年来中国游戏制作环境的进步与社会环境（对游戏看法）的改变。2.“天地不仁以万物为刍狗”的意思是，自然界没有好恶倾向，因此对人对狗对万物都一视同仁，人与狗平等，万物不分高低尊卑贵贱，而非游戏中蜘蛛精师兄所取的隐喻等级之意。这算是个经典谬误了，所以大概提一下。3.反传统、反主流的目的是批判旧的不合理的东西，不是因为成王败寇今天好运没轮到我所以鼓吹“我命由我不由天”。石猴大闹天宫是出于对天庭蔑视自己，自我价值被他人否定，潜能被浪费，不被人尊重的愤慨，这与黑神话中佛道相争，天界动荡于是三界四洲不得安生的封建史观是南辕北辙的两码事。历史是由多数人书写的，不是极少数的几个英雄/精英，推动时代改变的也是历史的趋势，而非英雄/精英史观下一神几人的四两拨千斤。人有欲，有贪嗔痴，欲望是驱使人行为的源动力，是人的自由意志，是“因为无聊，所以想要做点啥”的具体表现，所以欲望本是中性的，可为什么人又会有贪嗔痴呢？如果人性是恶的，人性中就没有善的部分了吗？人本来只是在特定方面才有所长的高级动物，是社会塑造了人，人性就是社会性，是社会关系的集合共同塑造了人性。无论是金池长老的贪、黄眉与金蝉子的赌注，又或是沟槽的玉帝嫦娥偷情这种宫廷史观的市侩野史；只摒弃后西游时代能让妖魔当道的社会黑暗现实，不批判造就如此后西游时代黑暗现实的社会结构、社会制度，反把一切过错全部简单归因到“人性”这个虚无缥缈的概念上，就是黑神话这部作品对严肃议题的敷衍与谬论了。人为什么革命？因为分赃不均；为什么朝不保夕？因为人性使然。解构解构，抓不住后现代稀释权威性还权利于大众的精髓，只学了个资本主义下消费重点元素进行扁平矮化娱乐化的臭皮囊。封建时代的农民起义大呼王侯将相宁有种乎，是对自身不平等待遇的愤慨，上个世纪政治领袖感慨王侯将相宁有种乎，是对封建制度吃人现实的反思与批判，而今天黑神话质疑天、反对天、与天斗的主旨，却又绕了个大弯重新回到封建时代屠龙因为自己不是龙的陈词老调上来。只有干翻天庭才能安生，拳头大的才配说话，三界四洲到处是家破人亡的零和博弈。起义因为自己不是当权者，革命因为自己不是既得利益者。革命的正义性被消解，现实的不合理被接纳，达官显赫里也有好人，穷苦贫民窟里钻出来的多是人心不古的贱民，一切问题回答到最后又重复落入老生常谈且低能的人性论，这样的糟粕就是从二十年前就已经盛产的文化遗毒了。戏说不是胡说，改编不是乱编。中美合拍说的这句话理是不糙的，可人是糙的，因为中美合拍将自己与孙悟空的形象绑定，垄断了形象，所以任何对孙悟空形象的“二次创作”，无论好坏其实都在把观众心中孙悟空形象与中美合拍解绑，这是砸人饭碗了，于是有了他 “~戏说~胡说~” 的名言。这个事例也同时说明，影响力本身是中性的，而具备影响力事物的好坏，也同时可能在其触及领域造成长久的好或坏的潜在影响。人糙理不糙，如果就事论事，中美合拍说的 “孙悟空到底谈了几个妖精女朋友” 这样的市侩庸俗描述确实是对《西游记》这样一部集合了元明两代百姓创作智慧结晶的庸俗矮化。当把“无关好坏，只有立场”这种折中主义+功利主义的论调拿来当成理论中心，故事中正义性的确立、好坏的区分也不再是必要的了，反正站在我这边的就是好的，挡我路的都是坏的，对具体事物的批判自然也名存实亡，剩下的就只有 “你到底站哪边” 如此的二极世界。标新立异真不是这么标的。民族的就是世界的，对外文化输出如果是输出的糟粕，那该改个名叫文化入侵、文化污染。黑神话的黑如果只是黑深残的黑，是厚黑学的黑，是对“存在即合理”，客观现实造就的具体情况的唯心主义反对+批判，说实话这样的黑神话也真不是我等了4年的中国式3A单机了。4.我自己个人是一直这么看：一部作品受限于创作时代、作者身平，必定会有相当的局限性。而作为未来的作者（对比作品创作年代），职责的其中之一就是突破过往的限制，在原有的基础上突破局限性给出新时代视角的答案。所以客观来说，一部作品在未来的改编，必定是受到所在未来的时代（环境）因素所制约的，但同时突破这两层制约与限制（原作品的时代局限，当下的时代局限）又正是改编作者的重要历史担当。革命的重点从来都有两个，一个是暴力的革命，一个是暴力革命后第二天的从新建设。可惜全世界的文艺作品从来大都只突出第一个问题而忽视第二个问题。黑神话开了个头，无论好坏与否这个头是及其重要且必要的，至于下一章如何，只有未来才能见真章了。 | J97: =IF(SUM(R97:T97)>0,1,0) -> 1 | K97: =IF(SUM(U97:Y97)>0,1,0) -> 1 | L97: =IF(SUM(Z97:AC97)>0,1,0) -> 0 | M97: =IF(SUM(AD97:AF97)>0,1,0) -> 0 | N97: =IF(SUM(AG97:AH97)>0,1,0) -> 1 | O97: =IF(SUM(AI97:AL97)>0,1,0) -> 1 | P97: =IF(SUM(AM97:AQ97)>0,1,0) -> 1 | Q97: =IF(AR97>0,1,0) -> 1 | R97: 1 | S97: 0 | T97: 0 | U97: 0 | V97: 0 | W97: 1 | X97: 1 | Y97: 0 | Z97: 0 | AA97: 0 | AB97: 0 | AC97: 0 | AD97: 0 | AE97: 0 | AF97: 0 | AG97: 1 | AH97: 1 | AI97: 1 | AJ97: 0 | AK97: 0 | AL97: 1 | AM97: 0 | AN97: 0 | AO97: 0 | AP97: 0 | AQ97: 1 | AR97: 1 | AS97: =SUM(J97:Q97) -> 6 | AT97: =SUM(R97:AR97) -> 9 | AU97: 画面美术场景；难度挑战；锁定视角；整体完成度；推荐价值判断；西游悟空符号；中国文化宗教语言审美；角色期待意义偏移；国产3A身份期待 | AV97: =IF(AT97>0,1,0) -> 1 | AW97: =IF(AT97=0,1,0) -> 0 | AX97: =IF(AT97>=8,1,0) -> 1 | AY97: 21 | AZ97: 正面 | BA97: P | BB97: 原文
A98: CN-P-097 | B98: 中文 | C98: 推荐 | D98: 76 | E98: 3 | F98: 59.4 | G98: 2024-08-22 | H98: 非常棒的画面和游戏剧情，流畅的操作感，值得购买！ | I98: 非常棒的画面和游戏剧情，流畅的操作感，值得购买！ | J98: =IF(SUM(R98:T98)>0,1,0) -> 1 | K98: =IF(SUM(U98:Y98)>0,1,0) -> 1 | L98: =IF(SUM(Z98:AC98)>0,1,0) -> 0 | M98: =IF(SUM(AD98:AF98)>0,1,0) -> 1 | N98: =IF(SUM(AG98:AH98)>0,1,0) -> 1 | O98: =IF(SUM(AI98:AL98)>0,1,0) -> 0 | P98: =IF(SUM(AM98:AQ98)>0,1,0) -> 0 | Q98: =IF(AR98>0,1,0) -> 0 | R98: 1 | S98: 0 | T98: 0 | U98: 1 | V98: 0 | W98: 0 | X98: 0 | Y98: 0 | Z98: 0 | AA98: 0 | AB98: 0 | AC98: 0 | AD98: 1 | AE98: 0 | AF98: 0 | AG98: 0 | AH98: 1 | AI98: 0 | AJ98: 0 | AK98: 0 | AL98: 0 | AM98: 0 | AN98: 0 | AO98: 0 | AP98: 0 | AQ98: 0 | AR98: 0 | AS98: =SUM(J98:Q98) -> 4 | AT98: =SUM(R98:AR98) -> 4 | AU98: 画面美术场景；动作打击手感；优化帧率；推荐价值判断 | AV98: =IF(AT98>0,1,0) -> 1 | AW98: =IF(AT98=0,1,0) -> 0 | AX98: =IF(AT98>=8,1,0) -> 0 | AY98: 5.5 | AZ98: 正面 | BA98: P | BB98: 原文
A99: CN-P-098 | B99: 中文 | C99: 推荐 | D99: 72 | E99: 1 | F99: 198.1 | G99: 2024-08-22 | H99: 一句话评测：大圣已死六根散，天命轮回西行人。眼耳口鼻心意念，妖魔能否成仙佛？ 原以为我是大圣归来，实际上我是马喽菜鸡。 别人打我如赶小鸡，我打别人似推憨牛。 麻蛋，究竟谁是天命人呀！我看你们才是！ 欢迎关注网易UU鉴赏家培养计划 关注UU加速器VX公众号，回复“steam”，获得专属玩家群邀请。 里面的怪物形态各异，女妖精那更是个顶个的可爱。 这游戏的妖更像是妖，仙更像是仙，就是人都不是人了，全都成了尸骸了。 整体来说，作为一款国内3A大作来说，前两天媒体吹得太过了，优势劣势都很明显。 先说优势：很明显，钻入骨髓的西游故事游戏化的展现，视觉冲击，动作打斗，环境塑造与妖魔理念，甜不甜那都是家乡水，什么叫基因唤醒，《黑神话》算是在游戏界里的基因唤醒器。 它的理念、故事与音乐绝对值得你一玩，尤其是那种常年沉浸在国外游戏大作的玩家来说，你不差钱，又见多识广下，你更能体会到什么叫做基因唤醒，你一拿上手就知道，只有中国人能做出这样的游戏，外国人绝对不懂，这不是技术原因，这是文化根基。 再说劣势：关卡设计与地图展现，是他宝贝的一塌糊涂。 一共六张地图，你会发现所有的地图都展现出来了，人神共愤的大范围的同色彩沿用，无与伦比的超大范围的又遮蔽性质的物质出现，比如雪天，比如黄沙，比如地穴的黑暗。 虽然游戏作为关卡制，但地图极大，在缺失地标元素，没有全景大地图，甚至无法做地图自主标记的前提下，迷路加迷路加迷路的爆炸心态直接让22°的空调都无法降温了。 在我看来，黑神话也正是国内游戏的短板问题： 美术OK 剧情OK 角色OK 但场景设计不OK 关卡设计不OK 尤其是在大地图的情况下，如何对场景进行有效的识别，关卡的设计让人玩起来在紧张与轻松里互相交替，不至于过于劳累，绝对需要沉淀的技术工种，有些可以拿钱砸，有些真的是拿钱砸也砸不出来，就是需要项目与时间来培养。 这些人对游戏而言，是绝对的大宝贝，培养出来一个，都是中国游戏界的集体贡献。 把整体态势说完后，我们说细节的内容 战前的大圣，战后的马猴 战斗采取一个棍子打天下的方式，充分发挥只要长处够长，就能填补短处的方式。 我见到怪，那就是捅捅捅捅捅捅，左捅捅，右捅捅，上捅捅，下捅捅。 正好棍子分为了三个不同的姿态，每一次都是上下左右四面捅，三个姿态可以无缝切换，根据怪物的出招方式来进行瞬间地改变，从而打出对应的硬质。 这游戏的重击绝对是伤害的主要手段，合理利用绝对会让你顺利清怪。 除了棍子外，第二个攻击的手段就是法术，法术的方式包含了： 定、分身、隐身以及钢筋铁骨甚至更多。 法术的CD还是挺长的，一场BOSS战大概一个法术能用2次，最多装备3个法术，也就是说，我们有机会使用6次法术。 而第三个输出手段就是黑猴里最有趣的变身了，你可以收起其他精英怪物的武器，然后化身成为他们的样子，进行变身攻击。 变身后，战斗招式与血条与本体独立，也就是说，等于你操作了完全不同的一个角色，绝对是十分的亮点！ 血染的西游，永远的大圣 很多的时候，大圣的含义代表了一种不屈服，对强敌的不屈服，对强权的不屈服，也是对自己的不屈服。 《黑神话》虽然里面带了一个黑字，故事里对神佛也确实有点黑的意思，但是整体的构造依旧保持着，绝对的不驯服，如果强权要让你屈服，要让你低头，我们一定会抬起头颅，用命抵抗。 整个故事的主旨同样也是再次，大圣虽然在开头就已经告诉我们死去了，天命人的目的是复活大圣，但是天命人在寻找回大圣的遗物的过程里，也让自己逐渐地靠近大圣，靠近理想中的那一个至高的存在。 而里面的BOSS怪物或者神仙都有自己的目的，这些目的有些太过腌臜，有些则隐晦不堪。 黑神话的时间线虽然是西游后的故事，但是其实在我看来理念并不只致敬西游，而是构建出来了自己的一套叙事逻辑，大家可以自己看。 但是对西游的致敬就很明显了，明显到了，甚至是直接文本的复刻，连标点符号都不会改变的那种。 如果你熟悉西游原作，绝对在游戏里能够看到太多的致敬了。 这个游戏里有众多的剧情分支与隐藏的角色，需要你在关键的时刻进行存档，而游戏内的存档并不多，如果你把自己的存档多样化的保存的话，可以使用UU云存档，给你的存档上个保险。 游戏虽然精彩，可别让游戏外的事情扫了兴！ 无论是换电脑玩时存档误覆盖，还是各种问题导致存档损坏。相信这样惨痛的经历依然时常发生，但这次决不能。所以，使用「UU云存档」，来为你的存档上个保险吧！ 使用起来简单方便，打开UU，一键开启就能用 全程自动保存，无需手动操作，不干扰你的游戏体验 不影响原平台正常存储档，UU与平台云存档同步运行 一键备份存档，一键锁定存档，重要的档要保存好 不用会员，好用免费 雕塑的佛像，至臻的瑰宝 黑神话里的雕像，真的是采用了众多的显示里的佛像古迹。 对众多的玩家而言，与其说享受制作组的在现实基础上构建的美术，我们历史上众多的精美遗产其实还没有电子化的展现。 对制作组而言，冥思苦想的美术基调，很有可能走歪，在现实的基础上，重新加工与润泽历史瑰宝绝对值得一试。 更何况西游的本质是是佛道儒三家的一个融合的作品，里面不论是出现佛家元素，道家元素还是儒家元素都完全的搭配至极呀。 我认为制作组在美术这一方面的发挥，真的是取长补短，弘扬历史，再现瑰宝与互相融合了。 说句玩笑话，单纯你就是欣赏里面的雕像与景色也能够让你回本了。 最后祝愿 通关了，我可以说，这个游戏的剧情没有讲完，游戏科学还有第二部，说不定是三部曲。 如果真是这样，很有可能黑神话会是一个延续十年左右的长期IP。 但从这几天的售卖信息来看，游戏科学应该是回本了。 我不求别的，只希望，这个游戏的出现，能让国内出现更多的优秀作品，更多才华横溢的制作组，更多让玩家们喜欢的游戏。 伴随着国内的经济快速发展与国际地位的提升，我相信接下来的几年会是中国各个方面巨大膨胀的时代。 黑神话看似是一不留神走到了风口，看似走上了政府支持的一个快车道。 任何的历史机遇都是可遇不可求的，黑神话遇到了这个机遇，也是我们国内的所有单机游戏爱好者的一个基于。 我们用着自己的金钱，向所有的国内制作组发出最高的呐喊，你们不需要怕好游戏做出来没人买。 国内的用户群体早已能够支撑的气一个3A游戏的内部循环了，而这一次的黑神话的成功，自然是个再明白不过的例子。 游戏不再是洪水猛兽，游戏是如今电子化的历史潮流里，根本无法避开的东西，扫码点餐、网上购物，早已成为了我们经济消费里的一环。 电子游戏，也一定会成为我们精神娱乐的一环。 最后祝，中国的单机游戏，再次一的崛起成功！ 接下来的三四年是一个机遇，希望更多的制作组大步尝试！ | I99: 一句话评测：大圣已死六根散，天命轮回西行人。眼耳口鼻心意念，妖魔能否成仙佛？ 原以为我是大圣归来，实际上我是马喽菜鸡。 别人打我如赶小鸡，我打别人似推憨牛。 麻蛋，究竟谁是天命人呀！我看你们才是！ 欢迎关注网易UU鉴赏家培养计划 关注UU加速器VX公众号，回复“steam”，获得专属玩家群邀请。 里面的怪物形态各异，女妖精那更是个顶个的可爱。 这游戏的妖更像是妖，仙更像是仙，就是人都不是人了，全都成了尸骸了。 整体来说，作为一款国内3A大作来说，前两天媒体吹得太过了，优势劣势都很明显。 先说优势：很明显，钻入骨髓的西游故事游戏化的展现，视觉冲击，动作打斗，环境塑造与妖魔理念，甜不甜那都是家乡水，什么叫基因唤醒，《黑神话》算是在游戏界里的基因唤醒器。 它的理念、故事与音乐绝对值得你一玩，尤其是那种常年沉浸在国外游戏大作的玩家来说，你不差钱，又见多识广下，你更能体会到什么叫做基因唤醒，你一拿上手就知道，只有中国人能做出这样的游戏，外国人绝对不懂，这不是技术原因，这是文化根基。 再说劣势：关卡设计与地图展现，是他宝贝的一塌糊涂。 一共六张地图，你会发现所有的地图都展现出来了，人神共愤的大范围的同色彩沿用，无与伦比的超大范围的又遮蔽性质的物质出现，比如雪天，比如黄沙，比如地穴的黑暗。 虽然游戏作为关卡制，但地图极大，在缺失地标元素，没有全景大地图，甚至无法做地图自主标记的前提下，迷路加迷路加迷路的爆炸心态直接让22°的空调都无法降温了。 在我看来，黑神话也正是国内游戏的短板问题： 美术OK 剧情OK 角色OK 但场景设计不OK 关卡设计不OK 尤其是在大地图的情况下，如何对场景进行有效的识别，关卡的设计让人玩起来在紧张与轻松里互相交替，不至于过于劳累，绝对需要沉淀的技术工种，有些可以拿钱砸，有些真的是拿钱砸也砸不出来，就是需要项目与时间来培养。 这些人对游戏而言，是绝对的大宝贝，培养出来一个，都是中国游戏界的集体贡献。 把整体态势说完后，我们说细节的内容 战前的大圣，战后的马猴 战斗采取一个棍子打天下的方式，充分发挥只要长处够长，就能填补短处的方式。 我见到怪，那就是捅捅捅捅捅捅，左捅捅，右捅捅，上捅捅，下捅捅。 正好棍子分为了三个不同的姿态，每一次都是上下左右四面捅，三个姿态可以无缝切换，根据怪物的出招方式来进行瞬间地改变，从而打出对应的硬质。 这游戏的重击绝对是伤害的主要手段，合理利用绝对会让你顺利清怪。 除了棍子外，第二个攻击的手段就是法术，法术的方式包含了： 定、分身、隐身以及钢筋铁骨甚至更多。 法术的CD还是挺长的，一场BOSS战大概一个法术能用2次，最多装备3个法术，也就是说，我们有机会使用6次法术。 而第三个输出手段就是黑猴里最有趣的变身了，你可以收起其他精英怪物的武器，然后化身成为他们的样子，进行变身攻击。 变身后，战斗招式与血条与本体独立，也就是说，等于你操作了完全不同的一个角色，绝对是十分的亮点！ 血染的西游，永远的大圣 很多的时候，大圣的含义代表了一种不屈服，对强敌的不屈服，对强权的不屈服，也是对自己的不屈服。 《黑神话》虽然里面带了一个黑字，故事里对神佛也确实有点黑的意思，但是整体的构造依旧保持着，绝对的不驯服，如果强权要让你屈服，要让你低头，我们一定会抬起头颅，用命抵抗。 整个故事的主旨同样也是再次，大圣虽然在开头就已经告诉我们死去了，天命人的目的是复活大圣，但是天命人在寻找回大圣的遗物的过程里，也让自己逐渐地靠近大圣，靠近理想中的那一个至高的存在。 而里面的BOSS怪物或者神仙都有自己的目的，这些目的有些太过腌臜，有些则隐晦不堪。 黑神话的时间线虽然是西游后的故事，但是其实在我看来理念并不只致敬西游，而是构建出来了自己的一套叙事逻辑，大家可以自己看。 但是对西游的致敬就很明显了，明显到了，甚至是直接文本的复刻，连标点符号都不会改变的那种。 如果你熟悉西游原作，绝对在游戏里能够看到太多的致敬了。 这个游戏里有众多的剧情分支与隐藏的角色，需要你在关键的时刻进行存档，而游戏内的存档并不多，如果你把自己的存档多样化的保存的话，可以使用UU云存档，给你的存档上个保险。 游戏虽然精彩，可别让游戏外的事情扫了兴！ 无论是换电脑玩时存档误覆盖，还是各种问题导致存档损坏。相信这样惨痛的经历依然时常发生，但这次决不能。所以，使用「UU云存档」，来为你的存档上个保险吧！ 使用起来简单方便，打开UU，一键开启就能用 全程自动保存，无需手动操作，不干扰你的游戏体验 不影响原平台正常存储档，UU与平台云存档同步运行 一键备份存档，一键锁定存档，重要的档要保存好 不用会员，好用免费 雕塑的佛像，至臻的瑰宝 黑神话里的雕像，真的是采用了众多的显示里的佛像古迹。 对众多的玩家而言，与其说享受制作组的在现实基础上构建的美术，我们历史上众多的精美遗产其实还没有电子化的展现。 对制作组而言，冥思苦想的美术基调，很有可能走歪，在现实的基础上，重新加工与润泽历史瑰宝绝对值得一试。 更何况西游的本质是是佛道儒三家的一个融合的作品，里面不论是出现佛家元素，道家元素还是儒家元素都完全的搭配至极呀。 我认为制作组在美术这一方面的发挥，真的是取长补短，弘扬历史，再现瑰宝与互相融合了。 说句玩笑话，单纯你就是欣赏里面的雕像与景色也能够让你回本了。 最后祝愿 通关了，我可以说，这个游戏的剧情没有讲完，游戏科学还有第二部，说不定是三部曲。 如果真是这样，很有可能黑神话会是一个延续十年左右的长期IP。 但从这几天的售卖信息来看，游戏科学应该是回本了。 我不求别的，只希望，这个游戏的出现，能让国内出现更多的优秀作品，更多才华横溢的制作组，更多让玩家们喜欢的游戏。 伴随着国内的经济快速发展与国际地位的提升，我相信接下来的几年会是中国各个方面巨大膨胀的时代。 黑神话看似是一不留神走到了风口，看似走上了政府支持的一个快车道。 任何的历史机遇都是可遇不可求的，黑神话遇到了这个机遇，也是我们国内的所有单机游戏爱好者的一个基于。 我们用着自己的金钱，向所有的国内制作组发出最高的呐喊，你们不需要怕好游戏做出来没人买。 国内的用户群体早已能够支撑的气一个3A游戏的内部循环了，而这一次的黑神话的成功，自然是个再明白不过的例子。 游戏不再是洪水猛兽，游戏是如今电子化的历史潮流里，根本无法避开的东西，扫码点餐、网上购物，早已成为了我们经济消费里的一环。 电子游戏，也一定会成为我们精神娱乐的一环。 最后祝，中国的单机游戏，再次一的崛起成功！ 接下来的三四年是一个机遇，希望更多的制作组大步尝试！ | J99: =IF(SUM(R99:T99)>0,1,0) -> 1 | K99: =IF(SUM(U99:Y99)>0,1,0) -> 1 | L99: =IF(SUM(Z99:AC99)>0,1,0) -> 1 | M99: =IF(SUM(AD99:AF99)>0,1,0) -> 0 | N99: =IF(SUM(AG99:AH99)>0,1,0) -> 1 | O99: =IF(SUM(AI99:AL99)>0,1,0) -> 1 | P99: =IF(SUM(AM99:AQ99)>0,1,0) -> 1 | Q99: =IF(AR99>0,1,0) -> 1 | R99: 1 | S99: 1 | T99: 0 | U99: 1 | V99: 1 | W99: 1 | X99: 1 | Y99: 0 | Z99: 1 | AA99: 0 | AB99: 1 | AC99: 1 | AD99: 0 | AE99: 0 | AF99: 0 | AG99: 0 | AH99: 1 | AI99: 1 | AJ99: 0 | AK99: 0 | AL99: 1 | AM99: 0 | AN99: 1 | AO99: 0 | AP99: 0 | AQ99: 0 | AR99: 1 | AS99: =SUM(J99:Q99) -> 7 | AT99: =SUM(R99:AR99) -> 14 | AU99: 画面美术场景；音乐音效配音；动作打击手感；Boss战斗节奏；难度挑战；锁定视角；地图路线；探索隐藏支线；引导迷路单线；推荐价值判断；西游悟空符号；中国文化宗教语言审美；原典知识人物关系专名；国产3A身份期待 | AV99: =IF(AT99>0,1,0) -> 1 | AW99: =IF(AT99=0,1,0) -> 0 | AX99: =IF(AT99>=8,1,0) -> 1 | AY99: 79.5 | AZ99: 正面 | BA99: P | BB99: 原文
A100: CN-P-099 | B100: 中文 | C100: 不推荐 | D100: 4660 | E100: 195 | F100: 64.5 | G100: 2024-08-23 | H100: 叠个甲吧，差评并不是为了否定这款游戏，而是希望游科能够看到我的评价，能够正视自己游戏存在的一些问题。 开篇先谈谈我自己的成分，我（自认）作为一个普普通通臭打游戏的，我认为黑神话的品质只能算是“合格的3A”而不是“优秀的3A” 毫无疑问黑神话是一款非常有“潜力”的游戏，虽然它作为国内第一款3A要走的路还很长，但不可否认黑神话充满了潜力，在吸收了现有的错误和缺陷后，有了足够资源的游戏科学会在dlc（或下一作）将这种“潜力”转变为品质，所以加油吧（但这并不代表游科不需要为黑神话现有的问题买单，这也是我给出差评的主要原因。） 当然，这一切的前提是不要捂嘴不要捂嘴，有问题该提就提，感到不合理了就客观讨论，不要动不动就扣帽子/人身攻击/举报，哥们steam今天都被某些成分不明的人干成社区红信了，还好客服通情达理，看出是恶意举报帮我解了。 接下来进行游戏本身的讨论，大家都是来玩游戏的，所以在讨论游戏时不要带有“国内第一款3A大作”“四大名著之西游记衍生的游戏”等滤镜来美化这款游戏。实事求是，优秀的地方就夸，有问题的地方就改，只有直面问题，正视问题，才能够解决问题，得到提升。 首先，我认为这款游戏最大的问题是目标锁定： 1，锁定目标异常，你除了可以锁怪，还可以在身边有两只怪的情况下锁黄风岭地上的虫子，锁小西天的果树。 2，锁定视角异常，当怪物比你高的情况下很容易出现你的视角看向地面，或者是你只能看天上，完全看不到地面，这里点名各种会飞的小怪（视角看地），近战锁黑熊精（视角看地），亢金龙BOSS战全程（视角看天，亢金龙释放落泪时如果不和boss拉开距离，你甚至看不到雷的落点）。毒敌大王更是优秀设计，攻击前摇看的不是动作而是手和尾，但你们自己玩的时候贴身目标锁定能看见它的手吗？怎么，虽然没给其他玩家远程手段，但你们自己有远程手段不用近战是吧？ 百目魔君（锁中间打两边）这大哥脚下空气墙，能被打中的是左右两边的腿，但锁定又锁在boss正中央。天才，你们游科一百来人个顶个的聪明，就这玩意成品能放的出来？你们一百来人发售前游玩的是黑神话？真的不是黑棉花？ 3，视角移动异常，当怪物移动速度过快或移动范围过大时，玩家的锁定视野会丢失（怪跑到屏幕外）然后镜头会慢慢拉过去（点名灵虚子，亢金龙，魔将·妙音） ———————————————————————————— 其次是地图设计问题： 1，地图空气墙，这个问题已经被很多人提过了，只能说每个人都是从第一章开始撞着空气墙玩下去的。 2，地图假路口，众所周知这类游戏是很需要玩家进行“探索”行为的，但每张地图都有很多很多（不是一个两个，是每张地图五六个的程度）看起来很像能走的假路口/假山洞/假山崖，这就导致玩家更加频繁的遇到空气墙，偏偏制作组又真的在各种地图塞了小路口（比如打完妙音出门左转的山崖可以跳下去拿道具），这就逼迫玩家必须用头去一遍又一遍的撞墙。 3，地图分支道路过多且辨识度不高，这是很多线性流程地图都有的通病，不予讨论。 ------------------------------------------------------------------------------------------- 只是关于防具的设定（全段划掉，是个人游戏进度不足没有解锁防具升阶功能） -------------------------------------------------------------------------- 2024/8/23新增，在序章结束我的游戏就发生过闪退，重新启动后要再打一次序章。第二次发生闪退是在打死魔将·妙音的击杀CG时，闪退后就无法启动游戏了（启动就会闪退）在重启电脑并验证游戏完整性后可以正常进入游戏（虽然解锁了成就但需要重打BOSS）。第三次闪退是在刚战胜不能的时候，也就是现在...又出现了再次启动游戏会闪退的情况，希望尽快优化吧。 -------------------------------------------------------------------------- 2024/10/04新增，关于BOSS设计与玩家战斗体验方面，评测者个人非常推荐各位去看B站UP主“Pen盆ぺん”制作的《【可以锐评吗】你那黑神话，从来没那么圆满——黑神话：悟空》这期视频（BV14BtYePEfC）基本把我能想到的或我想不到的相关问题都说的很清楚。 2024/8/24新增，本来我是不打算在通关前评价战斗部分和boss设计的，但这个不空给了我当头一棒（x）我就简单说一些吧。 识破，这样一个高风险高收益的操作，却因为各种抽象设计和离谱的boss的设计吞掉了收益，只剩下风险。 1，亢龙星君，本身不是一个很强的boss，但有一项独特的“天赋”，识破反击命中后亢龙星君会被击飞很远，导致识破衔接的二段下劈打空（我连续识破三次，二段下劈空了两次，第三次下劈才中，有视频为证，不服的可以来管我要） 2，以寅虎为首的大部分高韧性boss，在面对这些boss时玩家就要思考识破的风险和收益是否对等了，因为玩家哪怕是使用识破接住了对方的攻击，也会在反击时被下一击打中，更不要说后续派生的二段下劈了（总的来说就是识破反击前摇太长且造成的削韧不够将boss打入硬直） 3，根基天赋中的翻滚不会打断普攻天赋（别问为什么点，不点无法解锁后续天赋），这个天赋和识破组合起来形成了负面的化学反应，让玩家在与boss战斗时不但要考虑boss的出招，还要考虑自己普攻到了第几段，翻滚后是第几段，这个时候是否可以使用识破接住boss攻击。 4，小黄龙，因为小黄龙大部分攻击模组带有位移性质，可能会导致识破反击打空，直接断掉玩家节奏（当时这个反击打空直接把我心态打崩了）（好吧，不止是小黄龙，后面很多boss都会经常让玩家的攻击打空，我不清楚这是锁敌有问题还是游科故意设计的，总之打起来很怪，玩家既要背板躲技能，又要应付各种意外情况，不太好评价） 5，百目魔君，喜欢我boss脚下是一块空气墙的设定吗？boss面前能被攻击到的是两条腿，但无论是重击还是识破反击都很容易打到boss中间的空气，幽默设计。 定身术瞬机，这样一个极高风险，理应也有极高收益的操作（判定帧极短，用早了无法触发瞬机天赋，用晚了会吃伤害并且被吞技能）却因为一些boss无视定身/弱化定身效果的设计变得毫无收益，说的就是你，寅虎（被定身后吃一段伤害就会破开），不空（完全不吃定身）。我个人并不认可将瞬机定身和普通定身一概而论的设计理念，毕竟前者要求极为严苛，甚至可以说是极端严苛，后者只要是个健全的人类（哪怕是部分不健全的人类）都能释放。 2024/8/28更新，幽默瞬机的延长定身时间机制导致我连打两套轻击硬是没破开定身，这也导致没吃到破开定身的回蓝效果（x）所以我个人还是更支持瞬机触发就回蓝 这螳螂攻击时被我瞬机定身，打破定身后螳螂没有被打断攻击？？而是可以继续之前的攻击？？不是，哥们，那这瞬机定身的存在意义是什么？打破定身后的回蓝奖励是钓鱼用的是吧？现在我感觉游科只是一拍脑袋想出了定身瞬机这个设定，但根本没想着完善这个设定。 铜头铁臂，和普通定身术类似，只要是正常的玩家都能够找到合适的时机释放，有风险但不高，但我认为收益依旧不如风险（耗蓝也是风险的一部分）。这两天经常有Boss被铜头铁臂反震后没什么硬直直接跑掉的情况发生。 2024/8/25新增，看到留言区有人说是游科为了让玩家选择其他流派，所以把定身瞬机和劈棍识破设计成这个高风险低收益的样子。对此我的观点是： 1，劈棍识破是要消耗一层棍势的，而戳棍退寸并不需要消耗棍势（同时玩家要面临没弹到/反击打空断节奏/反击打中没硬直等各种负面情况） 2，我能理解boss免疫/耐受定身的情况，但我不能理解的是定身触发瞬机这种极高风险的操作却换不回任何收益的设定，既然定身瞬机的设计就是为了让玩家“见招拆招”，为什么优先级还是和普通定身相同呢？（怪猎盾斧gp都有额外防性，大部分游戏盾牌格挡和弹反区别都极大，为什么到了你游就要将无风险有收益和极高风险极高收益一概而论呢？） 3，我自始至终都不认可削弱式平衡，如果真如你所说游科是为了让玩家选择其他流派而选择性的削弱了劈棍识破和定身瞬机，那我认为这个差评是游科应得的。 -------------------------------------------------------------------------- 2024/8/25新增，战胜小黄龙后在土地庙查看兵器锻造时游戏卡死。到达黄花观土地庙后电脑死机。（我是A卡，几年前配的电脑了，CPU5600x，GPU6700xt，32G内存）（希望大家在说“怎么我不闪退，就你闪退呢？找找你的原因”之前，想想“为什么我别的游戏不闪退？只有这个游戏闪退？”这种话，大部分人的电脑配置都是不同的，每个人都有自己的情况，你自己没有闪退就能代表所有人都不闪退？以后这种屁话见一个删一个） -------------------------------------------------------------------------- 2024/8/27新增，游科你可真是那个啊，动作游戏几十年的糟粕被你四年学完了是吧？火焰山土地公召唤那条鱼是人能设计出来的？难打吗？不难打，甚至我打到一半直接不碰左摇杆了，只需要翻滚和普攻就能打死。但你问我恶心吗？太恶心了，打一套轻攻击就拉远朝你吐口水，吐完回来在你面前晃悠一下甩尾两次又拉远，这不是恶心人吗？经典的boss不主动近战攻击玩家，玩家就只能看着boss表演。 火焰山打完土地后遇到的那个B火车，那么大模型给那么小个战斗场地？设计者是蜗居在上海两平米小单间做出来的是吧？让玩家都体会一下你的痛苦？还有这个B火车屁股喷火攻击也有大问题，单次喷火中能造成四次伤害（你以为是只打四段伤害？是我满血只能吃四段伤害）上一个这么抽象的设计还是环DLC野猪骑士的冲刺（因为攻击判定bug两段超高伤害，能秒人）和野猪骑士的后蹬腿（同因为攻击碰撞bug导致两段伤害，能打玩家五分之四血）但你一个静止的喷火动作怎么也能设计成这样？ -------------------------------------------------------------------------- 2024/8/27新增，这次我终于弄清楚为什么有些boss打起来这么难受了。 先举个例子吧，游戏科学一位员工的办公桌上有个装满水的水杯，当这位员工想喝水时，他的第一步是把手伸向水杯（第一帧），然后跳过手摸水杯，把水杯握住，把水杯举起来，送到嘴边和几个动作，第二步直接开始喝水（第二帧）。 到这里可能有些的人不太懂我举的例子，我举几个例子（不是踩一捧一，只是方便各位理解）寅虎的投技，玩家在初见寅虎转身消失并且一言不发时能想到这是投技吗？躲开的概率又有多大呢？小黄龙的飞天，初见时谁能想到这招爆气后直接冲脸？然后飞起来用不同的节奏连冲三次？甚至收尾都有三种情况？（重要的是根本不给临时反应时间，上一帧摆poss，下一帧冲脸了）斩龙（怪猎，重复一遍只是方便理解）360°拔刀，同样是摆出一个姿势，初见时谁能知道攻击方式和攻击范围还有出招的时机？约定之王的光斩（法环DLC，二阶段陨石之后接的那个）在造成伤害前初见的人也完全无法想象会受到怎样的攻击，又该怎样躲避。 这种设计不是不可以存在，而是大部分情况下都拿来做“压箱底”的招式，毕竟玩家试错是需要“时间成本”的，还要记出招动作，记攻击节奏和攻击范围/模式，对玩家操作要求很严格。但黑神话boss的设计违背了这一点，频繁且大量的加入这种招式只会让玩家疲于应对的同时深感折磨。 后面这些个boss都有这个毛病，无论是红孩儿还是杨戬又或是王灵官，区别只是这种动作有多有少罢了。 1，红孩儿，一阶段和二阶段都有这种动作，但只有一点点（大部分动作哪怕是初见也能凭借反应速度闪避） 2，杨戬，连贯的攻击动作和这种1帧出刀各占一半（导致各种招式并不是只靠反应能力就能躲，要一次次熟悉招式寻找节奏躲避） 3，王灵官，这位更是重量级，在1帧出刀中少量加入一些普通招式（比如挥剑第二段）上一帧远在天边，下一帧直接踹我脸上。（几乎无法通过反应/肌肉记忆来躲避攻击，只能靠预判..也就是猜，或者是慢慢熟悉攻击节奏，等能够读取到对方“想喝水”这个想法时，才能成功躲开这些招式） 其实不止这几个boss有这种问题，从小西天开始这类boss一直在恶心玩家（游科您是不会做从挥刀第一帧到最后一帧的动作吗？非得上一帧抬手，下一帧已经砍完了吗？） 最后拿石子举例子吧，石子有一招跳起来砸地，正常的BOSS跳起来砸地动作应该是匀速的吧？但游科设计的BOSS不是，这石子跳起来会有一个短暂的“悬空”动作（停在空中），隔几帧后直接落在地上（至于隔几帧，完全看游科想让它隔几帧，完全无法在吃过这招之前猜到） 本条的存在意义是为了辩证为何有些boss打起来很舒服（爽），而有些boss打起来很难受（粪）而不是什么能不能打过。 -------------------------------------------------------------------------- 最后的最后，目前国区黑神话的舆论有些过于恐怖了（二极管，非黑即白，而且大部分都是二极管且白）但凡有人说黑神话哪里哪里做的不好都会被扣上各种帽子，包括但不限于“你不会是云玩家吧”“外媒的狗”“你更适合玩米家游戏”，我的评价是有些过于极端了。我认为黑神话作为一款面向全球的游戏，最需要的并不是无脑的吹捧，而是有价值的建议和对错误的指正。希望大家能够不掺杂任何“政治因素”和“国单滤镜”的讨论这款游戏。如果我的评价有错误也欢迎指正。 2024/8/31新增，该账号因恶意举报导致社区红信，虽然联系客服后解除了红信，但评测者不想再冒着“你号没了”的风险进行相关讨论了。该评测就此停更，未来将不会再进行编辑或新增内容。（视情况是否关闭留言或筛选可见性） | I100: 叠个甲吧，差评并不是为了否定这款游戏，而是希望游科能够看到我的评价，能够正视自己游戏存在的一些问题。 开篇先谈谈我自己的成分，我（自认）作为一个普普通通臭打游戏的，我认为黑神话的品质只能算是“合格的3A”而不是“优秀的3A” 毫无疑问黑神话是一款非常有“潜力”的游戏，虽然它作为国内第一款3A要走的路还很长，但不可否认黑神话充满了潜力，在吸收了现有的错误和缺陷后，有了足够资源的游戏科学会在dlc（或下一作）将这种“潜力”转变为品质，所以加油吧（但这并不代表游科不需要为黑神话现有的问题买单，这也是我给出差评的主要原因。） 当然，这一切的前提是不要捂嘴不要捂嘴，有问题该提就提，感到不合理了就客观讨论，不要动不动就扣帽子/人身攻击/举报，哥们steam今天都被某些成分不明的人干成社区红信了，还好客服通情达理，看出是恶意举报帮我解了。 接下来进行游戏本身的讨论，大家都是来玩游戏的，所以在讨论游戏时不要带有“国内第一款3A大作”“四大名著之西游记衍生的游戏”等滤镜来美化这款游戏。实事求是，优秀的地方就夸，有问题的地方就改，只有直面问题，正视问题，才能够解决问题，得到提升。 首先，我认为这款游戏最大的问题是目标锁定： 1，锁定目标异常，你除了可以锁怪，还可以在身边有两只怪的情况下锁黄风岭地上的虫子，锁小西天的果树。 2，锁定视角异常，当怪物比你高的情况下很容易出现你的视角看向地面，或者是你只能看天上，完全看不到地面，这里点名各种会飞的小怪（视角看地），近战锁黑熊精（视角看地），亢金龙BOSS战全程（视角看天，亢金龙释放落泪时如果不和boss拉开距离，你甚至看不到雷的落点）。毒敌大王更是优秀设计，攻击前摇看的不是动作而是手和尾，但你们自己玩的时候贴身目标锁定能看见它的手吗？怎么，虽然没给其他玩家远程手段，但你们自己有远程手段不用近战是吧？ 百目魔君（锁中间打两边）这大哥脚下空气墙，能被打中的是左右两边的腿，但锁定又锁在boss正中央。天才，你们游科一百来人个顶个的聪明，就这玩意成品能放的出来？你们一百来人发售前游玩的是黑神话？真的不是黑棉花？ 3，视角移动异常，当怪物移动速度过快或移动范围过大时，玩家的锁定视野会丢失（怪跑到屏幕外）然后镜头会慢慢拉过去（点名灵虚子，亢金龙，魔将·妙音） ———————————————————————————— 其次是地图设计问题： 1，地图空气墙，这个问题已经被很多人提过了，只能说每个人都是从第一章开始撞着空气墙玩下去的。 2，地图假路口，众所周知这类游戏是很需要玩家进行“探索”行为的，但每张地图都有很多很多（不是一个两个，是每张地图五六个的程度）看起来很像能走的假路口/假山洞/假山崖，这就导致玩家更加频繁的遇到空气墙，偏偏制作组又真的在各种地图塞了小路口（比如打完妙音出门左转的山崖可以跳下去拿道具），这就逼迫玩家必须用头去一遍又一遍的撞墙。 3，地图分支道路过多且辨识度不高，这是很多线性流程地图都有的通病，不予讨论。 ------------------------------------------------------------------------------------------- 只是关于防具的设定（全段划掉，是个人游戏进度不足没有解锁防具升阶功能） -------------------------------------------------------------------------- 2024/8/23新增，在序章结束我的游戏就发生过闪退，重新启动后要再打一次序章。第二次发生闪退是在打死魔将·妙音的击杀CG时，闪退后就无法启动游戏了（启动就会闪退）在重启电脑并验证游戏完整性后可以正常进入游戏（虽然解锁了成就但需要重打BOSS）。第三次闪退是在刚战胜不能的时候，也就是现在...又出现了再次启动游戏会闪退的情况，希望尽快优化吧。 -------------------------------------------------------------------------- 2024/10/04新增，关于BOSS设计与玩家战斗体验方面，评测者个人非常推荐各位去看B站UP主“Pen盆ぺん”制作的《【可以锐评吗】你那黑神话，从来没那么圆满——黑神话：悟空》这期视频（BV14BtYePEfC）基本把我能想到的或我想不到的相关问题都说的很清楚。 2024/8/24新增，本来我是不打算在通关前评价战斗部分和boss设计的，但这个不空给了我当头一棒（x）我就简单说一些吧。 识破，这样一个高风险高收益的操作，却因为各种抽象设计和离谱的boss的设计吞掉了收益，只剩下风险。 1，亢龙星君，本身不是一个很强的boss，但有一项独特的“天赋”，识破反击命中后亢龙星君会被击飞很远，导致识破衔接的二段下劈打空（我连续识破三次，二段下劈空了两次，第三次下劈才中，有视频为证，不服的可以来管我要） 2，以寅虎为首的大部分高韧性boss，在面对这些boss时玩家就要思考识破的风险和收益是否对等了，因为玩家哪怕是使用识破接住了对方的攻击，也会在反击时被下一击打中，更不要说后续派生的二段下劈了（总的来说就是识破反击前摇太长且造成的削韧不够将boss打入硬直） 3，根基天赋中的翻滚不会打断普攻天赋（别问为什么点，不点无法解锁后续天赋），这个天赋和识破组合起来形成了负面的化学反应，让玩家在与boss战斗时不但要考虑boss的出招，还要考虑自己普攻到了第几段，翻滚后是第几段，这个时候是否可以使用识破接住boss攻击。 4，小黄龙，因为小黄龙大部分攻击模组带有位移性质，可能会导致识破反击打空，直接断掉玩家节奏（当时这个反击打空直接把我心态打崩了）（好吧，不止是小黄龙，后面很多boss都会经常让玩家的攻击打空，我不清楚这是锁敌有问题还是游科故意设计的，总之打起来很怪，玩家既要背板躲技能，又要应付各种意外情况，不太好评价） 5，百目魔君，喜欢我boss脚下是一块空气墙的设定吗？boss面前能被攻击到的是两条腿，但无论是重击还是识破反击都很容易打到boss中间的空气，幽默设计。 定身术瞬机，这样一个极高风险，理应也有极高收益的操作（判定帧极短，用早了无法触发瞬机天赋，用晚了会吃伤害并且被吞技能）却因为一些boss无视定身/弱化定身效果的设计变得毫无收益，说的就是你，寅虎（被定身后吃一段伤害就会破开），不空（完全不吃定身）。我个人并不认可将瞬机定身和普通定身一概而论的设计理念，毕竟前者要求极为严苛，甚至可以说是极端严苛，后者只要是个健全的人类（哪怕是部分不健全的人类）都能释放。 2024/8/28更新，幽默瞬机的延长定身时间机制导致我连打两套轻击硬是没破开定身，这也导致没吃到破开定身的回蓝效果（x）所以我个人还是更支持瞬机触发就回蓝 这螳螂攻击时被我瞬机定身，打破定身后螳螂没有被打断攻击？？而是可以继续之前的攻击？？不是，哥们，那这瞬机定身的存在意义是什么？打破定身后的回蓝奖励是钓鱼用的是吧？现在我感觉游科只是一拍脑袋想出了定身瞬机这个设定，但根本没想着完善这个设定。 铜头铁臂，和普通定身术类似，只要是正常的玩家都能够找到合适的时机释放，有风险但不高，但我认为收益依旧不如风险（耗蓝也是风险的一部分）。这两天经常有Boss被铜头铁臂反震后没什么硬直直接跑掉的情况发生。 2024/8/25新增，看到留言区有人说是游科为了让玩家选择其他流派，所以把定身瞬机和劈棍识破设计成这个高风险低收益的样子。对此我的观点是： 1，劈棍识破是要消耗一层棍势的，而戳棍退寸并不需要消耗棍势（同时玩家要面临没弹到/反击打空断节奏/反击打中没硬直等各种负面情况） 2，我能理解boss免疫/耐受定身的情况，但我不能理解的是定身触发瞬机这种极高风险的操作却换不回任何收益的设定，既然定身瞬机的设计就是为了让玩家“见招拆招”，为什么优先级还是和普通定身相同呢？（怪猎盾斧gp都有额外防性，大部分游戏盾牌格挡和弹反区别都极大，为什么到了你游就要将无风险有收益和极高风险极高收益一概而论呢？） 3，我自始至终都不认可削弱式平衡，如果真如你所说游科是为了让玩家选择其他流派而选择性的削弱了劈棍识破和定身瞬机，那我认为这个差评是游科应得的。 -------------------------------------------------------------------------- 2024/8/25新增，战胜小黄龙后在土地庙查看兵器锻造时游戏卡死。到达黄花观土地庙后电脑死机。（我是A卡，几年前配的电脑了，CPU5600x，GPU6700xt，32G内存）（希望大家在说“怎么我不闪退，就你闪退呢？找找你的原因”之前，想想“为什么我别的游戏不闪退？只有这个游戏闪退？”这种话，大部分人的电脑配置都是不同的，每个人都有自己的情况，你自己没有闪退就能代表所有人都不闪退？以后这种屁话见一个删一个） -------------------------------------------------------------------------- 2024/8/27新增，游科你可真是那个啊，动作游戏几十年的糟粕被你四年学完了是吧？火焰山土地公召唤那条鱼是人能设计出来的？难打吗？不难打，甚至我打到一半直接不碰左摇杆了，只需要翻滚和普攻就能打死。但你问我恶心吗？太恶心了，打一套轻攻击就拉远朝你吐口水，吐完回来在你面前晃悠一下甩尾两次又拉远，这不是恶心人吗？经典的boss不主动近战攻击玩家，玩家就只能看着boss表演。 火焰山打完土地后遇到的那个B火车，那么大模型给那么小个战斗场地？设计者是蜗居在上海两平米小单间做出来的是吧？让玩家都体会一下你的痛苦？还有这个B火车屁股喷火攻击也有大问题，单次喷火中能造成四次伤害（你以为是只打四段伤害？是我满血只能吃四段伤害）上一个这么抽象的设计还是环DLC野猪骑士的冲刺（因为攻击判定bug两段超高伤害，能秒人）和野猪骑士的后蹬腿（同因为攻击碰撞bug导致两段伤害，能打玩家五分之四血）但你一个静止的喷火动作怎么也能设计成这样？ -------------------------------------------------------------------------- 2024/8/27新增，这次我终于弄清楚为什么有些boss打起来这么难受了。 先举个例子吧，游戏科学一位员工的办公桌上有个装满水的水杯，当这位员工想喝水时，他的第一步是把手伸向水杯（第一帧），然后跳过手摸水杯，把水杯握住，把水杯举起来，送到嘴边和几个动作，第二步直接开始喝水（第二帧）。 到这里可能有些的人不太懂我举的例子，我举几个例子（不是踩一捧一，只是方便各位理解）寅虎的投技，玩家在初见寅虎转身消失并且一言不发时能想到这是投技吗？躲开的概率又有多大呢？小黄龙的飞天，初见时谁能想到这招爆气后直接冲脸？然后飞起来用不同的节奏连冲三次？甚至收尾都有三种情况？（重要的是根本不给临时反应时间，上一帧摆poss，下一帧冲脸了）斩龙（怪猎，重复一遍只是方便理解）360°拔刀，同样是摆出一个姿势，初见时谁能知道攻击方式和攻击范围还有出招的时机？约定之王的光斩（法环DLC，二阶段陨石之后接的那个）在造成伤害前初见的人也完全无法想象会受到怎样的攻击，又该怎样躲避。 这种设计不是不可以存在，而是大部分情况下都拿来做“压箱底”的招式，毕竟玩家试错是需要“时间成本”的，还要记出招动作，记攻击节奏和攻击范围/模式，对玩家操作要求很严格。但黑神话boss的设计违背了这一点，频繁且大量的加入这种招式只会让玩家疲于应对的同时深感折磨。 后面这些个boss都有这个毛病，无论是红孩儿还是杨戬又或是王灵官，区别只是这种动作有多有少罢了。 1，红孩儿，一阶段和二阶段都有这种动作，但只有一点点（大部分动作哪怕是初见也能凭借反应速度闪避） 2，杨戬，连贯的攻击动作和这种1帧出刀各占一半（导致各种招式并不是只靠反应能力就能躲，要一次次熟悉招式寻找节奏躲避） 3，王灵官，这位更是重量级，在1帧出刀中少量加入一些普通招式（比如挥剑第二段）上一帧远在天边，下一帧直接踹我脸上。（几乎无法通过反应/肌肉记忆来躲避攻击，只能靠预判..也就是猜，或者是慢慢熟悉攻击节奏，等能够读取到对方“想喝水”这个想法时，才能成功躲开这些招式） 其实不止这几个boss有这种问题，从小西天开始这类boss一直在恶心玩家（游科您是不会做从挥刀第一帧到最后一帧的动作吗？非得上一帧抬手，下一帧已经砍完了吗？） 最后拿石子举例子吧，石子有一招跳起来砸地，正常的BOSS跳起来砸地动作应该是匀速的吧？但游科设计的BOSS不是，这石子跳起来会有一个短暂的“悬空”动作（停在空中），隔几帧后直接落在地上（至于隔几帧，完全看游科想让它隔几帧，完全无法在吃过这招之前猜到） 本条的存在意义是为了辩证为何有些boss打起来很舒服（爽），而有些boss打起来很难受（粪）而不是什么能不能打过。 -------------------------------------------------------------------------- 最后的最后，目前国区黑神话的舆论有些过于恐怖了（二极管，非黑即白，而且大部分都是二极管且白）但凡有人说黑神话哪里哪里做的不好都会被扣上各种帽子，包括但不限于“你不会是云玩家吧”“外媒的狗”“你更适合玩米家游戏”，我的评价是有些过于极端了。我认为黑神话作为一款面向全球的游戏，最需要的并不是无脑的吹捧，而是有价值的建议和对错误的指正。希望大家能够不掺杂任何“政治因素”和“国单滤镜”的讨论这款游戏。如果我的评价有错误也欢迎指正。 2024/8/31新增，该账号因恶意举报导致社区红信，虽然联系客服后解除了红信，但评测者不想再冒着“你号没了”的风险进行相关讨论了。该评测就此停更，未来将不会再进行编辑或新增内容。（视情况是否关闭留言或筛选可见性） | J100: =IF(SUM(R100:T100)>0,1,0) -> 1 | K100: =IF(SUM(U100:Y100)>0,1,0) -> 1 | L100: =IF(SUM(Z100:AC100)>0,1,0) -> 1 | M100: =IF(SUM(AD100:AF100)>0,1,0) -> 1 | N100: =IF(SUM(AG100:AH100)>0,1,0) -> 1 | O100: =IF(SUM(AI100:AL100)>0,1,0) -> 1 | P100: =IF(SUM(AM100:AQ100)>0,1,0) -> 0 | Q100: =IF(AR100>0,1,0) -> 1 | R100: 0 | S100: 0 | T100: 1 | U100: 1 | V100: 1 | W100: 1 | X100: 1 | Y100: 1 | Z100: 1 | AA100: 1 | AB100: 1 | AC100: 1 | AD100: 1 | AE100: 1 | AF100: 1 | AG100: 1 | AH100: 1 | AI100: 1 | AJ100: 1 | AK100: 0 | AL100: 0 | AM100: 0 | AN100: 0 | AO100: 0 | AP100: 0 | AQ100: 0 | AR100: 1 | AS100: =SUM(J100:Q100) -> 7 | AT100: =SUM(R100:AR100) -> 18 | AU100: 演出角色怪物设计；动作打击手感；Boss战斗节奏；难度挑战；锁定视角；判定反馈；地图路线；空气墙可达性；探索隐藏支线；引导迷路单线；优化帧率；崩溃闪退；Bug兼容硬件；整体完成度；推荐价值判断；西游悟空符号；童年记忆情怀；国产3A身份期待 | AV100: =IF(AT100>0,1,0) -> 1 | AW100: =IF(AT100=0,1,0) -> 0 | AX100: =IF(AT100>=8,1,0) -> 1 | AY100: 27.5 | AZ100: 正面 | BA100: P | BB100: 原文
A101: CN-P-100 | B101: 中文 | C101: 不推荐 | D101: 824 | E101: 60 | F101: 38.7 | G101: 2024-08-23 | H101: 本人已经通关，所有boss都打了一遍，第一次在steam写评论，说说对黑神话的看法。作为国产第一个3A，黑神话悟空无疑是开天辟地的一个作品。地图美术、boss种类和设计在我这里都是将近满分的水平，虽然地图引导和关卡设计略显平庸，但在我眼里都是啥大问题，下面重点聊剧情。前三章的剧情很不错，至少没啥阴谋论的影子(反正我没看出来)。第四章就开始变味了，非要加那个b爱情戏，在游客主创眼里西游记必须得包含爱情戏是吧？第五章更是逆天，一整个大型家庭伦理剧，牛魔王被牛了？牛魔王居然还有个私生女？红孩儿是喝了子母河的水生下来的，子母河不是只能生女儿？这就是杨奇眼里的尊重原著，自己口口声声说改编不是乱编，就编成这个b样子？最后的孙悟空塑造的什么b样子，什么三爱白骨精，动画里抱着六耳猕猴伤心，真的给我看笑了，这几个都是孙悟空最讨厌的几个妖怪了吧。那可是齐天大圣，是中国几百年塑造的神话英雄，是聪明、机智、悟性高、有反抗精神的英雄人物。打败了他就能成为孙悟空？就能成为斗战胜佛？没有西行取经算什么斗战胜佛。阴谋论这种几十年前都烂大街的题材，你们制作组还视若珍宝，真的是low到家了。制作组采访时口口声声说自己尊重原著，说不能随意改变，既然改编成这个b样子能不能不要碰瓷原著？怎么有脸用86版西游记bgm的，又想标新立异，又要去蹭原著的流量，真是狗改不了吃屎。还好外文翻译的不是很好，要不然ign的8分给高了。以后外国人一想到孙悟空，就会说他三次杀了他的爱人，想想就令人恶心。当时听那些sb自媒体吹什么不看原著看不懂剧情，剧情立意很深，我特意去重温一遍西游记，现在看来自己纯纯小丑。一群恶臭文青意淫出来的剧情，居然有脸碰瓷原著和86版西游记，真是为了营销脸都不要了。最后引用六老师的一句话：改编不是乱编，戏说不是胡说。 | I101: 本人已经通关，所有boss都打了一遍，第一次在steam写评论，说说对黑神话的看法。作为国产第一个3A，黑神话悟空无疑是开天辟地的一个作品。地图美术、boss种类和设计在我这里都是将近满分的水平，虽然地图引导和关卡设计略显平庸，但在我眼里都是啥大问题，下面重点聊剧情。前三章的剧情很不错，至少没啥阴谋论的影子(反正我没看出来)。第四章就开始变味了，非要加那个b爱情戏，在游客主创眼里西游记必须得包含爱情戏是吧？第五章更是逆天，一整个大型家庭伦理剧，牛魔王被牛了？牛魔王居然还有个私生女？红孩儿是喝了子母河的水生下来的，子母河不是只能生女儿？这就是杨奇眼里的尊重原著，自己口口声声说改编不是乱编，就编成这个b样子？最后的孙悟空塑造的什么b样子，什么三爱白骨精，动画里抱着六耳猕猴伤心，真的给我看笑了，这几个都是孙悟空最讨厌的几个妖怪了吧。那可是齐天大圣，是中国几百年塑造的神话英雄，是聪明、机智、悟性高、有反抗精神的英雄人物。打败了他就能成为孙悟空？就能成为斗战胜佛？没有西行取经算什么斗战胜佛。阴谋论这种几十年前都烂大街的题材，你们制作组还视若珍宝，真的是low到家了。制作组采访时口口声声说自己尊重原著，说不能随意改变，既然改编成这个b样子能不能不要碰瓷原著？怎么有脸用86版西游记bgm的，又想标新立异，又要去蹭原著的流量，真是狗改不了吃屎。还好外文翻译的不是很好，要不然ign的8分给高了。以后外国人一想到孙悟空，就会说他三次杀了他的爱人，想想就令人恶心。当时听那些sb自媒体吹什么不看原著看不懂剧情，剧情立意很深，我特意去重温一遍西游记，现在看来自己纯纯小丑。一群恶臭文青意淫出来的剧情，居然有脸碰瓷原著和86版西游记，真是为了营销脸都不要了。最后引用六老师的一句话：改编不是乱编，戏说不是胡说。 | J101: =IF(SUM(R101:T101)>0,1,0) -> 1 | K101: =IF(SUM(U101:Y101)>0,1,0) -> 1 | L101: =IF(SUM(Z101:AC101)>0,1,0) -> 1 | M101: =IF(SUM(AD101:AF101)>0,1,0) -> 0 | N101: =IF(SUM(AG101:AH101)>0,1,0) -> 1 | O101: =IF(SUM(AI101:AL101)>0,1,0) -> 1 | P101: =IF(SUM(AM101:AQ101)>0,1,0) -> 1 | Q101: =IF(AR101>0,1,0) -> 1 | R101: 1 | S101: 1 | T101: 1 | U101: 0 | V101: 1 | W101: 0 | X101: 0 | Y101: 0 | Z101: 1 | AA101: 0 | AB101: 0 | AC101: 1 | AD101: 0 | AE101: 0 | AF101: 0 | AG101: 1 | AH101: 1 | AI101: 1 | AJ101: 0 | AK101: 1 | AL101: 1 | AM101: 1 | AN101: 1 | AO101: 0 | AP101: 0 | AQ101: 1 | AR101: 1 | AS101: =SUM(J101:Q101) -> 7 | AT101: =SUM(R101:AR101) -> 15 | AU101: 画面美术场景；音乐音效配音；演出角色怪物设计；Boss战斗节奏；地图路线；引导迷路单线；整体完成度；推荐价值判断；西游悟空符号；本国媒介路径；中国文化宗教语言审美；剧情叙事理解；原典知识人物关系专名；角色期待意义偏移；国产3A身份期待 | AV101: =IF(AT101>0,1,0) -> 1 | AW101: =IF(AT101=0,1,0) -> 0 | AX101: =IF(AT101>=8,1,0) -> 1 | AY101: 1 | AZ101: 正面 | BA101: P | BB101: 原文
